Workbook
Name anno: "2025"
Name cell_perc_RR: 10
Name mese: "10"
Name quarter: "Q4"

Sheet Budget
A1: FORMULA | K1: TO UPDATE BY SOFTWARE
A2: da considerare?_ | B2: BusinessArea_ | C2: ProjType_ | D2: ProjType Cluster 1_ | E2: ProjType Cluster 2_ | F2: Nome progetto_ | G2: EngUnit area cluster 1_ | H2: BDG est_ | I2: BDG int_ | J2: BDG_ | K2: Business | L2: CATEGORIA | M2: INT | N2: EST | O2: totale Gamberini | P2: INT2 | Q2: EST3 | R2: totale Lanzarini | S2: TOTALE TOT
A3: =IF(AND(tblBudget[[#This Row],[Business ]]>"",tblBudget[[#This Row],[CATEGORIA]]=""),"no","sì") -> sì | B3: =tblBudget[[#This Row],[Business ]] -> Business Sample | C3: =INDEX(tab_ProjTypeCluster[ProjType],MATCH(tblBudget[[#This Row],[CATEGORIA]],tab_ProjTypeCluster[Macro area],0)) -> #N/A | D3: =INDEX(tab_ProjTypeCluster[ProjType Cluster 1],MATCH(tblBudget[[#This Row],[CATEGORIA]],tab_ProjTypeCluster[Macro area],0)) -> #N/A | E3: =INDEX(tab_ProjTypeCluster[ProjType Cluster 2],MATCH(tblBudget[[#This Row],[CATEGORIA]],tab_ProjTypeCluster[Macro area],0)) -> #N/A | G3: =INDEX(tab_resp1liv[EngUnit area cluster 1_],MATCH(SUBSTITUTE(SUBSTITUTE(#REF!,"(ai)","")," ",""),tab_resp1liv[SearchKey],0)) -> #REF! | H3: =tblBudget[[#This Row],[EST]]+tblBudget[[#This Row],[EST3]] -> 15 | I3: =tblBudget[[#This Row],[INT]]+tblBudget[[#This Row],[INT2]] -> 25 | J3: =tblBudget[[#This Row],[TOTALE TOT]] -> 80 | K3: Business Sample | L3: Categoria A | M3: 10 | N3: 12 | O3: 22 | P3: 15 | Q3: 3 | R3: 18 | S3: 80

Sheet Forecast
A1: FORMULA | P1: TO UPDATE BY SOFTWARE
A2: da considerare? | B2: Proj type cluster 1 | C2: Proj type cluster 2 | D2: Business | E2: CATEGORIA_ | F2: ENG TOB - INT_ | G2: ENG TOB - EST_ | H2: ENG TOB Totale_ | I2: ENG LPP - INT_ | J2: ENG LPP - EST_ | K2: ENG LPP Totale_ | L2: int FORECAST_ | M2: ext FORECAST_ | N2: FORECAST Totale_ | O2: CATEGORIA TMP | P2: Business | Q2: CATEGORIA | R2: INT | S2: EST | T2: totale Gamberini | U2: INT2 | V2: EST3 | W2: totale Lanzarini | X2: TOTALE TOT
A3: =IF(AND(tblForecast[[#This Row],[Business ]]>"",tblForecast[[#This Row],[CATEGORIA]]=""),"no","sì") -> sì | B3: =IF(tblForecast[[#This Row],[da considerare?]]="sì",INDEX(tab_ProjType[ProjType Cluster 1],MATCH(tblForecast[[#This Row],[CATEGORIA TMP]],tab_ProjType[Macro area],0)),"") -> #N/A | C3: =IF(tblForecast[[#This Row],[da considerare?]]="sì",INDEX(tab_ProjType[ProjType Cluster 2],MATCH(tblForecast[[#This Row],[CATEGORIA TMP]],tab_ProjType[Macro area],0)),"") -> #N/A | D3: =IF(tblForecast[[#This Row],[Business ]]>"",tblForecast[[#This Row],[Business ]],D2) -> Business Sample | E3: =tblForecast[[#This Row],[CATEGORIA TMP]]&"" -> Categoria A | F3: =tblForecast[[#This Row],[INT]] -> 10 | G3: =tblForecast[[#This Row],[EST]] -> 12 | H3: =tblForecast[[#This Row],[totale Gamberini]] -> 22 | I3: =tblForecast[[#This Row],[INT2]] -> 15 | J3: =tblForecast[[#This Row],[EST3]] -> 3 | K3: =tblForecast[[#This Row],[totale Lanzarini]] -> 18 | L3: =tblForecast[[#This Row],[INT]]+tblForecast[[#This Row],[INT2]] -> 25 | M3: =tblForecast[[#This Row],[EST]]+tblForecast[[#This Row],[EST3]] -> 15 | N3: =tblForecast[[#This Row],[TOTALE TOT]] -> 80 | O3: =IF(LEFT(tblForecast[[#This Row],[CATEGORIA]],3)="R&D","R&D",tblForecast[[#This Row],[CATEGORIA]]) -> Categoria A | P3: Business Sample | Q3: Categoria A | R3: 10 | S3: 12 | T3: 22 | U3: 15 | V3: 3 | W3: 18 | X3: 80

Sheet RunRate
A1: 01 | B1: 02 | C1: 03 | D1: 04 | E1: 05 | F1: 06 | G1: 07 | H1: 08 | I1: 09 | J1: 10 | K1: 11 | L1: 12
A2: 0.15 | B2: 0.1 | C2: 0.05 | D2: 0.1 | E2: 0.15 | F2: 0.2 | G2: 0.25 | H2: 0.2 | I2: 0.15 | J2: 0.1 | K2: 0.05 | L2: 0.1

Sheet Superdetails
A1: FORMULA | AE1: TO UPDATE BY SOFTWARE
A2: da considerare?_ | B2: Anno_ | C2: Anno di prima marcatura (=anno di apertura progetto) | D2: WBS_ | E2: ProjType_ | F2: U ProjType_ | G2: ProjType Cluster | H2: ProjType Cluster2 | I2: BussinessArea Cluster | J2: ORE_ | K2: gen_ | L2: feb_ | M2: mar_ | N2: apr_ | O2: mag_ | P2: giu_ | Q2: lug_ | R2: ago_ | S2: set_ | T2: ott_ | U2: nov_ | V2: dic_ | W2: tipo risorsa_ | X2: Resp 1°liv_ | Y2: EngUnit area cluster 1_ | Z2: WBS description_ | AA2: WBE description_ | AB2: WBS D description_ | AC2: WBS M description_ | AD2: WBE per WBS-K | AE2: Sender Cost Center | AF2: Personnel Number | AG2: Last name First name | AH2: Project Description | AI2: WBS Element | AJ2: Network | AK2: Operation/Activity | AL2: Acct assgnt text | AM2: WBS Element - Project Definition (Text) | AN2: Network descr | AO2: PROJ CODE | AP2: INT/EST | AQ2: Raggr. X Struttura | AR2: MESE | AS2: Resp 2°liv | AT2: CDC bdg | AU2: Resp 1°liv | AV2: Resp DT | AW2: TIPO REP | AX2: Bus Area GDLT | AY2: Bus Area_2 | AZ2: tipo progetto | BA2: Proj name | BB2: machine code | BC2: product area | BD2: Resp del Prodotto | BE2: Area di bdg | BF2: Macchina | BG2: Sottotipo | BH2: Cluster | BI2: Quadrante | BJ2: 01.2025 | BK2: 02.2025 | BL2: 03.2025 | BM2: 04.2025 | BN2: 05.2025 | BO2: 06.2025 | BP2: 07.2025 | BQ2: 08.2025 | BR2: 09.2025 | BS2: 10.2025 | BT2: 11.2025 | BU2: 12.2025 | BV2: Total | BW2: WBE Status | BX2: competence date | BY2: Proj. Type | BZ2: WBE Name | CA2: Engineering Area | CB2: Data Accettazione | CC2: Data Uscita GD | CD2: REP UT
A3: =IF(UPPER(LEFT(tabSuperdettagli[[#This Row],[WBE Status]],1))="S","sì","no") -> no | B3: 2000 | C3: =VLOOKUP(tabSuperdettagli[[#This Row],[WBS_]], 'pivot di appoggio'!A:B,2,FALSE) -> 2000 | D3: =LEFT(tabSuperdettagli[[#This Row],[Network]],10) -> 5447634 | E3: =LEFT(tabSuperdettagli[[#This Row],[Network]],1) -> 5 | F3: =LOWER(TRIM(tabSuperdettagli[[#This Row],[Proj. Type ]])) | G3: =IF(OR(tabSuperdettagli[[#This Row],[ProjType_]]="C",tabSuperdettagli[[#This Row],[ProjType_]]="A",tabSuperdettagli[[#This Row],[ProjType_]]="R",tabSuperdettagli[[#This Row],[ProjType_]]="E"),"C A R E",IF(tabSuperdettagli[[#This Row],[ProjType_]]="U","U ("&tabSuperdettagli[[#This Row],[U ProjType_]]&")",tabSuperdettagli[[#This Row],[ProjType_]])) -> 5 | I3: Int | J3: =tabSuperdettagli[[#This Row],[07.2025]] -> 10 | K3: =tabSuperdettagli[[#This Row],[Resp del Prodotto]] -> 0 | L3: =tabSuperdettagli[[#This Row],[Area di bdg]] -> 0 | M3: =tabSuperdettagli[[#This Row],[Macchina]] -> 0 | N3: =tabSuperdettagli[[#This Row],[Sottotipo]] -> 0 | O3: =tabSuperdettagli[[#This Row],[Cluster]] -> 0 | P3: =tabSuperdettagli[[#This Row],[Quadrante]] -> 0 | Q3: =tabSuperdettagli[[#This Row],[01.2025]] -> 0 | R3: =tabSuperdettagli[[#This Row],[02.2025]] -> 0 | S3: =tabSuperdettagli[[#This Row],[03.2025]] -> 0 | T3: =tabSuperdettagli[[#This Row],[04.2025]] -> 0 | U3: =tabSuperdettagli[[#This Row],[05.2025]] -> 0 | V3: =tabSuperdettagli[[#This Row],[06.2025]] -> 84 | W3: =tabSuperdettagli[[#This Row],[PROJ CODE]] -> CONV NGP PLATFORM ENG | X3: =tabSuperdettagli[[#This Row],[Resp 2°liv]]&"" -> Gamberini G. | Y3: =INDEX(tab_resp1liv[EngUnit area cluster 1_],MATCH(SUBSTITUTE(tabSuperdettagli[[#This Row],[Resp 2°liv]]," ",""),tab_resp1liv[SearchKey],0)) -> #N/A | Z3: =tabSuperdettagli[[#This Row],[WBS Element]]&"" -> Go | AA3: =tabSuperdettagli[[#This Row],[09.2025]] -> 234 | AC3: =IF(tabSuperdettagli[[#This Row],[ProjType_]]="M",IF(AND(tabSuperdettagli[[#This Row],[Resp 1°liv_]]="Guidotti C.",tabSuperdettagli[[#This Row],[WBE description_]]="Machine Mgmt"),"Documentation",tabSuperdettagli[[#This Row],[WBE description_]]),"") | AD3: =LEFT(tabSuperdettagli[[#This Row],[Network]],18) -> 5447634 | AE3: C005RD234 | AF3: SMEI LUCA | AG3: pippo | AH3: FATTIBILITA' DEL 2025 TOBACCO | AI3: Go | AJ3: 5447634 | AK3: 2025 | AL3: LAYOUT - PROPOSTE E DEFINIZIONE | AM3: K005.00012 | AN3: Int. | AO3: CONV NGP PLATFORM ENG | AP3: Est. | AQ3: C005RD334 | AR3: Seren E. | AS3: Gamberini G. | AT3: LAY | AU3: TOB | AV3: TOB PK | AW3: K | AX3: FATTIBILITA' DEL 2025 TOBACCO | AY3: 345 | AZ3: CANALI E LAYOUT | BA3: Seren | BB3: LAYOUT | BC3: 84 | BD3: 0 | BE3: 0 | BF3: 0 | BG3: 0 | BH3: 0 | BI3: 0 | BJ3: 0 | BK3: 0 | BL3: 0 | BM3: 0 | BN3: 0 | BO3: 84 | BP3: 10 | BQ3: Proposte di layout | BR3: 234 | BS3: Seren E. | BT3: K | BU3: K005.00012.PAC.999 | BV3: sì | BZ3: OTHERS (1)
A4: =IF( UPPER(LEFT( tabSuperdettagli[[#This Row],[WBE Status]],1) ) = "S", "sì", "no" ) -> no | B4: 2020 | C4: =VLOOKUP(tabSuperdettagli[[#This Row],[WBS_]], 'pivot di appoggio'!A:B,2,FALSE) -> 2000 | D4: =LEFT(tabSuperdettagli[[#This Row],[Network]], 10) -> 5447634 | E4: =LEFT(tabSuperdettagli[[#This Row],[Network]], 1) -> 5 | F4: =LOWER(TRIM( tabSuperdettagli[[#This Row],[Proj. Type ]] )) | G4: =IF( OR( tabSuperdettagli[[#This Row],[ProjType_]]="C", tabSuperdettagli[[#This Row],[ProjType_]]="A", tabSuperdettagli[[#This Row],[ProjType_]]="R", tabSuperdettagli[[#This Row],[ProjType_]]="E"), "C A R E", IF( tabSuperdettagli[[#This Row],[ProjType_]]="U", "U (" & tabSuperdettagli[[#This Row],[U ProjType_]] & ")", tabSuperdettagli[[#This Row],[ProjType_]]) ) -> 5 | I4: =IF( TRIM(#REF!)> "", TRIM(#REF!), TRIM(tabSuperdettagli[[#This Row],[Resp DT]] ) ) -> #REF! | J4: =tabSuperdettagli[[#This Row],[07.2025]] -> 10 | K4: =tabSuperdettagli[[#This Row],[Resp del Prodotto]] -> 0 | L4: =tabSuperdettagli[[#This Row],[Area di bdg]] -> 0 | W4: =tabSuperdettagli[[#This Row],[PROJ CODE]] -> CONV NGP PLATFORM ENG | X4: =tabSuperdettagli[[#This Row],[Resp 2°liv]]&"" -> Gamberini G. | Y4: =INDEX( tab_resp1liv[EngUnit area cluster 1_], MATCH( SUBSTITUTE(tabSuperdettagli[[#This Row],[Resp 2°liv]], " ", ""), tab_resp1liv[SearchKey],0)) -> #N/A | Z4: =tabSuperdettagli[[#This Row],[WBS Element]]&"" -> Go | AA4: =tabSuperdettagli[[#This Row],[09.2025]] -> 234 | AC4: =IF( tabSuperdettagli[[#This Row],[ProjType_]]="M", IF( AND(tabSuperdettagli[[#This Row],[Resp 1°liv_]]="Guidotti C.", tabSuperdettagli[[#This Row],[WBE description_]]="Machine Mgmt"), "Documentation", tabSuperdettagli[[#This Row],[WBE description_]]), "" ) | AD4: =LEFT(tabSuperdettagli[[#This Row],[Network]], 18 ) -> 5447634 | AE4: C005RD234 | AF4: SMEI LUCA | AG4: pippo | AH4: FATTIBILITA' DEL 2025 TOBACCO | AI4: Go | AJ4: 5447634 | AK4: 2025 | AL4: LAYOUT - PROPOSTE E DEFINIZIONE | AM4: K005.00012 | AN4: Int. | AO4: CONV NGP PLATFORM ENG | AP4: Est. | AQ4: C005RD334 | AR4: Seren E. | AS4: Gamberini G. | AT4: LAY | AU4: TOB | AV4: TOB PK | AW4: K | AX4: FATTIBILITA' DEL 2025 TOBACCO | AY4: 345 | AZ4: CANALI E LAYOUT | BA4: Seren | BB4: LAYOUT | BC4: 84 | BD4: 0 | BE4: 0 | BF4: 0 | BG4: 0 | BH4: 0 | BI4: 0 | BJ4: 0 | BK4: 0 | BL4: 0 | BM4: 0 | BN4: 0 | BO4: 84 | BP4: 10 | BQ4: Proposte di layout | BR4: 234 | BS4: Seren E. | BT4: K | BU4: K005.00012.PAC.999 | BV4: sì | BZ4: OTHERS (1)
A5: =IF( UPPER(LEFT( tabSuperdettagli[[#This Row],[WBE Status]],1) ) = "S", "sì", "no" ) -> no | B5: 2020 | C5: =VLOOKUP(tabSuperdettagli[[#This Row],[WBS_]], 'pivot di appoggio'!A:B,2,FALSE) -> 2000 | D5: =LEFT(tabSuperdettagli[[#This Row],[Network]], 10) -> 5447634 | E5: =LEFT(tabSuperdettagli[[#This Row],[Network]], 1) -> 5 | F5: =LOWER(TRIM( tabSuperdettagli[[#This Row],[Proj. Type ]] )) | G5: =IF( OR( tabSuperdettagli[[#This Row],[ProjType_]]="C", tabSuperdettagli[[#This Row],[ProjType_]]="A", tabSuperdettagli[[#This Row],[ProjType_]]="R", tabSuperdettagli[[#This Row],[ProjType_]]="E"), "C A R E", IF( tabSuperdettagli[[#This Row],[ProjType_]]="U", "U (" & tabSuperdettagli[[#This Row],[U ProjType_]] & ")", tabSuperdettagli[[#This Row],[ProjType_]]) ) -> 5 | I5: =IF( TRIM(#REF!)> "", TRIM(#REF!), TRIM(tabSuperdettagli[[#This Row],[Resp DT]] ) ) -> #REF! | J5: =tabSuperdettagli[[#This Row],[07.2025]] -> 10 | K5: =tabSuperdettagli[[#This Row],[Resp del Prodotto]] -> 0 | L5: =tabSuperdettagli[[#This Row],[Area di bdg]] -> 0 | W5: =tabSuperdettagli[[#This Row],[PROJ CODE]] -> CONV NGP PLATFORM ENG | X5: =tabSuperdettagli[[#This Row],[Resp 2°liv]]&"" -> Gamberini G. | Y5: =INDEX( tab_resp1liv[EngUnit area cluster 1_], MATCH( SUBSTITUTE(tabSuperdettagli[[#This Row],[Resp 2°liv]], " ", ""), tab_resp1liv[SearchKey],0)) -> #N/A | Z5: =tabSuperdettagli[[#This Row],[WBS Element]]&"" -> Go | AA5: =tabSuperdettagli[[#This Row],[09.2025]] -> 234 | AC5: =IF( tabSuperdettagli[[#This Row],[ProjType_]]="M", IF( AND(tabSuperdettagli[[#This Row],[Resp 1°liv_]]="Guidotti C.", tabSuperdettagli[[#This Row],[WBE description_]]="Machine Mgmt"), "Documentation", tabSuperdettagli[[#This Row],[WBE description_]]), "" ) | AD5: =LEFT(tabSuperdettagli[[#This Row],[Network]], 18 ) -> 5447634 | AE5: C005RD234 | AF5: SMEI LUCA | AG5: pippo | AH5: FATTIBILITA' DEL 2025 TOBACCO | AI5: Go | AJ5: 5447634 | AK5: 2025 | AL5: LAYOUT - PROPOSTE E DEFINIZIONE | AM5: K005.00012 | AN5: Int. | AO5: CONV NGP PLATFORM ENG | AP5: Est. | AQ5: C005RD334 | AR5: Seren E. | AS5: Gamberini G. | AT5: LAY | AU5: TOB | AV5: TOB PK | AW5: K | AX5: FATTIBILITA' DEL 2025 TOBACCO | AY5: 345 | AZ5: CANALI E LAYOUT | BA5: Seren | BB5: LAYOUT | BC5: 84 | BD5: 0 | BE5: 0 | BF5: 0 | BG5: 0 | BH5: 0 | BI5: 0 | BJ5: 0 | BK5: 0 | BL5: 0 | BM5: 0 | BN5: 0 | BO5: 84 | BP5: 10 | BQ5: Proposte di layout | BR5: 234 | BS5: Seren E. | BT5: K | BU5: K005.00012.PAC.999 | BV5: sì | BZ5: OTHERS (1)
A6: =IF( UPPER(LEFT( tabSuperdettagli[[#This Row],[WBE Status]],1) ) = "S", "sì", "no" ) -> no | B6: 2021 | C6: =VLOOKUP(tabSuperdettagli[[#This Row],[WBS_]], 'pivot di appoggio'!A:B,2,FALSE) -> 2000 | D6: =LEFT(tabSuperdettagli[[#This Row],[Network]], 10) -> 5447634 | E6: =LEFT(tabSuperdettagli[[#This Row],[Network]], 1) -> 5 | F6: =LOWER(TRIM( tabSuperdettagli[[#This Row],[Proj. Type ]] )) | G6: =IF( OR( tabSuperdettagli[[#This Row],[ProjType_]]="C", tabSuperdettagli[[#This Row],[ProjType_]]="A", tabSuperdettagli[[#This Row],[ProjType_]]="R", tabSuperdettagli[[#This Row],[ProjType_]]="E"), "C A R E", IF( tabSuperdettagli[[#This Row],[ProjType_]]="U", "U (" & tabSuperdettagli[[#This Row],[U ProjType_]] & ")", tabSuperdettagli[[#This Row],[ProjType_]]) ) -> 5 | I6: =IF( TRIM(#REF!)> "", TRIM(#REF!), TRIM(tabSuperdettagli[[#This Row],[Resp DT]] ) ) -> #REF! | J6: =tabSuperdettagli[[#This Row],[07.2025]] -> 10 | K6: =tabSuperdettagli[[#This Row],[Resp del Prodotto]] -> 0 | L6: =tabSuperdettagli[[#This Row],[Area di bdg]] -> 0 | W6: =tabSuperdettagli[[#This Row],[PROJ CODE]] -> CONV NGP PLATFORM ENG | X6: =tabSuperdettagli[[#This Row],[Resp 2°liv]]&"" -> Gamberini G. | Y6: =INDEX( tab_resp1liv[EngUnit area cluster 1_], MATCH( SUBSTITUTE(tabSuperdettagli[[#This Row],[Resp 2°liv]], " ", ""), tab_resp1liv[SearchKey],0)) -> #N/A | Z6: =tabSuperdettagli[[#This Row],[WBS Element]]&"" -> Go | AA6: =tabSuperdettagli[[#This Row],[09.2025]] -> 234 | AC6: =IF( tabSuperdettagli[[#This Row],[ProjType_]]="M", IF( AND(tabSuperdettagli[[#This Row],[Resp 1°liv_]]="Guidotti C.", tabSuperdettagli[[#This Row],[WBE description_]]="Machine Mgmt"), "Documentation", tabSuperdettagli[[#This Row],[WBE description_]]), "" ) | AD6: =LEFT(tabSuperdettagli[[#This Row],[Network]], 18 ) -> 5447634 | AE6: C005RD234 | AF6: SMEI LUCA | AG6: pippo | AH6: FATTIBILITA' DEL 2025 TOBACCO | AI6: Go | AJ6: 5447634 | AK6: 2025 | AL6: LAYOUT - PROPOSTE E DEFINIZIONE | AM6: K005.00012 | AN6: Int. | AO6: CONV NGP PLATFORM ENG | AP6: Est. | AQ6: C005RD334 | AR6: Seren E. | AS6: Gamberini G. | AT6: LAY | AU6: TOB | AV6: TOB PK | AW6: K | AX6: FATTIBILITA' DEL 2025 TOBACCO | AY6: 345 | AZ6: CANALI E LAYOUT | BA6: Seren | BB6: LAYOUT | BC6: 84 | BD6: 0 | BE6: 0 | BF6: 0 | BG6: 0 | BH6: 0 | BI6: 0 | BJ6: 0 | BK6: 0 | BL6: 0 | BM6: 0 | BN6: 0 | BO6: 84 | BP6: 10 | BQ6: Proposte di layout | BR6: 234 | BS6: Seren E. | BT6: K | BU6: K005.00012.PAC.999 | BV6: sì | BZ6: OTHERS (1)
A7: =IF( UPPER(LEFT( tabSuperdettagli[[#This Row],[WBE Status]],1) ) = "S", "sì", "no" ) -> no | B7: 2021 | C7: =VLOOKUP(tabSuperdettagli[[#This Row],[WBS_]], 'pivot di appoggio'!A:B,2,FALSE) -> 2000 | D7: =LEFT(tabSuperdettagli[[#This Row],[Network]], 10) -> 5447634 | E7: =LEFT(tabSuperdettagli[[#This Row],[Network]], 1) -> 5 | F7: =LOWER(TRIM( tabSuperdettagli[[#This Row],[Proj. Type ]] )) | G7: =IF( OR( tabSuperdettagli[[#This Row],[ProjType_]]="C", tabSuperdettagli[[#This Row],[ProjType_]]="A", tabSuperdettagli[[#This Row],[ProjType_]]="R", tabSuperdettagli[[#This Row],[ProjType_]]="E"), "C A R E", IF( tabSuperdettagli[[#This Row],[ProjType_]]="U", "U (" & tabSuperdettagli[[#This Row],[U ProjType_]] & ")", tabSuperdettagli[[#This Row],[ProjType_]]) ) -> 5 | I7: =IF( TRIM(#REF!)> "", TRIM(#REF!), TRIM(tabSuperdettagli[[#This Row],[Resp DT]] ) ) -> #REF! | J7: =tabSuperdettagli[[#This Row],[07.2025]] -> 10 | K7: =tabSuperdettagli[[#This Row],[Resp del Prodotto]] -> 0 | L7: =tabSuperdettagli[[#This Row],[Area di bdg]] -> 0 | W7: =tabSuperdettagli[[#This Row],[PROJ CODE]] -> CONV NGP PLATFORM ENG | X7: =tabSuperdettagli[[#This Row],[Resp 2°liv]]&"" -> Gamberini G. | Y7: =INDEX( tab_resp1liv[EngUnit area cluster 1_], MATCH( SUBSTITUTE(tabSuperdettagli[[#This Row],[Resp 2°liv]], " ", ""), tab_resp1liv[SearchKey],0)) -> #N/A | Z7: =tabSuperdettagli[[#This Row],[WBS Element]]&"" -> Go | AA7: =tabSuperdettagli[[#This Row],[09.2025]] -> 234 | AC7: =IF( tabSuperdettagli[[#This Row],[ProjType_]]="M", IF( AND(tabSuperdettagli[[#This Row],[Resp 1°liv_]]="Guidotti C.", tabSuperdettagli[[#This Row],[WBE description_]]="Machine Mgmt"), "Documentation", tabSuperdettagli[[#This Row],[WBE description_]]), "" ) | AD7: =LEFT(tabSuperdettagli[[#This Row],[Network]], 18 ) -> 5447634 | AE7: C005RD234 | AF7: SMEI LUCA | AG7: pippo | AH7: FATTIBILITA' DEL 2025 TOBACCO | AI7: Go | AJ7: 5447634 | AK7: 2025 | AL7: LAYOUT - PROPOSTE E DEFINIZIONE | AM7: K005.00012 | AN7: Int. | AO7: CONV NGP PLATFORM ENG | AP7: Est. | AQ7: C005RD334 | AR7: Seren E. | AS7: Gamberini G. | AT7: LAY | AU7: TOB | AV7: TOB PK | AW7: K | AX7: FATTIBILITA' DEL 2025 TOBACCO | AY7: 345 | AZ7: CANALI E LAYOUT | BA7: Seren | BB7: LAYOUT | BC7: 84 | BD7: 0 | BE7: 0 | BF7: 0 | BG7: 0 | BH7: 0 | BI7: 0 | BJ7: 0 | BK7: 0 | BL7: 0 | BM7: 0 | BN7: 0 | BO7: 84 | BP7: 10 | BQ7: Proposte di layout | BR7: 234 | BS7: Seren E. | BT7: K | BU7: K005.00012.PAC.999 | BV7: sì | BZ7: OTHERS (1)
A8: =IF( UPPER(LEFT( tabSuperdettagli[[#This Row],[WBE Status]],1) ) = "S", "sì", "no" ) -> no | B8: 2025 | C8: =VLOOKUP(tabSuperdettagli[[#This Row],[WBS_]], 'pivot di appoggio'!A:B,2,FALSE) -> 2000 | D8: =LEFT(tabSuperdettagli[[#This Row],[Network]], 10) -> 5447634 | E8: =LEFT(tabSuperdettagli[[#This Row],[Network]], 1) -> 5 | F8: =LOWER(TRIM( tabSuperdettagli[[#This Row],[Proj. Type ]] )) | G8: =IF( OR( tabSuperdettagli[[#This Row],[ProjType_]]="C", tabSuperdettagli[[#This Row],[ProjType_]]="A", tabSuperdettagli[[#This Row],[ProjType_]]="R", tabSuperdettagli[[#This Row],[ProjType_]]="E"), "C A R E", IF( tabSuperdettagli[[#This Row],[ProjType_]]="U", "U (" & tabSuperdettagli[[#This Row],[U ProjType_]] & ")", tabSuperdettagli[[#This Row],[ProjType_]]) ) -> 5 | I8: =IF( TRIM(#REF!)> "", TRIM(#REF!), TRIM(tabSuperdettagli[[#This Row],[Resp DT]] ) ) -> #REF! | J8: =tabSuperdettagli[[#This Row],[07.2025]] -> 10 | K8: =tabSuperdettagli[[#This Row],[Resp del Prodotto]] -> 0 | L8: =tabSuperdettagli[[#This Row],[Area di bdg]] -> 0 | W8: =tabSuperdettagli[[#This Row],[PROJ CODE]] -> CONV NGP PLATFORM ENG | X8: =tabSuperdettagli[[#This Row],[Resp 2°liv]]&"" -> Gamberini G. | Y8: =INDEX( tab_resp1liv[EngUnit area cluster 1_], MATCH( SUBSTITUTE(tabSuperdettagli[[#This Row],[Resp 2°liv]], " ", ""), tab_resp1liv[SearchKey],0)) -> #N/A | Z8: =tabSuperdettagli[[#This Row],[WBS Element]]&"" -> Go | AA8: =tabSuperdettagli[[#This Row],[09.2025]] -> 234 | AC8: =IF( tabSuperdettagli[[#This Row],[ProjType_]]="M", IF( AND(tabSuperdettagli[[#This Row],[Resp 1°liv_]]="Guidotti C.", tabSuperdettagli[[#This Row],[WBE description_]]="Machine Mgmt"), "Documentation", tabSuperdettagli[[#This Row],[WBE description_]]), "" ) | AD8: =LEFT(tabSuperdettagli[[#This Row],[Network]], 18 ) -> 5447634 | AE8: C005RD234 | AF8: SMEI LUCA | AG8: pippo | AH8: FATTIBILITA' DEL 2025 TOBACCO | AI8: Go | AJ8: 5447634 | AK8: 2025 | AL8: LAYOUT - PROPOSTE E DEFINIZIONE | AM8: K005.00012 | AN8: Int. | AO8: CONV NGP PLATFORM ENG | AP8: Est. | AQ8: C005RD334 | AR8: Seren E. | AS8: Gamberini G. | AT8: LAY | AU8: TOB | AV8: TOB PK | AW8: K | AX8: FATTIBILITA' DEL 2025 TOBACCO | AY8: 345 | AZ8: CANALI E LAYOUT | BA8: Seren | BB8: LAYOUT | BC8: 84 | BD8: 0 | BE8: 0 | BF8: 0 | BG8: 0 | BH8: 0 | BI8: 0 | BJ8: 0 | BK8: 0 | BL8: 0 | BM8: 0 | BN8: 0 | BO8: 84 | BP8: 10 | BQ8: Proposte di layout | BR8: 234 | BS8: Seren E. | BT8: K | BU8: K005.00012.PAC.999 | BV8: sì | BZ8: OTHERS (1)
A9: =IF( UPPER(LEFT( tabSuperdettagli[[#This Row],[WBE Status]],1) ) = "S", "sì", "no" ) -> no | B9: 2025 | C9: =VLOOKUP(tabSuperdettagli[[#This Row],[WBS_]], 'pivot di appoggio'!A:B,2,FALSE) -> 2000 | D9: =LEFT(tabSuperdettagli[[#This Row],[Network]], 10) -> 5447634 | E9: =LEFT(tabSuperdettagli[[#This Row],[Network]], 1) -> 5 | F9: =LOWER(TRIM( tabSuperdettagli[[#This Row],[Proj. Type ]] )) | G9: =IF( OR( tabSuperdettagli[[#This Row],[ProjType_]]="C", tabSuperdettagli[[#This Row],[ProjType_]]="A", tabSuperdettagli[[#This Row],[ProjType_]]="R", tabSuperdettagli[[#This Row],[ProjType_]]="E"), "C A R E", IF( tabSuperdettagli[[#This Row],[ProjType_]]="U", "U (" & tabSuperdettagli[[#This Row],[U ProjType_]] & ")", tabSuperdettagli[[#This Row],[ProjType_]]) ) -> 5 | I9: =IF( TRIM(#REF!)> "", TRIM(#REF!), TRIM(tabSuperdettagli[[#This Row],[Resp DT]] ) ) -> #REF! | J9: =tabSuperdettagli[[#This Row],[07.2025]] -> 10 | K9: =tabSuperdettagli[[#This Row],[Resp del Prodotto]] -> 0 | L9: =tabSuperdettagli[[#This Row],[Area di bdg]] -> 0 | W9: =tabSuperdettagli[[#This Row],[PROJ CODE]] -> CONV NGP PLATFORM ENG | X9: =tabSuperdettagli[[#This Row],[Resp 2°liv]]&"" -> Gamberini G. | Y9: =INDEX( tab_resp1liv[EngUnit area cluster 1_], MATCH( SUBSTITUTE(tabSuperdettagli[[#This Row],[Resp 2°liv]], " ", ""), tab_resp1liv[SearchKey],0)) -> #N/A | Z9: =tabSuperdettagli[[#This Row],[WBS Element]]&"" -> Go | AA9: =tabSuperdettagli[[#This Row],[09.2025]] -> 234 | AC9: =IF( tabSuperdettagli[[#This Row],[ProjType_]]="M", IF( AND(tabSuperdettagli[[#This Row],[Resp 1°liv_]]="Guidotti C.", tabSuperdettagli[[#This Row],[WBE description_]]="Machine Mgmt"), "Documentation", tabSuperdettagli[[#This Row],[WBE description_]]), "" ) | AD9: =LEFT(tabSuperdettagli[[#This Row],[Network]], 18 ) -> 5447634 | AE9: C005RD234 | AF9: SMEI LUCA | AG9: pippo | AH9: FATTIBILITA' DEL 2025 TOBACCO | AI9: Go | AJ9: 5447634 | AK9: 2025 | AL9: LAYOUT - PROPOSTE E DEFINIZIONE | AM9: K005.00012 | AN9: Int. | AO9: CONV NGP PLATFORM ENG | AP9: Est. | AQ9: C005RD334 | AR9: Seren E. | AS9: Gamberini G. | AT9: LAY | AU9: TOB | AV9: TOB PK | AW9: K | AX9: FATTIBILITA' DEL 2025 TOBACCO | AY9: 345 | AZ9: CANALI E LAYOUT | BA9: Seren | BB9: LAYOUT | BC9: 84 | BD9: 0 | BE9: 0 | BF9: 0 | BG9: 0 | BH9: 0 | BI9: 0 | BJ9: 0 | BK9: 0 | BL9: 0 | BM9: 0 | BN9: 0 | BO9: 84 | BP9: 10 | BQ9: Proposte di layout | BR9: 234 | BS9: Seren E. | BT9: K | BU9: K005.00012.PAC.999 | BV9: sì | BZ9: OTHERS (1)
A10: =IF( UPPER(LEFT( tabSuperdettagli[[#This Row],[WBE Status]],1) ) = "S", "sì", "no" ) -> no | B10: 2025 | C10: =VLOOKUP(tabSuperdettagli[[#This Row],[WBS_]], 'pivot di appoggio'!A:B,2,FALSE) -> 2000 | D10: =LEFT(tabSuperdettagli[[#This Row],[Network]], 10) -> 5447634 | E10: =LEFT(tabSuperdettagli[[#This Row],[Network]], 1) -> 5 | F10: =LOWER(TRIM( tabSuperdettagli[[#This Row],[Proj. Type ]] )) | G10: =IF( OR( tabSuperdettagli[[#This Row],[ProjType_]]="C", tabSuperdettagli[[#This Row],[ProjType_]]="A", tabSuperdettagli[[#This Row],[ProjType_]]="R", tabSuperdettagli[[#This Row],[ProjType_]]="E"), "C A R E", IF( tabSuperdettagli[[#This Row],[ProjType_]]="U", "U (" & tabSuperdettagli[[#This Row],[U ProjType_]] & ")", tabSuperdettagli[[#This Row],[ProjType_]]) ) -> 5 | I10: =IF( TRIM(#REF!)> "", TRIM(#REF!), TRIM(tabSuperdettagli[[#This Row],[Resp DT]] ) ) -> #REF! | J10: =tabSuperdettagli[[#This Row],[07.2025]] -> 10 | K10: =tabSuperdettagli[[#This Row],[Resp del Prodotto]] -> 0 | L10: =tabSuperdettagli[[#This Row],[Area di bdg]] -> 0 | W10: =tabSuperdettagli[[#This Row],[PROJ CODE]] -> CONV NGP PLATFORM ENG | X10: =tabSuperdettagli[[#This Row],[Resp 2°liv]]&"" -> Gamberini G. | Y10: =INDEX( tab_resp1liv[EngUnit area cluster 1_], MATCH( SUBSTITUTE(tabSuperdettagli[[#This Row],[Resp 2°liv]], " ", ""), tab_resp1liv[SearchKey],0)) -> #N/A | Z10: =tabSuperdettagli[[#This Row],[WBS Element]]&"" -> Go | AA10: =tabSuperdettagli[[#This Row],[09.2025]] -> 234 | AC10: =IF( tabSuperdettagli[[#This Row],[ProjType_]]="M", IF( AND(tabSuperdettagli[[#This Row],[Resp 1°liv_]]="Guidotti C.", tabSuperdettagli[[#This Row],[WBE description_]]="Machine Mgmt"), "Documentation", tabSuperdettagli[[#This Row],[WBE description_]]), "" ) | AD10: =LEFT(tabSuperdettagli[[#This Row],[Network]], 18 ) -> 5447634 | AE10: C005RD234 | AF10: SMEI LUCA | AG10: pippo | AH10: FATTIBILITA' DEL 2025 TOBACCO | AI10: Go | AJ10: 5447634 | AK10: 2025 | AL10: LAYOUT - PROPOSTE E DEFINIZIONE | AM10: K005.00012 | AN10: Int. | AO10: CONV NGP PLATFORM ENG | AP10: Est. | AQ10: C005RD334 | AR10: Seren E. | AS10: Gamberini G. | AT10: LAY | AU10: TOB | AV10: TOB PK | AW10: K | AX10: FATTIBILITA' DEL 2025 TOBACCO | AY10: 345 | AZ10: CANALI E LAYOUT | BA10: Seren | BB10: LAYOUT | BC10: 84 | BD10: 0 | BE10: 0 | BF10: 0 | BG10: 0 | BH10: 0 | BI10: 0 | BJ10: 0 | BK10: 0 | BL10: 0 | BM10: 0 | BN10: 0 | BO10: 84 | BP10: 10 | BQ10: Proposte di layout | BR10: 234 | BS10: Seren E. | BT10: K | BU10: K005.00012.PAC.999 | BV10: sì | BZ10: OTHERS (1)
A11: =IF( UPPER(LEFT( tabSuperdettagli[[#This Row],[WBE Status]],1) ) = "S", "sì", "no" ) -> no | B11: 2025 | C11: =VLOOKUP(tabSuperdettagli[[#This Row],[WBS_]], 'pivot di appoggio'!A:B,2,FALSE) -> 2000 | D11: =LEFT(tabSuperdettagli[[#This Row],[Network]], 10) -> 5447634 | E11: =LEFT(tabSuperdettagli[[#This Row],[Network]], 1) -> 5 | F11: =LOWER(TRIM( tabSuperdettagli[[#This Row],[Proj. Type ]] )) | G11: =IF( OR( tabSuperdettagli[[#This Row],[ProjType_]]="C", tabSuperdettagli[[#This Row],[ProjType_]]="A", tabSuperdettagli[[#This Row],[ProjType_]]="R", tabSuperdettagli[[#This Row],[ProjType_]]="E"), "C A R E", IF( tabSuperdettagli[[#This Row],[ProjType_]]="U", "U (" & tabSuperdettagli[[#This Row],[U ProjType_]] & ")", tabSuperdettagli[[#This Row],[ProjType_]]) ) -> 5 | I11: =IF( TRIM(#REF!)> "", TRIM(#REF!), TRIM(tabSuperdettagli[[#This Row],[Resp DT]] ) ) -> #REF! | J11: =tabSuperdettagli[[#This Row],[07.2025]] -> 10 | K11: =tabSuperdettagli[[#This Row],[Resp del Prodotto]] -> 0 | L11: =tabSuperdettagli[[#This Row],[Area di bdg]] -> 0 | W11: =tabSuperdettagli[[#This Row],[PROJ CODE]] -> CONV NGP PLATFORM ENG | X11: =tabSuperdettagli[[#This Row],[Resp 2°liv]]&"" -> Gamberini G. | Y11: =INDEX( tab_resp1liv[EngUnit area cluster 1_], MATCH( SUBSTITUTE(tabSuperdettagli[[#This Row],[Resp 2°liv]], " ", ""), tab_resp1liv[SearchKey],0)) -> #N/A | Z11: =tabSuperdettagli[[#This Row],[WBS Element]]&"" -> Go | AA11: =tabSuperdettagli[[#This Row],[09.2025]] -> 234 | AC11: =IF( tabSuperdettagli[[#This Row],[ProjType_]]="M", IF( AND(tabSuperdettagli[[#This Row],[Resp 1°liv_]]="Guidotti C.", tabSuperdettagli[[#This Row],[WBE description_]]="Machine Mgmt"), "Documentation", tabSuperdettagli[[#This Row],[WBE description_]]), "" ) | AD11: =LEFT(tabSuperdettagli[[#This Row],[Network]], 18 ) -> 5447634 | AE11: C005RD234 | AF11: SMEI LUCA | AG11: pippo | AH11: FATTIBILITA' DEL 2025 TOBACCO | AI11: Go | AJ11: 5447634 | AK11: 2025 | AL11: LAYOUT - PROPOSTE E DEFINIZIONE | AM11: K005.00012 | AN11: Int. | AO11: CONV NGP PLATFORM ENG | AP11: Est. | AQ11: C005RD334 | AR11: Seren E. | AS11: Gamberini G. | AT11: LAY | AU11: TOB | AV11: TOB PK | AW11: K | AX11: FATTIBILITA' DEL 2025 TOBACCO | AY11: 345 | AZ11: CANALI E LAYOUT | BA11: Seren | BB11: LAYOUT | BC11: 84 | BD11: 0 | BE11: 0 | BF11: 0 | BG11: 0 | BH11: 0 | BI11: 0 | BJ11: 0 | BK11: 0 | BL11: 0 | BM11: 0 | BN11: 0 | BO11: 84 | BP11: 10 | BQ11: Proposte di layout | BR11: 234 | BS11: Seren E. | BT11: K | BU11: K005.00012.PAC.999 | BV11: sì | BZ11: OTHERS (1)
A12: =IF( UPPER(LEFT( tabSuperdettagli[[#This Row],[WBE Status]],1) ) = "S", "sì", "no" ) -> no | B12: 2025 | C12: =VLOOKUP(tabSuperdettagli[[#This Row],[WBS_]], 'pivot di appoggio'!A:B,2,FALSE) -> 2000 | D12: =LEFT(tabSuperdettagli[[#This Row],[Network]], 10) -> 5447634 | E12: =LEFT(tabSuperdettagli[[#This Row],[Network]], 1) -> 5 | F12: =LOWER(TRIM( tabSuperdettagli[[#This Row],[Proj. Type ]] )) | G12: =IF( OR( tabSuperdettagli[[#This Row],[ProjType_]]="C", tabSuperdettagli[[#This Row],[ProjType_]]="A", tabSuperdettagli[[#This Row],[ProjType_]]="R", tabSuperdettagli[[#This Row],[ProjType_]]="E"), "C A R E", IF( tabSuperdettagli[[#This Row],[ProjType_]]="U", "U (" & tabSuperdettagli[[#This Row],[U ProjType_]] & ")", tabSuperdettagli[[#This Row],[ProjType_]]) ) -> 5 | I12: =IF( TRIM(#REF!)> "", TRIM(#REF!), TRIM(tabSuperdettagli[[#This Row],[Resp DT]] ) ) -> #REF! | J12: =tabSuperdettagli[[#This Row],[07.2025]] -> 10 | K12: =tabSuperdettagli[[#This Row],[Resp del Prodotto]] -> 0 | L12: =tabSuperdettagli[[#This Row],[Area di bdg]] -> 0 | W12: =tabSuperdettagli[[#This Row],[PROJ CODE]] -> CONV NGP PLATFORM ENG | X12: =tabSuperdettagli[[#This Row],[Resp 2°liv]]&"" -> Gamberini G. | Y12: =INDEX( tab_resp1liv[EngUnit area cluster 1_], MATCH( SUBSTITUTE(tabSuperdettagli[[#This Row],[Resp 2°liv]], " ", ""), tab_resp1liv[SearchKey],0)) -> #N/A | Z12: =tabSuperdettagli[[#This Row],[WBS Element]]&"" -> Go | AA12: =tabSuperdettagli[[#This Row],[09.2025]] -> 234 | AC12: =IF( tabSuperdettagli[[#This Row],[ProjType_]]="M", IF( AND(tabSuperdettagli[[#This Row],[Resp 1°liv_]]="Guidotti C.", tabSuperdettagli[[#This Row],[WBE description_]]="Machine Mgmt"), "Documentation", tabSuperdettagli[[#This Row],[WBE description_]]), "" ) | AD12: =LEFT(tabSuperdettagli[[#This Row],[Network]], 18 ) -> 5447634 | AE12: C005RD234 | AF12: SMEI LUCA | AG12: pippo | AH12: FATTIBILITA' DEL 2025 TOBACCO | AI12: Go | AJ12: 5447634 | AK12: 2025 | AL12: LAYOUT - PROPOSTE E DEFINIZIONE | AM12: K005.00012 | AN12: Int. | AO12: CONV NGP PLATFORM ENG | AP12: Est. | AQ12: C005RD334 | AR12: Seren E. | AS12: Gamberini G. | AT12: LAY | AU12: TOB | AV12: TOB PK | AW12: K | AX12: FATTIBILITA' DEL 2025 TOBACCO | AY12: 345 | AZ12: CANALI E LAYOUT | BA12: Seren | BB12: LAYOUT | BC12: 84 | BD12: 0 | BE12: 0 | BF12: 0 | BG12: 0 | BH12: 0 | BI12: 0 | BJ12: 0 | BK12: 0 | BL12: 0 | BM12: 0 | BN12: 0 | BO12: 84 | BP12: 10 | BQ12: Proposte di layout | BR12: 234 | BS12: Seren E. | BT12: K | BU12: K005.00012.PAC.999 | BV12: sì | BZ12: OTHERS (1)
A13: =IF( UPPER(LEFT( tabSuperdettagli[[#This Row],[WBE Status]],1) ) = "S", "sì", "no" ) -> no | B13: 2025 | C13: =VLOOKUP(tabSuperdettagli[[#This Row],[WBS_]], 'pivot di appoggio'!A:B,2,FALSE) -> 2000 | D13: =LEFT(tabSuperdettagli[[#This Row],[Network]], 10) -> 5447634 | E13: =LEFT(tabSuperdettagli[[#This Row],[Network]], 1) -> 5 | F13: =LOWER(TRIM( tabSuperdettagli[[#This Row],[Proj. Type ]] )) | G13: =IF( OR( tabSuperdettagli[[#This Row],[ProjType_]]="C", tabSuperdettagli[[#This Row],[ProjType_]]="A", tabSuperdettagli[[#This Row],[ProjType_]]="R", tabSuperdettagli[[#This Row],[ProjType_]]="E"), "C A R E", IF( tabSuperdettagli[[#This Row],[ProjType_]]="U", "U (" & tabSuperdettagli[[#This Row],[U ProjType_]] & ")", tabSuperdettagli[[#This Row],[ProjType_]]) ) -> 5 | I13: =IF( TRIM(#REF!)> "", TRIM(#REF!), TRIM(tabSuperdettagli[[#This Row],[Resp DT]] ) ) -> #REF! | J13: =tabSuperdettagli[[#This Row],[07.2025]] -> 10 | K13: =tabSuperdettagli[[#This Row],[Resp del Prodotto]] -> 0 | L13: =tabSuperdettagli[[#This Row],[Area di bdg]] -> 0 | W13: =tabSuperdettagli[[#This Row],[PROJ CODE]] -> CONV NGP PLATFORM ENG | X13: =tabSuperdettagli[[#This Row],[Resp 2°liv]]&"" -> Gamberini G. | Y13: =INDEX( tab_resp1liv[EngUnit area cluster 1_], MATCH( SUBSTITUTE(tabSuperdettagli[[#This Row],[Resp 2°liv]], " ", ""), tab_resp1liv[SearchKey],0)) -> #N/A | Z13: =tabSuperdettagli[[#This Row],[WBS Element]]&"" -> Go | AA13: =tabSuperdettagli[[#This Row],[09.2025]] -> 234 | AC13: =IF( tabSuperdettagli[[#This Row],[ProjType_]]="M", IF( AND(tabSuperdettagli[[#This Row],[Resp 1°liv_]]="Guidotti C.", tabSuperdettagli[[#This Row],[WBE description_]]="Machine Mgmt"), "Documentation", tabSuperdettagli[[#This Row],[WBE description_]]), "" ) | AD13: =LEFT(tabSuperdettagli[[#This Row],[Network]], 18 ) -> 5447634 | AE13: C005RD234 | AF13: SMEI LUCA | AG13: pippo | AH13: FATTIBILITA' DEL 2025 TOBACCO | AI13: Go | AJ13: 5447634 | AK13: 2025 | AL13: LAYOUT - PROPOSTE E DEFINIZIONE | AM13: K005.00012 | AN13: Int. | AO13: CONV NGP PLATFORM ENG | AP13: Est. | AQ13: C005RD334 | AR13: Seren E. | AS13: Gamberini G. | AT13: LAY | AU13: TOB | AV13: TOB PK | AW13: K | AX13: FATTIBILITA' DEL 2025 TOBACCO | AY13: 345 | AZ13: CANALI E LAYOUT | BA13: Seren | BB13: LAYOUT | BC13: 84 | BD13: 0 | BE13: 0 | BF13: 0 | BG13: 0 | BH13: 0 | BI13: 0 | BJ13: 0 | BK13: 0 | BL13: 0 | BM13: 0 | BN13: 0 | BO13: 84 | BP13: 10 | BQ13: Proposte di layout | BR13: 234 | BS13: Seren E. | BT13: K | BU13: K005.00012.PAC.999 | BV13: sì | BZ13: OTHERS (1)
A14: =IF( UPPER(LEFT( tabSuperdettagli[[#This Row],[WBE Status]],1) ) = "S", "sì", "no" ) -> no | B14: 2025 | C14: =VLOOKUP(tabSuperdettagli[[#This Row],[WBS_]], 'pivot di appoggio'!A:B,2,FALSE) -> 2000 | D14: =LEFT(tabSuperdettagli[[#This Row],[Network]], 10) -> 5447634 | E14: =LEFT(tabSuperdettagli[[#This Row],[Network]], 1) -> 5 | F14: =LOWER(TRIM( tabSuperdettagli[[#This Row],[Proj. Type ]] )) | G14: =IF( OR( tabSuperdettagli[[#This Row],[ProjType_]]="C", tabSuperdettagli[[#This Row],[ProjType_]]="A", tabSuperdettagli[[#This Row],[ProjType_]]="R", tabSuperdettagli[[#This Row],[ProjType_]]="E"), "C A R E", IF( tabSuperdettagli[[#This Row],[ProjType_]]="U", "U (" & tabSuperdettagli[[#This Row],[U ProjType_]] & ")", tabSuperdettagli[[#This Row],[ProjType_]]) ) -> 5 | I14: =IF( TRIM(#REF!)> "", TRIM(#REF!), TRIM(tabSuperdettagli[[#This Row],[Resp DT]] ) ) -> #REF! | J14: =tabSuperdettagli[[#This Row],[07.2025]] -> 10 | K14: =tabSuperdettagli[[#This Row],[Resp del Prodotto]] -> 0 | L14: =tabSuperdettagli[[#This Row],[Area di bdg]] -> 0 | W14: =tabSuperdettagli[[#This Row],[PROJ CODE]] -> CONV NGP PLATFORM ENG | X14: =tabSuperdettagli[[#This Row],[Resp 2°liv]]&"" -> Gamberini G. | Y14: =INDEX( tab_resp1liv[EngUnit area cluster 1_], MATCH( SUBSTITUTE(tabSuperdettagli[[#This Row],[Resp 2°liv]], " ", ""), tab_resp1liv[SearchKey],0)) -> #N/A | Z14: =tabSuperdettagli[[#This Row],[WBS Element]]&"" -> Go | AA14: =tabSuperdettagli[[#This Row],[09.2025]] -> 234 | AC14: =IF( tabSuperdettagli[[#This Row],[ProjType_]]="M", IF( AND(tabSuperdettagli[[#This Row],[Resp 1°liv_]]="Guidotti C.", tabSuperdettagli[[#This Row],[WBE description_]]="Machine Mgmt"), "Documentation", tabSuperdettagli[[#This Row],[WBE description_]]), "" ) | AD14: =LEFT(tabSuperdettagli[[#This Row],[Network]], 18 ) -> 5447634 | AE14: C005RD234 | AF14: SMEI LUCA | AG14: pippo | AH14: FATTIBILITA' DEL 2025 TOBACCO | AI14: Go | AJ14: 5447634 | AK14: 2025 | AL14: LAYOUT - PROPOSTE E DEFINIZIONE | AM14: K005.00012 | AN14: Int. | AO14: CONV NGP PLATFORM ENG | AP14: Est. | AQ14: C005RD334 | AR14: Seren E. | AS14: Gamberini G. | AT14: LAY | AU14: TOB | AV14: TOB PK | AW14: K | AX14: FATTIBILITA' DEL 2025 TOBACCO | AY14: 345 | AZ14: CANALI E LAYOUT | BA14: Seren | BB14: LAYOUT | BC14: 84 | BD14: 0 | BE14: 0 | BF14: 0 | BG14: 0 | BH14: 0 | BI14: 0 | BJ14: 0 | BK14: 0 | BL14: 0 | BM14: 0 | BN14: 0 | BO14: 84 | BP14: 10 | BQ14: Proposte di layout | BR14: 234 | BS14: Seren E. | BT14: K | BU14: K005.00012.PAC.999 | BV14: sì | BZ14: OTHERS (1)
A15: =IF( UPPER(LEFT( tabSuperdettagli[[#This Row],[WBE Status]],1) ) = "S", "sì", "no" ) -> no | B15: 2025 | C15: =VLOOKUP(tabSuperdettagli[[#This Row],[WBS_]], 'pivot di appoggio'!A:B,2,FALSE) -> 2000 | D15: =LEFT(tabSuperdettagli[[#This Row],[Network]], 10) -> 5447634 | E15: =LEFT(tabSuperdettagli[[#This Row],[Network]], 1) -> 5 | F15: =LOWER(TRIM( tabSuperdettagli[[#This Row],[Proj. Type ]] )) | G15: =IF( OR( tabSuperdettagli[[#This Row],[ProjType_]]="C", tabSuperdettagli[[#This Row],[ProjType_]]="A", tabSuperdettagli[[#This Row],[ProjType_]]="R", tabSuperdettagli[[#This Row],[ProjType_]]="E"), "C A R E", IF( tabSuperdettagli[[#This Row],[ProjType_]]="U", "U (" & tabSuperdettagli[[#This Row],[U ProjType_]] & ")", tabSuperdettagli[[#This Row],[ProjType_]]) ) -> 5 | I15: =IF( TRIM(#REF!)> "", TRIM(#REF!), TRIM(tabSuperdettagli[[#This Row],[Resp DT]] ) ) -> #REF! | J15: =tabSuperdettagli[[#This Row],[07.2025]] -> 10 | K15: =tabSuperdettagli[[#This Row],[Resp del Prodotto]] -> 0 | L15: =tabSuperdettagli[[#This Row],[Area di bdg]] -> 0 | W15: =tabSuperdettagli[[#This Row],[PROJ CODE]] -> CONV NGP PLATFORM ENG | X15: =tabSuperdettagli[[#This Row],[Resp 2°liv]]&"" -> Gamberini G. | Y15: =INDEX( tab_resp1liv[EngUnit area cluster 1_], MATCH( SUBSTITUTE(tabSuperdettagli[[#This Row],[Resp 2°liv]], " ", ""), tab_resp1liv[SearchKey],0)) -> #N/A | Z15: =tabSuperdettagli[[#This Row],[WBS Element]]&"" -> Go | AA15: =tabSuperdettagli[[#This Row],[09.2025]] -> 234 | AC15: =IF( tabSuperdettagli[[#This Row],[ProjType_]]="M", IF( AND(tabSuperdettagli[[#This Row],[Resp 1°liv_]]="Guidotti C.", tabSuperdettagli[[#This Row],[WBE description_]]="Machine Mgmt"), "Documentation", tabSuperdettagli[[#This Row],[WBE description_]]), "" ) | AD15: =LEFT(tabSuperdettagli[[#This Row],[Network]], 18 ) -> 5447634 | AE15: C005RD234 | AF15: SMEI LUCA | AG15: pippo | AH15: FATTIBILITA' DEL 2025 TOBACCO | AI15: Go | AJ15: 5447634 | AK15: 2025 | AL15: LAYOUT - PROPOSTE E DEFINIZIONE | AM15: K005.00012 | AN15: Int. | AO15: CONV NGP PLATFORM ENG | AP15: Est. | AQ15: C005RD334 | AR15: Seren E. | AS15: Gamberini G. | AT15: LAY | AU15: TOB | AV15: TOB PK | AW15: K | AX15: FATTIBILITA' DEL 2025 TOBACCO | AY15: 345 | AZ15: CANALI E LAYOUT | BA15: Seren | BB15: LAYOUT | BC15: 84 | BD15: 0 | BE15: 0 | BF15: 0 | BG15: 0 | BH15: 0 | BI15: 0 | BJ15: 0 | BK15: 0 | BL15: 0 | BM15: 0 | BN15: 0 | BO15: 84 | BP15: 10 | BQ15: Proposte di layout | BR15: 234 | BS15: Seren E. | BT15: K | BU15: K005.00012.PAC.999 | BV15: sì | BZ15: OTHERS (1)
... A26: =IF( UPPER(LEFT( tabSuperdettagli[[#This Row],[WBE Status]],1) ) = "S", "sì", "no" ) -> no | B26: 2025 | C26: =VLOOKUP(tabSuperdettagli[[#This Row],[WBS_]], 'pivot di appoggio'!A:B,2,FALSE) -> 2000 | D26: =LEFT(tabSuperdettagli[[#This Row],[Network]], 10) -> 5447634 | E26: =LEFT(tabSuperdettagli[[#This Row],[Network]], 1) -> 5 | F26: =LOWER(TRIM( tabSuperdettagli[[#This Row],[Proj. Type ]] )) | G26: =IF( OR( tabSuperdettagli[[#This Row],[ProjType_]]="C", tabSuperdettagli[[#This Row],[ProjType_]]="A", tabSuperdettagli[[#This Row],[ProjType_]]="R", tabSuperdettagli[[#This Row],[ProjType_]]="E"), "C A R E", IF( tabSuperdettagli[[#This Row],[ProjType_]]="U", "U (" & tabSuperdettagli[[#This Row],[U ProjType_]] & ")", tabSuperdettagli[[#This Row],[ProjType_]]) ) -> 5 | I26: =IF( TRIM(#REF!)> "", TRIM(#REF!), TRIM(tabSuperdettagli[[#This Row],[Resp DT]] ) ) -> #REF! | J26: =tabSuperdettagli[[#This Row],[07.2025]] -> 10 | K26: =tabSuperdettagli[[#This Row],[Resp del Prodotto]] -> 0 | L26: =tabSuperdettagli[[#This Row],[Area di bdg]] -> 0 | W26: =tabSuperdettagli[[#This Row],[PROJ CODE]] -> CONV NGP PLATFORM ENG | X26: =tabSuperdettagli[[#This Row],[Resp 2°liv]]&"" -> Gamberini G. | Y26: =INDEX( tab_resp1liv[EngUnit area cluster 1_], MATCH( SUBSTITUTE(tabSuperdettagli[[#This Row],[Resp 2°liv]], " ", ""), tab_resp1liv[SearchKey],0)) -> #N/A | Z26: =tabSuperdettagli[[#This Row],[WBS Element]]&"" -> Go | AA26: =tabSuperdettagli[[#This Row],[09.2025]] -> 234 | AC26: =IF( tabSuperdettagli[[#This Row],[ProjType_]]="M", IF( AND(tabSuperdettagli[[#This Row],[Resp 1°liv_]]="Guidotti C.", tabSuperdettagli[[#This Row],[WBE description_]]="Machine Mgmt"), "Documentation", tabSuperdettagli[[#This Row],[WBE description_]]), "" ) | AD26: =LEFT(tabSuperdettagli[[#This Row],[Network]], 18 ) -> 5447634 | AE26: C005RD234 | AF26: SMEI LUCA | AG26: pippo | AH26: FATTIBILITA' DEL 2025 TOBACCO | AI26: Go | AJ26: 5447634 | AK26: 2025 | AL26: LAYOUT - PROPOSTE E DEFINIZIONE | AM26: K005.00012 | AN26: Int. | AO26: CONV NGP PLATFORM ENG | AP26: Est. | AQ26: C005RD334 | AR26: Seren E. | AS26: Gamberini G. | AT26: LAY | AU26: TOB | AV26: TOB PK | AW26: K | AX26: FATTIBILITA' DEL 2025 TOBACCO | AY26: 345 | AZ26: CANALI E LAYOUT | BA26: Seren | BB26: LAYOUT | BC26: 84 | BD26: 0 | BE26: 0 | BF26: 0 | BG26: 0 | BH26: 0 | BI26: 0 | BJ26: 0 | BK26: 0 | BL26: 0 | BM26: 0 | BN26: 0 | BO26: 84 | BP26: 10 | BQ26: Proposte di layout | BR26: 234 | BS26: Seren E. | BT26: K | BU26: K005.00012.PAC.999 | BV26: sì | BZ26: OTHERS (1)
A27: =IF( UPPER(LEFT( tabSuperdettagli[[#This Row],[WBE Status]],1) ) = "S", "sì", "no" ) -> no | B27: 2025 | C27: =VLOOKUP(tabSuperdettagli[[#This Row],[WBS_]], 'pivot di appoggio'!A:B,2,FALSE) -> 2000 | D27: =LEFT(tabSuperdettagli[[#This Row],[Network]], 10) -> 5447634 | E27: =LEFT(tabSuperdettagli[[#This Row],[Network]], 1) -> 5 | F27: =LOWER(TRIM( tabSuperdettagli[[#This Row],[Proj. Type ]] )) | G27: =IF( OR( tabSuperdettagli[[#This Row],[ProjType_]]="C", tabSuperdettagli[[#This Row],[ProjType_]]="A", tabSuperdettagli[[#This Row],[ProjType_]]="R", tabSuperdettagli[[#This Row],[ProjType_]]="E"), "C A R E", IF( tabSuperdettagli[[#This Row],[ProjType_]]="U", "U (" & tabSuperdettagli[[#This Row],[U ProjType_]] & ")", tabSuperdettagli[[#This Row],[ProjType_]]) ) -> 5 | I27: Int | J27: =tabSuperdettagli[[#This Row],[07.2025]] -> 10 | K27: =tabSuperdettagli[[#This Row],[Resp del Prodotto]] -> 0 | L27: =tabSuperdettagli[[#This Row],[Area di bdg]] -> 0 | W27: =tabSuperdettagli[[#This Row],[PROJ CODE]] -> CONV NGP PLATFORM ENG | X27: =tabSuperdettagli[[#This Row],[Resp 2°liv]]&"" -> Gamberini G. | Y27: =INDEX( tab_resp1liv[EngUnit area cluster 1_], MATCH( SUBSTITUTE(tabSuperdettagli[[#This Row],[Resp 2°liv]], " ", ""), tab_resp1liv[SearchKey],0)) -> #N/A | Z27: =tabSuperdettagli[[#This Row],[WBS Element]]&"" -> Go | AA27: =tabSuperdettagli[[#This Row],[09.2025]] -> 234 | AC27: =IF( tabSuperdettagli[[#This Row],[ProjType_]]="M", IF( AND(tabSuperdettagli[[#This Row],[Resp 1°liv_]]="Guidotti C.", tabSuperdettagli[[#This Row],[WBE description_]]="Machine Mgmt"), "Documentation", tabSuperdettagli[[#This Row],[WBE description_]]), "" ) | AD27: =LEFT(tabSuperdettagli[[#This Row],[Network]], 18 ) -> 5447634 | AE27: C005RD234 | AF27: SMEI LUCA | AG27: pippo | AH27: FATTIBILITA' DEL 2025 TOBACCO | AI27: Go | AJ27: 5447634 | AK27: 2025 | AL27: LAYOUT - PROPOSTE E DEFINIZIONE | AM27: K005.00012 | AN27: Int. | AO27: CONV NGP PLATFORM ENG | AP27: Est. | AQ27: C005RD334 | AR27: Seren E. | AS27: Gamberini G. | AT27: LAY | AU27: TOB | AV27: TOB PK | AW27: K | AX27: FATTIBILITA' DEL 2025 TOBACCO | AY27: 345 | AZ27: CANALI E LAYOUT | BA27: Seren | BB27: LAYOUT | BC27: 84 | BD27: 0 | BE27: 0 | BF27: 0 | BG27: 0 | BH27: 0 | BI27: 0 | BJ27: 0 | BK27: 0 | BL27: 0 | BM27: 0 | BN27: 0 | BO27: 84 | BP27: 10 | BQ27: Proposte di layout | BR27: 234 | BS27: Seren E. | BT27: K | BU27: K005.00012.PAC.999 | BV27: sì | BZ27: OTHERS (1)
A28: =IF(UPPER(LEFT(tabSuperdettagli[[#This Row],[WBE Status]],1))="S","sì","no") -> no | B28: 2025 | C28: =VLOOKUP(tabSuperdettagli[[#This Row],[WBS_]], 'pivot di appoggio'!A:B,2,FALSE) -> 2000 | D28: =LEFT(tabSuperdettagli[[#This Row],[Network]],10) -> 5447634 | E28: =LEFT(tabSuperdettagli[[#This Row],[Network]],1) -> 5 | F28: =LOWER(TRIM(tabSuperdettagli[[#This Row],[Proj. Type ]])) | G28: =IF(OR(tabSuperdettagli[[#This Row],[ProjType_]]="C",tabSuperdettagli[[#This Row],[ProjType_]]="A",tabSuperdettagli[[#This Row],[ProjType_]]="R",tabSuperdettagli[[#This Row],[ProjType_]]="E"),"C A R E",IF(tabSuperdettagli[[#This Row],[ProjType_]]="U","U ("&tabSuperdettagli[[#This Row],[U ProjType_]]&")",tabSuperdettagli[[#This Row],[ProjType_]])) -> 5 | I28: Int | J28: =tabSuperdettagli[[#This Row],[07.2025]] -> 10 | K28: =tabSuperdettagli[[#This Row],[Resp del Prodotto]] -> 0 | L28: =tabSuperdettagli[[#This Row],[Area di bdg]] -> 0 | M28: =tabSuperdettagli[[#This Row],[Macchina]] -> 0 | N28: =tabSuperdettagli[[#This Row],[Sottotipo]] -> 0 | O28: =tabSuperdettagli[[#This Row],[Cluster]] -> 0 | P28: =tabSuperdettagli[[#This Row],[Quadrante]] -> 0 | Q28: =tabSuperdettagli[[#This Row],[01.2025]] -> 0 | R28: =tabSuperdettagli[[#This Row],[02.2025]] -> 0 | S28: =tabSuperdettagli[[#This Row],[03.2025]] -> 0 | T28: =tabSuperdettagli[[#This Row],[04.2025]] -> 0 | U28: =tabSuperdettagli[[#This Row],[05.2025]] -> 0 | V28: =tabSuperdettagli[[#This Row],[06.2025]] -> 84 | W28: =tabSuperdettagli[[#This Row],[PROJ CODE]] -> CONV NGP PLATFORM ENG | X28: =tabSuperdettagli[[#This Row],[Resp 2°liv]]&"" -> Gamberini G. | Y28: =INDEX(tab_resp1liv[EngUnit area cluster 1_],MATCH(SUBSTITUTE(tabSuperdettagli[[#This Row],[Resp 2°liv]]," ",""),tab_resp1liv[SearchKey],0)) -> #N/A | Z28: =tabSuperdettagli[[#This Row],[WBS Element]]&"" -> Go | AA28: =tabSuperdettagli[[#This Row],[09.2025]] -> 234 | AC28: =IF(tabSuperdettagli[[#This Row],[ProjType_]]="M",IF(AND(tabSuperdettagli[[#This Row],[Resp 1°liv_]]="Guidotti C.",tabSuperdettagli[[#This Row],[WBE description_]]="Machine Mgmt"),"Documentation",tabSuperdettagli[[#This Row],[WBE description_]]),"") | AD28: =LEFT(tabSuperdettagli[[#This Row],[Network]],18) -> 5447634 | AE28: C005RD234 | AF28: SMEI LUCA | AG28: pippo | AH28: FATTIBILITA' DEL 2025 TOBACCO | AI28: Go | AJ28: 5447634 | AK28: 2025 | AL28: LAYOUT - PROPOSTE E DEFINIZIONE | AM28: K005.00012 | AN28: Int. | AO28: CONV NGP PLATFORM ENG | AP28: Est. | AQ28: C005RD334 | AR28: Seren E. | AS28: Gamberini G. | AT28: LAY | AU28: TOB | AV28: TOB PK | AW28: K | AX28: FATTIBILITA' DEL 2025 TOBACCO | AY28: 345 | AZ28: CANALI E LAYOUT | BA28: Seren | BB28: LAYOUT | BC28: 84 | BD28: 0 | BE28: 0 | BF28: 0 | BG28: 0 | BH28: 0 | BI28: 0 | BJ28: 0 | BK28: 0 | BL28: 0 | BM28: 0 | BN28: 0 | BO28: 84 | BP28: 10 | BQ28: Proposte di layout | BR28: 234 | BS28: Seren E. | BT28: K | BU28: K005.00012.PAC.999 | BV28: sì | BZ28: OTHERS (1)
A29: =IF(UPPER(LEFT(tabSuperdettagli[[#This Row],[WBE Status]],1))="S","sì","no") -> no | B29: 2025 | C29: =VLOOKUP(tabSuperdettagli[[#This Row],[WBS_]], 'pivot di appoggio'!A:B,2,FALSE) -> 2000 | D29: =LEFT(tabSuperdettagli[[#This Row],[Network]],10) -> 5447634 | E29: =LEFT(tabSuperdettagli[[#This Row],[Network]],1) -> 5 | F29: =LOWER(TRIM(tabSuperdettagli[[#This Row],[Proj. Type ]])) | G29: =IF(OR(tabSuperdettagli[[#This Row],[ProjType_]]="C",tabSuperdettagli[[#This Row],[ProjType_]]="A",tabSuperdettagli[[#This Row],[ProjType_]]="R",tabSuperdettagli[[#This Row],[ProjType_]]="E"),"C A R E",IF(tabSuperdettagli[[#This Row],[ProjType_]]="U","U ("&tabSuperdettagli[[#This Row],[U ProjType_]]&")",tabSuperdettagli[[#This Row],[ProjType_]])) -> 5 | I29: Int | J29: =tabSuperdettagli[[#This Row],[07.2025]] -> 10 | K29: =tabSuperdettagli[[#This Row],[Resp del Prodotto]] -> 0 | L29: =tabSuperdettagli[[#This Row],[Area di bdg]] -> 0 | M29: =tabSuperdettagli[[#This Row],[Macchina]] -> 0 | N29: =tabSuperdettagli[[#This Row],[Sottotipo]] -> 0 | O29: =tabSuperdettagli[[#This Row],[Cluster]] -> 0 | P29: =tabSuperdettagli[[#This Row],[Quadrante]] -> 0 | Q29: =tabSuperdettagli[[#This Row],[01.2025]] -> 0 | R29: =tabSuperdettagli[[#This Row],[02.2025]] -> 0 | S29: =tabSuperdettagli[[#This Row],[03.2025]] -> 0 | T29: =tabSuperdettagli[[#This Row],[04.2025]] -> 0 | U29: =tabSuperdettagli[[#This Row],[05.2025]] -> 0 | V29: =tabSuperdettagli[[#This Row],[06.2025]] -> 84 | W29: =tabSuperdettagli[[#This Row],[PROJ CODE]] -> CONV NGP PLATFORM ENG | X29: =tabSuperdettagli[[#This Row],[Resp 2°liv]]&"" -> Gamberini G. | Y29: =INDEX(tab_resp1liv[EngUnit area cluster 1_],MATCH(SUBSTITUTE(tabSuperdettagli[[#This Row],[Resp 2°liv]]," ",""),tab_resp1liv[SearchKey],0)) -> #N/A | Z29: =tabSuperdettagli[[#This Row],[WBS Element]]&"" -> Go | AA29: =tabSuperdettagli[[#This Row],[09.2025]] -> 234 | AC29: =IF(tabSuperdettagli[[#This Row],[ProjType_]]="M",IF(AND(tabSuperdettagli[[#This Row],[Resp 1°liv_]]="Guidotti C.",tabSuperdettagli[[#This Row],[WBE description_]]="Machine Mgmt"),"Documentation",tabSuperdettagli[[#This Row],[WBE description_]]),"") | AD29: =LEFT(tabSuperdettagli[[#This Row],[Network]],18) -> 5447634 | AE29: C005RD234 | AF29: SMEI LUCA | AG29: pippo | AH29: FATTIBILITA' DEL 2025 TOBACCO | AI29: Go | AJ29: 5447634 | AK29: 2025 | AL29: LAYOUT - PROPOSTE E DEFINIZIONE | AM29: K005.00012 | AN29: Int. | AO29: CONV NGP PLATFORM ENG | AP29: Est. | AQ29: C005RD334 | AR29: Seren E. | AS29: Gamberini G. | AT29: LAY | AU29: TOB | AV29: TOB PK | AW29: K | AX29: FATTIBILITA' DEL 2025 TOBACCO | AY29: 345 | AZ29: CANALI E LAYOUT | BA29: Seren | BB29: LAYOUT | BC29: 84 | BD29: 0 | BE29: 0 | BF29: 0 | BG29: 0 | BH29: 0 | BI29: 0 | BJ29: 0 | BK29: 0 | BL29: 0 | BM29: 0 | BN29: 0 | BO29: 84 | BP29: 10 | BQ29: Proposte di layout | BR29: 234 | BS29: Seren E. | BT29: K | BU29: K005.00012.PAC.999 | BV29: sì | BZ29: OTHERS (1)
A30: =IF(UPPER(LEFT(tabSuperdettagli[[#This Row],[WBE Status]],1))="S","sì","no") -> no | B30: 2025 | C30: =VLOOKUP(tabSuperdettagli[[#This Row],[WBS_]], 'pivot di appoggio'!A:B,2,FALSE) -> 2000 | D30: =LEFT(tabSuperdettagli[[#This Row],[Network]],10) -> 5447634 | E30: =LEFT(tabSuperdettagli[[#This Row],[Network]],1) -> 5 | F30: =LOWER(TRIM(tabSuperdettagli[[#This Row],[Proj. Type ]])) | G30: =IF(OR(tabSuperdettagli[[#This Row],[ProjType_]]="C",tabSuperdettagli[[#This Row],[ProjType_]]="A",tabSuperdettagli[[#This Row],[ProjType_]]="R",tabSuperdettagli[[#This Row],[ProjType_]]="E"),"C A R E",IF(tabSuperdettagli[[#This Row],[ProjType_]]="U","U ("&tabSuperdettagli[[#This Row],[U ProjType_]]&")",tabSuperdettagli[[#This Row],[ProjType_]])) -> 5 | I30: Int | J30: =tabSuperdettagli[[#This Row],[07.2025]] -> 10 | K30: =tabSuperdettagli[[#This Row],[Resp del Prodotto]] -> 0 | L30: =tabSuperdettagli[[#This Row],[Area di bdg]] -> 0 | M30: =tabSuperdettagli[[#This Row],[Macchina]] -> 0 | N30: =tabSuperdettagli[[#This Row],[Sottotipo]] -> 0 | O30: =tabSuperdettagli[[#This Row],[Cluster]] -> 0 | P30: =tabSuperdettagli[[#This Row],[Quadrante]] -> 0 | Q30: =tabSuperdettagli[[#This Row],[01.2025]] -> 0 | R30: =tabSuperdettagli[[#This Row],[02.2025]] -> 0 | S30: =tabSuperdettagli[[#This Row],[03.2025]] -> 0 | T30: =tabSuperdettagli[[#This Row],[04.2025]] -> 0 | U30: =tabSuperdettagli[[#This Row],[05.2025]] -> 0 | V30: =tabSuperdettagli[[#This Row],[06.2025]] -> 84 | W30: =tabSuperdettagli[[#This Row],[PROJ CODE]] -> CONV NGP PLATFORM ENG | X30: =tabSuperdettagli[[#This Row],[Resp 2°liv]]&"" -> Gamberini G. | Y30: =INDEX(tab_resp1liv[EngUnit area cluster 1_],MATCH(SUBSTITUTE(tabSuperdettagli[[#This Row],[Resp 2°liv]]," ",""),tab_resp1liv[SearchKey],0)) -> #N/A | Z30: =tabSuperdettagli[[#This Row],[WBS Element]]&"" -> Go | AA30: =tabSuperdettagli[[#This Row],[09.2025]] -> 234 | AC30: =IF(tabSuperdettagli[[#This Row],[ProjType_]]="M",IF(AND(tabSuperdettagli[[#This Row],[Resp 1°liv_]]="Guidotti C.",tabSuperdettagli[[#This Row],[WBE description_]]="Machine Mgmt"),"Documentation",tabSuperdettagli[[#This Row],[WBE description_]]),"") | AD30: =LEFT(tabSuperdettagli[[#This Row],[Network]],18) -> 5447634 | AE30: C005RD234 | AF30: SMEI LUCA | AG30: pippo | AH30: FATTIBILITA' DEL 2025 TOBACCO | AI30: Go | AJ30: 5447634 | AK30: 2025 | AL30: LAYOUT - PROPOSTE E DEFINIZIONE | AM30: K005.00012 | AN30: Int. | AO30: CONV NGP PLATFORM ENG | AP30: Est. | AQ30: C005RD334 | AR30: Seren E. | AS30: Gamberini G. | AT30: LAY | AU30: TOB | AV30: TOB PK | AW30: K | AX30: FATTIBILITA' DEL 2025 TOBACCO | AY30: 345 | AZ30: CANALI E LAYOUT | BA30: Seren | BB30: LAYOUT | BC30: 84 | BD30: 0 | BE30: 0 | BF30: 0 | BG30: 0 | BH30: 0 | BI30: 0 | BJ30: 0 | BK30: 0 | BL30: 0 | BM30: 0 | BN30: 0 | BO30: 84 | BP30: 10 | BQ30: Proposte di layout | BR30: 234 | BS30: Seren E. | BT30: K | BU30: K005.00012.PAC.999 | BV30: sì | BZ30: OTHERS (1)
A31: =IF(UPPER(LEFT(tabSuperdettagli[[#This Row],[WBE Status]],1))="S","sì","no") -> no | B31: 2025 | C31: =VLOOKUP(tabSuperdettagli[[#This Row],[WBS_]], 'pivot di appoggio'!A:B,2,FALSE) -> 2000 | D31: =LEFT(tabSuperdettagli[[#This Row],[Network]],10) -> 5447634 | E31: =LEFT(tabSuperdettagli[[#This Row],[Network]],1) -> 5 | F31: =LOWER(TRIM(tabSuperdettagli[[#This Row],[Proj. Type ]])) | G31: =IF(OR(tabSuperdettagli[[#This Row],[ProjType_]]="C",tabSuperdettagli[[#This Row],[ProjType_]]="A",tabSuperdettagli[[#This Row],[ProjType_]]="R",tabSuperdettagli[[#This Row],[ProjType_]]="E"),"C A R E",IF(tabSuperdettagli[[#This Row],[ProjType_]]="U","U ("&tabSuperdettagli[[#This Row],[U ProjType_]]&")",tabSuperdettagli[[#This Row],[ProjType_]])) -> 5 | I31: Int | J31: =tabSuperdettagli[[#This Row],[07.2025]] -> 10 | K31: =tabSuperdettagli[[#This Row],[Resp del Prodotto]] -> 0 | L31: =tabSuperdettagli[[#This Row],[Area di bdg]] -> 0 | M31: =tabSuperdettagli[[#This Row],[Macchina]] -> 0 | N31: =tabSuperdettagli[[#This Row],[Sottotipo]] -> 0 | O31: =tabSuperdettagli[[#This Row],[Cluster]] -> 0 | P31: =tabSuperdettagli[[#This Row],[Quadrante]] -> 0 | Q31: =tabSuperdettagli[[#This Row],[01.2025]] -> 0 | R31: =tabSuperdettagli[[#This Row],[02.2025]] -> 0 | S31: =tabSuperdettagli[[#This Row],[03.2025]] -> 0 | T31: =tabSuperdettagli[[#This Row],[04.2025]] -> 0 | U31: =tabSuperdettagli[[#This Row],[05.2025]] -> 0 | V31: =tabSuperdettagli[[#This Row],[06.2025]] -> 84 | W31: =tabSuperdettagli[[#This Row],[PROJ CODE]] -> CONV NGP PLATFORM ENG | X31: =tabSuperdettagli[[#This Row],[Resp 2°liv]]&"" -> Gamberini G. | Y31: =INDEX(tab_resp1liv[EngUnit area cluster 1_],MATCH(SUBSTITUTE(tabSuperdettagli[[#This Row],[Resp 2°liv]]," ",""),tab_resp1liv[SearchKey],0)) -> #N/A | Z31: =tabSuperdettagli[[#This Row],[WBS Element]]&"" -> Go | AA31: =tabSuperdettagli[[#This Row],[09.2025]] -> 234 | AC31: =IF(tabSuperdettagli[[#This Row],[ProjType_]]="M",IF(AND(tabSuperdettagli[[#This Row],[Resp 1°liv_]]="Guidotti C.",tabSuperdettagli[[#This Row],[WBE description_]]="Machine Mgmt"),"Documentation",tabSuperdettagli[[#This Row],[WBE description_]]),"") | AD31: =LEFT(tabSuperdettagli[[#This Row],[Network]],18) -> 5447634 | AE31: C005RD234 | AF31: SMEI LUCA | AG31: pippo | AH31: FATTIBILITA' DEL 2025 TOBACCO | AI31: Go | AJ31: 5447634 | AK31: 2025 | AL31: LAYOUT - PROPOSTE E DEFINIZIONE | AM31: K005.00012 | AN31: Int. | AO31: CONV NGP PLATFORM ENG | AP31: Est. | AQ31: C005RD334 | AR31: Seren E. | AS31: Gamberini G. | AT31: LAY | AU31: TOB | AV31: TOB PK | AW31: K | AX31: FATTIBILITA' DEL 2025 TOBACCO | AY31: 345 | AZ31: CANALI E LAYOUT | BA31: Seren | BB31: LAYOUT | BC31: 84 | BD31: 0 | BE31: 0 | BF31: 0 | BG31: 0 | BH31: 0 | BI31: 0 | BJ31: 0 | BK31: 0 | BL31: 0 | BM31: 0 | BN31: 0 | BO31: 84 | BP31: 10 | BQ31: Proposte di layout | BR31: 234 | BS31: Seren E. | BT31: K | BU31: K005.00012.PAC.999 | BV31: sì | BZ31: OTHERS (1)
A32: =IF(UPPER(LEFT(tabSuperdettagli[[#This Row],[WBE Status]],1))="S","sì","no") -> no | B32: 2025 | C32: =VLOOKUP(tabSuperdettagli[[#This Row],[WBS_]], 'pivot di appoggio'!A:B,2,FALSE) -> 2000 | D32: =LEFT(tabSuperdettagli[[#This Row],[Network]],10) -> 5447634 | E32: =LEFT(tabSuperdettagli[[#This Row],[Network]],1) -> 5 | F32: =LOWER(TRIM(tabSuperdettagli[[#This Row],[Proj. Type ]])) | G32: =IF(OR(tabSuperdettagli[[#This Row],[ProjType_]]="C",tabSuperdettagli[[#This Row],[ProjType_]]="A",tabSuperdettagli[[#This Row],[ProjType_]]="R",tabSuperdettagli[[#This Row],[ProjType_]]="E"),"C A R E",IF(tabSuperdettagli[[#This Row],[ProjType_]]="U","U ("&tabSuperdettagli[[#This Row],[U ProjType_]]&")",tabSuperdettagli[[#This Row],[ProjType_]])) -> 5 | I32: Int | J32: =tabSuperdettagli[[#This Row],[07.2025]] -> 10 | K32: =tabSuperdettagli[[#This Row],[Resp del Prodotto]] -> 0 | L32: =tabSuperdettagli[[#This Row],[Area di bdg]] -> 0 | M32: =tabSuperdettagli[[#This Row],[Macchina]] -> 0 | N32: =tabSuperdettagli[[#This Row],[Sottotipo]] -> 0 | O32: =tabSuperdettagli[[#This Row],[Cluster]] -> 0 | P32: =tabSuperdettagli[[#This Row],[Quadrante]] -> 0 | Q32: =tabSuperdettagli[[#This Row],[01.2025]] -> 0 | R32: =tabSuperdettagli[[#This Row],[02.2025]] -> 0 | S32: =tabSuperdettagli[[#This Row],[03.2025]] -> 0 | T32: =tabSuperdettagli[[#This Row],[04.2025]] -> 0 | U32: =tabSuperdettagli[[#This Row],[05.2025]] -> 0 | V32: =tabSuperdettagli[[#This Row],[06.2025]] -> 84 | W32: =tabSuperdettagli[[#This Row],[PROJ CODE]] -> CONV NGP PLATFORM ENG | X32: =tabSuperdettagli[[#This Row],[Resp 2°liv]]&"" -> Gamberini G. | Y32: =INDEX(tab_resp1liv[EngUnit area cluster 1_],MATCH(SUBSTITUTE(tabSuperdettagli[[#This Row],[Resp 2°liv]]," ",""),tab_resp1liv[SearchKey],0)) -> #N/A | Z32: =tabSuperdettagli[[#This Row],[WBS Element]]&"" -> Go | AA32: =tabSuperdettagli[[#This Row],[09.2025]] -> 234 | AC32: =IF(tabSuperdettagli[[#This Row],[ProjType_]]="M",IF(AND(tabSuperdettagli[[#This Row],[Resp 1°liv_]]="Guidotti C.",tabSuperdettagli[[#This Row],[WBE description_]]="Machine Mgmt"),"Documentation",tabSuperdettagli[[#This Row],[WBE description_]]),"") | AD32: =LEFT(tabSuperdettagli[[#This Row],[Network]],18) -> 5447634 | AE32: C005RD234 | AF32: SMEI LUCA | AG32: pippo | AH32: FATTIBILITA' DEL 2025 TOBACCO | AI32: Go | AJ32: 5447634 | AK32: 2025 | AL32: LAYOUT - PROPOSTE E DEFINIZIONE | AM32: K005.00012 | AN32: Int. | AO32: CONV NGP PLATFORM ENG | AP32: Est. | AQ32: C005RD334 | AR32: Seren E. | AS32: Gamberini G. | AT32: LAY | AU32: TOB | AV32: TOB PK | AW32: K | AX32: FATTIBILITA' DEL 2025 TOBACCO | AY32: 345 | AZ32: CANALI E LAYOUT | BA32: Seren | BB32: LAYOUT | BC32: 84 | BD32: 0 | BE32: 0 | BF32: 0 | BG32: 0 | BH32: 0 | BI32: 0 | BJ32: 0 | BK32: 0 | BL32: 0 | BM32: 0 | BN32: 0 | BO32: 84 | BP32: 10 | BQ32: Proposte di layout | BR32: 234 | BS32: Seren E. | BT32: K | BU32: K005.00012.PAC.999 | BV32: sì | BZ32: OTHERS (1)

Sheet CN43N
A1: Level | B1: Project definition | C1: Short ID (WBS elem) | D1: WBS element | E1: Name | F1: Proj.type | G1: Plant | H1: Status | I1: Results Analysis Key | J1: Competence date | K1: TechPlat/MachTp | L1: Profit center | M1: Basic start date | N1: Colonna1
A2: 1 | B2: A005.01234 | C2: A005.01234 | D2: A005.01234 | E2: Name | F2: 89 | G2: GD01 | H2: REL | J2: 42369 | M2: 42145
A3: 2 | B3: A005.01234 | C3: A005.01234.PK | D3: A005.01234.PK | E3: Packer | F3: 31 | G3: GD01 | H3: REL | J3: 42369 | M3: 42145

Sheet pivot di appoggio
A3: Row Labels | B3: Min of Anno_
A4: 5447634 | B4: 2000
A5: Grand Total | B5: 2000

Sheet table_tabProjType
A1: tab_ProjType | F1: Macro area | G1: ProjType | H1: ProjType Cluster 1 | I1: ProjType Cluster 2
F2: A | G2: A | H2: A | I2: A
F3: A | G3: A | H3: A | I3: A
F4: A | G4: A | H4: A | I4: A
F5: A | G5: A | H5: A | I5: A
F6: A | G6: A | H6: A | I6: A
F7: A | G7: A | H7: A | I7: A
F8: A | G8: A | H8: A | I8: A
F9: A | G9: A | H9: A | I9: A
F10: A | G10: A | H10: A | I10: A
F11: A | G11: A | H11: A | I11: A
F12: A | G12: A | H12: A | I12: A
F13: A | G13: A | H13: A | I13: A
... F15: A | G15: A | H15: A | I15: A

Sheet table_tabProjTypeCluster
A1: table_ProjTypeCluster | F1: Macro area | G1: ProjType | H1: ProjType Cluster 1 | I1: ProjType Cluster 2
F2: B | G2: B | H2: B | I2: B
F3: B | G3: B | H3: B | I3: B
F4: B | G4: B | H4: B | I4: B
F5: B | G5: B | H5: B | I5: B
F6: B | G6: B | H6: B | I6: B
F7: B | G7: B | H7: B | I7: B
F8: B | G8: B | H8: B | I8: B
F9: B | G9: B | H9: B | I9: B
F10: B | G10: B | H10: B | I10: B
F11: B | G11: B | H11: B | I11: B
F12: B | G12: B | H12: B | I12: B
F13: B | G13: B | H13: B | I13: B
... F21: B | G21: B | H21: B | I21: B

Sheet table_CommonTable
A1: SearchKey | B1: Resp 1°liv2 | C1: EngUnit area cluster 1_ | E1: EngUnit area cluster 2_
A2: =SUBSTITUTE(tab_resp1liv[[#This Row],[Resp 1°liv2]]," ","") -> C | B2: C | C2: C | E2: D
A3: =SUBSTITUTE(tab_resp1liv[[#This Row],[Resp 1°liv2]]," ","") -> C | B3: C | C3: C | E3: D
A4: =SUBSTITUTE(tab_resp1liv[[#This Row],[Resp 1°liv2]]," ","") -> C | B4: C | C4: C | E4: D
A5: =SUBSTITUTE(tab_resp1liv[[#This Row],[Resp 1°liv2]]," ","") -> C | B5: C | C5: C | E5: D
A6: =SUBSTITUTE(tab_resp1liv[[#This Row],[Resp 1°liv2]]," ","") -> C | B6: C | C6: C | E6: D
A7: =SUBSTITUTE(tab_resp1liv[[#This Row],[Resp 1°liv2]]," ","") -> C | B7: C | C7: C | E7: D
A8: =SUBSTITUTE(tab_resp1liv[[#This Row],[Resp 1°liv2]]," ","") -> C | B8: C | C8: C | E8: D
A9: =SUBSTITUTE(tab_resp1liv[[#This Row],[Resp 1°liv2]]," ","") -> C | B9: C | C9: C | E9: D
A10: =SUBSTITUTE(tab_resp1liv[[#This Row],[Resp 1°liv2]]," ","") -> C | B10: C | C10: C | E10: D
A11: =SUBSTITUTE(tab_resp1liv[[#This Row],[Resp 1°liv2]]," ","") -> C | B11: C | C11: C | E11: D
A12: =SUBSTITUTE(tab_resp1liv[[#This Row],[Resp 1°liv2]]," ","") -> C | B12: C | C12: C | E12: D
A13: =SUBSTITUTE(tab_resp1liv[[#This Row],[Resp 1°liv2]]," ","") -> C | B13: C | C13: C | E13: D
... A26: =SUBSTITUTE(tab_resp1liv[[#This Row],[Resp 1°liv2]]," ","") -> C | B26: C | C26: C | E26: D
A27: =SUBSTITUTE(tab_resp1liv[[#This Row],[Resp 1°liv2]]," ","") -> C | B27: C | C27: C

Sheet table_tabProgettiD
A3: WBS | B3: PROJECT HIGHLIGHT
A4: E | B4: E
A5: E | B5: E
A6: E | B6: E
A7: E | B7: E
A8: E | B8: E
A9: E | B9: E
A10: E | B10: E
A11: E | B11: E
A12: E | B12: E
A13: E | B13: E
A14: E | B14: E
... A363: E | B363: E

Sheet Powerpoint Configuration
A1: POWERPOINT TO GENERATE | K1: FIELD FILTERS
A3: Powerpoint File | B3: Title | C3: Content 1 | D3: Content 2 | E3: Content 3 | F3: Layout | K3: TABLE | L3: Nome colonna filtrabile
A4: Engineering KPI_Direzione.pptx | B4: Progetti per business area e project type | C4: PP_01 | H4: Layout Horizontal | K4: BUDGET | L4: Business
A5: Engineering KPI_Direzione.pptx | B5: Ore interne / esterne | C5: PP_02 | K5: BUDGET | L5: Categoria
A6: Engineering KPI_Direzione.pptx | B6: Progetti per Engineering unit e project type | C6: PP_03 | K6: FORECAST | L6: Business
A7: Engineering KPI_Direzione.pptx | B7: Progetti per business e tipo | C7: PP_04 | K7: FORECAST | L7: Categoria
A8: Engineering KPI_Direzione.pptx | B8: Progetti A | C8: PP_05 | K8: SUPERDETTAGLI | L8: Last name First name
A9: Engineering KPI_Direzione.pptx | B9: Progetti C | C9: PP_06 | K9: SUPERDETTAGLI | L9: Project Description
A10: Engineering KPI_Direzione.pptx | B10: Progetti R | C10: PP_07 | H10: Layout Vertical | K10: SUPERDETTAGLI | L10: Bus Area GDLT
A11: Engineering KPI_Direzione.pptx | B11: Progetti K | C11: PP_08
A12: Engineering KPI_Direzione.pptx | B12: Progetti D | C12: PP_09
A13: Engineering KPI_Direzione.pptx | B13: Progetti K Dettaglio | C13: PP_10
A14: Engineering KPI_Direzione.pptx | B14: Progetti D Dettaglio | C14: PP_11
A15: Engineering KPI_Direzione.pptx | B15: Progetti M | C15: PP_12
A16: Engineering KPI_Direzione.pptx | B16: Progetti U (imporoduttive) | C16: PP_13
A17: Engineering KPI_Direzione.pptx | B17: Progetti U (produttive indirette) | C17: PP_14
A18: Presentazione casi test.pptx | B18: Una slide | C18: PP_01
A19: Presentazione casi test.pptx | B19: =tblIndexPowerpoint7[[#This Row],[Content 1]]&" "&tblIndexPowerpoint7[[#This Row],[Content 2]]&" "&tblIndexPowerpoint7[[#This Row],[Content 3]]&" "&tblIndexPowerpoint7[[#This Row],[Layout]] -> PP_01 PP_02 Vertical | C19: PP_01 | D19: PP_02 | F19: Vertical
A20: Presentazione casi test.pptx | B20: =tblIndexPowerpoint7[[#This Row],[Content 1]]&" "&tblIndexPowerpoint7[[#This Row],[Content 2]]&" "&tblIndexPowerpoint7[[#This Row],[Content 3]]&" "&tblIndexPowerpoint7[[#This Row],[Layout]] -> PP_02 PP_03 Vertical | C20: PP_02 | D20: PP_03 | F20: Vertical
A21: Presentazione casi test.pptx | B21: =tblIndexPowerpoint7[[#This Row],[Content 1]]&" "&tblIndexPowerpoint7[[#This Row],[Content 2]]&" "&tblIndexPowerpoint7[[#This Row],[Content 3]]&" "&tblIndexPowerpoint7[[#This Row],[Layout]] -> PP_03 PP_04 Vertical | C21: PP_03 | D21: PP_04 | F21: Vertical
A22: Presentazione casi test.pptx | B22: =tblIndexPowerpoint7[[#This Row],[Content 1]]&" "&tblIndexPowerpoint7[[#This Row],[Content 2]]&" "&tblIndexPowerpoint7[[#This Row],[Content 3]]&" "&tblIndexPowerpoint7[[#This Row],[Layout]] -> PP_05 PP_06 Vertical | C22: PP_05 | D22: PP_06 | F22: Vertical
A23: Presentazione casi test.pptx | B23: =tblIndexPowerpoint7[[#This Row],[Content 1]]&" "&tblIndexPowerpoint7[[#This Row],[Content 2]]&" "&tblIndexPowerpoint7[[#This Row],[Content 3]]&" "&tblIndexPowerpoint7[[#This Row],[Layout]] -> PP_06 PP_07 Vertical | C23: PP_06 | D23: PP_07 | F23: Vertical
A24: Presentazione casi test.pptx | B24: =tblIndexPowerpoint7[[#This Row],[Content 1]]&" "&tblIndexPowerpoint7[[#This Row],[Content 2]]&" "&tblIndexPowerpoint7[[#This Row],[Content 3]]&" "&tblIndexPowerpoint7[[#This Row],[Layout]] -> PP_01 PP_02 Horizontal | C24: PP_01 | D24: PP_02 | F24: Horizontal
A25: Presentazione casi test.pptx | B25: =tblIndexPowerpoint7[[#This Row],[Content 1]]&" "&tblIndexPowerpoint7[[#This Row],[Content 2]]&" "&tblIndexPowerpoint7[[#This Row],[Content 3]]&" "&tblIndexPowerpoint7[[#This Row],[Layout]] -> PP_02 PP_03 Horizontal | C25: PP_02 | D25: PP_03 | F25: Horizontal
A26: Presentazione casi test.pptx | B26: =tblIndexPowerpoint7[[#This Row],[Content 1]]&" "&tblIndexPowerpoint7[[#This Row],[Content 2]]&" "&tblIndexPowerpoint7[[#This Row],[Content 3]]&" "&tblIndexPowerpoint7[[#This Row],[Layout]] -> PP_03 PP_04 Horizontal | C26: PP_03 | D26: PP_04 | F26: Horizontal
A27: Presentazione casi test.pptx | B27: =tblIndexPowerpoint7[[#This Row],[Content 1]]&" "&tblIndexPowerpoint7[[#This Row],[Content 2]]&" "&tblIndexPowerpoint7[[#This Row],[Content 3]]&" "&tblIndexPowerpoint7[[#This Row],[Layout]] -> PP_05 PP_06 Horizontal | C27: PP_05 | D27: PP_06 | F27: Horizontal
A28: Presentazione casi test.pptx | B28: =tblIndexPowerpoint7[[#This Row],[Content 1]]&" "&tblIndexPowerpoint7[[#This Row],[Content 2]]&" "&tblIndexPowerpoint7[[#This Row],[Content 3]]&" "&tblIndexPowerpoint7[[#This Row],[Layout]] -> PP_17 Horizontal | C28: PP_17 | F28: Horizontal
A29: Presentazione casi test.pptx | B29: =tblIndexPowerpoint7[[#This Row],[Content 1]]&" "&tblIndexPowerpoint7[[#This Row],[Content 2]]&" "&tblIndexPowerpoint7[[#This Row],[Content 3]]&" "&tblIndexPowerpoint7[[#This Row],[Layout]] -> PP_01 PP_02 PP_03 Vertical | C29: PP_01 | D29: PP_02 | E29: PP_03 | F29: Vertical
A30: Presentazione casi test.pptx | B30: =tblIndexPowerpoint7[[#This Row],[Content 1]]&" "&tblIndexPowerpoint7[[#This Row],[Content 2]]&" "&tblIndexPowerpoint7[[#This Row],[Content 3]]&" "&tblIndexPowerpoint7[[#This Row],[Layout]] -> PP_04 PP_05 PP_06 Vertical | C30: PP_04 | D30: PP_05 | E30: PP_06 | F30: Vertical
A31: Presentazione casi test.pptx | B31: =tblIndexPowerpoint7[[#This Row],[Content 1]]&" "&tblIndexPowerpoint7[[#This Row],[Content 2]]&" "&tblIndexPowerpoint7[[#This Row],[Content 3]]&" "&tblIndexPowerpoint7[[#This Row],[Layout]] -> PP_01 PP_02 PP_03 Horizontal | C31: PP_01 | D31: PP_02 | E31: PP_03 | F31: Horizontal
A32: Presentazione casi test.pptx | B32: =tblIndexPowerpoint7[[#This Row],[Content 1]]&" "&tblIndexPowerpoint7[[#This Row],[Content 2]]&" "&tblIndexPowerpoint7[[#This Row],[Content 3]]&" "&tblIndexPowerpoint7[[#This Row],[Layout]] -> PP_04 PP_05 PP_06 Horizontal | C32: PP_04 | D32: PP_05 | E32: PP_06 | F32: Horizontal

Sheet Alias-Business
A1: Alias for the column Business
A2: Row values | B2: New value
A3: abcd* | B3: Match caso 1
A4: ef*gh | B4: Match caso 2
A5: *ilmn | B5: Match caso 3
A6: Caso 4 | B6: Match caso 4
A7: Pippo 1, Pippo 2, Pippo 3 | B7: Match caso Pippo
A8: COFFEE | B8: Match caso Caffè
A9: PHARMA* | B9: Match caso Farmacia
A26: Add instructions here to explain the usage of *

Sheet Alias-Categoria
A1: Alias for the column Categoria
A2: Row values | B2: New value
A3: R&D* | B3: R&D
A4: aaaa* | B4: Match caso A
A5: bb*bb | B5: Match caso B
A6: *cccc | B6: Match caso C
A7: Caso D | B7: Match caso D
A8: Pluto A, PlutoA, Pluto B, pluto C | B8: Match caso Pluto
A9: *MACCHINA* | B9: Match caso Macchina
A26: Add instructions here to explain the usage of *

Sheet PP_Template
A1: Powerpoint Configuration
A2: Print Area: | B2: C1:P30

Sheet PP_01
A1: Powerpoint Configuration
A2: Print Area: | B2: D1:P39
A4: Progetti per business area e project type
A5: 1
E22: 2023 | G22: 2024 | I22: 2025 | K22: 2025 | M22: 2025 | O22: 2025 Q2
E23: business area | F23: project type | G23: business area | H23: project type | I23: business area | J23: project type | K23: business area | L23: project type | M23: business area | N23: project type | O23: business area | P23: project type
D24: TOB | E24: =SUMIFS(tabSuperdettagli[ORE_],tabSuperdettagli[da considerare?_],"sì",tabSuperdettagli[Anno_],$E$22,tabSuperdettagli[BussinessArea Cluster],$D24)/1000 -> 0 | G24: =SUMIFS(tabSuperdettagli[ORE_],tabSuperdettagli[da considerare?_],"sì",tabSuperdettagli[Anno_],G$22,tabSuperdettagli[BussinessArea Cluster],$D24)/1000 -> 0 | I24: =SUMIFS(tblBudget[BDG_],tblBudget[da considerare?_],"sì",tblBudget[BusinessArea_],$D24)/1000 -> 0 | K24: 0.513 | M24: =SUMIFS(tabSuperdettagli[ORE_],tabSuperdettagli[da considerare?_],"sì",tabSuperdettagli[Anno_],M$22,tabSuperdettagli[BussinessArea Cluster],$D24)/1000 -> 0 | O24: =SUMIFS(tblForecast[FORECAST Totale_],tblForecast[da considerare?],"sì",tblForecast[Business],D24)/1000 -> 0
D25: PHARMA | E25: =SUMIFS(tabSuperdettagli[ORE_],tabSuperdettagli[da considerare?_],"sì",tabSuperdettagli[Anno_],$E$22,tabSuperdettagli[BussinessArea Cluster],$D25)/1000 -> 0 | G25: =SUMIFS(tabSuperdettagli[ORE_],tabSuperdettagli[da considerare?_],"sì",tabSuperdettagli[Anno_],G$22,tabSuperdettagli[BussinessArea Cluster],$D25)/1000 -> 0 | I25: =SUMIFS(tblBudget[BDG_],tblBudget[da considerare?_],"sì",tblBudget[BusinessArea_],$D25)/1000 -> 0 | K25: =M25/cell_perc_RR -> 0 | M25: =SUMIFS(tabSuperdettagli[ORE_],tabSuperdettagli[da considerare?_],"sì",tabSuperdettagli[Anno_],M$22,tabSuperdettagli[BussinessArea Cluster],$D25)/1000 -> 0 | O25: =SUMIFS(tblForecast[FORECAST Totale_],tblForecast[da considerare?],"sì",tblForecast[Business],D25)/1000 -> 0
D26: CONSUMER ELECTRONICS | E26: =SUMIFS(tabSuperdettagli[ORE_],tabSuperdettagli[da considerare?_],"sì",tabSuperdettagli[Anno_],$E$22,tabSuperdettagli[BussinessArea Cluster],$D26)/1000 -> 0 | G26: =SUMIFS(tabSuperdettagli[ORE_],tabSuperdettagli[da considerare?_],"sì",tabSuperdettagli[Anno_],G$22,tabSuperdettagli[BussinessArea Cluster],$D26)/1000 -> 0 | I26: =SUMIFS(tblBudget[BDG_],tblBudget[da considerare?_],"sì",tblBudget[BusinessArea_],$D26)/1000 -> 0 | K26: =M26/cell_perc_RR -> 0 | M26: =SUMIFS(tabSuperdettagli[ORE_],tabSuperdettagli[da considerare?_],"sì",tabSuperdettagli[Anno_],M$22,tabSuperdettagli[BussinessArea Cluster],$D26)/1000 -> 0 | O26: =SUMIFS(tblForecast[FORECAST Totale_],tblForecast[da considerare?],"sì",tblForecast[Business],D26)/1000 -> 0
D27: ESS | E27: =SUMIFS(tabSuperdettagli[ORE_],tabSuperdettagli[da considerare?_],"sì",tabSuperdettagli[Anno_],E$22,tabSuperdettagli[BussinessArea Cluster],$D27)/1000 -> 0 | G27: =SUMIFS(tabSuperdettagli[ORE_],tabSuperdettagli[da considerare?_],"sì",tabSuperdettagli[Anno_],G$22,tabSuperdettagli[BussinessArea Cluster],$D27)/1000 -> 0 | I27: =SUMIFS(tblBudget[BDG_],tblBudget[da considerare?_],"sì",tblBudget[BusinessArea_],$D27)/1000 -> 0 | K27: =M27/cell_perc_RR -> 0 | M27: =SUMIFS(tabSuperdettagli[ORE_],tabSuperdettagli[da considerare?_],"sì",tabSuperdettagli[Anno_],M$22,tabSuperdettagli[BussinessArea Cluster],$D27)/1000 -> 0 | O27: =SUMIFS(tblForecast[FORECAST Totale_],tblForecast[da considerare?],"sì",tblForecast[Business],D27)/1000 -> 0
D28: ALTRI BUSINESS
D29: Totale | E29: =SUM(E$24:E$28) -> 0 | G29: =SUM(G$24:G$28) -> 0 | I29: =SUM(I$24:I$28) -> 0 | K29: =M29/cell_perc_RR -> 0 | M29: =SUM(M$24:M$28) -> 0 | O29: =SUM(O24:O28) -> 0
D31: C | F31: =SUMIFS(tabSuperdettagli[ORE_],tabSuperdettagli[da considerare?_],"sì",tabSuperdettagli[Anno_],E$22,tabSuperdettagli[ProjType Cluster2],$D31)/1000 -> 0 | H31: =SUMIFS(tabSuperdettagli[ORE_],tabSuperdettagli[da considerare?_],"sì",tabSuperdettagli[Anno_],G$22,tabSuperdettagli[ProjType Cluster2],$D31)/1000 -> 0 | J31: =SUMIFS(tblBudget[BDG_],tblBudget[da considerare?_],"sì",tblBudget[ProjType Cluster 2_],$D31)/1000 -> 0 | L31: =N31/cell_perc_RR -> 0 | N31: =SUMIFS(tabSuperdettagli[ORE_],tabSuperdettagli[da considerare?_],"sì",tabSuperdettagli[Anno_],M$22,tabSuperdettagli[ProjType Cluster2],$D31)/1000 -> 0 | P31: =SUMIFS(tblForecast[FORECAST Totale_],tblForecast[da considerare?],"sì",tblForecast[Proj type cluster 2],D31)/1000 -> 0
D32: A R E | F32: =SUMIFS(tabSuperdettagli[ORE_],tabSuperdettagli[da considerare?_],"sì",tabSuperdettagli[Anno_],E$22,tabSuperdettagli[ProjType Cluster2],$D32)/1000 -> 0 | H32: =SUMIFS(tabSuperdettagli[ORE_],tabSuperdettagli[da considerare?_],"sì",tabSuperdettagli[Anno_],G$22,tabSuperdettagli[ProjType Cluster2],$D32)/1000 -> 0 | J32: =SUMIFS(tblBudget[BDG_],tblBudget[da considerare?_],"sì",tblBudget[ProjType Cluster 2_],$D32)/1000 -> 0 | L32: =N32/cell_perc_RR -> 0 | N32: =SUMIFS(tabSuperdettagli[ORE_],tabSuperdettagli[da considerare?_],"sì",tabSuperdettagli[Anno_],M$22,tabSuperdettagli[ProjType Cluster2],$D32)/1000 -> 0 | P32: =SUMIFS(tblForecast[FORECAST Totale_],tblForecast[da considerare?],"sì",tblForecast[Proj type cluster 2],D32)/1000 -> 0
D33: M | F33: =SUMIFS(tabSuperdettagli[ORE_],tabSuperdettagli[da considerare?_],"sì",tabSuperdettagli[Anno_],E$22,tabSuperdettagli[ProjType Cluster],$D33)/1000 -> 0 | H33: =SUMIFS(tabSuperdettagli[ORE_],tabSuperdettagli[da considerare?_],"sì",tabSuperdettagli[Anno_],G$22,tabSuperdettagli[ProjType Cluster],$D33)/1000 -> 0 | J33: =SUMIFS(tblBudget[BDG_],tblBudget[da considerare?_],"sì",tblBudget[ProjType Cluster 1_],$D33)/1000 -> 0 | L33: =N33/cell_perc_RR -> 0 | N33: =SUMIFS(tabSuperdettagli[ORE_],tabSuperdettagli[da considerare?_],"sì",tabSuperdettagli[Anno_],M$22,tabSuperdettagli[ProjType Cluster],$D33)/1000 -> 0 | P33: =SUMIFS(tblForecast[FORECAST Totale_],tblForecast[da considerare?],"sì",tblForecast[Proj type cluster 1],D33)/1000 -> 0
D34: D | F34: =SUMIFS(tabSuperdettagli[ORE_],tabSuperdettagli[da considerare?_],"sì",tabSuperdettagli[Anno_],E$22,tabSuperdettagli[ProjType Cluster],$D34)/1000 -> 0 | H34: =SUMIFS(tabSuperdettagli[ORE_],tabSuperdettagli[da considerare?_],"sì",tabSuperdettagli[Anno_],G$22,tabSuperdettagli[ProjType Cluster],$D34)/1000 -> 0 | J34: =SUMIFS(tblBudget[BDG_],tblBudget[da considerare?_],"sì",tblBudget[ProjType Cluster 1_],$D34)/1000 -> 0 | L34: =N34/cell_perc_RR -> 0 | N34: =SUMIFS(tabSuperdettagli[ORE_],tabSuperdettagli[da considerare?_],"sì",tabSuperdettagli[Anno_],M$22,tabSuperdettagli[ProjType Cluster],$D34)/1000 -> 0 | P34: =SUMIFS(tblForecast[FORECAST Totale_],tblForecast[da considerare?],"sì",tblForecast[Proj type cluster 1],D34)/1000 -> 0
D35: K | F35: =SUMIFS(tabSuperdettagli[ORE_],tabSuperdettagli[da considerare?_],"sì",tabSuperdettagli[Anno_],E$22,tabSuperdettagli[ProjType Cluster],$D35)/1000 -> 0 | H35: =SUMIFS(tabSuperdettagli[ORE_],tabSuperdettagli[da considerare?_],"sì",tabSuperdettagli[Anno_],G$22,tabSuperdettagli[ProjType Cluster],$D35)/1000 -> 0 | J35: =SUMIFS(tblBudget[BDG_],tblBudget[da considerare?_],"sì",tblBudget[ProjType Cluster 1_],$D35)/1000 -> 0 | L35: =N35/cell_perc_RR -> 0 | N35: =SUMIFS(tabSuperdettagli[ORE_],tabSuperdettagli[da considerare?_],"sì",tabSuperdettagli[Anno_],M$22,tabSuperdettagli[ProjType Cluster],$D35)/1000 -> 0 | P35: =SUMIFS(tblForecast[FORECAST Totale_],tblForecast[da considerare?],"sì",tblForecast[Proj type cluster 1],D35)/1000 -> 0
D36: U (prod ind) | F36: =SUMIFS(tabSuperdettagli[ORE_],tabSuperdettagli[da considerare?_],"sì",tabSuperdettagli[Anno_],E$22,tabSuperdettagli[ProjType Cluster],$D36)/1000 -> 0 | H36: =SUMIFS(tabSuperdettagli[ORE_],tabSuperdettagli[da considerare?_],"sì",tabSuperdettagli[Anno_],G$22,tabSuperdettagli[ProjType Cluster],$D36)/1000 -> 0 | J36: =SUMIFS(tblBudget[BDG_],tblBudget[da considerare?_],"sì",tblBudget[ProjType Cluster 1_],$D36)/1000 -> 0 | L36: =N36/cell_perc_RR -> 0 | N36: =SUMIFS(tabSuperdettagli[ORE_],tabSuperdettagli[da considerare?_],"sì",tabSuperdettagli[Anno_],M$22,tabSuperdettagli[ProjType Cluster],$D36)/1000 -> 0 | P36: =SUMIFS(tblForecast[FORECAST Totale_],tblForecast[da considerare?],"sì",tblForecast[Proj type cluster 1],D36)/1000 -> 0
D37: U (impr) | F37: =SUMIFS(tabSuperdettagli[ORE_],tabSuperdettagli[da considerare?_],"sì",tabSuperdettagli[Anno_],E$22,tabSuperdettagli[ProjType Cluster],$D37)/1000 -> 0 | H37: =SUMIFS(tabSuperdettagli[ORE_],tabSuperdettagli[da considerare?_],"sì",tabSuperdettagli[Anno_],G$22,tabSuperdettagli[ProjType Cluster],$D37)/1000 -> 0 | J37: =SUMIFS(tblBudget[BDG_],tblBudget[da considerare?_],"sì",tblBudget[ProjType Cluster 1_],$D37)/1000 -> 0 | L37: =N37/cell_perc_RR -> 0 | N37: =SUMIFS(tabSuperdettagli[ORE_],tabSuperdettagli[da considerare?_],"sì",tabSuperdettagli[Anno_],M$22,tabSuperdettagli[ProjType Cluster],$D37)/1000 -> 0 | P37: =SUMIFS(tblForecast[FORECAST Totale_],tblForecast[da considerare?],"sì",tblForecast[Proj type cluster 1],D37)/1000 -> 0
D38: altri ProjType | F38: =ROUND(SUMIFS(tabSuperdettagli[ORE_],tabSuperdettagli[da considerare?_],"sì",tabSuperdettagli[Anno_],E$22)/1000-SUM(F31:F37),0) -> 0 | H38: =ROUND(SUMIFS(tabSuperdettagli[ORE_],tabSuperdettagli[da considerare?_],"sì",tabSuperdettagli[Anno_],G$28)/1000-SUM(H31:H37),0) -> 0 | J38: =ROUND(SUMIFS(tblBudget[BDG_],tblBudget[da considerare?_],"sì")/1000-SUM(J$31:J$37),0) -> 0 | L38: =N38/cell_perc_RR -> 0 | N38: =ROUND(SUMIFS(tabSuperdettagli[ORE_],tabSuperdettagli[da considerare?_],"sì",tabSuperdettagli[Anno_],M$28)/1000-SUM(N31:N37),0) -> 0 | P38: =SUMIFS(tblForecast[FORECAST Totale_],tblForecast[da considerare?],"sì")/1000-SUM(P31:P37) -> 0.08
D39: Totale | F39: =SUM(F31:F38) -> 0 | H39: =SUM(H31:H38) -> 0 | J39: =SUM(J31:J38) -> 0 | L39: =N39/cell_perc_RR -> 0 | N39: =SUM(N31:N38) -> 0 | P39: =SUM(P31:P38) -> 0.08

Sheet PP_02
A1: Powerpoint Configuration
A2: Print Area: | B2: D1:P30
D5: Row Labels
D6: 2023
D7: 5447634
D8: Grand Total

Sheet PP_03
A1: Powerpoint Configuration
A2: Print Area: | B2: D1:P20

Sheet PP_04
A1: Powerpoint Configuration
A2: Print Area: | B2: D1:P30

Sheet PP_05
A1: Powerpoint Configuration
A2: Print Area: | B2: D1:H30

Sheet PP_06
A1: Powerpoint Configuration
A2: Print Area: | B2: D1:M30

Sheet PP_07
A1: Powerpoint Configuration
A2: Print Area: | B2: D1:P30

Sheet PP_08
A1: Powerpoint Configuration
A2: Print Area: | B2: D1:P30

Sheet PP_09
A1: Powerpoint Configuration
A2: Print Area: | B2: D1:P30

Sheet PP_10
A1: Powerpoint Configuration
A2: Print Area: | B2: D1:P30

Sheet PP_11
A1: Powerpoint Configuration
A2: Print Area: | B2: D1:P30

Sheet PP_12
A1: Powerpoint Configuration
A2: Print Area: | B2: D1:P30

Sheet PP_13
A1: Powerpoint Configuration
A2: Print Area: | B2: D1:P30

Sheet PP_14
A1: Powerpoint Configuration
A2: Print Area: | B2: D1:P30

Sheet PP_15
A1: Powerpoint Configuration
A2: Print Area: | B2: D1:P30

Sheet PP_16
A1: Powerpoint Configuration
A2: Print Area: | B2: D1:P30

Sheet PP_17
A1: Powerpoint Configuration
A2: Print Area: | B2: D1:P30
