Workbook
Name anno: "2025"
Name cell_perc_RR: 10
Name mese: "10"
Name quarter: "Q4"

Sheet Budget
A1: FORMULA | K1: TO UPDATE BY SOFTWARE
A2: da considerare?_ | B2: BusinessArea_ | C2: ProjType_ | D2: ProjType Cluster 1_ | E2: ProjType Cluster 2_ | F2: Nome progetto_ | G2: EngUnit area cluster 1_ | H2: BDG est_ | I2: BDG int_ | J2: BDG_ | K2: Business | L2: CATEGORIA | M2: INT | N2: EST | O2: totale Gamberini | P2: INT2 | Q2: EST3 | R2: totale Lanzarini | S2: TOTALE TOT
A3: =IF(AND(tblBudget[[#This Row],[Business ]]>"",tblBudget[[#This Row],[CATEGORIA]]=""),"no","sì") -> sì | B3: =tblBudget[[#This Row],[Business ]] -> Business Sample | C3: =INDEX(tab_ProjTypeCluster[ProjType],MATCH(tblBudget[[#This Row],[CATEGORIA]],tab_ProjTypeCluster[Macro area],0)) -> #N/A | D3: =INDEX(tab_ProjTypeCluster[ProjType Cluster 1],MATCH(tblBudget[[#This Row],[CATEGORIA]],tab_ProjTypeCluster[Macro area],0)) -> #N/A | E3: =INDEX(tab_ProjTypeCluster[ProjType Cluster 2],MATCH(tblBudget[[#This Row],[CATEGORIA]],tab_ProjTypeCluster[Macro area],0)) -> #N/A | G3: =INDEX(tab_resp1liv[EngUnit area cluster 1_],MATCH(SUBSTITUTE(SUBSTITUTE(#REF!,"(ai)","")," ",""),tab_resp1liv[SearchKey],0)) -> #REF! | H3: =tblBudget[[#This Row],[EST]]+tblBudget[[#This Row],[EST3]] -> 15 | I3: =tblBudget[[#This Row],[INT]]+tblBudget[[#This Row],[INT2]] -> 25 | J3: =tblBudget[[#This Row],[TOTALE TOT]] -> 80 | K3: Business Sample | L3: Categoria A | M3: 10 | N3: 12 | O3: 22 | P3: 15 | Q3: 3 | R3: 18 | S3: 80

Sheet Forecast
A1: FORMULA | P1: TO UPDATE BY SOFTWARE
A2: da considerare? | B2: Proj type cluster 1 | C2: Proj type cluster 2 | D2: Business | E2: CATEGORIA_ | F2: ENG TOB - INT_ | G2: ENG TOB - EST_ | H2: ENG TOB Totale_ | I2: ENG LPP - INT_ | J2: ENG LPP - EST_ | K2: ENG LPP Totale_ | L2: int FORECAST_ | M2: ext FORECAST_ | N2: FORECAST Totale_ | O2: CATEGORIA TMP | P2: Business | Q2: CATEGORIA | R2: INT | S2: EST | T2: totale Gamberini | U2: INT2 | V2: EST3 | W2: totale Lanzarini | X2: TOTALE TOT
A3: =IF(AND(tblForecast[[#This Row],[Business ]]>"",tblForecast[[#This Row],[CATEGORIA]]=""),"no","sì") -> sì | B3: =IF(tblForecast[[#This Row],[da considerare?]]="sì",INDEX(tab_ProjType[ProjType Cluster 1],MATCH(tblForecast[[#This Row],[CATEGORIA TMP]],tab_ProjType[Macro area],0)),"") -> #N/A | C3: =IF(tblForecast[[#This Row],[da considerare?]]="sì",INDEX(tab_ProjType[ProjType Cluster 2],MATCH(tblForecast[[#This Row],[CATEGORIA TMP]],tab_ProjType[Macro area],0)),"") -> #N/A | D3: =IF(tblForecast[[#This Row],[Business ]]>"",tblForecast[[#This Row],[Business ]],D2) -> Business Sample | E3: =tblForecast[[#This Row],[CATEGORIA TMP]]&"" -> Categoria A | F3: =tblForecast[[#This Row],[INT]] -> 10 | G3: =tblForecast[[#This Row],[EST]] -> 12 | H3: =tblForecast[[#This Row],[totale Gamberini]] -> 22 | I3: =tblForecast[[#This Row],[INT2]] -> 15 | J3: =tblForecast[[#This Row],[EST3]] -> 3 | K3: =tblForecast[[#This Row],[totale Lanzarini]] -> 18 | L3: =tblForecast[[#This Row],[INT]]+tblForecast[[#This Row],[INT2]] -> 25 | M3: =tblForecast[[#This Row],[EST]]+tblForecast[[#This Row],[EST3]] -> 15 | N3: =tblForecast[[#This Row],[TOTALE TOT]] -> 80 | O3: =IF(LEFT(tblForecast[[#This Row],[CATEGORIA]],3)="R&D","R&D",tblForecast[[#This Row],[CATEGORIA]]) -> Categoria A | P3: Business Sample | Q3: Categoria A | R3: 10 | S3: 12 | T3: 22 | U3: 15 | V3: 3 | W3: 18 | X3: 80

Sheet RunRate
A1: 01 | B1: 02 | C1: 03 | D1: 04 | E1: 05 | F1: 06 | G1: 07 | H1: 08 | I1: 09 | J1: 10 | K1: 11 | L1: 12
A2: 0.15 | B2: 0.1 | C2: 0.05 | D2: 0.1 | E2: 0.15 | F2: 0.2 | G2: 0.25 | H2: 0.2 | I2: 0.15 | J2: 0.1 | K2: 0.05 | L2: 0.1

Sheet Superdetails
A1: FORMULA | AE1: TO UPDATE BY SOFTWARE
A2: da considerare?_ | B2: Anno_ | C2: Anno di prima marcatura (=anno di apertura progetto) | D2: WBS_ | E2: ProjType_ | F2: U ProjType_ | G2: ProjType Cluster | H2: ProjType Cluster2 | I2: BussinessArea Cluster | J2: ORE_ | K2: gen_ | L2: feb_ | M2: mar_ | N2: apr_ | O2: mag_ | P2: giu_ | Q2: lug_ | R2: ago_ | S2: set_ | T2: ott_ | U2: nov_ | V2: dic_ | W2: tipo risorsa_ | X2: Resp 1°liv_ | Y2: EngUnit area cluster 1_ | Z2: WBS description_ | AA2: WBE description_ | AB2: WBS D description_ | AC2: WBS M description_ | AD2: WBE per WBS-K | AE2: Sender Cost Center | AF2: Personnel Number | AG2: Last name First name | AH2: Project Description | AI2: WBS Element | AJ2: Network | AK2: Operation/Activity | AL2: Acct assgnt text | AM2: WBS Element - Project Definition (Text) | AN2: Network descr | AO2: PROJ CODE | AP2: INT/EST | AQ2: Raggr. X Struttura | AR2: MESE | AS2: Resp 2°liv | AT2: CDC bdg | AU2: Resp 1°liv | AV2: Resp DT | AW2: TIPO REP | AX2: Bus Area GDLT | AY2: Bus Area_2 | AZ2: tipo progetto | BA2: Proj name | BB2: machine code | BC2: product area | BD2: Resp del Prodotto | BE2: Area di bdg | BF2: Macchina | BG2: Sottotipo | BH2: Cluster | BI2: Quadrante | BJ2: 01.2025 | BK2: 02.2025 | BL2: 03.2025 | BM2: 04.2025 | BN2: 05.2025 | BO2: 06.2025 | BP2: 07.2025 | BQ2: 08.2025 | BR2: 09.2025 | BS2: 10.2025 | BT2: 11.2025 | BU2: 12.2025 | BV2: Total | BW2: WBE Status | BX2: competence date | BY2: Proj. Type | BZ2: WBE Name | CA2: Engineering Area | CB2: Data Accettazione | CC2: Data Uscita GD | CD2: REP UT
A3: =IF(UPPER(LEFT(tabSuperdettagli[[#This Row],[WBE Status]],1))="S","sì","no") -> no | B3: 2015 | C3: =VLOOKUP(tabSuperdettagli[[#This Row],[WBS_]],Pivot_AnnoPrimaMarcatura!A:B,2,FALSE) -> #N/A | D3: =LEFT(tabSuperdettagli[[#This Row],[Network]],10) | E3: =LEFT(tabSuperdettagli[[#This Row],[Network]],1) | F3: =LOWER(TRIM(tabSuperdettagli[[#This Row],[Proj. Type ]])) | G3: =IF(OR(tabSuperdettagli[[#This Row],[ProjType_]]="C",tabSuperdettagli[[#This Row],[ProjType_]]="A",tabSuperdettagli[[#This Row],[ProjType_]]="R",tabSuperdettagli[[#This Row],[ProjType_]]="E"),"C A R E",IF(tabSuperdettagli[[#This Row],[ProjType_]]="U","U ("&tabSuperdettagli[[#This Row],[U ProjType_]]&")",tabSuperdettagli[[#This Row],[ProjType_]])) | I3: =IF( TRIM(tabSuperdettagli[[#This Row],[Raggr. X Struttura]])> "", TRIM(tabSuperdettagli[[#This Row],[Raggr. X Struttura]]), TRIM(tabSuperdettagli[[#This Row],[Resp DT]] ) ) -> Gruppo struttura 1 | J3: =tabSuperdettagli[[#This Row],[Total]] -> 55 | K3: =tabSuperdettagli[[#This Row],[01.2025]] -> 1 | L3: =tabSuperdettagli[[#This Row],[02.2025]] -> 2 | M3: =tabSuperdettagli[[#This Row],[03.2025]] -> 3 | N3: =tabSuperdettagli[[#This Row],[04.2025]] -> 4 | O3: =tabSuperdettagli[[#This Row],[05.2025]] -> 5 | P3: =tabSuperdettagli[[#This Row],[06.2025]] -> 6 | Q3: =tabSuperdettagli[[#This Row],[07.2025]] -> 7 | R3: =tabSuperdettagli[[#This Row],[08.2025]] -> 8 | S3: =tabSuperdettagli[[#This Row],[09.2025]] -> 9 | T3: =tabSuperdettagli[[#This Row],[10.2025]] -> 10 | U3: =tabSuperdettagli[[#This Row],[11.2025]] -> 0 | V3: =tabSuperdettagli[[#This Row],[12.2025]] -> 0 | W3: =tabSuperdettagli[[#This Row],[INT/EST]] -> Int. | X3: =tabSuperdettagli[[#This Row],[Resp 2°liv]]&"" | Y3: =INDEX(tab_resp1liv[EngUnit area cluster 1_],MATCH(SUBSTITUTE(tabSuperdettagli[[#This Row],[Resp 2°liv]]," ",""),tab_resp1liv[SearchKey],0)) -> #N/A | Z3: =tabSuperdettagli[[#This Row],[WBS Element]]&"" | AA3: =tabSuperdettagli[[#This Row],[09.2025]] -> 9 | AC3: =IF(tabSuperdettagli[[#This Row],[ProjType_]]="M",IF(AND(tabSuperdettagli[[#This Row],[Resp 1°liv_]]="Guidotti C.",tabSuperdettagli[[#This Row],[WBE description_]]="Machine Mgmt"),"Documentation",tabSuperdettagli[[#This Row],[WBE description_]]),"") | AD3: =LEFT(tabSuperdettagli[[#This Row],[Network]],18) | AE3: Send cost A | AP3: Int. | AQ3: Gruppo struttura 1 | AV3: Responsabile A | BJ3: 1 | BK3: 2 | BL3: 3 | BM3: 4 | BN3: 5 | BO3: 6 | BP3: 7 | BQ3: 8 | BR3: 9 | BS3: 10 | BV3: 55 | BX3: 42006 | CB3: 42005 | CC3: 42045
A4: =IF(UPPER(LEFT(tabSuperdettagli[[#This Row],[WBE Status]],1))="S","sì","no") -> no | B4: 2015 | C4: =VLOOKUP(tabSuperdettagli[[#This Row],[WBS_]],Pivot_AnnoPrimaMarcatura!A:B,2,FALSE) -> #N/A | D4: =LEFT(tabSuperdettagli[[#This Row],[Network]], 10) | E4: =LEFT(tabSuperdettagli[[#This Row],[Network]], 1) | F4: =LOWER(TRIM( tabSuperdettagli[[#This Row],[Proj. Type ]] )) | G4: =IF( OR( tabSuperdettagli[[#This Row],[ProjType_]]="C", tabSuperdettagli[[#This Row],[ProjType_]]="A", tabSuperdettagli[[#This Row],[ProjType_]]="R", tabSuperdettagli[[#This Row],[ProjType_]]="E"), "C A R E", IF( tabSuperdettagli[[#This Row],[ProjType_]]="U", "U (" & tabSuperdettagli[[#This Row],[U ProjType_]] & ")", tabSuperdettagli[[#This Row],[ProjType_]]) ) | I4: =IF( TRIM(tabSuperdettagli[[#This Row],[Raggr. X Struttura]])> "", TRIM(tabSuperdettagli[[#This Row],[Raggr. X Struttura]]), TRIM(tabSuperdettagli[[#This Row],[Resp DT]] ) ) -> Gruppo struttura 1 | J4: =tabSuperdettagli[[#This Row],[Total]] -> 1055 | K4: =tabSuperdettagli[[#This Row],[01.2025]] -> 101 | L4: =tabSuperdettagli[[#This Row],[02.2025]] -> 102 | M4: =tabSuperdettagli[[#This Row],[03.2025]] -> 103 | N4: =tabSuperdettagli[[#This Row],[04.2025]] -> 104 | O4: =tabSuperdettagli[[#This Row],[05.2025]] -> 105 | P4: =tabSuperdettagli[[#This Row],[06.2025]] -> 106 | Q4: =tabSuperdettagli[[#This Row],[07.2025]] -> 107 | R4: =tabSuperdettagli[[#This Row],[08.2025]] -> 108 | S4: =tabSuperdettagli[[#This Row],[09.2025]] -> 109 | T4: =tabSuperdettagli[[#This Row],[10.2025]] -> 110 | U4: =tabSuperdettagli[[#This Row],[11.2025]] -> 0 | V4: =tabSuperdettagli[[#This Row],[12.2025]] -> 0 | W4: =tabSuperdettagli[[#This Row],[INT/EST]] -> Est. | X4: =tabSuperdettagli[[#This Row],[Resp 2°liv]]&"" | Y4: =INDEX( tab_resp1liv[EngUnit area cluster 1_], MATCH( SUBSTITUTE(tabSuperdettagli[[#This Row],[Resp 2°liv]], " ", ""), tab_resp1liv[SearchKey],0)) -> #N/A | Z4: =tabSuperdettagli[[#This Row],[WBS Element]]&"" | AA4: =tabSuperdettagli[[#This Row],[09.2025]] -> 109 | AC4: =IF( tabSuperdettagli[[#This Row],[ProjType_]]="M", IF( AND(tabSuperdettagli[[#This Row],[Resp 1°liv_]]="Guidotti C.", tabSuperdettagli[[#This Row],[WBE description_]]="Machine Mgmt"), "Documentation", tabSuperdettagli[[#This Row],[WBE description_]]), "" ) | AD4: =LEFT(tabSuperdettagli[[#This Row],[Network]], 18 ) | AE4: Send cost A | AP4: Est. | AQ4: Gruppo struttura 1 | AV4: Responsabile B | BJ4: 101 | BK4: 102 | BL4: 103 | BM4: 104 | BN4: 105 | BO4: 106 | BP4: 107 | BQ4: 108 | BR4: 109 | BS4: 110 | BV4: 1055 | BX4: 42009 | CB4: 42008 | CC4: 42048
A5: =IF(UPPER(LEFT(tabSuperdettagli[[#This Row],[WBE Status]],1))="S","sì","no") -> no | B5: 2015 | C5: =VLOOKUP(tabSuperdettagli[[#This Row],[WBS_]],Pivot_AnnoPrimaMarcatura!A:B,2,FALSE) -> #N/A | D5: =LEFT(tabSuperdettagli[[#This Row],[Network]], 10) | E5: =LEFT(tabSuperdettagli[[#This Row],[Network]], 1) | F5: =LOWER(TRIM( tabSuperdettagli[[#This Row],[Proj. Type ]] )) | G5: =IF( OR( tabSuperdettagli[[#This Row],[ProjType_]]="C", tabSuperdettagli[[#This Row],[ProjType_]]="A", tabSuperdettagli[[#This Row],[ProjType_]]="R", tabSuperdettagli[[#This Row],[ProjType_]]="E"), "C A R E", IF( tabSuperdettagli[[#This Row],[ProjType_]]="U", "U (" & tabSuperdettagli[[#This Row],[U ProjType_]] & ")", tabSuperdettagli[[#This Row],[ProjType_]]) ) | I5: =IF( TRIM(tabSuperdettagli[[#This Row],[Raggr. X Struttura]])> "", TRIM(tabSuperdettagli[[#This Row],[Raggr. X Struttura]]), TRIM(tabSuperdettagli[[#This Row],[Resp DT]] ) ) -> Gruppo struttura 2 | J5: =tabSuperdettagli[[#This Row],[Total]] -> 2055 | K5: =tabSuperdettagli[[#This Row],[01.2025]] -> 201 | L5: =tabSuperdettagli[[#This Row],[02.2025]] -> 202 | M5: =tabSuperdettagli[[#This Row],[03.2025]] -> 203 | N5: =tabSuperdettagli[[#This Row],[04.2025]] -> 204 | O5: =tabSuperdettagli[[#This Row],[05.2025]] -> 205 | P5: =tabSuperdettagli[[#This Row],[06.2025]] -> 206 | Q5: =tabSuperdettagli[[#This Row],[07.2025]] -> 207 | R5: =tabSuperdettagli[[#This Row],[08.2025]] -> 208 | S5: =tabSuperdettagli[[#This Row],[09.2025]] -> 209 | T5: =tabSuperdettagli[[#This Row],[10.2025]] -> 210 | U5: =tabSuperdettagli[[#This Row],[11.2025]] -> 0 | V5: =tabSuperdettagli[[#This Row],[12.2025]] -> 0 | W5: =tabSuperdettagli[[#This Row],[INT/EST]] -> Est. | X5: =tabSuperdettagli[[#This Row],[Resp 2°liv]]&"" | Y5: =INDEX( tab_resp1liv[EngUnit area cluster 1_], MATCH( SUBSTITUTE(tabSuperdettagli[[#This Row],[Resp 2°liv]], " ", ""), tab_resp1liv[SearchKey],0)) -> #N/A | Z5: =tabSuperdettagli[[#This Row],[WBS Element]]&"" | AA5: =tabSuperdettagli[[#This Row],[09.2025]] -> 209 | AC5: =IF( tabSuperdettagli[[#This Row],[ProjType_]]="M", IF( AND(tabSuperdettagli[[#This Row],[Resp 1°liv_]]="Guidotti C.", tabSuperdettagli[[#This Row],[WBE description_]]="Machine Mgmt"), "Documentation", tabSuperdettagli[[#This Row],[WBE description_]]), "" ) | AD5: =LEFT(tabSuperdettagli[[#This Row],[Network]], 18 ) | AE5: Send cost A | AP5: Est. | AQ5: Gruppo struttura 2 | AV5: Responsabile C | BJ5: 201 | BK5: 202 | BL5: 203 | BM5: 204 | BN5: 205 | BO5: 206 | BP5: 207 | BQ5: 208 | BR5: 209 | BS5: 210 | BV5: 2055 | BX5: 42012 | CB5: 42011 | CC5: 42051
A6: =IF(UPPER(LEFT(tabSuperdettagli[[#This Row],[WBE Status]],1))="S","sì","no") -> no | B6: 2015 | C6: =VLOOKUP(tabSuperdettagli[[#This Row],[WBS_]],Pivot_AnnoPrimaMarcatura!A:B,2,FALSE) -> #N/A | D6: =LEFT(tabSuperdettagli[[#This Row],[Network]], 10) | E6: =LEFT(tabSuperdettagli[[#This Row],[Network]], 1) | F6: =LOWER(TRIM( tabSuperdettagli[[#This Row],[Proj. Type ]] )) | G6: =IF( OR( tabSuperdettagli[[#This Row],[ProjType_]]="C", tabSuperdettagli[[#This Row],[ProjType_]]="A", tabSuperdettagli[[#This Row],[ProjType_]]="R", tabSuperdettagli[[#This Row],[ProjType_]]="E"), "C A R E", IF( tabSuperdettagli[[#This Row],[ProjType_]]="U", "U (" & tabSuperdettagli[[#This Row],[U ProjType_]] & ")", tabSuperdettagli[[#This Row],[ProjType_]]) ) | I6: =IF( TRIM(tabSuperdettagli[[#This Row],[Raggr. X Struttura]])> "", TRIM(tabSuperdettagli[[#This Row],[Raggr. X Struttura]]), TRIM(tabSuperdettagli[[#This Row],[Resp DT]] ) ) -> Gruppo struttura 1 | J6: =tabSuperdettagli[[#This Row],[Total]] -> 55 | K6: =tabSuperdettagli[[#This Row],[01.2025]] -> 1 | L6: =tabSuperdettagli[[#This Row],[02.2025]] -> 2 | M6: =tabSuperdettagli[[#This Row],[03.2025]] -> 3 | N6: =tabSuperdettagli[[#This Row],[04.2025]] -> 4 | O6: =tabSuperdettagli[[#This Row],[05.2025]] -> 5 | P6: =tabSuperdettagli[[#This Row],[06.2025]] -> 6 | Q6: =tabSuperdettagli[[#This Row],[07.2025]] -> 7 | R6: =tabSuperdettagli[[#This Row],[08.2025]] -> 8 | S6: =tabSuperdettagli[[#This Row],[09.2025]] -> 9 | T6: =tabSuperdettagli[[#This Row],[10.2025]] -> 10 | U6: =tabSuperdettagli[[#This Row],[11.2025]] -> 0 | V6: =tabSuperdettagli[[#This Row],[12.2025]] -> 0 | W6: =tabSuperdettagli[[#This Row],[INT/EST]] -> Int. | X6: =tabSuperdettagli[[#This Row],[Resp 2°liv]]&"" | Y6: =INDEX( tab_resp1liv[EngUnit area cluster 1_], MATCH( SUBSTITUTE(tabSuperdettagli[[#This Row],[Resp 2°liv]], " ", ""), tab_resp1liv[SearchKey],0)) -> #N/A | Z6: =tabSuperdettagli[[#This Row],[WBS Element]]&"" | AA6: =tabSuperdettagli[[#This Row],[09.2025]] -> 9 | AC6: =IF( tabSuperdettagli[[#This Row],[ProjType_]]="M", IF( AND(tabSuperdettagli[[#This Row],[Resp 1°liv_]]="Guidotti C.", tabSuperdettagli[[#This Row],[WBE description_]]="Machine Mgmt"), "Documentation", tabSuperdettagli[[#This Row],[WBE description_]]), "" ) | AD6: =LEFT(tabSuperdettagli[[#This Row],[Network]], 18 ) | AE6: Send cost A | AP6: Int. | AQ6: Gruppo struttura 1 | AV6: Responsabile A | BJ6: 1 | BK6: 2 | BL6: 3 | BM6: 4 | BN6: 5 | BO6: 6 | BP6: 7 | BQ6: 8 | BR6: 9 | BS6: 10 | BV6: 55 | BX6: 42015 | CB6: 42014 | CC6: 42054
A7: =IF(UPPER(LEFT(tabSuperdettagli[[#This Row],[WBE Status]],1))="S","sì","no") -> no | B7: 2015 | C7: =VLOOKUP(tabSuperdettagli[[#This Row],[WBS_]],Pivot_AnnoPrimaMarcatura!A:B,2,FALSE) -> #N/A | D7: =LEFT(tabSuperdettagli[[#This Row],[Network]], 10) | E7: =LEFT(tabSuperdettagli[[#This Row],[Network]], 1) | F7: =LOWER(TRIM( tabSuperdettagli[[#This Row],[Proj. Type ]] )) | G7: =IF( OR( tabSuperdettagli[[#This Row],[ProjType_]]="C", tabSuperdettagli[[#This Row],[ProjType_]]="A", tabSuperdettagli[[#This Row],[ProjType_]]="R", tabSuperdettagli[[#This Row],[ProjType_]]="E"), "C A R E", IF( tabSuperdettagli[[#This Row],[ProjType_]]="U", "U (" & tabSuperdettagli[[#This Row],[U ProjType_]] & ")", tabSuperdettagli[[#This Row],[ProjType_]]) ) | I7: =IF( TRIM(tabSuperdettagli[[#This Row],[Raggr. X Struttura]])> "", TRIM(tabSuperdettagli[[#This Row],[Raggr. X Struttura]]), TRIM(tabSuperdettagli[[#This Row],[Resp DT]] ) ) -> Gruppo struttura 4 | J7: =tabSuperdettagli[[#This Row],[Total]] -> 1055 | K7: =tabSuperdettagli[[#This Row],[01.2025]] -> 101 | L7: =tabSuperdettagli[[#This Row],[02.2025]] -> 102 | M7: =tabSuperdettagli[[#This Row],[03.2025]] -> 103 | N7: =tabSuperdettagli[[#This Row],[04.2025]] -> 104 | O7: =tabSuperdettagli[[#This Row],[05.2025]] -> 105 | P7: =tabSuperdettagli[[#This Row],[06.2025]] -> 106 | Q7: =tabSuperdettagli[[#This Row],[07.2025]] -> 107 | R7: =tabSuperdettagli[[#This Row],[08.2025]] -> 108 | S7: =tabSuperdettagli[[#This Row],[09.2025]] -> 109 | T7: =tabSuperdettagli[[#This Row],[10.2025]] -> 110 | U7: =tabSuperdettagli[[#This Row],[11.2025]] -> 0 | V7: =tabSuperdettagli[[#This Row],[12.2025]] -> 0 | W7: =tabSuperdettagli[[#This Row],[INT/EST]] -> Est. | X7: =tabSuperdettagli[[#This Row],[Resp 2°liv]]&"" | Y7: =INDEX( tab_resp1liv[EngUnit area cluster 1_], MATCH( SUBSTITUTE(tabSuperdettagli[[#This Row],[Resp 2°liv]], " ", ""), tab_resp1liv[SearchKey],0)) -> #N/A | Z7: =tabSuperdettagli[[#This Row],[WBS Element]]&"" | AA7: =tabSuperdettagli[[#This Row],[09.2025]] -> 109 | AC7: =IF( tabSuperdettagli[[#This Row],[ProjType_]]="M", IF( AND(tabSuperdettagli[[#This Row],[Resp 1°liv_]]="Guidotti C.", tabSuperdettagli[[#This Row],[WBE description_]]="Machine Mgmt"), "Documentation", tabSuperdettagli[[#This Row],[WBE description_]]), "" ) | AD7: =LEFT(tabSuperdettagli[[#This Row],[Network]], 18 ) | AE7: Send cost A | AP7: Est. | AQ7: Gruppo struttura 4 | AV7: Responsabile A | BJ7: 101 | BK7: 102 | BL7: 103 | BM7: 104 | BN7: 105 | BO7: 106 | BP7: 107 | BQ7: 108 | BR7: 109 | BS7: 110 | BV7: 1055 | BX7: 42018 | CB7: 42017 | CC7: 42057
A8: =IF(UPPER(LEFT(tabSuperdettagli[[#This Row],[WBE Status]],1))="S","sì","no") -> no | B8: 2015 | C8: =VLOOKUP(tabSuperdettagli[[#This Row],[WBS_]],Pivot_AnnoPrimaMarcatura!A:B,2,FALSE) -> #N/A | D8: =LEFT(tabSuperdettagli[[#This Row],[Network]], 10) | E8: =LEFT(tabSuperdettagli[[#This Row],[Network]], 1) | F8: =LOWER(TRIM( tabSuperdettagli[[#This Row],[Proj. Type ]] )) | G8: =IF( OR( tabSuperdettagli[[#This Row],[ProjType_]]="C", tabSuperdettagli[[#This Row],[ProjType_]]="A", tabSuperdettagli[[#This Row],[ProjType_]]="R", tabSuperdettagli[[#This Row],[ProjType_]]="E"), "C A R E", IF( tabSuperdettagli[[#This Row],[ProjType_]]="U", "U (" & tabSuperdettagli[[#This Row],[U ProjType_]] & ")", tabSuperdettagli[[#This Row],[ProjType_]]) ) | I8: =IF( TRIM(tabSuperdettagli[[#This Row],[Raggr. X Struttura]])> "", TRIM(tabSuperdettagli[[#This Row],[Raggr. X Struttura]]), TRIM(tabSuperdettagli[[#This Row],[Resp DT]] ) ) -> Gruppo struttura 3 | J8: =tabSuperdettagli[[#This Row],[Total]] -> 2055 | K8: =tabSuperdettagli[[#This Row],[01.2025]] -> 201 | L8: =tabSuperdettagli[[#This Row],[02.2025]] -> 202 | M8: =tabSuperdettagli[[#This Row],[03.2025]] -> 203 | N8: =tabSuperdettagli[[#This Row],[04.2025]] -> 204 | O8: =tabSuperdettagli[[#This Row],[05.2025]] -> 205 | P8: =tabSuperdettagli[[#This Row],[06.2025]] -> 206 | Q8: =tabSuperdettagli[[#This Row],[07.2025]] -> 207 | R8: =tabSuperdettagli[[#This Row],[08.2025]] -> 208 | S8: =tabSuperdettagli[[#This Row],[09.2025]] -> 209 | T8: =tabSuperdettagli[[#This Row],[10.2025]] -> 210 | U8: =tabSuperdettagli[[#This Row],[11.2025]] -> 0 | V8: =tabSuperdettagli[[#This Row],[12.2025]] -> 0 | W8: =tabSuperdettagli[[#This Row],[INT/EST]] -> Est. | X8: =tabSuperdettagli[[#This Row],[Resp 2°liv]]&"" | Y8: =INDEX( tab_resp1liv[EngUnit area cluster 1_], MATCH( SUBSTITUTE(tabSuperdettagli[[#This Row],[Resp 2°liv]], " ", ""), tab_resp1liv[SearchKey],0)) -> #N/A | Z8: =tabSuperdettagli[[#This Row],[WBS Element]]&"" | AA8: =tabSuperdettagli[[#This Row],[09.2025]] -> 209 | AC8: =IF( tabSuperdettagli[[#This Row],[ProjType_]]="M", IF( AND(tabSuperdettagli[[#This Row],[Resp 1°liv_]]="Guidotti C.", tabSuperdettagli[[#This Row],[WBE description_]]="Machine Mgmt"), "Documentation", tabSuperdettagli[[#This Row],[WBE description_]]), "" ) | AD8: =LEFT(tabSuperdettagli[[#This Row],[Network]], 18 ) | AE8: Send cost A | AP8: Est. | AQ8: Gruppo struttura 3 | AV8: Responsabile A | BJ8: 201 | BK8: 202 | BL8: 203 | BM8: 204 | BN8: 205 | BO8: 206 | BP8: 207 | BQ8: 208 | BR8: 209 | BS8: 210 | BV8: 2055 | BX8: 42021 | CB8: 42020 | CC8: 42060
A9: =IF(UPPER(LEFT(tabSuperdettagli[[#This Row],[WBE Status]],1))="S","sì","no") -> no | B9: 2015 | C9: =VLOOKUP(tabSuperdettagli[[#This Row],[WBS_]],Pivot_AnnoPrimaMarcatura!A:B,2,FALSE) -> #N/A | D9: =LEFT(tabSuperdettagli[[#This Row],[Network]], 10) | E9: =LEFT(tabSuperdettagli[[#This Row],[Network]], 1) | F9: =LOWER(TRIM( tabSuperdettagli[[#This Row],[Proj. Type ]] )) | G9: =IF( OR( tabSuperdettagli[[#This Row],[ProjType_]]="C", tabSuperdettagli[[#This Row],[ProjType_]]="A", tabSuperdettagli[[#This Row],[ProjType_]]="R", tabSuperdettagli[[#This Row],[ProjType_]]="E"), "C A R E", IF( tabSuperdettagli[[#This Row],[ProjType_]]="U", "U (" & tabSuperdettagli[[#This Row],[U ProjType_]] & ")", tabSuperdettagli[[#This Row],[ProjType_]]) ) | I9: =IF( TRIM(tabSuperdettagli[[#This Row],[Raggr. X Struttura]])> "", TRIM(tabSuperdettagli[[#This Row],[Raggr. X Struttura]]), TRIM(tabSuperdettagli[[#This Row],[Resp DT]] ) ) -> Gruppo struttura 1 | J9: =tabSuperdettagli[[#This Row],[Total]] -> 3055 | K9: =tabSuperdettagli[[#This Row],[01.2025]] -> 301 | L9: =tabSuperdettagli[[#This Row],[02.2025]] -> 302 | M9: =tabSuperdettagli[[#This Row],[03.2025]] -> 303 | N9: =tabSuperdettagli[[#This Row],[04.2025]] -> 304 | O9: =tabSuperdettagli[[#This Row],[05.2025]] -> 305 | P9: =tabSuperdettagli[[#This Row],[06.2025]] -> 306 | Q9: =tabSuperdettagli[[#This Row],[07.2025]] -> 307 | R9: =tabSuperdettagli[[#This Row],[08.2025]] -> 308 | S9: =tabSuperdettagli[[#This Row],[09.2025]] -> 309 | T9: =tabSuperdettagli[[#This Row],[10.2025]] -> 310 | U9: =tabSuperdettagli[[#This Row],[11.2025]] -> 0 | V9: =tabSuperdettagli[[#This Row],[12.2025]] -> 0 | W9: =tabSuperdettagli[[#This Row],[INT/EST]] -> Int. | X9: =tabSuperdettagli[[#This Row],[Resp 2°liv]]&"" | Y9: =INDEX( tab_resp1liv[EngUnit area cluster 1_], MATCH( SUBSTITUTE(tabSuperdettagli[[#This Row],[Resp 2°liv]], " ", ""), tab_resp1liv[SearchKey],0)) -> #N/A | Z9: =tabSuperdettagli[[#This Row],[WBS Element]]&"" | AA9: =tabSuperdettagli[[#This Row],[09.2025]] -> 309 | AC9: =IF( tabSuperdettagli[[#This Row],[ProjType_]]="M", IF( AND(tabSuperdettagli[[#This Row],[Resp 1°liv_]]="Guidotti C.", tabSuperdettagli[[#This Row],[WBE description_]]="Machine Mgmt"), "Documentation", tabSuperdettagli[[#This Row],[WBE description_]]), "" ) | AD9: =LEFT(tabSuperdettagli[[#This Row],[Network]], 18 ) | AE9: Send cost A | AP9: Int. | AQ9: Gruppo struttura 1 | AV9: Responsabile A | BJ9: 301 | BK9: 302 | BL9: 303 | BM9: 304 | BN9: 305 | BO9: 306 | BP9: 307 | BQ9: 308 | BR9: 309 | BS9: 310 | BV9: 3055 | BX9: 42024 | CB9: 42023 | CC9: 42063
A10: =IF(UPPER(LEFT(tabSuperdettagli[[#This Row],[WBE Status]],1))="S","sì","no") -> no | B10: 2015 | C10: =VLOOKUP(tabSuperdettagli[[#This Row],[WBS_]],Pivot_AnnoPrimaMarcatura!A:B,2,FALSE) -> #N/A | D10: =LEFT(tabSuperdettagli[[#This Row],[Network]], 10) | E10: =LEFT(tabSuperdettagli[[#This Row],[Network]], 1) | F10: =LOWER(TRIM( tabSuperdettagli[[#This Row],[Proj. Type ]] )) | G10: =IF( OR( tabSuperdettagli[[#This Row],[ProjType_]]="C", tabSuperdettagli[[#This Row],[ProjType_]]="A", tabSuperdettagli[[#This Row],[ProjType_]]="R", tabSuperdettagli[[#This Row],[ProjType_]]="E"), "C A R E", IF( tabSuperdettagli[[#This Row],[ProjType_]]="U", "U (" & tabSuperdettagli[[#This Row],[U ProjType_]] & ")", tabSuperdettagli[[#This Row],[ProjType_]]) ) | I10: =IF( TRIM(tabSuperdettagli[[#This Row],[Raggr. X Struttura]])> "", TRIM(tabSuperdettagli[[#This Row],[Raggr. X Struttura]]), TRIM(tabSuperdettagli[[#This Row],[Resp DT]] ) ) -> Gruppo struttura 6 | J10: =tabSuperdettagli[[#This Row],[Total]] -> 4055 | K10: =tabSuperdettagli[[#This Row],[01.2025]] -> 401 | L10: =tabSuperdettagli[[#This Row],[02.2025]] -> 402 | M10: =tabSuperdettagli[[#This Row],[03.2025]] -> 403 | N10: =tabSuperdettagli[[#This Row],[04.2025]] -> 404 | O10: =tabSuperdettagli[[#This Row],[05.2025]] -> 405 | P10: =tabSuperdettagli[[#This Row],[06.2025]] -> 406 | Q10: =tabSuperdettagli[[#This Row],[07.2025]] -> 407 | R10: =tabSuperdettagli[[#This Row],[08.2025]] -> 408 | S10: =tabSuperdettagli[[#This Row],[09.2025]] -> 409 | T10: =tabSuperdettagli[[#This Row],[10.2025]] -> 410 | U10: =tabSuperdettagli[[#This Row],[11.2025]] -> 0 | V10: =tabSuperdettagli[[#This Row],[12.2025]] -> 0 | W10: =tabSuperdettagli[[#This Row],[INT/EST]] -> Int. | X10: =tabSuperdettagli[[#This Row],[Resp 2°liv]]&"" | Y10: =INDEX( tab_resp1liv[EngUnit area cluster 1_], MATCH( SUBSTITUTE(tabSuperdettagli[[#This Row],[Resp 2°liv]], " ", ""), tab_resp1liv[SearchKey],0)) -> #N/A | Z10: =tabSuperdettagli[[#This Row],[WBS Element]]&"" | AA10: =tabSuperdettagli[[#This Row],[09.2025]] -> 409 | AC10: =IF( tabSuperdettagli[[#This Row],[ProjType_]]="M", IF( AND(tabSuperdettagli[[#This Row],[Resp 1°liv_]]="Guidotti C.", tabSuperdettagli[[#This Row],[WBE description_]]="Machine Mgmt"), "Documentation", tabSuperdettagli[[#This Row],[WBE description_]]), "" ) | AD10: =LEFT(tabSuperdettagli[[#This Row],[Network]], 18 ) | AE10: Send cost A | AP10: Int. | AQ10: Gruppo struttura 6 | AV10: Responsabile A | BJ10: 401 | BK10: 402 | BL10: 403 | BM10: 404 | BN10: 405 | BO10: 406 | BP10: 407 | BQ10: 408 | BR10: 409 | BS10: 410 | BV10: 4055 | BX10: 42027 | CB10: 42026 | CC10: 42066
A11: =IF(UPPER(LEFT(tabSuperdettagli[[#This Row],[WBE Status]],1))="S","sì","no") -> no | B11: 2015 | C11: =VLOOKUP(tabSuperdettagli[[#This Row],[WBS_]],Pivot_AnnoPrimaMarcatura!A:B,2,FALSE) -> #N/A | D11: =LEFT(tabSuperdettagli[[#This Row],[Network]], 10) | E11: =LEFT(tabSuperdettagli[[#This Row],[Network]], 1) | F11: =LOWER(TRIM( tabSuperdettagli[[#This Row],[Proj. Type ]] )) | G11: =IF( OR( tabSuperdettagli[[#This Row],[ProjType_]]="C", tabSuperdettagli[[#This Row],[ProjType_]]="A", tabSuperdettagli[[#This Row],[ProjType_]]="R", tabSuperdettagli[[#This Row],[ProjType_]]="E"), "C A R E", IF( tabSuperdettagli[[#This Row],[ProjType_]]="U", "U (" & tabSuperdettagli[[#This Row],[U ProjType_]] & ")", tabSuperdettagli[[#This Row],[ProjType_]]) ) | I11: =IF( TRIM(tabSuperdettagli[[#This Row],[Raggr. X Struttura]])> "", TRIM(tabSuperdettagli[[#This Row],[Raggr. X Struttura]]), TRIM(tabSuperdettagli[[#This Row],[Resp DT]] ) ) -> Gruppo struttura 1 | J11: =tabSuperdettagli[[#This Row],[Total]] -> 55 | K11: =tabSuperdettagli[[#This Row],[01.2025]] -> 1 | L11: =tabSuperdettagli[[#This Row],[02.2025]] -> 2 | M11: =tabSuperdettagli[[#This Row],[03.2025]] -> 3 | N11: =tabSuperdettagli[[#This Row],[04.2025]] -> 4 | O11: =tabSuperdettagli[[#This Row],[05.2025]] -> 5 | P11: =tabSuperdettagli[[#This Row],[06.2025]] -> 6 | Q11: =tabSuperdettagli[[#This Row],[07.2025]] -> 7 | R11: =tabSuperdettagli[[#This Row],[08.2025]] -> 8 | S11: =tabSuperdettagli[[#This Row],[09.2025]] -> 9 | T11: =tabSuperdettagli[[#This Row],[10.2025]] -> 10 | U11: =tabSuperdettagli[[#This Row],[11.2025]] -> 0 | V11: =tabSuperdettagli[[#This Row],[12.2025]] -> 0 | W11: =tabSuperdettagli[[#This Row],[INT/EST]] -> Int. | X11: =tabSuperdettagli[[#This Row],[Resp 2°liv]]&"" | Y11: =INDEX( tab_resp1liv[EngUnit area cluster 1_], MATCH( SUBSTITUTE(tabSuperdettagli[[#This Row],[Resp 2°liv]], " ", ""), tab_resp1liv[SearchKey],0)) -> #N/A | Z11: =tabSuperdettagli[[#This Row],[WBS Element]]&"" | AA11: =tabSuperdettagli[[#This Row],[09.2025]] -> 9 | AC11: =IF( tabSuperdettagli[[#This Row],[ProjType_]]="M", IF( AND(tabSuperdettagli[[#This Row],[Resp 1°liv_]]="Guidotti C.", tabSuperdettagli[[#This Row],[WBE description_]]="Machine Mgmt"), "Documentation", tabSuperdettagli[[#This Row],[WBE description_]]), "" ) | AD11: =LEFT(tabSuperdettagli[[#This Row],[Network]], 18 ) | AE11: Send cost A | AP11: Int. | AQ11: Gruppo struttura 1 | AV11: Responsabile A | BJ11: 1 | BK11: 2 | BL11: 3 | BM11: 4 | BN11: 5 | BO11: 6 | BP11: 7 | BQ11: 8 | BR11: 9 | BS11: 10 | BV11: 55 | BX11: 42030 | CB11: 42029 | CC11: 42069
A12: =IF(UPPER(LEFT(tabSuperdettagli[[#This Row],[WBE Status]],1))="S","sì","no") -> no | B12: 2015 | C12: =VLOOKUP(tabSuperdettagli[[#This Row],[WBS_]],Pivot_AnnoPrimaMarcatura!A:B,2,FALSE) -> #N/A | D12: =LEFT(tabSuperdettagli[[#This Row],[Network]], 10) | E12: =LEFT(tabSuperdettagli[[#This Row],[Network]], 1) | F12: =LOWER(TRIM( tabSuperdettagli[[#This Row],[Proj. Type ]] )) | G12: =IF( OR( tabSuperdettagli[[#This Row],[ProjType_]]="C", tabSuperdettagli[[#This Row],[ProjType_]]="A", tabSuperdettagli[[#This Row],[ProjType_]]="R", tabSuperdettagli[[#This Row],[ProjType_]]="E"), "C A R E", IF( tabSuperdettagli[[#This Row],[ProjType_]]="U", "U (" & tabSuperdettagli[[#This Row],[U ProjType_]] & ")", tabSuperdettagli[[#This Row],[ProjType_]]) ) | I12: =IF( TRIM(tabSuperdettagli[[#This Row],[Raggr. X Struttura]])> "", TRIM(tabSuperdettagli[[#This Row],[Raggr. X Struttura]]), TRIM(tabSuperdettagli[[#This Row],[Resp DT]] ) ) -> Gruppo struttura 1 | J12: =tabSuperdettagli[[#This Row],[Total]] -> 1055 | K12: =tabSuperdettagli[[#This Row],[01.2025]] -> 101 | L12: =tabSuperdettagli[[#This Row],[02.2025]] -> 102 | M12: =tabSuperdettagli[[#This Row],[03.2025]] -> 103 | N12: =tabSuperdettagli[[#This Row],[04.2025]] -> 104 | O12: =tabSuperdettagli[[#This Row],[05.2025]] -> 105 | P12: =tabSuperdettagli[[#This Row],[06.2025]] -> 106 | Q12: =tabSuperdettagli[[#This Row],[07.2025]] -> 107 | R12: =tabSuperdettagli[[#This Row],[08.2025]] -> 108 | S12: =tabSuperdettagli[[#This Row],[09.2025]] -> 109 | T12: =tabSuperdettagli[[#This Row],[10.2025]] -> 110 | U12: =tabSuperdettagli[[#This Row],[11.2025]] -> 0 | V12: =tabSuperdettagli[[#This Row],[12.2025]] -> 0 | W12: =tabSuperdettagli[[#This Row],[INT/EST]] -> Int. | X12: =tabSuperdettagli[[#This Row],[Resp 2°liv]]&"" | Y12: =INDEX( tab_resp1liv[EngUnit area cluster 1_], MATCH( SUBSTITUTE(tabSuperdettagli[[#This Row],[Resp 2°liv]], " ", ""), tab_resp1liv[SearchKey],0)) -> #N/A | Z12: =tabSuperdettagli[[#This Row],[WBS Element]]&"" | AA12: =tabSuperdettagli[[#This Row],[09.2025]] -> 109 | AC12: =IF( tabSuperdettagli[[#This Row],[ProjType_]]="M", IF( AND(tabSuperdettagli[[#This Row],[Resp 1°liv_]]="Guidotti C.", tabSuperdettagli[[#This Row],[WBE description_]]="Machine Mgmt"), "Documentation", tabSuperdettagli[[#This Row],[WBE description_]]), "" ) | AD12: =LEFT(tabSuperdettagli[[#This Row],[Network]], 18 ) | AE12: Send cost A | AP12: Int. | AQ12: Gruppo struttura 1 | AV12: Responsabile B | BJ12: 101 | BK12: 102 | BL12: 103 | BM12: 104 | BN12: 105 | BO12: 106 | BP12: 107 | BQ12: 108 | BR12: 109 | BS12: 110 | BV12: 1055 | BX12: 42033 | CB12: 42032 | CC12: 42072
A13: =IF(UPPER(LEFT(tabSuperdettagli[[#This Row],[WBE Status]],1))="S","sì","no") -> no | B13: 2016 | C13: =VLOOKUP(tabSuperdettagli[[#This Row],[WBS_]],Pivot_AnnoPrimaMarcatura!A:B,2,FALSE) -> #N/A | D13: =LEFT(tabSuperdettagli[[#This Row],[Network]], 10) | E13: =LEFT(tabSuperdettagli[[#This Row],[Network]], 1) | F13: =LOWER(TRIM( tabSuperdettagli[[#This Row],[Proj. Type ]] )) | G13: =IF( OR( tabSuperdettagli[[#This Row],[ProjType_]]="C", tabSuperdettagli[[#This Row],[ProjType_]]="A", tabSuperdettagli[[#This Row],[ProjType_]]="R", tabSuperdettagli[[#This Row],[ProjType_]]="E"), "C A R E", IF( tabSuperdettagli[[#This Row],[ProjType_]]="U", "U (" & tabSuperdettagli[[#This Row],[U ProjType_]] & ")", tabSuperdettagli[[#This Row],[ProjType_]]) ) | I13: =IF( TRIM(tabSuperdettagli[[#This Row],[Raggr. X Struttura]])> "", TRIM(tabSuperdettagli[[#This Row],[Raggr. X Struttura]]), TRIM(tabSuperdettagli[[#This Row],[Resp DT]] ) ) -> Gruppo struttura 1 | J13: =tabSuperdettagli[[#This Row],[Total]] -> 2055 | K13: =tabSuperdettagli[[#This Row],[01.2025]] -> 201 | L13: =tabSuperdettagli[[#This Row],[02.2025]] -> 202 | M13: =tabSuperdettagli[[#This Row],[03.2025]] -> 203 | N13: =tabSuperdettagli[[#This Row],[04.2025]] -> 204 | O13: =tabSuperdettagli[[#This Row],[05.2025]] -> 205 | P13: =tabSuperdettagli[[#This Row],[06.2025]] -> 206 | Q13: =tabSuperdettagli[[#This Row],[07.2025]] -> 207 | R13: =tabSuperdettagli[[#This Row],[08.2025]] -> 208 | S13: =tabSuperdettagli[[#This Row],[09.2025]] -> 209 | T13: =tabSuperdettagli[[#This Row],[10.2025]] -> 210 | U13: =tabSuperdettagli[[#This Row],[11.2025]] -> 0 | V13: =tabSuperdettagli[[#This Row],[12.2025]] -> 0 | W13: =tabSuperdettagli[[#This Row],[INT/EST]] -> Int. | X13: =tabSuperdettagli[[#This Row],[Resp 2°liv]]&"" | Y13: =INDEX( tab_resp1liv[EngUnit area cluster 1_], MATCH( SUBSTITUTE(tabSuperdettagli[[#This Row],[Resp 2°liv]], " ", ""), tab_resp1liv[SearchKey],0)) -> #N/A | Z13: =tabSuperdettagli[[#This Row],[WBS Element]]&"" | AA13: =tabSuperdettagli[[#This Row],[09.2025]] -> 209 | AC13: =IF( tabSuperdettagli[[#This Row],[ProjType_]]="M", IF( AND(tabSuperdettagli[[#This Row],[Resp 1°liv_]]="Guidotti C.", tabSuperdettagli[[#This Row],[WBE description_]]="Machine Mgmt"), "Documentation", tabSuperdettagli[[#This Row],[WBE description_]]), "" ) | AD13: =LEFT(tabSuperdettagli[[#This Row],[Network]], 18 ) | AE13: Send cost B | AP13: Int. | AQ13: Gruppo struttura 1 | AV13: Responsabile A | BJ13: 201 | BK13: 202 | BL13: 203 | BM13: 204 | BN13: 205 | BO13: 206 | BP13: 207 | BQ13: 208 | BR13: 209 | BS13: 210 | BV13: 2055 | BX13: 42036 | CB13: 42035 | CC13: 42075
A14: =IF(UPPER(LEFT(tabSuperdettagli[[#This Row],[WBE Status]],1))="S","sì","no") -> no | B14: 2016 | C14: =VLOOKUP(tabSuperdettagli[[#This Row],[WBS_]],Pivot_AnnoPrimaMarcatura!A:B,2,FALSE) -> #N/A | D14: =LEFT(tabSuperdettagli[[#This Row],[Network]], 10) | E14: =LEFT(tabSuperdettagli[[#This Row],[Network]], 1) | F14: =LOWER(TRIM( tabSuperdettagli[[#This Row],[Proj. Type ]] )) | G14: =IF( OR( tabSuperdettagli[[#This Row],[ProjType_]]="C", tabSuperdettagli[[#This Row],[ProjType_]]="A", tabSuperdettagli[[#This Row],[ProjType_]]="R", tabSuperdettagli[[#This Row],[ProjType_]]="E"), "C A R E", IF( tabSuperdettagli[[#This Row],[ProjType_]]="U", "U (" & tabSuperdettagli[[#This Row],[U ProjType_]] & ")", tabSuperdettagli[[#This Row],[ProjType_]]) ) | I14: =IF( TRIM(tabSuperdettagli[[#This Row],[Raggr. X Struttura]])> "", TRIM(tabSuperdettagli[[#This Row],[Raggr. X Struttura]]), TRIM(tabSuperdettagli[[#This Row],[Resp DT]] ) ) -> Gruppo struttura 1 | J14: =tabSuperdettagli[[#This Row],[Total]] -> 3055 | K14: =tabSuperdettagli[[#This Row],[01.2025]] -> 301 | L14: =tabSuperdettagli[[#This Row],[02.2025]] -> 302 | M14: =tabSuperdettagli[[#This Row],[03.2025]] -> 303 | N14: =tabSuperdettagli[[#This Row],[04.2025]] -> 304 | O14: =tabSuperdettagli[[#This Row],[05.2025]] -> 305 | P14: =tabSuperdettagli[[#This Row],[06.2025]] -> 306 | Q14: =tabSuperdettagli[[#This Row],[07.2025]] -> 307 | R14: =tabSuperdettagli[[#This Row],[08.2025]] -> 308 | S14: =tabSuperdettagli[[#This Row],[09.2025]] -> 309 | T14: =tabSuperdettagli[[#This Row],[10.2025]] -> 310 | U14: =tabSuperdettagli[[#This Row],[11.2025]] -> 0 | V14: =tabSuperdettagli[[#This Row],[12.2025]] -> 0 | W14: =tabSuperdettagli[[#This Row],[INT/EST]] -> Int. | X14: =tabSuperdettagli[[#This Row],[Resp 2°liv]]&"" | Y14: =INDEX( tab_resp1liv[EngUnit area cluster 1_], MATCH( SUBSTITUTE(tabSuperdettagli[[#This Row],[Resp 2°liv]], " ", ""), tab_resp1liv[SearchKey],0)) -> #N/A | Z14: =tabSuperdettagli[[#This Row],[WBS Element]]&"" | AA14: =tabSuperdettagli[[#This Row],[09.2025]] -> 309 | AC14: =IF( tabSuperdettagli[[#This Row],[ProjType_]]="M", IF( AND(tabSuperdettagli[[#This Row],[Resp 1°liv_]]="Guidotti C.", tabSuperdettagli[[#This Row],[WBE description_]]="Machine Mgmt"), "Documentation", tabSuperdettagli[[#This Row],[WBE description_]]), "" ) | AD14: =LEFT(tabSuperdettagli[[#This Row],[Network]], 18 ) | AE14: Send cost B | AP14: Int. | AQ14: Gruppo struttura 1 | AV14: Responsabile C | BJ14: 301 | BK14: 302 | BL14: 303 | BM14: 304 | BN14: 305 | BO14: 306 | BP14: 307 | BQ14: 308 | BR14: 309 | BS14: 310 | BV14: 3055 | BX14: 42039 | CB14: 42038 | CC14: 42078
A15: =IF(UPPER(LEFT(tabSuperdettagli[[#This Row],[WBE Status]],1))="S","sì","no") -> no | B15: 2016 | C15: =VLOOKUP(tabSuperdettagli[[#This Row],[WBS_]],Pivot_AnnoPrimaMarcatura!A:B,2,FALSE) -> #N/A | D15: =LEFT(tabSuperdettagli[[#This Row],[Network]], 10) | E15: =LEFT(tabSuperdettagli[[#This Row],[Network]], 1) | F15: =LOWER(TRIM( tabSuperdettagli[[#This Row],[Proj. Type ]] )) | G15: =IF( OR( tabSuperdettagli[[#This Row],[ProjType_]]="C", tabSuperdettagli[[#This Row],[ProjType_]]="A", tabSuperdettagli[[#This Row],[ProjType_]]="R", tabSuperdettagli[[#This Row],[ProjType_]]="E"), "C A R E", IF( tabSuperdettagli[[#This Row],[ProjType_]]="U", "U (" & tabSuperdettagli[[#This Row],[U ProjType_]] & ")", tabSuperdettagli[[#This Row],[ProjType_]]) ) | I15: =IF( TRIM(tabSuperdettagli[[#This Row],[Raggr. X Struttura]])> "", TRIM(tabSuperdettagli[[#This Row],[Raggr. X Struttura]]), TRIM(tabSuperdettagli[[#This Row],[Resp DT]] ) ) -> Gruppo struttura 1 | J15: =tabSuperdettagli[[#This Row],[Total]] -> 4055 | K15: =tabSuperdettagli[[#This Row],[01.2025]] -> 401 | L15: =tabSuperdettagli[[#This Row],[02.2025]] -> 402 | M15: =tabSuperdettagli[[#This Row],[03.2025]] -> 403 | N15: =tabSuperdettagli[[#This Row],[04.2025]] -> 404 | O15: =tabSuperdettagli[[#This Row],[05.2025]] -> 405 | P15: =tabSuperdettagli[[#This Row],[06.2025]] -> 406 | Q15: =tabSuperdettagli[[#This Row],[07.2025]] -> 407 | R15: =tabSuperdettagli[[#This Row],[08.2025]] -> 408 | S15: =tabSuperdettagli[[#This Row],[09.2025]] -> 409 | T15: =tabSuperdettagli[[#This Row],[10.2025]] -> 410 | U15: =tabSuperdettagli[[#This Row],[11.2025]] -> 0 | V15: =tabSuperdettagli[[#This Row],[12.2025]] -> 0 | W15: =tabSuperdettagli[[#This Row],[INT/EST]] -> Est. | X15: =tabSuperdettagli[[#This Row],[Resp 2°liv]]&"" | Y15: =INDEX( tab_resp1liv[EngUnit area cluster 1_], MATCH( SUBSTITUTE(tabSuperdettagli[[#This Row],[Resp 2°liv]], " ", ""), tab_resp1liv[SearchKey],0)) -> #N/A | Z15: =tabSuperdettagli[[#This Row],[WBS Element]]&"" | AA15: =tabSuperdettagli[[#This Row],[09.2025]] -> 409 | AC15: =IF( tabSuperdettagli[[#This Row],[ProjType_]]="M", IF( AND(tabSuperdettagli[[#This Row],[Resp 1°liv_]]="Guidotti C.", tabSuperdettagli[[#This Row],[WBE description_]]="Machine Mgmt"), "Documentation", tabSuperdettagli[[#This Row],[WBE description_]]), "" ) | AD15: =LEFT(tabSuperdettagli[[#This Row],[Network]], 18 ) | AE15: Send cost B | AP15: Est. | AQ15: Gruppo struttura 1 | AV15: Responsabile A | BJ15: 401 | BK15: 402 | BL15: 403 | BM15: 404 | BN15: 405 | BO15: 406 | BP15: 407 | BQ15: 408 | BR15: 409 | BS15: 410 | BV15: 4055 | BX15: 42042 | CB15: 42041 | CC15: 42081
... A21: =IF(UPPER(LEFT(tabSuperdettagli[[#This Row],[WBE Status]],1))="S","sì","no") -> no | B21: 2016 | C21: =VLOOKUP(tabSuperdettagli[[#This Row],[WBS_]],Pivot_AnnoPrimaMarcatura!A:B,2,FALSE) -> #N/A | D21: =LEFT(tabSuperdettagli[[#This Row],[Network]], 10) | E21: =LEFT(tabSuperdettagli[[#This Row],[Network]], 1) | F21: =LOWER(TRIM( tabSuperdettagli[[#This Row],[Proj. Type ]] )) | G21: =IF( OR( tabSuperdettagli[[#This Row],[ProjType_]]="C", tabSuperdettagli[[#This Row],[ProjType_]]="A", tabSuperdettagli[[#This Row],[ProjType_]]="R", tabSuperdettagli[[#This Row],[ProjType_]]="E"), "C A R E", IF( tabSuperdettagli[[#This Row],[ProjType_]]="U", "U (" & tabSuperdettagli[[#This Row],[U ProjType_]] & ")", tabSuperdettagli[[#This Row],[ProjType_]]) ) | I21: =IF( TRIM(tabSuperdettagli[[#This Row],[Raggr. X Struttura]])> "", TRIM(tabSuperdettagli[[#This Row],[Raggr. X Struttura]]), TRIM(tabSuperdettagli[[#This Row],[Resp DT]] ) ) -> Gruppo struttura 5 | J21: =tabSuperdettagli[[#This Row],[Total]] -> 55 | K21: =tabSuperdettagli[[#This Row],[01.2025]] -> 1 | L21: =tabSuperdettagli[[#This Row],[02.2025]] -> 2 | M21: =tabSuperdettagli[[#This Row],[03.2025]] -> 3 | N21: =tabSuperdettagli[[#This Row],[04.2025]] -> 4 | O21: =tabSuperdettagli[[#This Row],[05.2025]] -> 5 | P21: =tabSuperdettagli[[#This Row],[06.2025]] -> 6 | Q21: =tabSuperdettagli[[#This Row],[07.2025]] -> 7 | R21: =tabSuperdettagli[[#This Row],[08.2025]] -> 8 | S21: =tabSuperdettagli[[#This Row],[09.2025]] -> 9 | T21: =tabSuperdettagli[[#This Row],[10.2025]] -> 10 | U21: =tabSuperdettagli[[#This Row],[11.2025]] -> 0 | V21: =tabSuperdettagli[[#This Row],[12.2025]] -> 0 | W21: =tabSuperdettagli[[#This Row],[INT/EST]] -> Int. | X21: =tabSuperdettagli[[#This Row],[Resp 2°liv]]&"" | Y21: =INDEX( tab_resp1liv[EngUnit area cluster 1_], MATCH( SUBSTITUTE(tabSuperdettagli[[#This Row],[Resp 2°liv]], " ", ""), tab_resp1liv[SearchKey],0)) -> #N/A | Z21: =tabSuperdettagli[[#This Row],[WBS Element]]&"" | AA21: =tabSuperdettagli[[#This Row],[09.2025]] -> 9 | AC21: =IF( tabSuperdettagli[[#This Row],[ProjType_]]="M", IF( AND(tabSuperdettagli[[#This Row],[Resp 1°liv_]]="Guidotti C.", tabSuperdettagli[[#This Row],[WBE description_]]="Machine Mgmt"), "Documentation", tabSuperdettagli[[#This Row],[WBE description_]]), "" ) | AD21: =LEFT(tabSuperdettagli[[#This Row],[Network]], 18 ) | AE21: Send cost B | AP21: Int. | AQ21: Gruppo struttura 5 | AV21: Responsabile C | BJ21: 1 | BK21: 2 | BL21: 3 | BM21: 4 | BN21: 5 | BO21: 6 | BP21: 7 | BQ21: 8 | BR21: 9 | BS21: 10 | BV21: 55 | BX21: 42060 | CB21: 42059 | CC21: 42099
A22: =IF(UPPER(LEFT(tabSuperdettagli[[#This Row],[WBE Status]],1))="S","sì","no") -> no | B22: 2016 | C22: =VLOOKUP(tabSuperdettagli[[#This Row],[WBS_]],Pivot_AnnoPrimaMarcatura!A:B,2,FALSE) -> #N/A | D22: =LEFT(tabSuperdettagli[[#This Row],[Network]], 10) | E22: =LEFT(tabSuperdettagli[[#This Row],[Network]], 1) | F22: =LOWER(TRIM( tabSuperdettagli[[#This Row],[Proj. Type ]] )) | G22: =IF( OR( tabSuperdettagli[[#This Row],[ProjType_]]="C", tabSuperdettagli[[#This Row],[ProjType_]]="A", tabSuperdettagli[[#This Row],[ProjType_]]="R", tabSuperdettagli[[#This Row],[ProjType_]]="E"), "C A R E", IF( tabSuperdettagli[[#This Row],[ProjType_]]="U", "U (" & tabSuperdettagli[[#This Row],[U ProjType_]] & ")", tabSuperdettagli[[#This Row],[ProjType_]]) ) | I22: =IF( TRIM(tabSuperdettagli[[#This Row],[Raggr. X Struttura]])> "", TRIM(tabSuperdettagli[[#This Row],[Raggr. X Struttura]]), TRIM(tabSuperdettagli[[#This Row],[Resp DT]] ) ) -> Responsabile B | J22: =tabSuperdettagli[[#This Row],[Total]] -> 1055 | K22: =tabSuperdettagli[[#This Row],[01.2025]] -> 101 | L22: =tabSuperdettagli[[#This Row],[02.2025]] -> 102 | M22: =tabSuperdettagli[[#This Row],[03.2025]] -> 103 | N22: =tabSuperdettagli[[#This Row],[04.2025]] -> 104 | O22: =tabSuperdettagli[[#This Row],[05.2025]] -> 105 | P22: =tabSuperdettagli[[#This Row],[06.2025]] -> 106 | Q22: =tabSuperdettagli[[#This Row],[07.2025]] -> 107 | R22: =tabSuperdettagli[[#This Row],[08.2025]] -> 108 | S22: =tabSuperdettagli[[#This Row],[09.2025]] -> 109 | T22: =tabSuperdettagli[[#This Row],[10.2025]] -> 110 | U22: =tabSuperdettagli[[#This Row],[11.2025]] -> 0 | V22: =tabSuperdettagli[[#This Row],[12.2025]] -> 0 | W22: =tabSuperdettagli[[#This Row],[INT/EST]] -> Int. | X22: =tabSuperdettagli[[#This Row],[Resp 2°liv]]&"" | Y22: =INDEX( tab_resp1liv[EngUnit area cluster 1_], MATCH( SUBSTITUTE(tabSuperdettagli[[#This Row],[Resp 2°liv]], " ", ""), tab_resp1liv[SearchKey],0)) -> #N/A | Z22: =tabSuperdettagli[[#This Row],[WBS Element]]&"" | AA22: =tabSuperdettagli[[#This Row],[09.2025]] -> 109 | AC22: =IF( tabSuperdettagli[[#This Row],[ProjType_]]="M", IF( AND(tabSuperdettagli[[#This Row],[Resp 1°liv_]]="Guidotti C.", tabSuperdettagli[[#This Row],[WBE description_]]="Machine Mgmt"), "Documentation", tabSuperdettagli[[#This Row],[WBE description_]]), "" ) | AD22: =LEFT(tabSuperdettagli[[#This Row],[Network]], 18 ) | AE22: Send cost B | AP22: Int. | AV22: Responsabile B | BJ22: 101 | BK22: 102 | BL22: 103 | BM22: 104 | BN22: 105 | BO22: 106 | BP22: 107 | BQ22: 108 | BR22: 109 | BS22: 110 | BV22: 1055 | BX22: 42063 | CB22: 42062 | CC22: 42102
A23: =IF(UPPER(LEFT(tabSuperdettagli[[#This Row],[WBE Status]],1))="S","sì","no") -> no | B23: 2017 | C23: =VLOOKUP(tabSuperdettagli[[#This Row],[WBS_]],Pivot_AnnoPrimaMarcatura!A:B,2,FALSE) -> #N/A | D23: =LEFT(tabSuperdettagli[[#This Row],[Network]], 10) | E23: =LEFT(tabSuperdettagli[[#This Row],[Network]], 1) | F23: =LOWER(TRIM( tabSuperdettagli[[#This Row],[Proj. Type ]] )) | G23: =IF( OR( tabSuperdettagli[[#This Row],[ProjType_]]="C", tabSuperdettagli[[#This Row],[ProjType_]]="A", tabSuperdettagli[[#This Row],[ProjType_]]="R", tabSuperdettagli[[#This Row],[ProjType_]]="E"), "C A R E", IF( tabSuperdettagli[[#This Row],[ProjType_]]="U", "U (" & tabSuperdettagli[[#This Row],[U ProjType_]] & ")", tabSuperdettagli[[#This Row],[ProjType_]]) ) | I23: =IF( TRIM(tabSuperdettagli[[#This Row],[Raggr. X Struttura]])> "", TRIM(tabSuperdettagli[[#This Row],[Raggr. X Struttura]]), TRIM(tabSuperdettagli[[#This Row],[Resp DT]] ) ) -> Gruppo struttura 3 | J23: =tabSuperdettagli[[#This Row],[Total]] -> 2055 | K23: =tabSuperdettagli[[#This Row],[01.2025]] -> 201 | L23: =tabSuperdettagli[[#This Row],[02.2025]] -> 202 | M23: =tabSuperdettagli[[#This Row],[03.2025]] -> 203 | N23: =tabSuperdettagli[[#This Row],[04.2025]] -> 204 | O23: =tabSuperdettagli[[#This Row],[05.2025]] -> 205 | P23: =tabSuperdettagli[[#This Row],[06.2025]] -> 206 | Q23: =tabSuperdettagli[[#This Row],[07.2025]] -> 207 | R23: =tabSuperdettagli[[#This Row],[08.2025]] -> 208 | S23: =tabSuperdettagli[[#This Row],[09.2025]] -> 209 | T23: =tabSuperdettagli[[#This Row],[10.2025]] -> 210 | U23: =tabSuperdettagli[[#This Row],[11.2025]] -> 0 | V23: =tabSuperdettagli[[#This Row],[12.2025]] -> 0 | W23: =tabSuperdettagli[[#This Row],[INT/EST]] -> Est. | X23: =tabSuperdettagli[[#This Row],[Resp 2°liv]]&"" | Y23: =INDEX( tab_resp1liv[EngUnit area cluster 1_], MATCH( SUBSTITUTE(tabSuperdettagli[[#This Row],[Resp 2°liv]], " ", ""), tab_resp1liv[SearchKey],0)) -> #N/A | Z23: =tabSuperdettagli[[#This Row],[WBS Element]]&"" | AA23: =tabSuperdettagli[[#This Row],[09.2025]] -> 209 | AC23: =IF( tabSuperdettagli[[#This Row],[ProjType_]]="M", IF( AND(tabSuperdettagli[[#This Row],[Resp 1°liv_]]="Guidotti C.", tabSuperdettagli[[#This Row],[WBE description_]]="Machine Mgmt"), "Documentation", tabSuperdettagli[[#This Row],[WBE description_]]), "" ) | AD23: =LEFT(tabSuperdettagli[[#This Row],[Network]], 18 ) | AE23: Send cost C | AP23: Est. | AQ23: Gruppo struttura 3 | AV23: Responsabile A | BJ23: 201 | BK23: 202 | BL23: 203 | BM23: 204 | BN23: 205 | BO23: 206 | BP23: 207 | BQ23: 208 | BR23: 209 | BS23: 210 | BV23: 2055 | BX23: 42066 | CB23: 42065 | CC23: 42105
A24: =IF(UPPER(LEFT(tabSuperdettagli[[#This Row],[WBE Status]],1))="S","sì","no") -> no | B24: 2017 | C24: =VLOOKUP(tabSuperdettagli[[#This Row],[WBS_]],Pivot_AnnoPrimaMarcatura!A:B,2,FALSE) -> #N/A | D24: =LEFT(tabSuperdettagli[[#This Row],[Network]], 10) | E24: =LEFT(tabSuperdettagli[[#This Row],[Network]], 1) | F24: =LOWER(TRIM( tabSuperdettagli[[#This Row],[Proj. Type ]] )) | G24: =IF( OR( tabSuperdettagli[[#This Row],[ProjType_]]="C", tabSuperdettagli[[#This Row],[ProjType_]]="A", tabSuperdettagli[[#This Row],[ProjType_]]="R", tabSuperdettagli[[#This Row],[ProjType_]]="E"), "C A R E", IF( tabSuperdettagli[[#This Row],[ProjType_]]="U", "U (" & tabSuperdettagli[[#This Row],[U ProjType_]] & ")", tabSuperdettagli[[#This Row],[ProjType_]]) ) | I24: =IF( TRIM(tabSuperdettagli[[#This Row],[Raggr. X Struttura]])> "", TRIM(tabSuperdettagli[[#This Row],[Raggr. X Struttura]]), TRIM(tabSuperdettagli[[#This Row],[Resp DT]] ) ) -> Gruppo struttura 1 | J24: =tabSuperdettagli[[#This Row],[Total]] -> 3055 | K24: =tabSuperdettagli[[#This Row],[01.2025]] -> 301 | L24: =tabSuperdettagli[[#This Row],[02.2025]] -> 302 | M24: =tabSuperdettagli[[#This Row],[03.2025]] -> 303 | N24: =tabSuperdettagli[[#This Row],[04.2025]] -> 304 | O24: =tabSuperdettagli[[#This Row],[05.2025]] -> 305 | P24: =tabSuperdettagli[[#This Row],[06.2025]] -> 306 | Q24: =tabSuperdettagli[[#This Row],[07.2025]] -> 307 | R24: =tabSuperdettagli[[#This Row],[08.2025]] -> 308 | S24: =tabSuperdettagli[[#This Row],[09.2025]] -> 309 | T24: =tabSuperdettagli[[#This Row],[10.2025]] -> 310 | U24: =tabSuperdettagli[[#This Row],[11.2025]] -> 0 | V24: =tabSuperdettagli[[#This Row],[12.2025]] -> 0 | W24: =tabSuperdettagli[[#This Row],[INT/EST]] -> Est. | X24: =tabSuperdettagli[[#This Row],[Resp 2°liv]]&"" | Y24: =INDEX( tab_resp1liv[EngUnit area cluster 1_], MATCH( SUBSTITUTE(tabSuperdettagli[[#This Row],[Resp 2°liv]], " ", ""), tab_resp1liv[SearchKey],0)) -> #N/A | Z24: =tabSuperdettagli[[#This Row],[WBS Element]]&"" | AA24: =tabSuperdettagli[[#This Row],[09.2025]] -> 309 | AC24: =IF( tabSuperdettagli[[#This Row],[ProjType_]]="M", IF( AND(tabSuperdettagli[[#This Row],[Resp 1°liv_]]="Guidotti C.", tabSuperdettagli[[#This Row],[WBE description_]]="Machine Mgmt"), "Documentation", tabSuperdettagli[[#This Row],[WBE description_]]), "" ) | AD24: =LEFT(tabSuperdettagli[[#This Row],[Network]], 18 ) | AE24: Send cost C | AP24: Est. | AQ24: Gruppo struttura 1 | AV24: Responsabile A | BJ24: 301 | BK24: 302 | BL24: 303 | BM24: 304 | BN24: 305 | BO24: 306 | BP24: 307 | BQ24: 308 | BR24: 309 | BS24: 310 | BV24: 3055 | BX24: 42069 | CB24: 42068 | CC24: 42108
A25: =IF(UPPER(LEFT(tabSuperdettagli[[#This Row],[WBE Status]],1))="S","sì","no") -> no | B25: 2017 | C25: =VLOOKUP(tabSuperdettagli[[#This Row],[WBS_]],Pivot_AnnoPrimaMarcatura!A:B,2,FALSE) -> #N/A | D25: =LEFT(tabSuperdettagli[[#This Row],[Network]], 10) | E25: =LEFT(tabSuperdettagli[[#This Row],[Network]], 1) | F25: =LOWER(TRIM( tabSuperdettagli[[#This Row],[Proj. Type ]] )) | G25: =IF( OR( tabSuperdettagli[[#This Row],[ProjType_]]="C", tabSuperdettagli[[#This Row],[ProjType_]]="A", tabSuperdettagli[[#This Row],[ProjType_]]="R", tabSuperdettagli[[#This Row],[ProjType_]]="E"), "C A R E", IF( tabSuperdettagli[[#This Row],[ProjType_]]="U", "U (" & tabSuperdettagli[[#This Row],[U ProjType_]] & ")", tabSuperdettagli[[#This Row],[ProjType_]]) ) | I25: =IF( TRIM(tabSuperdettagli[[#This Row],[Raggr. X Struttura]])> "", TRIM(tabSuperdettagli[[#This Row],[Raggr. X Struttura]]), TRIM(tabSuperdettagli[[#This Row],[Resp DT]] ) ) -> Gruppo struttura 1 | J25: =tabSuperdettagli[[#This Row],[Total]] -> 4055 | K25: =tabSuperdettagli[[#This Row],[01.2025]] -> 401 | L25: =tabSuperdettagli[[#This Row],[02.2025]] -> 402 | M25: =tabSuperdettagli[[#This Row],[03.2025]] -> 403 | N25: =tabSuperdettagli[[#This Row],[04.2025]] -> 404 | O25: =tabSuperdettagli[[#This Row],[05.2025]] -> 405 | P25: =tabSuperdettagli[[#This Row],[06.2025]] -> 406 | Q25: =tabSuperdettagli[[#This Row],[07.2025]] -> 407 | R25: =tabSuperdettagli[[#This Row],[08.2025]] -> 408 | S25: =tabSuperdettagli[[#This Row],[09.2025]] -> 409 | T25: =tabSuperdettagli[[#This Row],[10.2025]] -> 410 | U25: =tabSuperdettagli[[#This Row],[11.2025]] -> 0 | V25: =tabSuperdettagli[[#This Row],[12.2025]] -> 0 | W25: =tabSuperdettagli[[#This Row],[INT/EST]] -> Int. | X25: =tabSuperdettagli[[#This Row],[Resp 2°liv]]&"" | Y25: =INDEX( tab_resp1liv[EngUnit area cluster 1_], MATCH( SUBSTITUTE(tabSuperdettagli[[#This Row],[Resp 2°liv]], " ", ""), tab_resp1liv[SearchKey],0)) -> #N/A | Z25: =tabSuperdettagli[[#This Row],[WBS Element]]&"" | AA25: =tabSuperdettagli[[#This Row],[09.2025]] -> 409 | AC25: =IF( tabSuperdettagli[[#This Row],[ProjType_]]="M", IF( AND(tabSuperdettagli[[#This Row],[Resp 1°liv_]]="Guidotti C.", tabSuperdettagli[[#This Row],[WBE description_]]="Machine Mgmt"), "Documentation", tabSuperdettagli[[#This Row],[WBE description_]]), "" ) | AD25: =LEFT(tabSuperdettagli[[#This Row],[Network]], 18 ) | AE25: Send cost C | AP25: Int. | AQ25: Gruppo struttura 1 | AV25: Responsabile A | BJ25: 401 | BK25: 402 | BL25: 403 | BM25: 404 | BN25: 405 | BO25: 406 | BP25: 407 | BQ25: 408 | BR25: 409 | BS25: 410 | BV25: 4055 | BX25: 42072 | CB25: 42071 | CC25: 42111
A26: =IF(UPPER(LEFT(tabSuperdettagli[[#This Row],[WBE Status]],1))="S","sì","no") -> no | B26: 2017 | C26: =VLOOKUP(tabSuperdettagli[[#This Row],[WBS_]],Pivot_AnnoPrimaMarcatura!A:B,2,FALSE) -> #N/A | D26: =LEFT(tabSuperdettagli[[#This Row],[Network]], 10) | E26: =LEFT(tabSuperdettagli[[#This Row],[Network]], 1) | F26: =LOWER(TRIM( tabSuperdettagli[[#This Row],[Proj. Type ]] )) | G26: =IF( OR( tabSuperdettagli[[#This Row],[ProjType_]]="C", tabSuperdettagli[[#This Row],[ProjType_]]="A", tabSuperdettagli[[#This Row],[ProjType_]]="R", tabSuperdettagli[[#This Row],[ProjType_]]="E"), "C A R E", IF( tabSuperdettagli[[#This Row],[ProjType_]]="U", "U (" & tabSuperdettagli[[#This Row],[U ProjType_]] & ")", tabSuperdettagli[[#This Row],[ProjType_]]) ) | I26: =IF( TRIM(tabSuperdettagli[[#This Row],[Raggr. X Struttura]])> "", TRIM(tabSuperdettagli[[#This Row],[Raggr. X Struttura]]), TRIM(tabSuperdettagli[[#This Row],[Resp DT]] ) ) -> Gruppo struttura 4 | J26: =tabSuperdettagli[[#This Row],[Total]] -> 5055 | K26: =tabSuperdettagli[[#This Row],[01.2025]] -> 501 | L26: =tabSuperdettagli[[#This Row],[02.2025]] -> 502 | M26: =tabSuperdettagli[[#This Row],[03.2025]] -> 503 | N26: =tabSuperdettagli[[#This Row],[04.2025]] -> 504 | O26: =tabSuperdettagli[[#This Row],[05.2025]] -> 505 | P26: =tabSuperdettagli[[#This Row],[06.2025]] -> 506 | Q26: =tabSuperdettagli[[#This Row],[07.2025]] -> 507 | R26: =tabSuperdettagli[[#This Row],[08.2025]] -> 508 | S26: =tabSuperdettagli[[#This Row],[09.2025]] -> 509 | T26: =tabSuperdettagli[[#This Row],[10.2025]] -> 510 | U26: =tabSuperdettagli[[#This Row],[11.2025]] -> 0 | V26: =tabSuperdettagli[[#This Row],[12.2025]] -> 0 | W26: =tabSuperdettagli[[#This Row],[INT/EST]] -> Int. | X26: =tabSuperdettagli[[#This Row],[Resp 2°liv]]&"" | Y26: =INDEX( tab_resp1liv[EngUnit area cluster 1_], MATCH( SUBSTITUTE(tabSuperdettagli[[#This Row],[Resp 2°liv]], " ", ""), tab_resp1liv[SearchKey],0)) -> #N/A | Z26: =tabSuperdettagli[[#This Row],[WBS Element]]&"" | AA26: =tabSuperdettagli[[#This Row],[09.2025]] -> 509 | AC26: =IF( tabSuperdettagli[[#This Row],[ProjType_]]="M", IF( AND(tabSuperdettagli[[#This Row],[Resp 1°liv_]]="Guidotti C.", tabSuperdettagli[[#This Row],[WBE description_]]="Machine Mgmt"), "Documentation", tabSuperdettagli[[#This Row],[WBE description_]]), "" ) | AD26: =LEFT(tabSuperdettagli[[#This Row],[Network]], 18 ) | AE26: Send cost C | AP26: Int. | AQ26: Gruppo struttura 4 | AV26: Responsabile A | BJ26: 501 | BK26: 502 | BL26: 503 | BM26: 504 | BN26: 505 | BO26: 506 | BP26: 507 | BQ26: 508 | BR26: 509 | BS26: 510 | BV26: 5055 | BX26: 42075 | CB26: 42074 | CC26: 42114
A27: =IF(UPPER(LEFT(tabSuperdettagli[[#This Row],[WBE Status]],1))="S","sì","no") -> no | B27: 2017 | C27: =VLOOKUP(tabSuperdettagli[[#This Row],[WBS_]],Pivot_AnnoPrimaMarcatura!A:B,2,FALSE) -> #N/A | D27: =LEFT(tabSuperdettagli[[#This Row],[Network]], 10) | E27: =LEFT(tabSuperdettagli[[#This Row],[Network]], 1) | F27: =LOWER(TRIM( tabSuperdettagli[[#This Row],[Proj. Type ]] )) | G27: =IF( OR( tabSuperdettagli[[#This Row],[ProjType_]]="C", tabSuperdettagli[[#This Row],[ProjType_]]="A", tabSuperdettagli[[#This Row],[ProjType_]]="R", tabSuperdettagli[[#This Row],[ProjType_]]="E"), "C A R E", IF( tabSuperdettagli[[#This Row],[ProjType_]]="U", "U (" & tabSuperdettagli[[#This Row],[U ProjType_]] & ")", tabSuperdettagli[[#This Row],[ProjType_]]) ) | I27: =IF( TRIM(tabSuperdettagli[[#This Row],[Raggr. X Struttura]])> "", TRIM(tabSuperdettagli[[#This Row],[Raggr. X Struttura]]), TRIM(tabSuperdettagli[[#This Row],[Resp DT]] ) ) -> Gruppo struttura 1 | J27: =tabSuperdettagli[[#This Row],[Total]] -> 6055 | K27: =tabSuperdettagli[[#This Row],[01.2025]] -> 601 | L27: =tabSuperdettagli[[#This Row],[02.2025]] -> 602 | M27: =tabSuperdettagli[[#This Row],[03.2025]] -> 603 | N27: =tabSuperdettagli[[#This Row],[04.2025]] -> 604 | O27: =tabSuperdettagli[[#This Row],[05.2025]] -> 605 | P27: =tabSuperdettagli[[#This Row],[06.2025]] -> 606 | Q27: =tabSuperdettagli[[#This Row],[07.2025]] -> 607 | R27: =tabSuperdettagli[[#This Row],[08.2025]] -> 608 | S27: =tabSuperdettagli[[#This Row],[09.2025]] -> 609 | T27: =tabSuperdettagli[[#This Row],[10.2025]] -> 610 | U27: =tabSuperdettagli[[#This Row],[11.2025]] -> 0 | V27: =tabSuperdettagli[[#This Row],[12.2025]] -> 0 | W27: =tabSuperdettagli[[#This Row],[INT/EST]] -> Int. | X27: =tabSuperdettagli[[#This Row],[Resp 2°liv]]&"" | Y27: =INDEX( tab_resp1liv[EngUnit area cluster 1_], MATCH( SUBSTITUTE(tabSuperdettagli[[#This Row],[Resp 2°liv]], " ", ""), tab_resp1liv[SearchKey],0)) -> #N/A | Z27: =tabSuperdettagli[[#This Row],[WBS Element]]&"" | AA27: =tabSuperdettagli[[#This Row],[09.2025]] -> 609 | AC27: =IF( tabSuperdettagli[[#This Row],[ProjType_]]="M", IF( AND(tabSuperdettagli[[#This Row],[Resp 1°liv_]]="Guidotti C.", tabSuperdettagli[[#This Row],[WBE description_]]="Machine Mgmt"), "Documentation", tabSuperdettagli[[#This Row],[WBE description_]]), "" ) | AD27: =LEFT(tabSuperdettagli[[#This Row],[Network]], 18 ) | AE27: Send cost C | AP27: Int. | AQ27: Gruppo struttura 1 | AV27: Responsabile A | BJ27: 601 | BK27: 602 | BL27: 603 | BM27: 604 | BN27: 605 | BO27: 606 | BP27: 607 | BQ27: 608 | BR27: 609 | BS27: 610 | BV27: 6055 | BX27: 42078 | CB27: 42077 | CC27: 42117
A28: =IF(UPPER(LEFT(tabSuperdettagli[[#This Row],[WBE Status]],1))="S","sì","no") -> no | B28: 2017 | C28: =VLOOKUP(tabSuperdettagli[[#This Row],[WBS_]],Pivot_AnnoPrimaMarcatura!A:B,2,FALSE) -> #N/A | D28: =LEFT(tabSuperdettagli[[#This Row],[Network]], 10) | E28: =LEFT(tabSuperdettagli[[#This Row],[Network]], 1) | F28: =LOWER(TRIM( tabSuperdettagli[[#This Row],[Proj. Type ]] )) | G28: =IF( OR( tabSuperdettagli[[#This Row],[ProjType_]]="C", tabSuperdettagli[[#This Row],[ProjType_]]="A", tabSuperdettagli[[#This Row],[ProjType_]]="R", tabSuperdettagli[[#This Row],[ProjType_]]="E"), "C A R E", IF( tabSuperdettagli[[#This Row],[ProjType_]]="U", "U (" & tabSuperdettagli[[#This Row],[U ProjType_]] & ")", tabSuperdettagli[[#This Row],[ProjType_]]) ) | I28: =IF( TRIM(tabSuperdettagli[[#This Row],[Raggr. X Struttura]])> "", TRIM(tabSuperdettagli[[#This Row],[Raggr. X Struttura]]), TRIM(tabSuperdettagli[[#This Row],[Resp DT]] ) ) -> Gruppo struttura 1 | J28: =tabSuperdettagli[[#This Row],[Total]] -> 55 | K28: =tabSuperdettagli[[#This Row],[01.2025]] -> 1 | L28: =tabSuperdettagli[[#This Row],[02.2025]] -> 2 | M28: =tabSuperdettagli[[#This Row],[03.2025]] -> 3 | N28: =tabSuperdettagli[[#This Row],[04.2025]] -> 4 | O28: =tabSuperdettagli[[#This Row],[05.2025]] -> 5 | P28: =tabSuperdettagli[[#This Row],[06.2025]] -> 6 | Q28: =tabSuperdettagli[[#This Row],[07.2025]] -> 7 | R28: =tabSuperdettagli[[#This Row],[08.2025]] -> 8 | S28: =tabSuperdettagli[[#This Row],[09.2025]] -> 9 | T28: =tabSuperdettagli[[#This Row],[10.2025]] -> 10 | U28: =tabSuperdettagli[[#This Row],[11.2025]] -> 0 | V28: =tabSuperdettagli[[#This Row],[12.2025]] -> 0 | W28: =tabSuperdettagli[[#This Row],[INT/EST]] -> Int. | X28: =tabSuperdettagli[[#This Row],[Resp 2°liv]]&"" | Y28: =INDEX( tab_resp1liv[EngUnit area cluster 1_], MATCH( SUBSTITUTE(tabSuperdettagli[[#This Row],[Resp 2°liv]], " ", ""), tab_resp1liv[SearchKey],0)) -> #N/A | Z28: =tabSuperdettagli[[#This Row],[WBS Element]]&"" | AA28: =tabSuperdettagli[[#This Row],[09.2025]] -> 9 | AC28: =IF( tabSuperdettagli[[#This Row],[ProjType_]]="M", IF( AND(tabSuperdettagli[[#This Row],[Resp 1°liv_]]="Guidotti C.", tabSuperdettagli[[#This Row],[WBE description_]]="Machine Mgmt"), "Documentation", tabSuperdettagli[[#This Row],[WBE description_]]), "" ) | AD28: =LEFT(tabSuperdettagli[[#This Row],[Network]], 18 ) | AE28: Send cost C | AP28: Int. | AQ28: Gruppo struttura 1 | AV28: Responsabile A | BJ28: 1 | BK28: 2 | BL28: 3 | BM28: 4 | BN28: 5 | BO28: 6 | BP28: 7 | BQ28: 8 | BR28: 9 | BS28: 10 | BV28: 55 | BX28: 42081 | CB28: 42080 | CC28: 42120
A29: =IF(UPPER(LEFT(tabSuperdettagli[[#This Row],[WBE Status]],1))="S","sì","no") -> no | B29: 2017 | C29: =VLOOKUP(tabSuperdettagli[[#This Row],[WBS_]],Pivot_AnnoPrimaMarcatura!A:B,2,FALSE) -> #N/A | D29: =LEFT(tabSuperdettagli[[#This Row],[Network]], 10) | E29: =LEFT(tabSuperdettagli[[#This Row],[Network]], 1) | F29: =LOWER(TRIM( tabSuperdettagli[[#This Row],[Proj. Type ]] )) | G29: =IF( OR( tabSuperdettagli[[#This Row],[ProjType_]]="C", tabSuperdettagli[[#This Row],[ProjType_]]="A", tabSuperdettagli[[#This Row],[ProjType_]]="R", tabSuperdettagli[[#This Row],[ProjType_]]="E"), "C A R E", IF( tabSuperdettagli[[#This Row],[ProjType_]]="U", "U (" & tabSuperdettagli[[#This Row],[U ProjType_]] & ")", tabSuperdettagli[[#This Row],[ProjType_]]) ) | I29: =IF( TRIM(tabSuperdettagli[[#This Row],[Raggr. X Struttura]])> "", TRIM(tabSuperdettagli[[#This Row],[Raggr. X Struttura]]), TRIM(tabSuperdettagli[[#This Row],[Resp DT]] ) ) -> Gruppo struttura 1 | J29: =tabSuperdettagli[[#This Row],[Total]] -> 1055 | K29: =tabSuperdettagli[[#This Row],[01.2025]] -> 101 | L29: =tabSuperdettagli[[#This Row],[02.2025]] -> 102 | M29: =tabSuperdettagli[[#This Row],[03.2025]] -> 103 | N29: =tabSuperdettagli[[#This Row],[04.2025]] -> 104 | O29: =tabSuperdettagli[[#This Row],[05.2025]] -> 105 | P29: =tabSuperdettagli[[#This Row],[06.2025]] -> 106 | Q29: =tabSuperdettagli[[#This Row],[07.2025]] -> 107 | R29: =tabSuperdettagli[[#This Row],[08.2025]] -> 108 | S29: =tabSuperdettagli[[#This Row],[09.2025]] -> 109 | T29: =tabSuperdettagli[[#This Row],[10.2025]] -> 110 | U29: =tabSuperdettagli[[#This Row],[11.2025]] -> 0 | V29: =tabSuperdettagli[[#This Row],[12.2025]] -> 0 | W29: =tabSuperdettagli[[#This Row],[INT/EST]] -> Int. | X29: =tabSuperdettagli[[#This Row],[Resp 2°liv]]&"" | Y29: =INDEX( tab_resp1liv[EngUnit area cluster 1_], MATCH( SUBSTITUTE(tabSuperdettagli[[#This Row],[Resp 2°liv]], " ", ""), tab_resp1liv[SearchKey],0)) -> #N/A | Z29: =tabSuperdettagli[[#This Row],[WBS Element]]&"" | AA29: =tabSuperdettagli[[#This Row],[09.2025]] -> 109 | AC29: =IF( tabSuperdettagli[[#This Row],[ProjType_]]="M", IF( AND(tabSuperdettagli[[#This Row],[Resp 1°liv_]]="Guidotti C.", tabSuperdettagli[[#This Row],[WBE description_]]="Machine Mgmt"), "Documentation", tabSuperdettagli[[#This Row],[WBE description_]]), "" ) | AD29: =LEFT(tabSuperdettagli[[#This Row],[Network]], 18 ) | AE29: Send cost C | AP29: Int. | AQ29: Gruppo struttura 1 | AV29: Responsabile A | BJ29: 101 | BK29: 102 | BL29: 103 | BM29: 104 | BN29: 105 | BO29: 106 | BP29: 107 | BQ29: 108 | BR29: 109 | BS29: 110 | BV29: 1055 | BX29: 42084 | CB29: 42083 | CC29: 42123
A30: =IF(UPPER(LEFT(tabSuperdettagli[[#This Row],[WBE Status]],1))="S","sì","no") -> no | B30: 2017 | C30: =VLOOKUP(tabSuperdettagli[[#This Row],[WBS_]],Pivot_AnnoPrimaMarcatura!A:B,2,FALSE) -> #N/A | D30: =LEFT(tabSuperdettagli[[#This Row],[Network]], 10) | E30: =LEFT(tabSuperdettagli[[#This Row],[Network]], 1) | F30: =LOWER(TRIM( tabSuperdettagli[[#This Row],[Proj. Type ]] )) | G30: =IF( OR( tabSuperdettagli[[#This Row],[ProjType_]]="C", tabSuperdettagli[[#This Row],[ProjType_]]="A", tabSuperdettagli[[#This Row],[ProjType_]]="R", tabSuperdettagli[[#This Row],[ProjType_]]="E"), "C A R E", IF( tabSuperdettagli[[#This Row],[ProjType_]]="U", "U (" & tabSuperdettagli[[#This Row],[U ProjType_]] & ")", tabSuperdettagli[[#This Row],[ProjType_]]) ) | I30: =IF( TRIM(tabSuperdettagli[[#This Row],[Raggr. X Struttura]])> "", TRIM(tabSuperdettagli[[#This Row],[Raggr. X Struttura]]), TRIM(tabSuperdettagli[[#This Row],[Resp DT]] ) ) -> Gruppo struttura 2 | J30: =tabSuperdettagli[[#This Row],[Total]] -> 2055 | K30: =tabSuperdettagli[[#This Row],[01.2025]] -> 201 | L30: =tabSuperdettagli[[#This Row],[02.2025]] -> 202 | M30: =tabSuperdettagli[[#This Row],[03.2025]] -> 203 | N30: =tabSuperdettagli[[#This Row],[04.2025]] -> 204 | O30: =tabSuperdettagli[[#This Row],[05.2025]] -> 205 | P30: =tabSuperdettagli[[#This Row],[06.2025]] -> 206 | Q30: =tabSuperdettagli[[#This Row],[07.2025]] -> 207 | R30: =tabSuperdettagli[[#This Row],[08.2025]] -> 208 | S30: =tabSuperdettagli[[#This Row],[09.2025]] -> 209 | T30: =tabSuperdettagli[[#This Row],[10.2025]] -> 210 | U30: =tabSuperdettagli[[#This Row],[11.2025]] -> 0 | V30: =tabSuperdettagli[[#This Row],[12.2025]] -> 0 | W30: =tabSuperdettagli[[#This Row],[INT/EST]] -> Int. | X30: =tabSuperdettagli[[#This Row],[Resp 2°liv]]&"" | Y30: =INDEX( tab_resp1liv[EngUnit area cluster 1_], MATCH( SUBSTITUTE(tabSuperdettagli[[#This Row],[Resp 2°liv]], " ", ""), tab_resp1liv[SearchKey],0)) -> #N/A | Z30: =tabSuperdettagli[[#This Row],[WBS Element]]&"" | AA30: =tabSuperdettagli[[#This Row],[09.2025]] -> 209 | AC30: =IF( tabSuperdettagli[[#This Row],[ProjType_]]="M", IF( AND(tabSuperdettagli[[#This Row],[Resp 1°liv_]]="Guidotti C.", tabSuperdettagli[[#This Row],[WBE description_]]="Machine Mgmt"), "Documentation", tabSuperdettagli[[#This Row],[WBE description_]]), "" ) | AD30: =LEFT(tabSuperdettagli[[#This Row],[Network]], 18 ) | AE30: Send cost C | AP30: Int. | AQ30: Gruppo struttura 2 | AV30: Responsabile E | BJ30: 201 | BK30: 202 | BL30: 203 | BM30: 204 | BN30: 205 | BO30: 206 | BP30: 207 | BQ30: 208 | BR30: 209 | BS30: 210 | BV30: 2055 | BX30: 42087 | CB30: 42086 | CC30: 42126
A31: =IF(UPPER(LEFT(tabSuperdettagli[[#This Row],[WBE Status]],1))="S","sì","no") -> no | B31: 2017 | C31: =VLOOKUP(tabSuperdettagli[[#This Row],[WBS_]],Pivot_AnnoPrimaMarcatura!A:B,2,FALSE) -> #N/A | D31: =LEFT(tabSuperdettagli[[#This Row],[Network]], 10) | E31: =LEFT(tabSuperdettagli[[#This Row],[Network]], 1) | F31: =LOWER(TRIM( tabSuperdettagli[[#This Row],[Proj. Type ]] )) | G31: =IF( OR( tabSuperdettagli[[#This Row],[ProjType_]]="C", tabSuperdettagli[[#This Row],[ProjType_]]="A", tabSuperdettagli[[#This Row],[ProjType_]]="R", tabSuperdettagli[[#This Row],[ProjType_]]="E"), "C A R E", IF( tabSuperdettagli[[#This Row],[ProjType_]]="U", "U (" & tabSuperdettagli[[#This Row],[U ProjType_]] & ")", tabSuperdettagli[[#This Row],[ProjType_]]) ) | I31: =IF( TRIM(tabSuperdettagli[[#This Row],[Raggr. X Struttura]])> "", TRIM(tabSuperdettagli[[#This Row],[Raggr. X Struttura]]), TRIM(tabSuperdettagli[[#This Row],[Resp DT]] ) ) -> Gruppo struttura 1 | J31: =tabSuperdettagli[[#This Row],[Total]] -> 3055 | K31: =tabSuperdettagli[[#This Row],[01.2025]] -> 301 | L31: =tabSuperdettagli[[#This Row],[02.2025]] -> 302 | M31: =tabSuperdettagli[[#This Row],[03.2025]] -> 303 | N31: =tabSuperdettagli[[#This Row],[04.2025]] -> 304 | O31: =tabSuperdettagli[[#This Row],[05.2025]] -> 305 | P31: =tabSuperdettagli[[#This Row],[06.2025]] -> 306 | Q31: =tabSuperdettagli[[#This Row],[07.2025]] -> 307 | R31: =tabSuperdettagli[[#This Row],[08.2025]] -> 308 | S31: =tabSuperdettagli[[#This Row],[09.2025]] -> 309 | T31: =tabSuperdettagli[[#This Row],[10.2025]] -> 310 | U31: =tabSuperdettagli[[#This Row],[11.2025]] -> 0 | V31: =tabSuperdettagli[[#This Row],[12.2025]] -> 0 | W31: =tabSuperdettagli[[#This Row],[INT/EST]] -> Est. | X31: =tabSuperdettagli[[#This Row],[Resp 2°liv]]&"" | Y31: =INDEX( tab_resp1liv[EngUnit area cluster 1_], MATCH( SUBSTITUTE(tabSuperdettagli[[#This Row],[Resp 2°liv]], " ", ""), tab_resp1liv[SearchKey],0)) -> #N/A | Z31: =tabSuperdettagli[[#This Row],[WBS Element]]&"" | AA31: =tabSuperdettagli[[#This Row],[09.2025]] -> 309 | AC31: =IF( tabSuperdettagli[[#This Row],[ProjType_]]="M", IF( AND(tabSuperdettagli[[#This Row],[Resp 1°liv_]]="Guidotti C.", tabSuperdettagli[[#This Row],[WBE description_]]="Machine Mgmt"), "Documentation", tabSuperdettagli[[#This Row],[WBE description_]]), "" ) | AD31: =LEFT(tabSuperdettagli[[#This Row],[Network]], 18 ) | AE31: Send cost C | AP31: Est. | AQ31: Gruppo struttura 1 | AV31: Responsabile B | BJ31: 301 | BK31: 302 | BL31: 303 | BM31: 304 | BN31: 305 | BO31: 306 | BP31: 307 | BQ31: 308 | BR31: 309 | BS31: 310 | BV31: 3055 | BX31: 42090 | CB31: 42089 | CC31: 42129
A32: =IF(UPPER(LEFT(tabSuperdettagli[[#This Row],[WBE Status]],1))="S","sì","no") -> no | B32: 2017 | C32: =VLOOKUP(tabSuperdettagli[[#This Row],[WBS_]],Pivot_AnnoPrimaMarcatura!A:B,2,FALSE) -> #N/A | D32: =LEFT(tabSuperdettagli[[#This Row],[Network]], 10) | E32: =LEFT(tabSuperdettagli[[#This Row],[Network]], 1) | F32: =LOWER(TRIM( tabSuperdettagli[[#This Row],[Proj. Type ]] )) | G32: =IF( OR( tabSuperdettagli[[#This Row],[ProjType_]]="C", tabSuperdettagli[[#This Row],[ProjType_]]="A", tabSuperdettagli[[#This Row],[ProjType_]]="R", tabSuperdettagli[[#This Row],[ProjType_]]="E"), "C A R E", IF( tabSuperdettagli[[#This Row],[ProjType_]]="U", "U (" & tabSuperdettagli[[#This Row],[U ProjType_]] & ")", tabSuperdettagli[[#This Row],[ProjType_]]) ) | I32: =IF( TRIM(tabSuperdettagli[[#This Row],[Raggr. X Struttura]])> "", TRIM(tabSuperdettagli[[#This Row],[Raggr. X Struttura]]), TRIM(tabSuperdettagli[[#This Row],[Resp DT]] ) ) -> Responsabile A | J32: =tabSuperdettagli[[#This Row],[Total]] -> 4055 | K32: =tabSuperdettagli[[#This Row],[01.2025]] -> 401 | L32: =tabSuperdettagli[[#This Row],[02.2025]] -> 402 | M32: =tabSuperdettagli[[#This Row],[03.2025]] -> 403 | N32: =tabSuperdettagli[[#This Row],[04.2025]] -> 404 | O32: =tabSuperdettagli[[#This Row],[05.2025]] -> 405 | P32: =tabSuperdettagli[[#This Row],[06.2025]] -> 406 | Q32: =tabSuperdettagli[[#This Row],[07.2025]] -> 407 | R32: =tabSuperdettagli[[#This Row],[08.2025]] -> 408 | S32: =tabSuperdettagli[[#This Row],[09.2025]] -> 409 | T32: =tabSuperdettagli[[#This Row],[10.2025]] -> 410 | U32: =tabSuperdettagli[[#This Row],[11.2025]] -> 0 | V32: =tabSuperdettagli[[#This Row],[12.2025]] -> 0 | W32: =tabSuperdettagli[[#This Row],[INT/EST]] -> Est. | X32: =tabSuperdettagli[[#This Row],[Resp 2°liv]]&"" | Y32: =INDEX( tab_resp1liv[EngUnit area cluster 1_], MATCH( SUBSTITUTE(tabSuperdettagli[[#This Row],[Resp 2°liv]], " ", ""), tab_resp1liv[SearchKey],0)) -> #N/A | Z32: =tabSuperdettagli[[#This Row],[WBS Element]]&"" | AA32: =tabSuperdettagli[[#This Row],[09.2025]] -> 409 | AC32: =IF( tabSuperdettagli[[#This Row],[ProjType_]]="M", IF( AND(tabSuperdettagli[[#This Row],[Resp 1°liv_]]="Guidotti C.", tabSuperdettagli[[#This Row],[WBE description_]]="Machine Mgmt"), "Documentation", tabSuperdettagli[[#This Row],[WBE description_]]), "" ) | AD32: =LEFT(tabSuperdettagli[[#This Row],[Network]], 18 ) | AE32: Send cost C | AP32: Est. | AV32: Responsabile A | BJ32: 401 | BK32: 402 | BL32: 403 | BM32: 404 | BN32: 405 | BO32: 406 | BP32: 407 | BQ32: 408 | BR32: 409 | BS32: 410 | BV32: 4055 | BX32: 42093 | CB32: 42092 | CC32: 42132
A33: =IF(UPPER(LEFT(tabSuperdettagli[[#This Row],[WBE Status]],1))="S","sì","no") -> no | B33: 2018 | C33: =VLOOKUP(tabSuperdettagli[[#This Row],[WBS_]],Pivot_AnnoPrimaMarcatura!A:B,2,FALSE) -> #N/A | D33: =LEFT(tabSuperdettagli[[#This Row],[Network]], 10) | E33: =LEFT(tabSuperdettagli[[#This Row],[Network]], 1) | F33: =LOWER(TRIM( tabSuperdettagli[[#This Row],[Proj. Type ]] )) | G33: =IF( OR( tabSuperdettagli[[#This Row],[ProjType_]]="C", tabSuperdettagli[[#This Row],[ProjType_]]="A", tabSuperdettagli[[#This Row],[ProjType_]]="R", tabSuperdettagli[[#This Row],[ProjType_]]="E"), "C A R E", IF( tabSuperdettagli[[#This Row],[ProjType_]]="U", "U (" & tabSuperdettagli[[#This Row],[U ProjType_]] & ")", tabSuperdettagli[[#This Row],[ProjType_]]) ) | I33: =IF( TRIM(tabSuperdettagli[[#This Row],[Raggr. X Struttura]])> "", TRIM(tabSuperdettagli[[#This Row],[Raggr. X Struttura]]), TRIM(tabSuperdettagli[[#This Row],[Resp DT]] ) ) -> Responsabile A | J33: =tabSuperdettagli[[#This Row],[Total]] -> 5055 | K33: =tabSuperdettagli[[#This Row],[01.2025]] -> 501 | L33: =tabSuperdettagli[[#This Row],[02.2025]] -> 502 | M33: =tabSuperdettagli[[#This Row],[03.2025]] -> 503 | N33: =tabSuperdettagli[[#This Row],[04.2025]] -> 504 | O33: =tabSuperdettagli[[#This Row],[05.2025]] -> 505 | P33: =tabSuperdettagli[[#This Row],[06.2025]] -> 506 | Q33: =tabSuperdettagli[[#This Row],[07.2025]] -> 507 | R33: =tabSuperdettagli[[#This Row],[08.2025]] -> 508 | S33: =tabSuperdettagli[[#This Row],[09.2025]] -> 509 | T33: =tabSuperdettagli[[#This Row],[10.2025]] -> 510 | U33: =tabSuperdettagli[[#This Row],[11.2025]] -> 0 | V33: =tabSuperdettagli[[#This Row],[12.2025]] -> 0 | W33: =tabSuperdettagli[[#This Row],[INT/EST]] -> Est. | X33: =tabSuperdettagli[[#This Row],[Resp 2°liv]]&"" | Y33: =INDEX( tab_resp1liv[EngUnit area cluster 1_], MATCH( SUBSTITUTE(tabSuperdettagli[[#This Row],[Resp 2°liv]], " ", ""), tab_resp1liv[SearchKey],0)) -> #N/A | Z33: =tabSuperdettagli[[#This Row],[WBS Element]]&"" | AA33: =tabSuperdettagli[[#This Row],[09.2025]] -> 509 | AC33: =IF( tabSuperdettagli[[#This Row],[ProjType_]]="M", IF( AND(tabSuperdettagli[[#This Row],[Resp 1°liv_]]="Guidotti C.", tabSuperdettagli[[#This Row],[WBE description_]]="Machine Mgmt"), "Documentation", tabSuperdettagli[[#This Row],[WBE description_]]), "" ) | AD33: =LEFT(tabSuperdettagli[[#This Row],[Network]], 18 ) | AE33: Send cost D | AP33: Est. | AV33: Responsabile A | BJ33: 501 | BK33: 502 | BL33: 503 | BM33: 504 | BN33: 505 | BO33: 506 | BP33: 507 | BQ33: 508 | BR33: 509 | BS33: 510 | BV33: 5055 | BX33: 42096 | CB33: 42095 | CC33: 42135
A34: =IF(UPPER(LEFT(tabSuperdettagli[[#This Row],[WBE Status]],1))="S","sì","no") -> no | B34: 2018 | C34: =VLOOKUP(tabSuperdettagli[[#This Row],[WBS_]],Pivot_AnnoPrimaMarcatura!A:B,2,FALSE) -> #N/A | D34: =LEFT(tabSuperdettagli[[#This Row],[Network]], 10) | E34: =LEFT(tabSuperdettagli[[#This Row],[Network]], 1) | F34: =LOWER(TRIM( tabSuperdettagli[[#This Row],[Proj. Type ]] )) | G34: =IF( OR( tabSuperdettagli[[#This Row],[ProjType_]]="C", tabSuperdettagli[[#This Row],[ProjType_]]="A", tabSuperdettagli[[#This Row],[ProjType_]]="R", tabSuperdettagli[[#This Row],[ProjType_]]="E"), "C A R E", IF( tabSuperdettagli[[#This Row],[ProjType_]]="U", "U (" & tabSuperdettagli[[#This Row],[U ProjType_]] & ")", tabSuperdettagli[[#This Row],[ProjType_]]) ) | I34: =IF( TRIM(tabSuperdettagli[[#This Row],[Raggr. X Struttura]])> "", TRIM(tabSuperdettagli[[#This Row],[Raggr. X Struttura]]), TRIM(tabSuperdettagli[[#This Row],[Resp DT]] ) ) -> Gruppo struttura 2 | J34: =tabSuperdettagli[[#This Row],[Total]] -> 6055 | K34: =tabSuperdettagli[[#This Row],[01.2025]] -> 601 | L34: =tabSuperdettagli[[#This Row],[02.2025]] -> 602 | M34: =tabSuperdettagli[[#This Row],[03.2025]] -> 603 | N34: =tabSuperdettagli[[#This Row],[04.2025]] -> 604 | O34: =tabSuperdettagli[[#This Row],[05.2025]] -> 605 | P34: =tabSuperdettagli[[#This Row],[06.2025]] -> 606 | Q34: =tabSuperdettagli[[#This Row],[07.2025]] -> 607 | R34: =tabSuperdettagli[[#This Row],[08.2025]] -> 608 | S34: =tabSuperdettagli[[#This Row],[09.2025]] -> 609 | T34: =tabSuperdettagli[[#This Row],[10.2025]] -> 610 | U34: =tabSuperdettagli[[#This Row],[11.2025]] -> 0 | V34: =tabSuperdettagli[[#This Row],[12.2025]] -> 0 | W34: =tabSuperdettagli[[#This Row],[INT/EST]] -> Est. | X34: =tabSuperdettagli[[#This Row],[Resp 2°liv]]&"" | Y34: =INDEX( tab_resp1liv[EngUnit area cluster 1_], MATCH( SUBSTITUTE(tabSuperdettagli[[#This Row],[Resp 2°liv]], " ", ""), tab_resp1liv[SearchKey],0)) -> #N/A | Z34: =tabSuperdettagli[[#This Row],[WBS Element]]&"" | AA34: =tabSuperdettagli[[#This Row],[09.2025]] -> 609 | AC34: =IF( tabSuperdettagli[[#This Row],[ProjType_]]="M", IF( AND(tabSuperdettagli[[#This Row],[Resp 1°liv_]]="Guidotti C.", tabSuperdettagli[[#This Row],[WBE description_]]="Machine Mgmt"), "Documentation", tabSuperdettagli[[#This Row],[WBE description_]]), "" ) | AD34: =LEFT(tabSuperdettagli[[#This Row],[Network]], 18 ) | AE34: Send cost D | AP34: Est. | AQ34: Gruppo struttura 2 | AV34: Responsabile C | BJ34: 601 | BK34: 602 | BL34: 603 | BM34: 604 | BN34: 605 | BO34: 606 | BP34: 607 | BQ34: 608 | BR34: 609 | BS34: 610 | BV34: 6055 | BX34: 42099 | CB34: 42098 | CC34: 42138
A35: =IF(UPPER(LEFT(tabSuperdettagli[[#This Row],[WBE Status]],1))="S","sì","no") -> no | B35: 2018 | C35: =VLOOKUP(tabSuperdettagli[[#This Row],[WBS_]],Pivot_AnnoPrimaMarcatura!A:B,2,FALSE) -> #N/A | D35: =LEFT(tabSuperdettagli[[#This Row],[Network]], 10) | E35: =LEFT(tabSuperdettagli[[#This Row],[Network]], 1) | F35: =LOWER(TRIM( tabSuperdettagli[[#This Row],[Proj. Type ]] )) | G35: =IF( OR( tabSuperdettagli[[#This Row],[ProjType_]]="C", tabSuperdettagli[[#This Row],[ProjType_]]="A", tabSuperdettagli[[#This Row],[ProjType_]]="R", tabSuperdettagli[[#This Row],[ProjType_]]="E"), "C A R E", IF( tabSuperdettagli[[#This Row],[ProjType_]]="U", "U (" & tabSuperdettagli[[#This Row],[U ProjType_]] & ")", tabSuperdettagli[[#This Row],[ProjType_]]) ) | I35: =IF( TRIM(tabSuperdettagli[[#This Row],[Raggr. X Struttura]])> "", TRIM(tabSuperdettagli[[#This Row],[Raggr. X Struttura]]), TRIM(tabSuperdettagli[[#This Row],[Resp DT]] ) ) -> Responsabile A | J35: =tabSuperdettagli[[#This Row],[Total]] -> 55 | K35: =tabSuperdettagli[[#This Row],[01.2025]] -> 1 | L35: =tabSuperdettagli[[#This Row],[02.2025]] -> 2 | M35: =tabSuperdettagli[[#This Row],[03.2025]] -> 3 | N35: =tabSuperdettagli[[#This Row],[04.2025]] -> 4 | O35: =tabSuperdettagli[[#This Row],[05.2025]] -> 5 | P35: =tabSuperdettagli[[#This Row],[06.2025]] -> 6 | Q35: =tabSuperdettagli[[#This Row],[07.2025]] -> 7 | R35: =tabSuperdettagli[[#This Row],[08.2025]] -> 8 | S35: =tabSuperdettagli[[#This Row],[09.2025]] -> 9 | T35: =tabSuperdettagli[[#This Row],[10.2025]] -> 10 | U35: =tabSuperdettagli[[#This Row],[11.2025]] -> 0 | V35: =tabSuperdettagli[[#This Row],[12.2025]] -> 0 | W35: =tabSuperdettagli[[#This Row],[INT/EST]] -> Est. | X35: =tabSuperdettagli[[#This Row],[Resp 2°liv]]&"" | Y35: =INDEX( tab_resp1liv[EngUnit area cluster 1_], MATCH( SUBSTITUTE(tabSuperdettagli[[#This Row],[Resp 2°liv]], " ", ""), tab_resp1liv[SearchKey],0)) -> #N/A | Z35: =tabSuperdettagli[[#This Row],[WBS Element]]&"" | AA35: =tabSuperdettagli[[#This Row],[09.2025]] -> 9 | AC35: =IF( tabSuperdettagli[[#This Row],[ProjType_]]="M", IF( AND(tabSuperdettagli[[#This Row],[Resp 1°liv_]]="Guidotti C.", tabSuperdettagli[[#This Row],[WBE description_]]="Machine Mgmt"), "Documentation", tabSuperdettagli[[#This Row],[WBE description_]]), "" ) | AD35: =LEFT(tabSuperdettagli[[#This Row],[Network]], 18 ) | AE35: Send cost D | AP35: Est. | AV35: Responsabile A | BJ35: 1 | BK35: 2 | BL35: 3 | BM35: 4 | BN35: 5 | BO35: 6 | BP35: 7 | BQ35: 8 | BR35: 9 | BS35: 10 | BV35: 55 | BX35: 42102 | CB35: 42101 | CC35: 42141
A36: =IF(UPPER(LEFT(tabSuperdettagli[[#This Row],[WBE Status]],1))="S","sì","no") -> no | B36: 2018 | C36: =VLOOKUP(tabSuperdettagli[[#This Row],[WBS_]],Pivot_AnnoPrimaMarcatura!A:B,2,FALSE) -> #N/A | D36: =LEFT(tabSuperdettagli[[#This Row],[Network]], 10) | E36: =LEFT(tabSuperdettagli[[#This Row],[Network]], 1) | F36: =LOWER(TRIM( tabSuperdettagli[[#This Row],[Proj. Type ]] )) | G36: =IF( OR( tabSuperdettagli[[#This Row],[ProjType_]]="C", tabSuperdettagli[[#This Row],[ProjType_]]="A", tabSuperdettagli[[#This Row],[ProjType_]]="R", tabSuperdettagli[[#This Row],[ProjType_]]="E"), "C A R E", IF( tabSuperdettagli[[#This Row],[ProjType_]]="U", "U (" & tabSuperdettagli[[#This Row],[U ProjType_]] & ")", tabSuperdettagli[[#This Row],[ProjType_]]) ) | I36: =IF( TRIM(tabSuperdettagli[[#This Row],[Raggr. X Struttura]])> "", TRIM(tabSuperdettagli[[#This Row],[Raggr. X Struttura]]), TRIM(tabSuperdettagli[[#This Row],[Resp DT]] ) ) -> Responsabile A | J36: =tabSuperdettagli[[#This Row],[Total]] -> 1055 | K36: =tabSuperdettagli[[#This Row],[01.2025]] -> 101 | L36: =tabSuperdettagli[[#This Row],[02.2025]] -> 102 | M36: =tabSuperdettagli[[#This Row],[03.2025]] -> 103 | N36: =tabSuperdettagli[[#This Row],[04.2025]] -> 104 | O36: =tabSuperdettagli[[#This Row],[05.2025]] -> 105 | P36: =tabSuperdettagli[[#This Row],[06.2025]] -> 106 | Q36: =tabSuperdettagli[[#This Row],[07.2025]] -> 107 | R36: =tabSuperdettagli[[#This Row],[08.2025]] -> 108 | S36: =tabSuperdettagli[[#This Row],[09.2025]] -> 109 | T36: =tabSuperdettagli[[#This Row],[10.2025]] -> 110 | U36: =tabSuperdettagli[[#This Row],[11.2025]] -> 0 | V36: =tabSuperdettagli[[#This Row],[12.2025]] -> 0 | W36: =tabSuperdettagli[[#This Row],[INT/EST]] -> Est. | X36: =tabSuperdettagli[[#This Row],[Resp 2°liv]]&"" | Y36: =INDEX( tab_resp1liv[EngUnit area cluster 1_], MATCH( SUBSTITUTE(tabSuperdettagli[[#This Row],[Resp 2°liv]], " ", ""), tab_resp1liv[SearchKey],0)) -> #N/A | Z36: =tabSuperdettagli[[#This Row],[WBS Element]]&"" | AA36: =tabSuperdettagli[[#This Row],[09.2025]] -> 109 | AC36: =IF( tabSuperdettagli[[#This Row],[ProjType_]]="M", IF( AND(tabSuperdettagli[[#This Row],[Resp 1°liv_]]="Guidotti C.", tabSuperdettagli[[#This Row],[WBE description_]]="Machine Mgmt"), "Documentation", tabSuperdettagli[[#This Row],[WBE description_]]), "" ) | AD36: =LEFT(tabSuperdettagli[[#This Row],[Network]], 18 ) | AE36: Send cost D | AP36: Est. | AV36: Responsabile A | BJ36: 101 | BK36: 102 | BL36: 103 | BM36: 104 | BN36: 105 | BO36: 106 | BP36: 107 | BQ36: 108 | BR36: 109 | BS36: 110 | BV36: 1055 | BX36: 42105 | CB36: 42104 | CC36: 42144
A37: =IF(UPPER(LEFT(tabSuperdettagli[[#This Row],[WBE Status]],1))="S","sì","no") -> no | B37: 2018 | C37: =VLOOKUP(tabSuperdettagli[[#This Row],[WBS_]],Pivot_AnnoPrimaMarcatura!A:B,2,FALSE) -> #N/A | D37: =LEFT(tabSuperdettagli[[#This Row],[Network]], 10) | E37: =LEFT(tabSuperdettagli[[#This Row],[Network]], 1) | F37: =LOWER(TRIM( tabSuperdettagli[[#This Row],[Proj. Type ]] )) | G37: =IF( OR( tabSuperdettagli[[#This Row],[ProjType_]]="C", tabSuperdettagli[[#This Row],[ProjType_]]="A", tabSuperdettagli[[#This Row],[ProjType_]]="R", tabSuperdettagli[[#This Row],[ProjType_]]="E"), "C A R E", IF( tabSuperdettagli[[#This Row],[ProjType_]]="U", "U (" & tabSuperdettagli[[#This Row],[U ProjType_]] & ")", tabSuperdettagli[[#This Row],[ProjType_]]) ) | I37: =IF( TRIM(tabSuperdettagli[[#This Row],[Raggr. X Struttura]])> "", TRIM(tabSuperdettagli[[#This Row],[Raggr. X Struttura]]), TRIM(tabSuperdettagli[[#This Row],[Resp DT]] ) ) -> Gruppo struttura 3 | J37: =tabSuperdettagli[[#This Row],[Total]] -> 2055 | K37: =tabSuperdettagli[[#This Row],[01.2025]] -> 201 | L37: =tabSuperdettagli[[#This Row],[02.2025]] -> 202 | M37: =tabSuperdettagli[[#This Row],[03.2025]] -> 203 | N37: =tabSuperdettagli[[#This Row],[04.2025]] -> 204 | O37: =tabSuperdettagli[[#This Row],[05.2025]] -> 205 | P37: =tabSuperdettagli[[#This Row],[06.2025]] -> 206 | Q37: =tabSuperdettagli[[#This Row],[07.2025]] -> 207 | R37: =tabSuperdettagli[[#This Row],[08.2025]] -> 208 | S37: =tabSuperdettagli[[#This Row],[09.2025]] -> 209 | T37: =tabSuperdettagli[[#This Row],[10.2025]] -> 210 | U37: =tabSuperdettagli[[#This Row],[11.2025]] -> 0 | V37: =tabSuperdettagli[[#This Row],[12.2025]] -> 0 | W37: =tabSuperdettagli[[#This Row],[INT/EST]] -> Est. | X37: =tabSuperdettagli[[#This Row],[Resp 2°liv]]&"" | Y37: =INDEX( tab_resp1liv[EngUnit area cluster 1_], MATCH( SUBSTITUTE(tabSuperdettagli[[#This Row],[Resp 2°liv]], " ", ""), tab_resp1liv[SearchKey],0)) -> #N/A | Z37: =tabSuperdettagli[[#This Row],[WBS Element]]&"" | AA37: =tabSuperdettagli[[#This Row],[09.2025]] -> 209 | AC37: =IF( tabSuperdettagli[[#This Row],[ProjType_]]="M", IF( AND(tabSuperdettagli[[#This Row],[Resp 1°liv_]]="Guidotti C.", tabSuperdettagli[[#This Row],[WBE description_]]="Machine Mgmt"), "Documentation", tabSuperdettagli[[#This Row],[WBE description_]]), "" ) | AD37: =LEFT(tabSuperdettagli[[#This Row],[Network]], 18 ) | AE37: Send cost D | AP37: Est. | AQ37: Gruppo struttura 3 | AV37: Responsabile A | BJ37: 201 | BK37: 202 | BL37: 203 | BM37: 204 | BN37: 205 | BO37: 206 | BP37: 207 | BQ37: 208 | BR37: 209 | BS37: 210 | BV37: 2055 | BX37: 42108 | CB37: 42107 | CC37: 42147
A38: =IF(UPPER(LEFT(tabSuperdettagli[[#This Row],[WBE Status]],1))="S","sì","no") -> no | B38: 2018 | C38: =VLOOKUP(tabSuperdettagli[[#This Row],[WBS_]],Pivot_AnnoPrimaMarcatura!A:B,2,FALSE) -> #N/A | D38: =LEFT(tabSuperdettagli[[#This Row],[Network]], 10) | E38: =LEFT(tabSuperdettagli[[#This Row],[Network]], 1) | F38: =LOWER(TRIM( tabSuperdettagli[[#This Row],[Proj. Type ]] )) | G38: =IF( OR( tabSuperdettagli[[#This Row],[ProjType_]]="C", tabSuperdettagli[[#This Row],[ProjType_]]="A", tabSuperdettagli[[#This Row],[ProjType_]]="R", tabSuperdettagli[[#This Row],[ProjType_]]="E"), "C A R E", IF( tabSuperdettagli[[#This Row],[ProjType_]]="U", "U (" & tabSuperdettagli[[#This Row],[U ProjType_]] & ")", tabSuperdettagli[[#This Row],[ProjType_]]) ) | I38: =IF( TRIM(tabSuperdettagli[[#This Row],[Raggr. X Struttura]])> "", TRIM(tabSuperdettagli[[#This Row],[Raggr. X Struttura]]), TRIM(tabSuperdettagli[[#This Row],[Resp DT]] ) ) -> Gruppo struttura 1 | J38: =tabSuperdettagli[[#This Row],[Total]] -> 3055 | K38: =tabSuperdettagli[[#This Row],[01.2025]] -> 301 | L38: =tabSuperdettagli[[#This Row],[02.2025]] -> 302 | M38: =tabSuperdettagli[[#This Row],[03.2025]] -> 303 | N38: =tabSuperdettagli[[#This Row],[04.2025]] -> 304 | O38: =tabSuperdettagli[[#This Row],[05.2025]] -> 305 | P38: =tabSuperdettagli[[#This Row],[06.2025]] -> 306 | Q38: =tabSuperdettagli[[#This Row],[07.2025]] -> 307 | R38: =tabSuperdettagli[[#This Row],[08.2025]] -> 308 | S38: =tabSuperdettagli[[#This Row],[09.2025]] -> 309 | T38: =tabSuperdettagli[[#This Row],[10.2025]] -> 310 | U38: =tabSuperdettagli[[#This Row],[11.2025]] -> 0 | V38: =tabSuperdettagli[[#This Row],[12.2025]] -> 0 | W38: =tabSuperdettagli[[#This Row],[INT/EST]] -> Est. | X38: =tabSuperdettagli[[#This Row],[Resp 2°liv]]&"" | Y38: =INDEX( tab_resp1liv[EngUnit area cluster 1_], MATCH( SUBSTITUTE(tabSuperdettagli[[#This Row],[Resp 2°liv]], " ", ""), tab_resp1liv[SearchKey],0)) -> #N/A | Z38: =tabSuperdettagli[[#This Row],[WBS Element]]&"" | AA38: =tabSuperdettagli[[#This Row],[09.2025]] -> 309 | AC38: =IF( tabSuperdettagli[[#This Row],[ProjType_]]="M", IF( AND(tabSuperdettagli[[#This Row],[Resp 1°liv_]]="Guidotti C.", tabSuperdettagli[[#This Row],[WBE description_]]="Machine Mgmt"), "Documentation", tabSuperdettagli[[#This Row],[WBE description_]]), "" ) | AD38: =LEFT(tabSuperdettagli[[#This Row],[Network]], 18 ) | AE38: Send cost D | AP38: Est. | AQ38: Gruppo struttura 1 | AV38: Responsabile D | BJ38: 301 | BK38: 302 | BL38: 303 | BM38: 304 | BN38: 305 | BO38: 306 | BP38: 307 | BQ38: 308 | BR38: 309 | BS38: 310 | BV38: 3055 | BX38: 42111 | CB38: 42110 | CC38: 42150
A39: =IF(UPPER(LEFT(tabSuperdettagli[[#This Row],[WBE Status]],1))="S","sì","no") -> no | B39: 2018 | C39: =VLOOKUP(tabSuperdettagli[[#This Row],[WBS_]],Pivot_AnnoPrimaMarcatura!A:B,2,FALSE) -> #N/A | D39: =LEFT(tabSuperdettagli[[#This Row],[Network]], 10) | E39: =LEFT(tabSuperdettagli[[#This Row],[Network]], 1) | F39: =LOWER(TRIM( tabSuperdettagli[[#This Row],[Proj. Type ]] )) | G39: =IF( OR( tabSuperdettagli[[#This Row],[ProjType_]]="C", tabSuperdettagli[[#This Row],[ProjType_]]="A", tabSuperdettagli[[#This Row],[ProjType_]]="R", tabSuperdettagli[[#This Row],[ProjType_]]="E"), "C A R E", IF( tabSuperdettagli[[#This Row],[ProjType_]]="U", "U (" & tabSuperdettagli[[#This Row],[U ProjType_]] & ")", tabSuperdettagli[[#This Row],[ProjType_]]) ) | I39: =IF( TRIM(tabSuperdettagli[[#This Row],[Raggr. X Struttura]])> "", TRIM(tabSuperdettagli[[#This Row],[Raggr. X Struttura]]), TRIM(tabSuperdettagli[[#This Row],[Resp DT]] ) ) -> Gruppo struttura 6 | J39: =tabSuperdettagli[[#This Row],[Total]] -> 4055 | K39: =tabSuperdettagli[[#This Row],[01.2025]] -> 401 | L39: =tabSuperdettagli[[#This Row],[02.2025]] -> 402 | M39: =tabSuperdettagli[[#This Row],[03.2025]] -> 403 | N39: =tabSuperdettagli[[#This Row],[04.2025]] -> 404 | O39: =tabSuperdettagli[[#This Row],[05.2025]] -> 405 | P39: =tabSuperdettagli[[#This Row],[06.2025]] -> 406 | Q39: =tabSuperdettagli[[#This Row],[07.2025]] -> 407 | R39: =tabSuperdettagli[[#This Row],[08.2025]] -> 408 | S39: =tabSuperdettagli[[#This Row],[09.2025]] -> 409 | T39: =tabSuperdettagli[[#This Row],[10.2025]] -> 410 | U39: =tabSuperdettagli[[#This Row],[11.2025]] -> 0 | V39: =tabSuperdettagli[[#This Row],[12.2025]] -> 0 | W39: =tabSuperdettagli[[#This Row],[INT/EST]] -> Est. | X39: =tabSuperdettagli[[#This Row],[Resp 2°liv]]&"" | Y39: =INDEX( tab_resp1liv[EngUnit area cluster 1_], MATCH( SUBSTITUTE(tabSuperdettagli[[#This Row],[Resp 2°liv]], " ", ""), tab_resp1liv[SearchKey],0)) -> #N/A | Z39: =tabSuperdettagli[[#This Row],[WBS Element]]&"" | AA39: =tabSuperdettagli[[#This Row],[09.2025]] -> 409 | AC39: =IF( tabSuperdettagli[[#This Row],[ProjType_]]="M", IF( AND(tabSuperdettagli[[#This Row],[Resp 1°liv_]]="Guidotti C.", tabSuperdettagli[[#This Row],[WBE description_]]="Machine Mgmt"), "Documentation", tabSuperdettagli[[#This Row],[WBE description_]]), "" ) | AD39: =LEFT(tabSuperdettagli[[#This Row],[Network]], 18 ) | AE39: Send cost D | AP39: Est. | AQ39: Gruppo struttura 6 | AV39: Responsabile A | BJ39: 401 | BK39: 402 | BL39: 403 | BM39: 404 | BN39: 405 | BO39: 406 | BP39: 407 | BQ39: 408 | BR39: 409 | BS39: 410 | BV39: 4055 | BX39: 42114 | CB39: 42113 | CC39: 42153
A40: =IF(UPPER(LEFT(tabSuperdettagli[[#This Row],[WBE Status]],1))="S","sì","no") -> no | B40: 2018 | C40: =VLOOKUP(tabSuperdettagli[[#This Row],[WBS_]],Pivot_AnnoPrimaMarcatura!A:B,2,FALSE) -> #N/A | D40: =LEFT(tabSuperdettagli[[#This Row],[Network]], 10) | E40: =LEFT(tabSuperdettagli[[#This Row],[Network]], 1) | F40: =LOWER(TRIM( tabSuperdettagli[[#This Row],[Proj. Type ]] )) | G40: =IF( OR( tabSuperdettagli[[#This Row],[ProjType_]]="C", tabSuperdettagli[[#This Row],[ProjType_]]="A", tabSuperdettagli[[#This Row],[ProjType_]]="R", tabSuperdettagli[[#This Row],[ProjType_]]="E"), "C A R E", IF( tabSuperdettagli[[#This Row],[ProjType_]]="U", "U (" & tabSuperdettagli[[#This Row],[U ProjType_]] & ")", tabSuperdettagli[[#This Row],[ProjType_]]) ) | I40: =IF( TRIM(tabSuperdettagli[[#This Row],[Raggr. X Struttura]])> "", TRIM(tabSuperdettagli[[#This Row],[Raggr. X Struttura]]), TRIM(tabSuperdettagli[[#This Row],[Resp DT]] ) ) -> Gruppo struttura 1 | J40: =tabSuperdettagli[[#This Row],[Total]] -> 5055 | K40: =tabSuperdettagli[[#This Row],[01.2025]] -> 501 | L40: =tabSuperdettagli[[#This Row],[02.2025]] -> 502 | M40: =tabSuperdettagli[[#This Row],[03.2025]] -> 503 | N40: =tabSuperdettagli[[#This Row],[04.2025]] -> 504 | O40: =tabSuperdettagli[[#This Row],[05.2025]] -> 505 | P40: =tabSuperdettagli[[#This Row],[06.2025]] -> 506 | Q40: =tabSuperdettagli[[#This Row],[07.2025]] -> 507 | R40: =tabSuperdettagli[[#This Row],[08.2025]] -> 508 | S40: =tabSuperdettagli[[#This Row],[09.2025]] -> 509 | T40: =tabSuperdettagli[[#This Row],[10.2025]] -> 510 | U40: =tabSuperdettagli[[#This Row],[11.2025]] -> 0 | V40: =tabSuperdettagli[[#This Row],[12.2025]] -> 0 | W40: =tabSuperdettagli[[#This Row],[INT/EST]] -> Est. | X40: =tabSuperdettagli[[#This Row],[Resp 2°liv]]&"" | Y40: =INDEX( tab_resp1liv[EngUnit area cluster 1_], MATCH( SUBSTITUTE(tabSuperdettagli[[#This Row],[Resp 2°liv]], " ", ""), tab_resp1liv[SearchKey],0)) -> #N/A | Z40: =tabSuperdettagli[[#This Row],[WBS Element]]&"" | AA40: =tabSuperdettagli[[#This Row],[09.2025]] -> 509 | AC40: =IF( tabSuperdettagli[[#This Row],[ProjType_]]="M", IF( AND(tabSuperdettagli[[#This Row],[Resp 1°liv_]]="Guidotti C.", tabSuperdettagli[[#This Row],[WBE description_]]="Machine Mgmt"), "Documentation", tabSuperdettagli[[#This Row],[WBE description_]]), "" ) | AD40: =LEFT(tabSuperdettagli[[#This Row],[Network]], 18 ) | AE40: Send cost D | AP40: Est. | AQ40: Gruppo struttura 1 | AV40: Responsabile A | BJ40: 501 | BK40: 502 | BL40: 503 | BM40: 504 | BN40: 505 | BO40: 506 | BP40: 507 | BQ40: 508 | BR40: 509 | BS40: 510 | BV40: 5055 | BX40: 42117 | CB40: 42116 | CC40: 42156
A41: =IF(UPPER(LEFT(tabSuperdettagli[[#This Row],[WBE Status]],1))="S","sì","no") -> no | B41: 2018 | C41: =VLOOKUP(tabSuperdettagli[[#This Row],[WBS_]],Pivot_AnnoPrimaMarcatura!A:B,2,FALSE) -> #N/A | D41: =LEFT(tabSuperdettagli[[#This Row],[Network]], 10) | E41: =LEFT(tabSuperdettagli[[#This Row],[Network]], 1) | F41: =LOWER(TRIM( tabSuperdettagli[[#This Row],[Proj. Type ]] )) | G41: =IF( OR( tabSuperdettagli[[#This Row],[ProjType_]]="C", tabSuperdettagli[[#This Row],[ProjType_]]="A", tabSuperdettagli[[#This Row],[ProjType_]]="R", tabSuperdettagli[[#This Row],[ProjType_]]="E"), "C A R E", IF( tabSuperdettagli[[#This Row],[ProjType_]]="U", "U (" & tabSuperdettagli[[#This Row],[U ProjType_]] & ")", tabSuperdettagli[[#This Row],[ProjType_]]) ) | I41: =IF( TRIM(tabSuperdettagli[[#This Row],[Raggr. X Struttura]])> "", TRIM(tabSuperdettagli[[#This Row],[Raggr. X Struttura]]), TRIM(tabSuperdettagli[[#This Row],[Resp DT]] ) ) -> Gruppo struttura 1 | J41: =tabSuperdettagli[[#This Row],[Total]] -> 6055 | K41: =tabSuperdettagli[[#This Row],[01.2025]] -> 601 | L41: =tabSuperdettagli[[#This Row],[02.2025]] -> 602 | M41: =tabSuperdettagli[[#This Row],[03.2025]] -> 603 | N41: =tabSuperdettagli[[#This Row],[04.2025]] -> 604 | O41: =tabSuperdettagli[[#This Row],[05.2025]] -> 605 | P41: =tabSuperdettagli[[#This Row],[06.2025]] -> 606 | Q41: =tabSuperdettagli[[#This Row],[07.2025]] -> 607 | R41: =tabSuperdettagli[[#This Row],[08.2025]] -> 608 | S41: =tabSuperdettagli[[#This Row],[09.2025]] -> 609 | T41: =tabSuperdettagli[[#This Row],[10.2025]] -> 610 | U41: =tabSuperdettagli[[#This Row],[11.2025]] -> 0 | V41: =tabSuperdettagli[[#This Row],[12.2025]] -> 0 | W41: =tabSuperdettagli[[#This Row],[INT/EST]] -> Est. | X41: =tabSuperdettagli[[#This Row],[Resp 2°liv]]&"" | Y41: =INDEX( tab_resp1liv[EngUnit area cluster 1_], MATCH( SUBSTITUTE(tabSuperdettagli[[#This Row],[Resp 2°liv]], " ", ""), tab_resp1liv[SearchKey],0)) -> #N/A | Z41: =tabSuperdettagli[[#This Row],[WBS Element]]&"" | AA41: =tabSuperdettagli[[#This Row],[09.2025]] -> 609 | AC41: =IF( tabSuperdettagli[[#This Row],[ProjType_]]="M", IF( AND(tabSuperdettagli[[#This Row],[Resp 1°liv_]]="Guidotti C.", tabSuperdettagli[[#This Row],[WBE description_]]="Machine Mgmt"), "Documentation", tabSuperdettagli[[#This Row],[WBE description_]]), "" ) | AD41: =LEFT(tabSuperdettagli[[#This Row],[Network]], 18 ) | AE41: Send cost D | AP41: Est. | AQ41: Gruppo struttura 1 | AV41: Responsabile A | BJ41: 601 | BK41: 602 | BL41: 603 | BM41: 604 | BN41: 605 | BO41: 606 | BP41: 607 | BQ41: 608 | BR41: 609 | BS41: 610 | BV41: 6055 | BX41: 42120 | CB41: 42119 | CC41: 42159
A42: =IF(UPPER(LEFT(tabSuperdettagli[[#This Row],[WBE Status]],1))="S","sì","no") -> no | B42: 2018 | C42: =VLOOKUP(tabSuperdettagli[[#This Row],[WBS_]],Pivot_AnnoPrimaMarcatura!A:B,2,FALSE) -> #N/A | D42: =LEFT(tabSuperdettagli[[#This Row],[Network]], 10) | E42: =LEFT(tabSuperdettagli[[#This Row],[Network]], 1) | F42: =LOWER(TRIM( tabSuperdettagli[[#This Row],[Proj. Type ]] )) | G42: =IF( OR( tabSuperdettagli[[#This Row],[ProjType_]]="C", tabSuperdettagli[[#This Row],[ProjType_]]="A", tabSuperdettagli[[#This Row],[ProjType_]]="R", tabSuperdettagli[[#This Row],[ProjType_]]="E"), "C A R E", IF( tabSuperdettagli[[#This Row],[ProjType_]]="U", "U (" & tabSuperdettagli[[#This Row],[U ProjType_]] & ")", tabSuperdettagli[[#This Row],[ProjType_]]) ) | I42: =IF( TRIM(tabSuperdettagli[[#This Row],[Raggr. X Struttura]])> "", TRIM(tabSuperdettagli[[#This Row],[Raggr. X Struttura]]), TRIM(tabSuperdettagli[[#This Row],[Resp DT]] ) ) -> Gruppo struttura 1 | J42: =tabSuperdettagli[[#This Row],[Total]] -> 55 | K42: =tabSuperdettagli[[#This Row],[01.2025]] -> 1 | L42: =tabSuperdettagli[[#This Row],[02.2025]] -> 2 | M42: =tabSuperdettagli[[#This Row],[03.2025]] -> 3 | N42: =tabSuperdettagli[[#This Row],[04.2025]] -> 4 | O42: =tabSuperdettagli[[#This Row],[05.2025]] -> 5 | P42: =tabSuperdettagli[[#This Row],[06.2025]] -> 6 | Q42: =tabSuperdettagli[[#This Row],[07.2025]] -> 7 | R42: =tabSuperdettagli[[#This Row],[08.2025]] -> 8 | S42: =tabSuperdettagli[[#This Row],[09.2025]] -> 9 | T42: =tabSuperdettagli[[#This Row],[10.2025]] -> 10 | U42: =tabSuperdettagli[[#This Row],[11.2025]] -> 0 | V42: =tabSuperdettagli[[#This Row],[12.2025]] -> 0 | W42: =tabSuperdettagli[[#This Row],[INT/EST]] -> Est. | X42: =tabSuperdettagli[[#This Row],[Resp 2°liv]]&"" | Y42: =INDEX( tab_resp1liv[EngUnit area cluster 1_], MATCH( SUBSTITUTE(tabSuperdettagli[[#This Row],[Resp 2°liv]], " ", ""), tab_resp1liv[SearchKey],0)) -> #N/A | Z42: =tabSuperdettagli[[#This Row],[WBS Element]]&"" | AA42: =tabSuperdettagli[[#This Row],[09.2025]] -> 9 | AC42: =IF( tabSuperdettagli[[#This Row],[ProjType_]]="M", IF( AND(tabSuperdettagli[[#This Row],[Resp 1°liv_]]="Guidotti C.", tabSuperdettagli[[#This Row],[WBE description_]]="Machine Mgmt"), "Documentation", tabSuperdettagli[[#This Row],[WBE description_]]), "" ) | AD42: =LEFT(tabSuperdettagli[[#This Row],[Network]], 18 ) | AE42: Send cost D | AP42: Est. | AQ42: Gruppo struttura 1 | AV42: Responsabile C | BJ42: 1 | BK42: 2 | BL42: 3 | BM42: 4 | BN42: 5 | BO42: 6 | BP42: 7 | BQ42: 8 | BR42: 9 | BS42: 10 | BV42: 55 | BX42: 42123 | CB42: 42122 | CC42: 42162
A43: =IF(UPPER(LEFT(tabSuperdettagli[[#This Row],[WBE Status]],1))="S","sì","no") -> no | B43: 2019 | C43: =VLOOKUP(tabSuperdettagli[[#This Row],[WBS_]],Pivot_AnnoPrimaMarcatura!A:B,2,FALSE) -> #N/A | D43: =LEFT(tabSuperdettagli[[#This Row],[Network]], 10) | E43: =LEFT(tabSuperdettagli[[#This Row],[Network]], 1) | F43: =LOWER(TRIM( tabSuperdettagli[[#This Row],[Proj. Type ]] )) | G43: =IF( OR( tabSuperdettagli[[#This Row],[ProjType_]]="C", tabSuperdettagli[[#This Row],[ProjType_]]="A", tabSuperdettagli[[#This Row],[ProjType_]]="R", tabSuperdettagli[[#This Row],[ProjType_]]="E"), "C A R E", IF( tabSuperdettagli[[#This Row],[ProjType_]]="U", "U (" & tabSuperdettagli[[#This Row],[U ProjType_]] & ")", tabSuperdettagli[[#This Row],[ProjType_]]) ) | I43: =IF( TRIM(tabSuperdettagli[[#This Row],[Raggr. X Struttura]])> "", TRIM(tabSuperdettagli[[#This Row],[Raggr. X Struttura]]), TRIM(tabSuperdettagli[[#This Row],[Resp DT]] ) ) -> Gruppo struttura 4 | J43: =tabSuperdettagli[[#This Row],[Total]] -> 1055 | K43: =tabSuperdettagli[[#This Row],[01.2025]] -> 101 | L43: =tabSuperdettagli[[#This Row],[02.2025]] -> 102 | M43: =tabSuperdettagli[[#This Row],[03.2025]] -> 103 | N43: =tabSuperdettagli[[#This Row],[04.2025]] -> 104 | O43: =tabSuperdettagli[[#This Row],[05.2025]] -> 105 | P43: =tabSuperdettagli[[#This Row],[06.2025]] -> 106 | Q43: =tabSuperdettagli[[#This Row],[07.2025]] -> 107 | R43: =tabSuperdettagli[[#This Row],[08.2025]] -> 108 | S43: =tabSuperdettagli[[#This Row],[09.2025]] -> 109 | T43: =tabSuperdettagli[[#This Row],[10.2025]] -> 110 | U43: =tabSuperdettagli[[#This Row],[11.2025]] -> 0 | V43: =tabSuperdettagli[[#This Row],[12.2025]] -> 0 | W43: =tabSuperdettagli[[#This Row],[INT/EST]] -> Est. | X43: =tabSuperdettagli[[#This Row],[Resp 2°liv]]&"" | Y43: =INDEX( tab_resp1liv[EngUnit area cluster 1_], MATCH( SUBSTITUTE(tabSuperdettagli[[#This Row],[Resp 2°liv]], " ", ""), tab_resp1liv[SearchKey],0)) -> #N/A | Z43: =tabSuperdettagli[[#This Row],[WBS Element]]&"" | AA43: =tabSuperdettagli[[#This Row],[09.2025]] -> 109 | AC43: =IF( tabSuperdettagli[[#This Row],[ProjType_]]="M", IF( AND(tabSuperdettagli[[#This Row],[Resp 1°liv_]]="Guidotti C.", tabSuperdettagli[[#This Row],[WBE description_]]="Machine Mgmt"), "Documentation", tabSuperdettagli[[#This Row],[WBE description_]]), "" ) | AD43: =LEFT(tabSuperdettagli[[#This Row],[Network]], 18 ) | AE43: Send cost E | AP43: Est. | AQ43: Gruppo struttura 4 | AV43: Responsabile B | BJ43: 101 | BK43: 102 | BL43: 103 | BM43: 104 | BN43: 105 | BO43: 106 | BP43: 107 | BQ43: 108 | BR43: 109 | BS43: 110 | BV43: 1055 | BX43: 42126 | CB43: 42125 | CC43: 42165
A44: =IF(UPPER(LEFT(tabSuperdettagli[[#This Row],[WBE Status]],1))="S","sì","no") -> no | B44: 2019 | C44: =VLOOKUP(tabSuperdettagli[[#This Row],[WBS_]],Pivot_AnnoPrimaMarcatura!A:B,2,FALSE) -> #N/A | D44: =LEFT(tabSuperdettagli[[#This Row],[Network]], 10) | E44: =LEFT(tabSuperdettagli[[#This Row],[Network]], 1) | F44: =LOWER(TRIM( tabSuperdettagli[[#This Row],[Proj. Type ]] )) | G44: =IF( OR( tabSuperdettagli[[#This Row],[ProjType_]]="C", tabSuperdettagli[[#This Row],[ProjType_]]="A", tabSuperdettagli[[#This Row],[ProjType_]]="R", tabSuperdettagli[[#This Row],[ProjType_]]="E"), "C A R E", IF( tabSuperdettagli[[#This Row],[ProjType_]]="U", "U (" & tabSuperdettagli[[#This Row],[U ProjType_]] & ")", tabSuperdettagli[[#This Row],[ProjType_]]) ) | I44: =IF( TRIM(tabSuperdettagli[[#This Row],[Raggr. X Struttura]])> "", TRIM(tabSuperdettagli[[#This Row],[Raggr. X Struttura]]), TRIM(tabSuperdettagli[[#This Row],[Resp DT]] ) ) -> Gruppo struttura 4 | J44: =tabSuperdettagli[[#This Row],[Total]] -> 2055 | K44: =tabSuperdettagli[[#This Row],[01.2025]] -> 201 | L44: =tabSuperdettagli[[#This Row],[02.2025]] -> 202 | M44: =tabSuperdettagli[[#This Row],[03.2025]] -> 203 | N44: =tabSuperdettagli[[#This Row],[04.2025]] -> 204 | O44: =tabSuperdettagli[[#This Row],[05.2025]] -> 205 | P44: =tabSuperdettagli[[#This Row],[06.2025]] -> 206 | Q44: =tabSuperdettagli[[#This Row],[07.2025]] -> 207 | R44: =tabSuperdettagli[[#This Row],[08.2025]] -> 208 | S44: =tabSuperdettagli[[#This Row],[09.2025]] -> 209 | T44: =tabSuperdettagli[[#This Row],[10.2025]] -> 210 | U44: =tabSuperdettagli[[#This Row],[11.2025]] -> 0 | V44: =tabSuperdettagli[[#This Row],[12.2025]] -> 0 | W44: =tabSuperdettagli[[#This Row],[INT/EST]] -> Int. | X44: =tabSuperdettagli[[#This Row],[Resp 2°liv]]&"" | Y44: =INDEX( tab_resp1liv[EngUnit area cluster 1_], MATCH( SUBSTITUTE(tabSuperdettagli[[#This Row],[Resp 2°liv]], " ", ""), tab_resp1liv[SearchKey],0)) -> #N/A | Z44: =tabSuperdettagli[[#This Row],[WBS Element]]&"" | AA44: =tabSuperdettagli[[#This Row],[09.2025]] -> 209 | AC44: =IF( tabSuperdettagli[[#This Row],[ProjType_]]="M", IF( AND(tabSuperdettagli[[#This Row],[Resp 1°liv_]]="Guidotti C.", tabSuperdettagli[[#This Row],[WBE description_]]="Machine Mgmt"), "Documentation", tabSuperdettagli[[#This Row],[WBE description_]]), "" ) | AD44: =LEFT(tabSuperdettagli[[#This Row],[Network]], 18 ) | AE44: Send cost E | AP44: Int. | AQ44: Gruppo struttura 4 | AV44: Responsabile A | BJ44: 201 | BK44: 202 | BL44: 203 | BM44: 204 | BN44: 205 | BO44: 206 | BP44: 207 | BQ44: 208 | BR44: 209 | BS44: 210 | BV44: 2055 | BX44: 42129 | CB44: 42128 | CC44: 42168
A45: =IF(UPPER(LEFT(tabSuperdettagli[[#This Row],[WBE Status]],1))="S","sì","no") -> no | B45: 2019 | C45: =VLOOKUP(tabSuperdettagli[[#This Row],[WBS_]],Pivot_AnnoPrimaMarcatura!A:B,2,FALSE) -> #N/A | D45: =LEFT(tabSuperdettagli[[#This Row],[Network]], 10) | E45: =LEFT(tabSuperdettagli[[#This Row],[Network]], 1) | F45: =LOWER(TRIM( tabSuperdettagli[[#This Row],[Proj. Type ]] )) | G45: =IF( OR( tabSuperdettagli[[#This Row],[ProjType_]]="C", tabSuperdettagli[[#This Row],[ProjType_]]="A", tabSuperdettagli[[#This Row],[ProjType_]]="R", tabSuperdettagli[[#This Row],[ProjType_]]="E"), "C A R E", IF( tabSuperdettagli[[#This Row],[ProjType_]]="U", "U (" & tabSuperdettagli[[#This Row],[U ProjType_]] & ")", tabSuperdettagli[[#This Row],[ProjType_]]) ) | I45: =IF( TRIM(tabSuperdettagli[[#This Row],[Raggr. X Struttura]])> "", TRIM(tabSuperdettagli[[#This Row],[Raggr. X Struttura]]), TRIM(tabSuperdettagli[[#This Row],[Resp DT]] ) ) -> Gruppo struttura 1 | J45: =tabSuperdettagli[[#This Row],[Total]] -> 3055 | K45: =tabSuperdettagli[[#This Row],[01.2025]] -> 301 | L45: =tabSuperdettagli[[#This Row],[02.2025]] -> 302 | M45: =tabSuperdettagli[[#This Row],[03.2025]] -> 303 | N45: =tabSuperdettagli[[#This Row],[04.2025]] -> 304 | O45: =tabSuperdettagli[[#This Row],[05.2025]] -> 305 | P45: =tabSuperdettagli[[#This Row],[06.2025]] -> 306 | Q45: =tabSuperdettagli[[#This Row],[07.2025]] -> 307 | R45: =tabSuperdettagli[[#This Row],[08.2025]] -> 308 | S45: =tabSuperdettagli[[#This Row],[09.2025]] -> 309 | T45: =tabSuperdettagli[[#This Row],[10.2025]] -> 310 | U45: =tabSuperdettagli[[#This Row],[11.2025]] -> 0 | V45: =tabSuperdettagli[[#This Row],[12.2025]] -> 0 | W45: =tabSuperdettagli[[#This Row],[INT/EST]] -> Int. | X45: =tabSuperdettagli[[#This Row],[Resp 2°liv]]&"" | Y45: =INDEX( tab_resp1liv[EngUnit area cluster 1_], MATCH( SUBSTITUTE(tabSuperdettagli[[#This Row],[Resp 2°liv]], " ", ""), tab_resp1liv[SearchKey],0)) -> #N/A | Z45: =tabSuperdettagli[[#This Row],[WBS Element]]&"" | AA45: =tabSuperdettagli[[#This Row],[09.2025]] -> 309 | AC45: =IF( tabSuperdettagli[[#This Row],[ProjType_]]="M", IF( AND(tabSuperdettagli[[#This Row],[Resp 1°liv_]]="Guidotti C.", tabSuperdettagli[[#This Row],[WBE description_]]="Machine Mgmt"), "Documentation", tabSuperdettagli[[#This Row],[WBE description_]]), "" ) | AD45: =LEFT(tabSuperdettagli[[#This Row],[Network]], 18 ) | AE45: Send cost E | AP45: Int. | AQ45: Gruppo struttura 1 | AV45: Responsabile E | BJ45: 301 | BK45: 302 | BL45: 303 | BM45: 304 | BN45: 305 | BO45: 306 | BP45: 307 | BQ45: 308 | BR45: 309 | BS45: 310 | BV45: 3055 | BX45: 42132 | CB45: 42131 | CC45: 42171
A46: =IF(UPPER(LEFT(tabSuperdettagli[[#This Row],[WBE Status]],1))="S","sì","no") -> no | B46: 2019 | C46: =VLOOKUP(tabSuperdettagli[[#This Row],[WBS_]],Pivot_AnnoPrimaMarcatura!A:B,2,FALSE) -> #N/A | D46: =LEFT(tabSuperdettagli[[#This Row],[Network]], 10) | E46: =LEFT(tabSuperdettagli[[#This Row],[Network]], 1) | F46: =LOWER(TRIM( tabSuperdettagli[[#This Row],[Proj. Type ]] )) | G46: =IF( OR( tabSuperdettagli[[#This Row],[ProjType_]]="C", tabSuperdettagli[[#This Row],[ProjType_]]="A", tabSuperdettagli[[#This Row],[ProjType_]]="R", tabSuperdettagli[[#This Row],[ProjType_]]="E"), "C A R E", IF( tabSuperdettagli[[#This Row],[ProjType_]]="U", "U (" & tabSuperdettagli[[#This Row],[U ProjType_]] & ")", tabSuperdettagli[[#This Row],[ProjType_]]) ) | I46: =IF( TRIM(tabSuperdettagli[[#This Row],[Raggr. X Struttura]])> "", TRIM(tabSuperdettagli[[#This Row],[Raggr. X Struttura]]), TRIM(tabSuperdettagli[[#This Row],[Resp DT]] ) ) -> Gruppo struttura 1 | J46: =tabSuperdettagli[[#This Row],[Total]] -> 4055 | K46: =tabSuperdettagli[[#This Row],[01.2025]] -> 401 | L46: =tabSuperdettagli[[#This Row],[02.2025]] -> 402 | M46: =tabSuperdettagli[[#This Row],[03.2025]] -> 403 | N46: =tabSuperdettagli[[#This Row],[04.2025]] -> 404 | O46: =tabSuperdettagli[[#This Row],[05.2025]] -> 405 | P46: =tabSuperdettagli[[#This Row],[06.2025]] -> 406 | Q46: =tabSuperdettagli[[#This Row],[07.2025]] -> 407 | R46: =tabSuperdettagli[[#This Row],[08.2025]] -> 408 | S46: =tabSuperdettagli[[#This Row],[09.2025]] -> 409 | T46: =tabSuperdettagli[[#This Row],[10.2025]] -> 410 | U46: =tabSuperdettagli[[#This Row],[11.2025]] -> 0 | V46: =tabSuperdettagli[[#This Row],[12.2025]] -> 0 | W46: =tabSuperdettagli[[#This Row],[INT/EST]] -> Int. | X46: =tabSuperdettagli[[#This Row],[Resp 2°liv]]&"" | Y46: =INDEX( tab_resp1liv[EngUnit area cluster 1_], MATCH( SUBSTITUTE(tabSuperdettagli[[#This Row],[Resp 2°liv]], " ", ""), tab_resp1liv[SearchKey],0)) -> #N/A | Z46: =tabSuperdettagli[[#This Row],[WBS Element]]&"" | AA46: =tabSuperdettagli[[#This Row],[09.2025]] -> 409 | AC46: =IF( tabSuperdettagli[[#This Row],[ProjType_]]="M", IF( AND(tabSuperdettagli[[#This Row],[Resp 1°liv_]]="Guidotti C.", tabSuperdettagli[[#This Row],[WBE description_]]="Machine Mgmt"), "Documentation", tabSuperdettagli[[#This Row],[WBE description_]]), "" ) | AD46: =LEFT(tabSuperdettagli[[#This Row],[Network]], 18 ) | AE46: Send cost E | AP46: Int. | AQ46: Gruppo struttura 1 | AV46: Responsabile A | BJ46: 401 | BK46: 402 | BL46: 403 | BM46: 404 | BN46: 405 | BO46: 406 | BP46: 407 | BQ46: 408 | BR46: 409 | BS46: 410 | BV46: 4055 | BX46: 42135 | CB46: 42134 | CC46: 42174
A47: =IF(UPPER(LEFT(tabSuperdettagli[[#This Row],[WBE Status]],1))="S","sì","no") -> no | B47: 2019 | C47: =VLOOKUP(tabSuperdettagli[[#This Row],[WBS_]],Pivot_AnnoPrimaMarcatura!A:B,2,FALSE) -> #N/A | D47: =LEFT(tabSuperdettagli[[#This Row],[Network]], 10) | E47: =LEFT(tabSuperdettagli[[#This Row],[Network]], 1) | F47: =LOWER(TRIM( tabSuperdettagli[[#This Row],[Proj. Type ]] )) | G47: =IF( OR( tabSuperdettagli[[#This Row],[ProjType_]]="C", tabSuperdettagli[[#This Row],[ProjType_]]="A", tabSuperdettagli[[#This Row],[ProjType_]]="R", tabSuperdettagli[[#This Row],[ProjType_]]="E"), "C A R E", IF( tabSuperdettagli[[#This Row],[ProjType_]]="U", "U (" & tabSuperdettagli[[#This Row],[U ProjType_]] & ")", tabSuperdettagli[[#This Row],[ProjType_]]) ) | I47: =IF( TRIM(tabSuperdettagli[[#This Row],[Raggr. X Struttura]])> "", TRIM(tabSuperdettagli[[#This Row],[Raggr. X Struttura]]), TRIM(tabSuperdettagli[[#This Row],[Resp DT]] ) ) -> Gruppo struttura 1 | J47: =tabSuperdettagli[[#This Row],[Total]] -> 5055 | K47: =tabSuperdettagli[[#This Row],[01.2025]] -> 501 | L47: =tabSuperdettagli[[#This Row],[02.2025]] -> 502 | M47: =tabSuperdettagli[[#This Row],[03.2025]] -> 503 | N47: =tabSuperdettagli[[#This Row],[04.2025]] -> 504 | O47: =tabSuperdettagli[[#This Row],[05.2025]] -> 505 | P47: =tabSuperdettagli[[#This Row],[06.2025]] -> 506 | Q47: =tabSuperdettagli[[#This Row],[07.2025]] -> 507 | R47: =tabSuperdettagli[[#This Row],[08.2025]] -> 508 | S47: =tabSuperdettagli[[#This Row],[09.2025]] -> 509 | T47: =tabSuperdettagli[[#This Row],[10.2025]] -> 510 | U47: =tabSuperdettagli[[#This Row],[11.2025]] -> 0 | V47: =tabSuperdettagli[[#This Row],[12.2025]] -> 0 | W47: =tabSuperdettagli[[#This Row],[INT/EST]] -> Int. | X47: =tabSuperdettagli[[#This Row],[Resp 2°liv]]&"" | Y47: =INDEX( tab_resp1liv[EngUnit area cluster 1_], MATCH( SUBSTITUTE(tabSuperdettagli[[#This Row],[Resp 2°liv]], " ", ""), tab_resp1liv[SearchKey],0)) -> #N/A | Z47: =tabSuperdettagli[[#This Row],[WBS Element]]&"" | AA47: =tabSuperdettagli[[#This Row],[09.2025]] -> 509 | AC47: =IF( tabSuperdettagli[[#This Row],[ProjType_]]="M", IF( AND(tabSuperdettagli[[#This Row],[Resp 1°liv_]]="Guidotti C.", tabSuperdettagli[[#This Row],[WBE description_]]="Machine Mgmt"), "Documentation", tabSuperdettagli[[#This Row],[WBE description_]]), "" ) | AD47: =LEFT(tabSuperdettagli[[#This Row],[Network]], 18 ) | AE47: Send cost E | AP47: Int. | AQ47: Gruppo struttura 1 | AV47: Responsabile A | BJ47: 501 | BK47: 502 | BL47: 503 | BM47: 504 | BN47: 505 | BO47: 506 | BP47: 507 | BQ47: 508 | BR47: 509 | BS47: 510 | BV47: 5055 | BX47: 42138 | CB47: 42137 | CC47: 42177
A48: =IF(UPPER(LEFT(tabSuperdettagli[[#This Row],[WBE Status]],1))="S","sì","no") -> no | B48: 2019 | C48: =VLOOKUP(tabSuperdettagli[[#This Row],[WBS_]],Pivot_AnnoPrimaMarcatura!A:B,2,FALSE) -> #N/A | D48: =LEFT(tabSuperdettagli[[#This Row],[Network]], 10) | E48: =LEFT(tabSuperdettagli[[#This Row],[Network]], 1) | F48: =LOWER(TRIM( tabSuperdettagli[[#This Row],[Proj. Type ]] )) | G48: =IF( OR( tabSuperdettagli[[#This Row],[ProjType_]]="C", tabSuperdettagli[[#This Row],[ProjType_]]="A", tabSuperdettagli[[#This Row],[ProjType_]]="R", tabSuperdettagli[[#This Row],[ProjType_]]="E"), "C A R E", IF( tabSuperdettagli[[#This Row],[ProjType_]]="U", "U (" & tabSuperdettagli[[#This Row],[U ProjType_]] & ")", tabSuperdettagli[[#This Row],[ProjType_]]) ) | I48: =IF( TRIM(tabSuperdettagli[[#This Row],[Raggr. X Struttura]])> "", TRIM(tabSuperdettagli[[#This Row],[Raggr. X Struttura]]), TRIM(tabSuperdettagli[[#This Row],[Resp DT]] ) ) -> Gruppo struttura 4 | J48: =tabSuperdettagli[[#This Row],[Total]] -> 6055 | K48: =tabSuperdettagli[[#This Row],[01.2025]] -> 601 | L48: =tabSuperdettagli[[#This Row],[02.2025]] -> 602 | M48: =tabSuperdettagli[[#This Row],[03.2025]] -> 603 | N48: =tabSuperdettagli[[#This Row],[04.2025]] -> 604 | O48: =tabSuperdettagli[[#This Row],[05.2025]] -> 605 | P48: =tabSuperdettagli[[#This Row],[06.2025]] -> 606 | Q48: =tabSuperdettagli[[#This Row],[07.2025]] -> 607 | R48: =tabSuperdettagli[[#This Row],[08.2025]] -> 608 | S48: =tabSuperdettagli[[#This Row],[09.2025]] -> 609 | T48: =tabSuperdettagli[[#This Row],[10.2025]] -> 610 | U48: =tabSuperdettagli[[#This Row],[11.2025]] -> 0 | V48: =tabSuperdettagli[[#This Row],[12.2025]] -> 0 | W48: =tabSuperdettagli[[#This Row],[INT/EST]] -> Est. | X48: =tabSuperdettagli[[#This Row],[Resp 2°liv]]&"" | Y48: =INDEX( tab_resp1liv[EngUnit area cluster 1_], MATCH( SUBSTITUTE(tabSuperdettagli[[#This Row],[Resp 2°liv]], " ", ""), tab_resp1liv[SearchKey],0)) -> #N/A | Z48: =tabSuperdettagli[[#This Row],[WBS Element]]&"" | AA48: =tabSuperdettagli[[#This Row],[09.2025]] -> 609 | AC48: =IF( tabSuperdettagli[[#This Row],[ProjType_]]="M", IF( AND(tabSuperdettagli[[#This Row],[Resp 1°liv_]]="Guidotti C.", tabSuperdettagli[[#This Row],[WBE description_]]="Machine Mgmt"), "Documentation", tabSuperdettagli[[#This Row],[WBE description_]]), "" ) | AD48: =LEFT(tabSuperdettagli[[#This Row],[Network]], 18 ) | AE48: Send cost E | AP48: Est. | AQ48: Gruppo struttura 4 | AV48: Responsabile A | BJ48: 601 | BK48: 602 | BL48: 603 | BM48: 604 | BN48: 605 | BO48: 606 | BP48: 607 | BQ48: 608 | BR48: 609 | BS48: 610 | BV48: 6055 | BX48: 42141 | CB48: 42140 | CC48: 42180
... A53: =IF(UPPER(LEFT(tabSuperdettagli[[#This Row],[WBE Status]],1))="S","sì","no") -> no | B53: 2020 | C53: =VLOOKUP(tabSuperdettagli[[#This Row],[WBS_]],Pivot_AnnoPrimaMarcatura!A:B,2,FALSE) -> #N/A | D53: =LEFT(tabSuperdettagli[[#This Row],[Network]], 10) | E53: =LEFT(tabSuperdettagli[[#This Row],[Network]], 1) | F53: =LOWER(TRIM( tabSuperdettagli[[#This Row],[Proj. Type ]] )) | G53: =IF( OR( tabSuperdettagli[[#This Row],[ProjType_]]="C", tabSuperdettagli[[#This Row],[ProjType_]]="A", tabSuperdettagli[[#This Row],[ProjType_]]="R", tabSuperdettagli[[#This Row],[ProjType_]]="E"), "C A R E", IF( tabSuperdettagli[[#This Row],[ProjType_]]="U", "U (" & tabSuperdettagli[[#This Row],[U ProjType_]] & ")", tabSuperdettagli[[#This Row],[ProjType_]]) ) | I53: =IF( TRIM(tabSuperdettagli[[#This Row],[Raggr. X Struttura]])> "", TRIM(tabSuperdettagli[[#This Row],[Raggr. X Struttura]]), TRIM(tabSuperdettagli[[#This Row],[Resp DT]] ) ) -> Gruppo struttura 5 | J53: =tabSuperdettagli[[#This Row],[Total]] -> 4055 | K53: =tabSuperdettagli[[#This Row],[01.2025]] -> 401 | L53: =tabSuperdettagli[[#This Row],[02.2025]] -> 402 | M53: =tabSuperdettagli[[#This Row],[03.2025]] -> 403 | N53: =tabSuperdettagli[[#This Row],[04.2025]] -> 404 | O53: =tabSuperdettagli[[#This Row],[05.2025]] -> 405 | P53: =tabSuperdettagli[[#This Row],[06.2025]] -> 406 | Q53: =tabSuperdettagli[[#This Row],[07.2025]] -> 407 | R53: =tabSuperdettagli[[#This Row],[08.2025]] -> 408 | S53: =tabSuperdettagli[[#This Row],[09.2025]] -> 409 | T53: =tabSuperdettagli[[#This Row],[10.2025]] -> 410 | U53: =tabSuperdettagli[[#This Row],[11.2025]] -> 0 | V53: =tabSuperdettagli[[#This Row],[12.2025]] -> 0 | W53: =tabSuperdettagli[[#This Row],[INT/EST]] -> Int. | X53: =tabSuperdettagli[[#This Row],[Resp 2°liv]]&"" | Y53: =INDEX( tab_resp1liv[EngUnit area cluster 1_], MATCH( SUBSTITUTE(tabSuperdettagli[[#This Row],[Resp 2°liv]], " ", ""), tab_resp1liv[SearchKey],0)) -> #N/A | Z53: =tabSuperdettagli[[#This Row],[WBS Element]]&"" | AA53: =tabSuperdettagli[[#This Row],[09.2025]] -> 409 | AC53: =IF( tabSuperdettagli[[#This Row],[ProjType_]]="M", IF( AND(tabSuperdettagli[[#This Row],[Resp 1°liv_]]="Guidotti C.", tabSuperdettagli[[#This Row],[WBE description_]]="Machine Mgmt"), "Documentation", tabSuperdettagli[[#This Row],[WBE description_]]), "" ) | AD53: =LEFT(tabSuperdettagli[[#This Row],[Network]], 18 ) | AE53: Send cost F | AP53: Int. | AQ53: Gruppo struttura 5 | AV53: Responsabile D | BJ53: 401 | BK53: 402 | BL53: 403 | BM53: 404 | BN53: 405 | BO53: 406 | BP53: 407 | BQ53: 408 | BR53: 409 | BS53: 410 | BV53: 4055 | BX53: 42156 | CB53: 42155 | CC53: 42195
A54: =IF(UPPER(LEFT(tabSuperdettagli[[#This Row],[WBE Status]],1))="S","sì","no") -> no | B54: 2020 | C54: =VLOOKUP(tabSuperdettagli[[#This Row],[WBS_]],Pivot_AnnoPrimaMarcatura!A:B,2,FALSE) -> #N/A | D54: =LEFT(tabSuperdettagli[[#This Row],[Network]], 10) | E54: =LEFT(tabSuperdettagli[[#This Row],[Network]], 1) | F54: =LOWER(TRIM( tabSuperdettagli[[#This Row],[Proj. Type ]] )) | G54: =IF( OR( tabSuperdettagli[[#This Row],[ProjType_]]="C", tabSuperdettagli[[#This Row],[ProjType_]]="A", tabSuperdettagli[[#This Row],[ProjType_]]="R", tabSuperdettagli[[#This Row],[ProjType_]]="E"), "C A R E", IF( tabSuperdettagli[[#This Row],[ProjType_]]="U", "U (" & tabSuperdettagli[[#This Row],[U ProjType_]] & ")", tabSuperdettagli[[#This Row],[ProjType_]]) ) | I54: =IF( TRIM(tabSuperdettagli[[#This Row],[Raggr. X Struttura]])> "", TRIM(tabSuperdettagli[[#This Row],[Raggr. X Struttura]]), TRIM(tabSuperdettagli[[#This Row],[Resp DT]] ) ) -> Responsabile D | J54: =tabSuperdettagli[[#This Row],[Total]] -> 5055 | K54: =tabSuperdettagli[[#This Row],[01.2025]] -> 501 | L54: =tabSuperdettagli[[#This Row],[02.2025]] -> 502 | M54: =tabSuperdettagli[[#This Row],[03.2025]] -> 503 | N54: =tabSuperdettagli[[#This Row],[04.2025]] -> 504 | O54: =tabSuperdettagli[[#This Row],[05.2025]] -> 505 | P54: =tabSuperdettagli[[#This Row],[06.2025]] -> 506 | Q54: =tabSuperdettagli[[#This Row],[07.2025]] -> 507 | R54: =tabSuperdettagli[[#This Row],[08.2025]] -> 508 | S54: =tabSuperdettagli[[#This Row],[09.2025]] -> 509 | T54: =tabSuperdettagli[[#This Row],[10.2025]] -> 510 | U54: =tabSuperdettagli[[#This Row],[11.2025]] -> 0 | V54: =tabSuperdettagli[[#This Row],[12.2025]] -> 0 | W54: =tabSuperdettagli[[#This Row],[INT/EST]] -> Est. | X54: =tabSuperdettagli[[#This Row],[Resp 2°liv]]&"" | Y54: =INDEX( tab_resp1liv[EngUnit area cluster 1_], MATCH( SUBSTITUTE(tabSuperdettagli[[#This Row],[Resp 2°liv]], " ", ""), tab_resp1liv[SearchKey],0)) -> #N/A | Z54: =tabSuperdettagli[[#This Row],[WBS Element]]&"" | AA54: =tabSuperdettagli[[#This Row],[09.2025]] -> 509 | AC54: =IF( tabSuperdettagli[[#This Row],[ProjType_]]="M", IF( AND(tabSuperdettagli[[#This Row],[Resp 1°liv_]]="Guidotti C.", tabSuperdettagli[[#This Row],[WBE description_]]="Machine Mgmt"), "Documentation", tabSuperdettagli[[#This Row],[WBE description_]]), "" ) | AD54: =LEFT(tabSuperdettagli[[#This Row],[Network]], 18 ) | AE54: Send cost F | AP54: Est. | AV54: Responsabile D | BJ54: 501 | BK54: 502 | BL54: 503 | BM54: 504 | BN54: 505 | BO54: 506 | BP54: 507 | BQ54: 508 | BR54: 509 | BS54: 510 | BV54: 5055 | BX54: 42159 | CB54: 42158 | CC54: 42198
A55: =IF(UPPER(LEFT(tabSuperdettagli[[#This Row],[WBE Status]],1))="S","sì","no") -> no | B55: 2020 | C55: =VLOOKUP(tabSuperdettagli[[#This Row],[WBS_]],Pivot_AnnoPrimaMarcatura!A:B,2,FALSE) -> #N/A | D55: =LEFT(tabSuperdettagli[[#This Row],[Network]], 10) | E55: =LEFT(tabSuperdettagli[[#This Row],[Network]], 1) | F55: =LOWER(TRIM( tabSuperdettagli[[#This Row],[Proj. Type ]] )) | G55: =IF( OR( tabSuperdettagli[[#This Row],[ProjType_]]="C", tabSuperdettagli[[#This Row],[ProjType_]]="A", tabSuperdettagli[[#This Row],[ProjType_]]="R", tabSuperdettagli[[#This Row],[ProjType_]]="E"), "C A R E", IF( tabSuperdettagli[[#This Row],[ProjType_]]="U", "U (" & tabSuperdettagli[[#This Row],[U ProjType_]] & ")", tabSuperdettagli[[#This Row],[ProjType_]]) ) | I55: =IF( TRIM(tabSuperdettagli[[#This Row],[Raggr. X Struttura]])> "", TRIM(tabSuperdettagli[[#This Row],[Raggr. X Struttura]]), TRIM(tabSuperdettagli[[#This Row],[Resp DT]] ) ) -> Responsabile A | J55: =tabSuperdettagli[[#This Row],[Total]] -> 55 | K55: =tabSuperdettagli[[#This Row],[01.2025]] -> 1 | L55: =tabSuperdettagli[[#This Row],[02.2025]] -> 2 | M55: =tabSuperdettagli[[#This Row],[03.2025]] -> 3 | N55: =tabSuperdettagli[[#This Row],[04.2025]] -> 4 | O55: =tabSuperdettagli[[#This Row],[05.2025]] -> 5 | P55: =tabSuperdettagli[[#This Row],[06.2025]] -> 6 | Q55: =tabSuperdettagli[[#This Row],[07.2025]] -> 7 | R55: =tabSuperdettagli[[#This Row],[08.2025]] -> 8 | S55: =tabSuperdettagli[[#This Row],[09.2025]] -> 9 | T55: =tabSuperdettagli[[#This Row],[10.2025]] -> 10 | U55: =tabSuperdettagli[[#This Row],[11.2025]] -> 0 | V55: =tabSuperdettagli[[#This Row],[12.2025]] -> 0 | W55: =tabSuperdettagli[[#This Row],[INT/EST]] -> Est. | X55: =tabSuperdettagli[[#This Row],[Resp 2°liv]]&"" | Y55: =INDEX( tab_resp1liv[EngUnit area cluster 1_], MATCH( SUBSTITUTE(tabSuperdettagli[[#This Row],[Resp 2°liv]], " ", ""), tab_resp1liv[SearchKey],0)) -> #N/A | Z55: =tabSuperdettagli[[#This Row],[WBS Element]]&"" | AA55: =tabSuperdettagli[[#This Row],[09.2025]] -> 9 | AC55: =IF( tabSuperdettagli[[#This Row],[ProjType_]]="M", IF( AND(tabSuperdettagli[[#This Row],[Resp 1°liv_]]="Guidotti C.", tabSuperdettagli[[#This Row],[WBE description_]]="Machine Mgmt"), "Documentation", tabSuperdettagli[[#This Row],[WBE description_]]), "" ) | AD55: =LEFT(tabSuperdettagli[[#This Row],[Network]], 18 ) | AE55: Send cost F | AP55: Est. | AV55: Responsabile A | BJ55: 1 | BK55: 2 | BL55: 3 | BM55: 4 | BN55: 5 | BO55: 6 | BP55: 7 | BQ55: 8 | BR55: 9 | BS55: 10 | BV55: 55 | BX55: 42162 | CB55: 42161 | CC55: 42201
A56: =IF(UPPER(LEFT(tabSuperdettagli[[#This Row],[WBE Status]],1))="S","sì","no") -> no | B56: 2020 | C56: =VLOOKUP(tabSuperdettagli[[#This Row],[WBS_]],Pivot_AnnoPrimaMarcatura!A:B,2,FALSE) -> #N/A | D56: =LEFT(tabSuperdettagli[[#This Row],[Network]], 10) | E56: =LEFT(tabSuperdettagli[[#This Row],[Network]], 1) | F56: =LOWER(TRIM( tabSuperdettagli[[#This Row],[Proj. Type ]] )) | G56: =IF( OR( tabSuperdettagli[[#This Row],[ProjType_]]="C", tabSuperdettagli[[#This Row],[ProjType_]]="A", tabSuperdettagli[[#This Row],[ProjType_]]="R", tabSuperdettagli[[#This Row],[ProjType_]]="E"), "C A R E", IF( tabSuperdettagli[[#This Row],[ProjType_]]="U", "U (" & tabSuperdettagli[[#This Row],[U ProjType_]] & ")", tabSuperdettagli[[#This Row],[ProjType_]]) ) | I56: =IF( TRIM(tabSuperdettagli[[#This Row],[Raggr. X Struttura]])> "", TRIM(tabSuperdettagli[[#This Row],[Raggr. X Struttura]]), TRIM(tabSuperdettagli[[#This Row],[Resp DT]] ) ) -> Responsabile A | J56: =tabSuperdettagli[[#This Row],[Total]] -> 1055 | K56: =tabSuperdettagli[[#This Row],[01.2025]] -> 101 | L56: =tabSuperdettagli[[#This Row],[02.2025]] -> 102 | M56: =tabSuperdettagli[[#This Row],[03.2025]] -> 103 | N56: =tabSuperdettagli[[#This Row],[04.2025]] -> 104 | O56: =tabSuperdettagli[[#This Row],[05.2025]] -> 105 | P56: =tabSuperdettagli[[#This Row],[06.2025]] -> 106 | Q56: =tabSuperdettagli[[#This Row],[07.2025]] -> 107 | R56: =tabSuperdettagli[[#This Row],[08.2025]] -> 108 | S56: =tabSuperdettagli[[#This Row],[09.2025]] -> 109 | T56: =tabSuperdettagli[[#This Row],[10.2025]] -> 110 | U56: =tabSuperdettagli[[#This Row],[11.2025]] -> 0 | V56: =tabSuperdettagli[[#This Row],[12.2025]] -> 0 | W56: =tabSuperdettagli[[#This Row],[INT/EST]] -> Est. | X56: =tabSuperdettagli[[#This Row],[Resp 2°liv]]&"" | Y56: =INDEX( tab_resp1liv[EngUnit area cluster 1_], MATCH( SUBSTITUTE(tabSuperdettagli[[#This Row],[Resp 2°liv]], " ", ""), tab_resp1liv[SearchKey],0)) -> #N/A | Z56: =tabSuperdettagli[[#This Row],[WBS Element]]&"" | AA56: =tabSuperdettagli[[#This Row],[09.2025]] -> 109 | AC56: =IF( tabSuperdettagli[[#This Row],[ProjType_]]="M", IF( AND(tabSuperdettagli[[#This Row],[Resp 1°liv_]]="Guidotti C.", tabSuperdettagli[[#This Row],[WBE description_]]="Machine Mgmt"), "Documentation", tabSuperdettagli[[#This Row],[WBE description_]]), "" ) | AD56: =LEFT(tabSuperdettagli[[#This Row],[Network]], 18 ) | AE56: Send cost F | AP56: Est. | AV56: Responsabile A | BJ56: 101 | BK56: 102 | BL56: 103 | BM56: 104 | BN56: 105 | BO56: 106 | BP56: 107 | BQ56: 108 | BR56: 109 | BS56: 110 | BV56: 1055 | BX56: 42165 | CB56: 42164 | CC56: 42204
A57: =IF(UPPER(LEFT(tabSuperdettagli[[#This Row],[WBE Status]],1))="S","sì","no") -> no | B57: 2020 | C57: =VLOOKUP(tabSuperdettagli[[#This Row],[WBS_]],Pivot_AnnoPrimaMarcatura!A:B,2,FALSE) -> #N/A | D57: =LEFT(tabSuperdettagli[[#This Row],[Network]], 10) | E57: =LEFT(tabSuperdettagli[[#This Row],[Network]], 1) | F57: =LOWER(TRIM( tabSuperdettagli[[#This Row],[Proj. Type ]] )) | G57: =IF( OR( tabSuperdettagli[[#This Row],[ProjType_]]="C", tabSuperdettagli[[#This Row],[ProjType_]]="A", tabSuperdettagli[[#This Row],[ProjType_]]="R", tabSuperdettagli[[#This Row],[ProjType_]]="E"), "C A R E", IF( tabSuperdettagli[[#This Row],[ProjType_]]="U", "U (" & tabSuperdettagli[[#This Row],[U ProjType_]] & ")", tabSuperdettagli[[#This Row],[ProjType_]]) ) | I57: =IF( TRIM(tabSuperdettagli[[#This Row],[Raggr. X Struttura]])> "", TRIM(tabSuperdettagli[[#This Row],[Raggr. X Struttura]]), TRIM(tabSuperdettagli[[#This Row],[Resp DT]] ) ) -> Responsabile A | J57: =tabSuperdettagli[[#This Row],[Total]] -> 2055 | K57: =tabSuperdettagli[[#This Row],[01.2025]] -> 201 | L57: =tabSuperdettagli[[#This Row],[02.2025]] -> 202 | M57: =tabSuperdettagli[[#This Row],[03.2025]] -> 203 | N57: =tabSuperdettagli[[#This Row],[04.2025]] -> 204 | O57: =tabSuperdettagli[[#This Row],[05.2025]] -> 205 | P57: =tabSuperdettagli[[#This Row],[06.2025]] -> 206 | Q57: =tabSuperdettagli[[#This Row],[07.2025]] -> 207 | R57: =tabSuperdettagli[[#This Row],[08.2025]] -> 208 | S57: =tabSuperdettagli[[#This Row],[09.2025]] -> 209 | T57: =tabSuperdettagli[[#This Row],[10.2025]] -> 210 | U57: =tabSuperdettagli[[#This Row],[11.2025]] -> 0 | V57: =tabSuperdettagli[[#This Row],[12.2025]] -> 0 | W57: =tabSuperdettagli[[#This Row],[INT/EST]] -> Est. | X57: =tabSuperdettagli[[#This Row],[Resp 2°liv]]&"" | Y57: =INDEX( tab_resp1liv[EngUnit area cluster 1_], MATCH( SUBSTITUTE(tabSuperdettagli[[#This Row],[Resp 2°liv]], " ", ""), tab_resp1liv[SearchKey],0)) -> #N/A | Z57: =tabSuperdettagli[[#This Row],[WBS Element]]&"" | AA57: =tabSuperdettagli[[#This Row],[09.2025]] -> 209 | AC57: =IF( tabSuperdettagli[[#This Row],[ProjType_]]="M", IF( AND(tabSuperdettagli[[#This Row],[Resp 1°liv_]]="Guidotti C.", tabSuperdettagli[[#This Row],[WBE description_]]="Machine Mgmt"), "Documentation", tabSuperdettagli[[#This Row],[WBE description_]]), "" ) | AD57: =LEFT(tabSuperdettagli[[#This Row],[Network]], 18 ) | AE57: Send cost F | AP57: Est. | AV57: Responsabile A | BJ57: 201 | BK57: 202 | BL57: 203 | BM57: 204 | BN57: 205 | BO57: 206 | BP57: 207 | BQ57: 208 | BR57: 209 | BS57: 210 | BV57: 2055 | BX57: 42168 | CB57: 42167 | CC57: 42207
A58: =IF(UPPER(LEFT(tabSuperdettagli[[#This Row],[WBE Status]],1))="S","sì","no") -> no | B58: 2020 | C58: =VLOOKUP(tabSuperdettagli[[#This Row],[WBS_]],Pivot_AnnoPrimaMarcatura!A:B,2,FALSE) -> #N/A | D58: =LEFT(tabSuperdettagli[[#This Row],[Network]], 10) | E58: =LEFT(tabSuperdettagli[[#This Row],[Network]], 1) | F58: =LOWER(TRIM( tabSuperdettagli[[#This Row],[Proj. Type ]] )) | G58: =IF( OR( tabSuperdettagli[[#This Row],[ProjType_]]="C", tabSuperdettagli[[#This Row],[ProjType_]]="A", tabSuperdettagli[[#This Row],[ProjType_]]="R", tabSuperdettagli[[#This Row],[ProjType_]]="E"), "C A R E", IF( tabSuperdettagli[[#This Row],[ProjType_]]="U", "U (" & tabSuperdettagli[[#This Row],[U ProjType_]] & ")", tabSuperdettagli[[#This Row],[ProjType_]]) ) | I58: =IF( TRIM(tabSuperdettagli[[#This Row],[Raggr. X Struttura]])> "", TRIM(tabSuperdettagli[[#This Row],[Raggr. X Struttura]]), TRIM(tabSuperdettagli[[#This Row],[Resp DT]] ) ) -> Gruppo struttura 4 | J58: =tabSuperdettagli[[#This Row],[Total]] -> 3055 | K58: =tabSuperdettagli[[#This Row],[01.2025]] -> 301 | L58: =tabSuperdettagli[[#This Row],[02.2025]] -> 302 | M58: =tabSuperdettagli[[#This Row],[03.2025]] -> 303 | N58: =tabSuperdettagli[[#This Row],[04.2025]] -> 304 | O58: =tabSuperdettagli[[#This Row],[05.2025]] -> 305 | P58: =tabSuperdettagli[[#This Row],[06.2025]] -> 306 | Q58: =tabSuperdettagli[[#This Row],[07.2025]] -> 307 | R58: =tabSuperdettagli[[#This Row],[08.2025]] -> 308 | S58: =tabSuperdettagli[[#This Row],[09.2025]] -> 309 | T58: =tabSuperdettagli[[#This Row],[10.2025]] -> 310 | U58: =tabSuperdettagli[[#This Row],[11.2025]] -> 0 | V58: =tabSuperdettagli[[#This Row],[12.2025]] -> 0 | W58: =tabSuperdettagli[[#This Row],[INT/EST]] -> Int. | X58: =tabSuperdettagli[[#This Row],[Resp 2°liv]]&"" | Y58: =INDEX( tab_resp1liv[EngUnit area cluster 1_], MATCH( SUBSTITUTE(tabSuperdettagli[[#This Row],[Resp 2°liv]], " ", ""), tab_resp1liv[SearchKey],0)) -> #N/A | Z58: =tabSuperdettagli[[#This Row],[WBS Element]]&"" | AA58: =tabSuperdettagli[[#This Row],[09.2025]] -> 309 | AC58: =IF( tabSuperdettagli[[#This Row],[ProjType_]]="M", IF( AND(tabSuperdettagli[[#This Row],[Resp 1°liv_]]="Guidotti C.", tabSuperdettagli[[#This Row],[WBE description_]]="Machine Mgmt"), "Documentation", tabSuperdettagli[[#This Row],[WBE description_]]), "" ) | AD58: =LEFT(tabSuperdettagli[[#This Row],[Network]], 18 ) | AE58: Send cost F | AP58: Int. | AQ58: Gruppo struttura 4 | AV58: Responsabile E | BJ58: 301 | BK58: 302 | BL58: 303 | BM58: 304 | BN58: 305 | BO58: 306 | BP58: 307 | BQ58: 308 | BR58: 309 | BS58: 310 | BV58: 3055 | BX58: 42171 | CB58: 42170 | CC58: 42210
A59: =IF(UPPER(LEFT(tabSuperdettagli[[#This Row],[WBE Status]],1))="S","sì","no") -> no | B59: 2020 | C59: =VLOOKUP(tabSuperdettagli[[#This Row],[WBS_]],Pivot_AnnoPrimaMarcatura!A:B,2,FALSE) -> #N/A | D59: =LEFT(tabSuperdettagli[[#This Row],[Network]], 10) | E59: =LEFT(tabSuperdettagli[[#This Row],[Network]], 1) | F59: =LOWER(TRIM( tabSuperdettagli[[#This Row],[Proj. Type ]] )) | G59: =IF( OR( tabSuperdettagli[[#This Row],[ProjType_]]="C", tabSuperdettagli[[#This Row],[ProjType_]]="A", tabSuperdettagli[[#This Row],[ProjType_]]="R", tabSuperdettagli[[#This Row],[ProjType_]]="E"), "C A R E", IF( tabSuperdettagli[[#This Row],[ProjType_]]="U", "U (" & tabSuperdettagli[[#This Row],[U ProjType_]] & ")", tabSuperdettagli[[#This Row],[ProjType_]]) ) | I59: =IF( TRIM(tabSuperdettagli[[#This Row],[Raggr. X Struttura]])> "", TRIM(tabSuperdettagli[[#This Row],[Raggr. X Struttura]]), TRIM(tabSuperdettagli[[#This Row],[Resp DT]] ) ) -> Gruppo struttura 1 | J59: =tabSuperdettagli[[#This Row],[Total]] -> 4055 | K59: =tabSuperdettagli[[#This Row],[01.2025]] -> 401 | L59: =tabSuperdettagli[[#This Row],[02.2025]] -> 402 | M59: =tabSuperdettagli[[#This Row],[03.2025]] -> 403 | N59: =tabSuperdettagli[[#This Row],[04.2025]] -> 404 | O59: =tabSuperdettagli[[#This Row],[05.2025]] -> 405 | P59: =tabSuperdettagli[[#This Row],[06.2025]] -> 406 | Q59: =tabSuperdettagli[[#This Row],[07.2025]] -> 407 | R59: =tabSuperdettagli[[#This Row],[08.2025]] -> 408 | S59: =tabSuperdettagli[[#This Row],[09.2025]] -> 409 | T59: =tabSuperdettagli[[#This Row],[10.2025]] -> 410 | U59: =tabSuperdettagli[[#This Row],[11.2025]] -> 0 | V59: =tabSuperdettagli[[#This Row],[12.2025]] -> 0 | W59: =tabSuperdettagli[[#This Row],[INT/EST]] -> Int. | X59: =tabSuperdettagli[[#This Row],[Resp 2°liv]]&"" | Y59: =INDEX( tab_resp1liv[EngUnit area cluster 1_], MATCH( SUBSTITUTE(tabSuperdettagli[[#This Row],[Resp 2°liv]], " ", ""), tab_resp1liv[SearchKey],0)) -> #N/A | Z59: =tabSuperdettagli[[#This Row],[WBS Element]]&"" | AA59: =tabSuperdettagli[[#This Row],[09.2025]] -> 409 | AC59: =IF( tabSuperdettagli[[#This Row],[ProjType_]]="M", IF( AND(tabSuperdettagli[[#This Row],[Resp 1°liv_]]="Guidotti C.", tabSuperdettagli[[#This Row],[WBE description_]]="Machine Mgmt"), "Documentation", tabSuperdettagli[[#This Row],[WBE description_]]), "" ) | AD59: =LEFT(tabSuperdettagli[[#This Row],[Network]], 18 ) | AE59: Send cost F | AP59: Int. | AQ59: Gruppo struttura 1 | AV59: Responsabile A | BJ59: 401 | BK59: 402 | BL59: 403 | BM59: 404 | BN59: 405 | BO59: 406 | BP59: 407 | BQ59: 408 | BR59: 409 | BS59: 410 | BV59: 4055 | BX59: 42174 | CB59: 42173 | CC59: 42213
A60: =IF(UPPER(LEFT(tabSuperdettagli[[#This Row],[WBE Status]],1))="S","sì","no") -> no | B60: 2020 | C60: =VLOOKUP(tabSuperdettagli[[#This Row],[WBS_]],Pivot_AnnoPrimaMarcatura!A:B,2,FALSE) -> #N/A | D60: =LEFT(tabSuperdettagli[[#This Row],[Network]], 10) | E60: =LEFT(tabSuperdettagli[[#This Row],[Network]], 1) | F60: =LOWER(TRIM( tabSuperdettagli[[#This Row],[Proj. Type ]] )) | G60: =IF( OR( tabSuperdettagli[[#This Row],[ProjType_]]="C", tabSuperdettagli[[#This Row],[ProjType_]]="A", tabSuperdettagli[[#This Row],[ProjType_]]="R", tabSuperdettagli[[#This Row],[ProjType_]]="E"), "C A R E", IF( tabSuperdettagli[[#This Row],[ProjType_]]="U", "U (" & tabSuperdettagli[[#This Row],[U ProjType_]] & ")", tabSuperdettagli[[#This Row],[ProjType_]]) ) | I60: =IF( TRIM(tabSuperdettagli[[#This Row],[Raggr. X Struttura]])> "", TRIM(tabSuperdettagli[[#This Row],[Raggr. X Struttura]]), TRIM(tabSuperdettagli[[#This Row],[Resp DT]] ) ) -> Gruppo struttura 1 | J60: =tabSuperdettagli[[#This Row],[Total]] -> 5055 | K60: =tabSuperdettagli[[#This Row],[01.2025]] -> 501 | L60: =tabSuperdettagli[[#This Row],[02.2025]] -> 502 | M60: =tabSuperdettagli[[#This Row],[03.2025]] -> 503 | N60: =tabSuperdettagli[[#This Row],[04.2025]] -> 504 | O60: =tabSuperdettagli[[#This Row],[05.2025]] -> 505 | P60: =tabSuperdettagli[[#This Row],[06.2025]] -> 506 | Q60: =tabSuperdettagli[[#This Row],[07.2025]] -> 507 | R60: =tabSuperdettagli[[#This Row],[08.2025]] -> 508 | S60: =tabSuperdettagli[[#This Row],[09.2025]] -> 509 | T60: =tabSuperdettagli[[#This Row],[10.2025]] -> 510 | U60: =tabSuperdettagli[[#This Row],[11.2025]] -> 0 | V60: =tabSuperdettagli[[#This Row],[12.2025]] -> 0 | W60: =tabSuperdettagli[[#This Row],[INT/EST]] -> Int. | X60: =tabSuperdettagli[[#This Row],[Resp 2°liv]]&"" | Y60: =INDEX( tab_resp1liv[EngUnit area cluster 1_], MATCH( SUBSTITUTE(tabSuperdettagli[[#This Row],[Resp 2°liv]], " ", ""), tab_resp1liv[SearchKey],0)) -> #N/A | Z60: =tabSuperdettagli[[#This Row],[WBS Element]]&"" | AA60: =tabSuperdettagli[[#This Row],[09.2025]] -> 509 | AC60: =IF( tabSuperdettagli[[#This Row],[ProjType_]]="M", IF( AND(tabSuperdettagli[[#This Row],[Resp 1°liv_]]="Guidotti C.", tabSuperdettagli[[#This Row],[WBE description_]]="Machine Mgmt"), "Documentation", tabSuperdettagli[[#This Row],[WBE description_]]), "" ) | AD60: =LEFT(tabSuperdettagli[[#This Row],[Network]], 18 ) | AE60: Send cost F | AP60: Int. | AQ60: Gruppo struttura 1 | AV60: Responsabile D | BJ60: 501 | BK60: 502 | BL60: 503 | BM60: 504 | BN60: 505 | BO60: 506 | BP60: 507 | BQ60: 508 | BR60: 509 | BS60: 510 | BV60: 5055 | BX60: 42177 | CB60: 42176 | CC60: 42216
A61: =IF(UPPER(LEFT(tabSuperdettagli[[#This Row],[WBE Status]],1))="S","sì","no") -> no | B61: 2020 | C61: =VLOOKUP(tabSuperdettagli[[#This Row],[WBS_]],Pivot_AnnoPrimaMarcatura!A:B,2,FALSE) -> #N/A | D61: =LEFT(tabSuperdettagli[[#This Row],[Network]], 10) | E61: =LEFT(tabSuperdettagli[[#This Row],[Network]], 1) | F61: =LOWER(TRIM( tabSuperdettagli[[#This Row],[Proj. Type ]] )) | G61: =IF( OR( tabSuperdettagli[[#This Row],[ProjType_]]="C", tabSuperdettagli[[#This Row],[ProjType_]]="A", tabSuperdettagli[[#This Row],[ProjType_]]="R", tabSuperdettagli[[#This Row],[ProjType_]]="E"), "C A R E", IF( tabSuperdettagli[[#This Row],[ProjType_]]="U", "U (" & tabSuperdettagli[[#This Row],[U ProjType_]] & ")", tabSuperdettagli[[#This Row],[ProjType_]]) ) | I61: =IF( TRIM(tabSuperdettagli[[#This Row],[Raggr. X Struttura]])> "", TRIM(tabSuperdettagli[[#This Row],[Raggr. X Struttura]]), TRIM(tabSuperdettagli[[#This Row],[Resp DT]] ) ) -> Responsabile A | J61: =tabSuperdettagli[[#This Row],[Total]] -> 6055 | K61: =tabSuperdettagli[[#This Row],[01.2025]] -> 601 | L61: =tabSuperdettagli[[#This Row],[02.2025]] -> 602 | M61: =tabSuperdettagli[[#This Row],[03.2025]] -> 603 | N61: =tabSuperdettagli[[#This Row],[04.2025]] -> 604 | O61: =tabSuperdettagli[[#This Row],[05.2025]] -> 605 | P61: =tabSuperdettagli[[#This Row],[06.2025]] -> 606 | Q61: =tabSuperdettagli[[#This Row],[07.2025]] -> 607 | R61: =tabSuperdettagli[[#This Row],[08.2025]] -> 608 | S61: =tabSuperdettagli[[#This Row],[09.2025]] -> 609 | T61: =tabSuperdettagli[[#This Row],[10.2025]] -> 610 | U61: =tabSuperdettagli[[#This Row],[11.2025]] -> 0 | V61: =tabSuperdettagli[[#This Row],[12.2025]] -> 0 | W61: =tabSuperdettagli[[#This Row],[INT/EST]] -> Int. | X61: =tabSuperdettagli[[#This Row],[Resp 2°liv]]&"" | Y61: =INDEX( tab_resp1liv[EngUnit area cluster 1_], MATCH( SUBSTITUTE(tabSuperdettagli[[#This Row],[Resp 2°liv]], " ", ""), tab_resp1liv[SearchKey],0)) -> #N/A | Z61: =tabSuperdettagli[[#This Row],[WBS Element]]&"" | AA61: =tabSuperdettagli[[#This Row],[09.2025]] -> 609 | AC61: =IF( tabSuperdettagli[[#This Row],[ProjType_]]="M", IF( AND(tabSuperdettagli[[#This Row],[Resp 1°liv_]]="Guidotti C.", tabSuperdettagli[[#This Row],[WBE description_]]="Machine Mgmt"), "Documentation", tabSuperdettagli[[#This Row],[WBE description_]]), "" ) | AD61: =LEFT(tabSuperdettagli[[#This Row],[Network]], 18 ) | AE61: Send cost F | AP61: Int. | AV61: Responsabile A | BJ61: 601 | BK61: 602 | BL61: 603 | BM61: 604 | BN61: 605 | BO61: 606 | BP61: 607 | BQ61: 608 | BR61: 609 | BS61: 610 | BV61: 6055 | BX61: 42180 | CB61: 42179 | CC61: 42219
A62: =IF(UPPER(LEFT(tabSuperdettagli[[#This Row],[WBE Status]],1))="S","sì","no") -> no | B62: 2020 | C62: =VLOOKUP(tabSuperdettagli[[#This Row],[WBS_]],Pivot_AnnoPrimaMarcatura!A:B,2,FALSE) -> #N/A | D62: =LEFT(tabSuperdettagli[[#This Row],[Network]], 10) | E62: =LEFT(tabSuperdettagli[[#This Row],[Network]], 1) | F62: =LOWER(TRIM( tabSuperdettagli[[#This Row],[Proj. Type ]] )) | G62: =IF( OR( tabSuperdettagli[[#This Row],[ProjType_]]="C", tabSuperdettagli[[#This Row],[ProjType_]]="A", tabSuperdettagli[[#This Row],[ProjType_]]="R", tabSuperdettagli[[#This Row],[ProjType_]]="E"), "C A R E", IF( tabSuperdettagli[[#This Row],[ProjType_]]="U", "U (" & tabSuperdettagli[[#This Row],[U ProjType_]] & ")", tabSuperdettagli[[#This Row],[ProjType_]]) ) | I62: =IF( TRIM(tabSuperdettagli[[#This Row],[Raggr. X Struttura]])> "", TRIM(tabSuperdettagli[[#This Row],[Raggr. X Struttura]]), TRIM(tabSuperdettagli[[#This Row],[Resp DT]] ) ) -> Gruppo struttura 2 | J62: =tabSuperdettagli[[#This Row],[Total]] -> 55 | K62: =tabSuperdettagli[[#This Row],[01.2025]] -> 1 | L62: =tabSuperdettagli[[#This Row],[02.2025]] -> 2 | M62: =tabSuperdettagli[[#This Row],[03.2025]] -> 3 | N62: =tabSuperdettagli[[#This Row],[04.2025]] -> 4 | O62: =tabSuperdettagli[[#This Row],[05.2025]] -> 5 | P62: =tabSuperdettagli[[#This Row],[06.2025]] -> 6 | Q62: =tabSuperdettagli[[#This Row],[07.2025]] -> 7 | R62: =tabSuperdettagli[[#This Row],[08.2025]] -> 8 | S62: =tabSuperdettagli[[#This Row],[09.2025]] -> 9 | T62: =tabSuperdettagli[[#This Row],[10.2025]] -> 10 | U62: =tabSuperdettagli[[#This Row],[11.2025]] -> 0 | V62: =tabSuperdettagli[[#This Row],[12.2025]] -> 0 | W62: =tabSuperdettagli[[#This Row],[INT/EST]] -> Int. | X62: =tabSuperdettagli[[#This Row],[Resp 2°liv]]&"" | Y62: =INDEX( tab_resp1liv[EngUnit area cluster 1_], MATCH( SUBSTITUTE(tabSuperdettagli[[#This Row],[Resp 2°liv]], " ", ""), tab_resp1liv[SearchKey],0)) -> #N/A | Z62: =tabSuperdettagli[[#This Row],[WBS Element]]&"" | AA62: =tabSuperdettagli[[#This Row],[09.2025]] -> 9 | AC62: =IF( tabSuperdettagli[[#This Row],[ProjType_]]="M", IF( AND(tabSuperdettagli[[#This Row],[Resp 1°liv_]]="Guidotti C.", tabSuperdettagli[[#This Row],[WBE description_]]="Machine Mgmt"), "Documentation", tabSuperdettagli[[#This Row],[WBE description_]]), "" ) | AD62: =LEFT(tabSuperdettagli[[#This Row],[Network]], 18 ) | AE62: Send cost F | AP62: Int. | AQ62: Gruppo struttura 2 | AV62: Responsabile A | BJ62: 1 | BK62: 2 | BL62: 3 | BM62: 4 | BN62: 5 | BO62: 6 | BP62: 7 | BQ62: 8 | BR62: 9 | BS62: 10 | BV62: 55 | BX62: 42183 | CB62: 42182 | CC62: 42222
A63: =IF(UPPER(LEFT(tabSuperdettagli[[#This Row],[WBE Status]],1))="S","sì","no") -> no | B63: 2021 | C63: =VLOOKUP(tabSuperdettagli[[#This Row],[WBS_]],Pivot_AnnoPrimaMarcatura!A:B,2,FALSE) -> #N/A | D63: =LEFT(tabSuperdettagli[[#This Row],[Network]], 10) | E63: =LEFT(tabSuperdettagli[[#This Row],[Network]], 1) | F63: =LOWER(TRIM( tabSuperdettagli[[#This Row],[Proj. Type ]] )) | G63: =IF( OR( tabSuperdettagli[[#This Row],[ProjType_]]="C", tabSuperdettagli[[#This Row],[ProjType_]]="A", tabSuperdettagli[[#This Row],[ProjType_]]="R", tabSuperdettagli[[#This Row],[ProjType_]]="E"), "C A R E", IF( tabSuperdettagli[[#This Row],[ProjType_]]="U", "U (" & tabSuperdettagli[[#This Row],[U ProjType_]] & ")", tabSuperdettagli[[#This Row],[ProjType_]]) ) | I63: =IF( TRIM(tabSuperdettagli[[#This Row],[Raggr. X Struttura]])> "", TRIM(tabSuperdettagli[[#This Row],[Raggr. X Struttura]]), TRIM(tabSuperdettagli[[#This Row],[Resp DT]] ) ) -> Gruppo struttura 1 | J63: =tabSuperdettagli[[#This Row],[Total]] -> 1055 | K63: =tabSuperdettagli[[#This Row],[01.2025]] -> 101 | L63: =tabSuperdettagli[[#This Row],[02.2025]] -> 102 | M63: =tabSuperdettagli[[#This Row],[03.2025]] -> 103 | N63: =tabSuperdettagli[[#This Row],[04.2025]] -> 104 | O63: =tabSuperdettagli[[#This Row],[05.2025]] -> 105 | P63: =tabSuperdettagli[[#This Row],[06.2025]] -> 106 | Q63: =tabSuperdettagli[[#This Row],[07.2025]] -> 107 | R63: =tabSuperdettagli[[#This Row],[08.2025]] -> 108 | S63: =tabSuperdettagli[[#This Row],[09.2025]] -> 109 | T63: =tabSuperdettagli[[#This Row],[10.2025]] -> 110 | U63: =tabSuperdettagli[[#This Row],[11.2025]] -> 0 | V63: =tabSuperdettagli[[#This Row],[12.2025]] -> 0 | W63: =tabSuperdettagli[[#This Row],[INT/EST]] -> Int. | X63: =tabSuperdettagli[[#This Row],[Resp 2°liv]]&"" | Y63: =INDEX( tab_resp1liv[EngUnit area cluster 1_], MATCH( SUBSTITUTE(tabSuperdettagli[[#This Row],[Resp 2°liv]], " ", ""), tab_resp1liv[SearchKey],0)) -> #N/A | Z63: =tabSuperdettagli[[#This Row],[WBS Element]]&"" | AA63: =tabSuperdettagli[[#This Row],[09.2025]] -> 109 | AC63: =IF( tabSuperdettagli[[#This Row],[ProjType_]]="M", IF( AND(tabSuperdettagli[[#This Row],[Resp 1°liv_]]="Guidotti C.", tabSuperdettagli[[#This Row],[WBE description_]]="Machine Mgmt"), "Documentation", tabSuperdettagli[[#This Row],[WBE description_]]), "" ) | AD63: =LEFT(tabSuperdettagli[[#This Row],[Network]], 18 ) | AE63: Send cost G | AP63: Int. | AQ63: Gruppo struttura 1 | AV63: Responsabile A | BJ63: 101 | BK63: 102 | BL63: 103 | BM63: 104 | BN63: 105 | BO63: 106 | BP63: 107 | BQ63: 108 | BR63: 109 | BS63: 110 | BV63: 1055 | BX63: 42186 | CB63: 42185 | CC63: 42225
A64: =IF(UPPER(LEFT(tabSuperdettagli[[#This Row],[WBE Status]],1))="S","sì","no") -> no | B64: 2021 | C64: =VLOOKUP(tabSuperdettagli[[#This Row],[WBS_]],Pivot_AnnoPrimaMarcatura!A:B,2,FALSE) -> #N/A | D64: =LEFT(tabSuperdettagli[[#This Row],[Network]], 10) | E64: =LEFT(tabSuperdettagli[[#This Row],[Network]], 1) | F64: =LOWER(TRIM( tabSuperdettagli[[#This Row],[Proj. Type ]] )) | G64: =IF( OR( tabSuperdettagli[[#This Row],[ProjType_]]="C", tabSuperdettagli[[#This Row],[ProjType_]]="A", tabSuperdettagli[[#This Row],[ProjType_]]="R", tabSuperdettagli[[#This Row],[ProjType_]]="E"), "C A R E", IF( tabSuperdettagli[[#This Row],[ProjType_]]="U", "U (" & tabSuperdettagli[[#This Row],[U ProjType_]] & ")", tabSuperdettagli[[#This Row],[ProjType_]]) ) | I64: =IF( TRIM(tabSuperdettagli[[#This Row],[Raggr. X Struttura]])> "", TRIM(tabSuperdettagli[[#This Row],[Raggr. X Struttura]]), TRIM(tabSuperdettagli[[#This Row],[Resp DT]] ) ) -> Gruppo struttura 3 | J64: =tabSuperdettagli[[#This Row],[Total]] -> 2055 | K64: =tabSuperdettagli[[#This Row],[01.2025]] -> 201 | L64: =tabSuperdettagli[[#This Row],[02.2025]] -> 202 | M64: =tabSuperdettagli[[#This Row],[03.2025]] -> 203 | N64: =tabSuperdettagli[[#This Row],[04.2025]] -> 204 | O64: =tabSuperdettagli[[#This Row],[05.2025]] -> 205 | P64: =tabSuperdettagli[[#This Row],[06.2025]] -> 206 | Q64: =tabSuperdettagli[[#This Row],[07.2025]] -> 207 | R64: =tabSuperdettagli[[#This Row],[08.2025]] -> 208 | S64: =tabSuperdettagli[[#This Row],[09.2025]] -> 209 | T64: =tabSuperdettagli[[#This Row],[10.2025]] -> 210 | U64: =tabSuperdettagli[[#This Row],[11.2025]] -> 0 | V64: =tabSuperdettagli[[#This Row],[12.2025]] -> 0 | W64: =tabSuperdettagli[[#This Row],[INT/EST]] -> Int. | X64: =tabSuperdettagli[[#This Row],[Resp 2°liv]]&"" | Y64: =INDEX( tab_resp1liv[EngUnit area cluster 1_], MATCH( SUBSTITUTE(tabSuperdettagli[[#This Row],[Resp 2°liv]], " ", ""), tab_resp1liv[SearchKey],0)) -> #N/A | Z64: =tabSuperdettagli[[#This Row],[WBS Element]]&"" | AA64: =tabSuperdettagli[[#This Row],[09.2025]] -> 209 | AC64: =IF( tabSuperdettagli[[#This Row],[ProjType_]]="M", IF( AND(tabSuperdettagli[[#This Row],[Resp 1°liv_]]="Guidotti C.", tabSuperdettagli[[#This Row],[WBE description_]]="Machine Mgmt"), "Documentation", tabSuperdettagli[[#This Row],[WBE description_]]), "" ) | AD64: =LEFT(tabSuperdettagli[[#This Row],[Network]], 18 ) | AE64: Send cost G | AP64: Int. | AQ64: Gruppo struttura 3 | AV64: Responsabile A | BJ64: 201 | BK64: 202 | BL64: 203 | BM64: 204 | BN64: 205 | BO64: 206 | BP64: 207 | BQ64: 208 | BR64: 209 | BS64: 210 | BV64: 2055 | BX64: 42189 | CB64: 42188 | CC64: 42228
A65: =IF(UPPER(LEFT(tabSuperdettagli[[#This Row],[WBE Status]],1))="S","sì","no") -> no | B65: 2021 | C65: =VLOOKUP(tabSuperdettagli[[#This Row],[WBS_]],Pivot_AnnoPrimaMarcatura!A:B,2,FALSE) -> #N/A | D65: =LEFT(tabSuperdettagli[[#This Row],[Network]], 10) | E65: =LEFT(tabSuperdettagli[[#This Row],[Network]], 1) | F65: =LOWER(TRIM( tabSuperdettagli[[#This Row],[Proj. Type ]] )) | G65: =IF( OR( tabSuperdettagli[[#This Row],[ProjType_]]="C", tabSuperdettagli[[#This Row],[ProjType_]]="A", tabSuperdettagli[[#This Row],[ProjType_]]="R", tabSuperdettagli[[#This Row],[ProjType_]]="E"), "C A R E", IF( tabSuperdettagli[[#This Row],[ProjType_]]="U", "U (" & tabSuperdettagli[[#This Row],[U ProjType_]] & ")", tabSuperdettagli[[#This Row],[ProjType_]]) ) | I65: =IF( TRIM(tabSuperdettagli[[#This Row],[Raggr. X Struttura]])> "", TRIM(tabSuperdettagli[[#This Row],[Raggr. X Struttura]]), TRIM(tabSuperdettagli[[#This Row],[Resp DT]] ) ) -> Gruppo struttura 1 | J65: =tabSuperdettagli[[#This Row],[Total]] -> 3055 | K65: =tabSuperdettagli[[#This Row],[01.2025]] -> 301 | L65: =tabSuperdettagli[[#This Row],[02.2025]] -> 302 | M65: =tabSuperdettagli[[#This Row],[03.2025]] -> 303 | N65: =tabSuperdettagli[[#This Row],[04.2025]] -> 304 | O65: =tabSuperdettagli[[#This Row],[05.2025]] -> 305 | P65: =tabSuperdettagli[[#This Row],[06.2025]] -> 306 | Q65: =tabSuperdettagli[[#This Row],[07.2025]] -> 307 | R65: =tabSuperdettagli[[#This Row],[08.2025]] -> 308 | S65: =tabSuperdettagli[[#This Row],[09.2025]] -> 309 | T65: =tabSuperdettagli[[#This Row],[10.2025]] -> 310 | U65: =tabSuperdettagli[[#This Row],[11.2025]] -> 0 | V65: =tabSuperdettagli[[#This Row],[12.2025]] -> 0 | W65: =tabSuperdettagli[[#This Row],[INT/EST]] -> Int. | X65: =tabSuperdettagli[[#This Row],[Resp 2°liv]]&"" | Y65: =INDEX( tab_resp1liv[EngUnit area cluster 1_], MATCH( SUBSTITUTE(tabSuperdettagli[[#This Row],[Resp 2°liv]], " ", ""), tab_resp1liv[SearchKey],0)) -> #N/A | Z65: =tabSuperdettagli[[#This Row],[WBS Element]]&"" | AA65: =tabSuperdettagli[[#This Row],[09.2025]] -> 309 | AC65: =IF( tabSuperdettagli[[#This Row],[ProjType_]]="M", IF( AND(tabSuperdettagli[[#This Row],[Resp 1°liv_]]="Guidotti C.", tabSuperdettagli[[#This Row],[WBE description_]]="Machine Mgmt"), "Documentation", tabSuperdettagli[[#This Row],[WBE description_]]), "" ) | AD65: =LEFT(tabSuperdettagli[[#This Row],[Network]], 18 ) | AE65: Send cost G | AP65: Int. | AQ65: Gruppo struttura 1 | AV65: Responsabile A | BJ65: 301 | BK65: 302 | BL65: 303 | BM65: 304 | BN65: 305 | BO65: 306 | BP65: 307 | BQ65: 308 | BR65: 309 | BS65: 310 | BV65: 3055 | BX65: 42192 | CB65: 42191 | CC65: 42231
A66: =IF(UPPER(LEFT(tabSuperdettagli[[#This Row],[WBE Status]],1))="S","sì","no") -> no | B66: 2021 | C66: =VLOOKUP(tabSuperdettagli[[#This Row],[WBS_]],Pivot_AnnoPrimaMarcatura!A:B,2,FALSE) -> #N/A | D66: =LEFT(tabSuperdettagli[[#This Row],[Network]], 10) | E66: =LEFT(tabSuperdettagli[[#This Row],[Network]], 1) | F66: =LOWER(TRIM( tabSuperdettagli[[#This Row],[Proj. Type ]] )) | G66: =IF( OR( tabSuperdettagli[[#This Row],[ProjType_]]="C", tabSuperdettagli[[#This Row],[ProjType_]]="A", tabSuperdettagli[[#This Row],[ProjType_]]="R", tabSuperdettagli[[#This Row],[ProjType_]]="E"), "C A R E", IF( tabSuperdettagli[[#This Row],[ProjType_]]="U", "U (" & tabSuperdettagli[[#This Row],[U ProjType_]] & ")", tabSuperdettagli[[#This Row],[ProjType_]]) ) | I66: =IF( TRIM(tabSuperdettagli[[#This Row],[Raggr. X Struttura]])> "", TRIM(tabSuperdettagli[[#This Row],[Raggr. X Struttura]]), TRIM(tabSuperdettagli[[#This Row],[Resp DT]] ) ) -> Gruppo struttura 1 | J66: =tabSuperdettagli[[#This Row],[Total]] -> 4055 | K66: =tabSuperdettagli[[#This Row],[01.2025]] -> 401 | L66: =tabSuperdettagli[[#This Row],[02.2025]] -> 402 | M66: =tabSuperdettagli[[#This Row],[03.2025]] -> 403 | N66: =tabSuperdettagli[[#This Row],[04.2025]] -> 404 | O66: =tabSuperdettagli[[#This Row],[05.2025]] -> 405 | P66: =tabSuperdettagli[[#This Row],[06.2025]] -> 406 | Q66: =tabSuperdettagli[[#This Row],[07.2025]] -> 407 | R66: =tabSuperdettagli[[#This Row],[08.2025]] -> 408 | S66: =tabSuperdettagli[[#This Row],[09.2025]] -> 409 | T66: =tabSuperdettagli[[#This Row],[10.2025]] -> 410 | U66: =tabSuperdettagli[[#This Row],[11.2025]] -> 0 | V66: =tabSuperdettagli[[#This Row],[12.2025]] -> 0 | W66: =tabSuperdettagli[[#This Row],[INT/EST]] -> Int. | X66: =tabSuperdettagli[[#This Row],[Resp 2°liv]]&"" | Y66: =INDEX( tab_resp1liv[EngUnit area cluster 1_], MATCH( SUBSTITUTE(tabSuperdettagli[[#This Row],[Resp 2°liv]], " ", ""), tab_resp1liv[SearchKey],0)) -> #N/A | Z66: =tabSuperdettagli[[#This Row],[WBS Element]]&"" | AA66: =tabSuperdettagli[[#This Row],[09.2025]] -> 409 | AC66: =IF( tabSuperdettagli[[#This Row],[ProjType_]]="M", IF( AND(tabSuperdettagli[[#This Row],[Resp 1°liv_]]="Guidotti C.", tabSuperdettagli[[#This Row],[WBE description_]]="Machine Mgmt"), "Documentation", tabSuperdettagli[[#This Row],[WBE description_]]), "" ) | AD66: =LEFT(tabSuperdettagli[[#This Row],[Network]], 18 ) | AE66: Send cost G | AP66: Int. | AQ66: Gruppo struttura 1 | AV66: Responsabile A | BJ66: 401 | BK66: 402 | BL66: 403 | BM66: 404 | BN66: 405 | BO66: 406 | BP66: 407 | BQ66: 408 | BR66: 409 | BS66: 410 | BV66: 4055 | BX66: 42195 | CB66: 42194 | CC66: 42234
A67: =IF(UPPER(LEFT(tabSuperdettagli[[#This Row],[WBE Status]],1))="S","sì","no") -> no | B67: 2021 | C67: =VLOOKUP(tabSuperdettagli[[#This Row],[WBS_]],Pivot_AnnoPrimaMarcatura!A:B,2,FALSE) -> #N/A | D67: =LEFT(tabSuperdettagli[[#This Row],[Network]], 10) | E67: =LEFT(tabSuperdettagli[[#This Row],[Network]], 1) | F67: =LOWER(TRIM( tabSuperdettagli[[#This Row],[Proj. Type ]] )) | G67: =IF( OR( tabSuperdettagli[[#This Row],[ProjType_]]="C", tabSuperdettagli[[#This Row],[ProjType_]]="A", tabSuperdettagli[[#This Row],[ProjType_]]="R", tabSuperdettagli[[#This Row],[ProjType_]]="E"), "C A R E", IF( tabSuperdettagli[[#This Row],[ProjType_]]="U", "U (" & tabSuperdettagli[[#This Row],[U ProjType_]] & ")", tabSuperdettagli[[#This Row],[ProjType_]]) ) | I67: =IF( TRIM(tabSuperdettagli[[#This Row],[Raggr. X Struttura]])> "", TRIM(tabSuperdettagli[[#This Row],[Raggr. X Struttura]]), TRIM(tabSuperdettagli[[#This Row],[Resp DT]] ) ) -> Gruppo struttura 6 | J67: =tabSuperdettagli[[#This Row],[Total]] -> 5055 | K67: =tabSuperdettagli[[#This Row],[01.2025]] -> 501 | L67: =tabSuperdettagli[[#This Row],[02.2025]] -> 502 | M67: =tabSuperdettagli[[#This Row],[03.2025]] -> 503 | N67: =tabSuperdettagli[[#This Row],[04.2025]] -> 504 | O67: =tabSuperdettagli[[#This Row],[05.2025]] -> 505 | P67: =tabSuperdettagli[[#This Row],[06.2025]] -> 506 | Q67: =tabSuperdettagli[[#This Row],[07.2025]] -> 507 | R67: =tabSuperdettagli[[#This Row],[08.2025]] -> 508 | S67: =tabSuperdettagli[[#This Row],[09.2025]] -> 509 | T67: =tabSuperdettagli[[#This Row],[10.2025]] -> 510 | U67: =tabSuperdettagli[[#This Row],[11.2025]] -> 0 | V67: =tabSuperdettagli[[#This Row],[12.2025]] -> 0 | W67: =tabSuperdettagli[[#This Row],[INT/EST]] -> Est. | X67: =tabSuperdettagli[[#This Row],[Resp 2°liv]]&"" | Y67: =INDEX( tab_resp1liv[EngUnit area cluster 1_], MATCH( SUBSTITUTE(tabSuperdettagli[[#This Row],[Resp 2°liv]], " ", ""), tab_resp1liv[SearchKey],0)) -> #N/A | Z67: =tabSuperdettagli[[#This Row],[WBS Element]]&"" | AA67: =tabSuperdettagli[[#This Row],[09.2025]] -> 509 | AC67: =IF( tabSuperdettagli[[#This Row],[ProjType_]]="M", IF( AND(tabSuperdettagli[[#This Row],[Resp 1°liv_]]="Guidotti C.", tabSuperdettagli[[#This Row],[WBE description_]]="Machine Mgmt"), "Documentation", tabSuperdettagli[[#This Row],[WBE description_]]), "" ) | AD67: =LEFT(tabSuperdettagli[[#This Row],[Network]], 18 ) | AE67: Send cost G | AP67: Est. | AQ67: Gruppo struttura 6 | AV67: Responsabile A | BJ67: 501 | BK67: 502 | BL67: 503 | BM67: 504 | BN67: 505 | BO67: 506 | BP67: 507 | BQ67: 508 | BR67: 509 | BS67: 510 | BV67: 5055 | BX67: 42198 | CB67: 42197 | CC67: 42237
A68: =IF(UPPER(LEFT(tabSuperdettagli[[#This Row],[WBE Status]],1))="S","sì","no") -> no | B68: 2021 | C68: =VLOOKUP(tabSuperdettagli[[#This Row],[WBS_]],Pivot_AnnoPrimaMarcatura!A:B,2,FALSE) -> #N/A | D68: =LEFT(tabSuperdettagli[[#This Row],[Network]], 10) | E68: =LEFT(tabSuperdettagli[[#This Row],[Network]], 1) | F68: =LOWER(TRIM( tabSuperdettagli[[#This Row],[Proj. Type ]] )) | G68: =IF( OR( tabSuperdettagli[[#This Row],[ProjType_]]="C", tabSuperdettagli[[#This Row],[ProjType_]]="A", tabSuperdettagli[[#This Row],[ProjType_]]="R", tabSuperdettagli[[#This Row],[ProjType_]]="E"), "C A R E", IF( tabSuperdettagli[[#This Row],[ProjType_]]="U", "U (" & tabSuperdettagli[[#This Row],[U ProjType_]] & ")", tabSuperdettagli[[#This Row],[ProjType_]]) ) | I68: =IF( TRIM(tabSuperdettagli[[#This Row],[Raggr. X Struttura]])> "", TRIM(tabSuperdettagli[[#This Row],[Raggr. X Struttura]]), TRIM(tabSuperdettagli[[#This Row],[Resp DT]] ) ) -> Gruppo struttura 1 | J68: =tabSuperdettagli[[#This Row],[Total]] -> 6055 | K68: =tabSuperdettagli[[#This Row],[01.2025]] -> 601 | L68: =tabSuperdettagli[[#This Row],[02.2025]] -> 602 | M68: =tabSuperdettagli[[#This Row],[03.2025]] -> 603 | N68: =tabSuperdettagli[[#This Row],[04.2025]] -> 604 | O68: =tabSuperdettagli[[#This Row],[05.2025]] -> 605 | P68: =tabSuperdettagli[[#This Row],[06.2025]] -> 606 | Q68: =tabSuperdettagli[[#This Row],[07.2025]] -> 607 | R68: =tabSuperdettagli[[#This Row],[08.2025]] -> 608 | S68: =tabSuperdettagli[[#This Row],[09.2025]] -> 609 | T68: =tabSuperdettagli[[#This Row],[10.2025]] -> 610 | U68: =tabSuperdettagli[[#This Row],[11.2025]] -> 0 | V68: =tabSuperdettagli[[#This Row],[12.2025]] -> 0 | W68: =tabSuperdettagli[[#This Row],[INT/EST]] -> Est. | X68: =tabSuperdettagli[[#This Row],[Resp 2°liv]]&"" | Y68: =INDEX( tab_resp1liv[EngUnit area cluster 1_], MATCH( SUBSTITUTE(tabSuperdettagli[[#This Row],[Resp 2°liv]], " ", ""), tab_resp1liv[SearchKey],0)) -> #N/A | Z68: =tabSuperdettagli[[#This Row],[WBS Element]]&"" | AA68: =tabSuperdettagli[[#This Row],[09.2025]] -> 609 | AC68: =IF( tabSuperdettagli[[#This Row],[ProjType_]]="M", IF( AND(tabSuperdettagli[[#This Row],[Resp 1°liv_]]="Guidotti C.", tabSuperdettagli[[#This Row],[WBE description_]]="Machine Mgmt"), "Documentation", tabSuperdettagli[[#This Row],[WBE description_]]), "" ) | AD68: =LEFT(tabSuperdettagli[[#This Row],[Network]], 18 ) | AE68: Send cost G | AP68: Est. | AQ68: Gruppo struttura 1 | AV68: Responsabile A | BJ68: 601 | BK68: 602 | BL68: 603 | BM68: 604 | BN68: 605 | BO68: 606 | BP68: 607 | BQ68: 608 | BR68: 609 | BS68: 610 | BV68: 6055 | BX68: 42201 | CB68: 42200 | CC68: 42240
A69: =IF(UPPER(LEFT(tabSuperdettagli[[#This Row],[WBE Status]],1))="S","sì","no") -> no | B69: 2021 | C69: =VLOOKUP(tabSuperdettagli[[#This Row],[WBS_]],Pivot_AnnoPrimaMarcatura!A:B,2,FALSE) -> #N/A | D69: =LEFT(tabSuperdettagli[[#This Row],[Network]], 10) | E69: =LEFT(tabSuperdettagli[[#This Row],[Network]], 1) | F69: =LOWER(TRIM( tabSuperdettagli[[#This Row],[Proj. Type ]] )) | G69: =IF( OR( tabSuperdettagli[[#This Row],[ProjType_]]="C", tabSuperdettagli[[#This Row],[ProjType_]]="A", tabSuperdettagli[[#This Row],[ProjType_]]="R", tabSuperdettagli[[#This Row],[ProjType_]]="E"), "C A R E", IF( tabSuperdettagli[[#This Row],[ProjType_]]="U", "U (" & tabSuperdettagli[[#This Row],[U ProjType_]] & ")", tabSuperdettagli[[#This Row],[ProjType_]]) ) | I69: =IF( TRIM(tabSuperdettagli[[#This Row],[Raggr. X Struttura]])> "", TRIM(tabSuperdettagli[[#This Row],[Raggr. X Struttura]]), TRIM(tabSuperdettagli[[#This Row],[Resp DT]] ) ) -> Gruppo struttura 3 | J69: =tabSuperdettagli[[#This Row],[Total]] -> 55 | K69: =tabSuperdettagli[[#This Row],[01.2025]] -> 1 | L69: =tabSuperdettagli[[#This Row],[02.2025]] -> 2 | M69: =tabSuperdettagli[[#This Row],[03.2025]] -> 3 | N69: =tabSuperdettagli[[#This Row],[04.2025]] -> 4 | O69: =tabSuperdettagli[[#This Row],[05.2025]] -> 5 | P69: =tabSuperdettagli[[#This Row],[06.2025]] -> 6 | Q69: =tabSuperdettagli[[#This Row],[07.2025]] -> 7 | R69: =tabSuperdettagli[[#This Row],[08.2025]] -> 8 | S69: =tabSuperdettagli[[#This Row],[09.2025]] -> 9 | T69: =tabSuperdettagli[[#This Row],[10.2025]] -> 10 | U69: =tabSuperdettagli[[#This Row],[11.2025]] -> 0 | V69: =tabSuperdettagli[[#This Row],[12.2025]] -> 0 | W69: =tabSuperdettagli[[#This Row],[INT/EST]] -> Est. | X69: =tabSuperdettagli[[#This Row],[Resp 2°liv]]&"" | Y69: =INDEX( tab_resp1liv[EngUnit area cluster 1_], MATCH( SUBSTITUTE(tabSuperdettagli[[#This Row],[Resp 2°liv]], " ", ""), tab_resp1liv[SearchKey],0)) -> #N/A | Z69: =tabSuperdettagli[[#This Row],[WBS Element]]&"" | AA69: =tabSuperdettagli[[#This Row],[09.2025]] -> 9 | AC69: =IF( tabSuperdettagli[[#This Row],[ProjType_]]="M", IF( AND(tabSuperdettagli[[#This Row],[Resp 1°liv_]]="Guidotti C.", tabSuperdettagli[[#This Row],[WBE description_]]="Machine Mgmt"), "Documentation", tabSuperdettagli[[#This Row],[WBE description_]]), "" ) | AD69: =LEFT(tabSuperdettagli[[#This Row],[Network]], 18 ) | AE69: Send cost G | AP69: Est. | AQ69: Gruppo struttura 3 | AV69: Responsabile E | BJ69: 1 | BK69: 2 | BL69: 3 | BM69: 4 | BN69: 5 | BO69: 6 | BP69: 7 | BQ69: 8 | BR69: 9 | BS69: 10 | BV69: 55 | BX69: 42204 | CB69: 42203 | CC69: 42243
A70: =IF(UPPER(LEFT(tabSuperdettagli[[#This Row],[WBE Status]],1))="S","sì","no") -> no | B70: 2021 | C70: =VLOOKUP(tabSuperdettagli[[#This Row],[WBS_]],Pivot_AnnoPrimaMarcatura!A:B,2,FALSE) -> #N/A | D70: =LEFT(tabSuperdettagli[[#This Row],[Network]], 10) | E70: =LEFT(tabSuperdettagli[[#This Row],[Network]], 1) | F70: =LOWER(TRIM( tabSuperdettagli[[#This Row],[Proj. Type ]] )) | G70: =IF( OR( tabSuperdettagli[[#This Row],[ProjType_]]="C", tabSuperdettagli[[#This Row],[ProjType_]]="A", tabSuperdettagli[[#This Row],[ProjType_]]="R", tabSuperdettagli[[#This Row],[ProjType_]]="E"), "C A R E", IF( tabSuperdettagli[[#This Row],[ProjType_]]="U", "U (" & tabSuperdettagli[[#This Row],[U ProjType_]] & ")", tabSuperdettagli[[#This Row],[ProjType_]]) ) | I70: =IF( TRIM(tabSuperdettagli[[#This Row],[Raggr. X Struttura]])> "", TRIM(tabSuperdettagli[[#This Row],[Raggr. X Struttura]]), TRIM(tabSuperdettagli[[#This Row],[Resp DT]] ) ) -> Gruppo struttura 3 | J70: =tabSuperdettagli[[#This Row],[Total]] -> 1055 | K70: =tabSuperdettagli[[#This Row],[01.2025]] -> 101 | L70: =tabSuperdettagli[[#This Row],[02.2025]] -> 102 | M70: =tabSuperdettagli[[#This Row],[03.2025]] -> 103 | N70: =tabSuperdettagli[[#This Row],[04.2025]] -> 104 | O70: =tabSuperdettagli[[#This Row],[05.2025]] -> 105 | P70: =tabSuperdettagli[[#This Row],[06.2025]] -> 106 | Q70: =tabSuperdettagli[[#This Row],[07.2025]] -> 107 | R70: =tabSuperdettagli[[#This Row],[08.2025]] -> 108 | S70: =tabSuperdettagli[[#This Row],[09.2025]] -> 109 | T70: =tabSuperdettagli[[#This Row],[10.2025]] -> 110 | U70: =tabSuperdettagli[[#This Row],[11.2025]] -> 0 | V70: =tabSuperdettagli[[#This Row],[12.2025]] -> 0 | W70: =tabSuperdettagli[[#This Row],[INT/EST]] -> Est. | X70: =tabSuperdettagli[[#This Row],[Resp 2°liv]]&"" | Y70: =INDEX( tab_resp1liv[EngUnit area cluster 1_], MATCH( SUBSTITUTE(tabSuperdettagli[[#This Row],[Resp 2°liv]], " ", ""), tab_resp1liv[SearchKey],0)) -> #N/A | Z70: =tabSuperdettagli[[#This Row],[WBS Element]]&"" | AA70: =tabSuperdettagli[[#This Row],[09.2025]] -> 109 | AC70: =IF( tabSuperdettagli[[#This Row],[ProjType_]]="M", IF( AND(tabSuperdettagli[[#This Row],[Resp 1°liv_]]="Guidotti C.", tabSuperdettagli[[#This Row],[WBE description_]]="Machine Mgmt"), "Documentation", tabSuperdettagli[[#This Row],[WBE description_]]), "" ) | AD70: =LEFT(tabSuperdettagli[[#This Row],[Network]], 18 ) | AE70: Send cost G | AP70: Est. | AQ70: Gruppo struttura 3 | AV70: Responsabile D | BJ70: 101 | BK70: 102 | BL70: 103 | BM70: 104 | BN70: 105 | BO70: 106 | BP70: 107 | BQ70: 108 | BR70: 109 | BS70: 110 | BV70: 1055 | BX70: 42207 | CB70: 42206 | CC70: 42246
A71: =IF(UPPER(LEFT(tabSuperdettagli[[#This Row],[WBE Status]],1))="S","sì","no") -> no | B71: 2021 | C71: =VLOOKUP(tabSuperdettagli[[#This Row],[WBS_]],Pivot_AnnoPrimaMarcatura!A:B,2,FALSE) -> #N/A | D71: =LEFT(tabSuperdettagli[[#This Row],[Network]], 10) | E71: =LEFT(tabSuperdettagli[[#This Row],[Network]], 1) | F71: =LOWER(TRIM( tabSuperdettagli[[#This Row],[Proj. Type ]] )) | G71: =IF( OR( tabSuperdettagli[[#This Row],[ProjType_]]="C", tabSuperdettagli[[#This Row],[ProjType_]]="A", tabSuperdettagli[[#This Row],[ProjType_]]="R", tabSuperdettagli[[#This Row],[ProjType_]]="E"), "C A R E", IF( tabSuperdettagli[[#This Row],[ProjType_]]="U", "U (" & tabSuperdettagli[[#This Row],[U ProjType_]] & ")", tabSuperdettagli[[#This Row],[ProjType_]]) ) | I71: =IF( TRIM(tabSuperdettagli[[#This Row],[Raggr. X Struttura]])> "", TRIM(tabSuperdettagli[[#This Row],[Raggr. X Struttura]]), TRIM(tabSuperdettagli[[#This Row],[Resp DT]] ) ) -> Gruppo struttura 1 | J71: =tabSuperdettagli[[#This Row],[Total]] -> 2055 | K71: =tabSuperdettagli[[#This Row],[01.2025]] -> 201 | L71: =tabSuperdettagli[[#This Row],[02.2025]] -> 202 | M71: =tabSuperdettagli[[#This Row],[03.2025]] -> 203 | N71: =tabSuperdettagli[[#This Row],[04.2025]] -> 204 | O71: =tabSuperdettagli[[#This Row],[05.2025]] -> 205 | P71: =tabSuperdettagli[[#This Row],[06.2025]] -> 206 | Q71: =tabSuperdettagli[[#This Row],[07.2025]] -> 207 | R71: =tabSuperdettagli[[#This Row],[08.2025]] -> 208 | S71: =tabSuperdettagli[[#This Row],[09.2025]] -> 209 | T71: =tabSuperdettagli[[#This Row],[10.2025]] -> 210 | U71: =tabSuperdettagli[[#This Row],[11.2025]] -> 0 | V71: =tabSuperdettagli[[#This Row],[12.2025]] -> 0 | W71: =tabSuperdettagli[[#This Row],[INT/EST]] -> Est. | X71: =tabSuperdettagli[[#This Row],[Resp 2°liv]]&"" | Y71: =INDEX( tab_resp1liv[EngUnit area cluster 1_], MATCH( SUBSTITUTE(tabSuperdettagli[[#This Row],[Resp 2°liv]], " ", ""), tab_resp1liv[SearchKey],0)) -> #N/A | Z71: =tabSuperdettagli[[#This Row],[WBS Element]]&"" | AA71: =tabSuperdettagli[[#This Row],[09.2025]] -> 209 | AC71: =IF( tabSuperdettagli[[#This Row],[ProjType_]]="M", IF( AND(tabSuperdettagli[[#This Row],[Resp 1°liv_]]="Guidotti C.", tabSuperdettagli[[#This Row],[WBE description_]]="Machine Mgmt"), "Documentation", tabSuperdettagli[[#This Row],[WBE description_]]), "" ) | AD71: =LEFT(tabSuperdettagli[[#This Row],[Network]], 18 ) | AE71: Send cost G | AP71: Est. | AQ71: Gruppo struttura 1 | AV71: Responsabile A | BJ71: 201 | BK71: 202 | BL71: 203 | BM71: 204 | BN71: 205 | BO71: 206 | BP71: 207 | BQ71: 208 | BR71: 209 | BS71: 210 | BV71: 2055 | BX71: 42210 | CB71: 42209 | CC71: 42249
A72: =IF(UPPER(LEFT(tabSuperdettagli[[#This Row],[WBE Status]],1))="S","sì","no") -> no | B72: 2021 | C72: =VLOOKUP(tabSuperdettagli[[#This Row],[WBS_]],Pivot_AnnoPrimaMarcatura!A:B,2,FALSE) -> #N/A | D72: =LEFT(tabSuperdettagli[[#This Row],[Network]], 10) | E72: =LEFT(tabSuperdettagli[[#This Row],[Network]], 1) | F72: =LOWER(TRIM( tabSuperdettagli[[#This Row],[Proj. Type ]] )) | G72: =IF( OR( tabSuperdettagli[[#This Row],[ProjType_]]="C", tabSuperdettagli[[#This Row],[ProjType_]]="A", tabSuperdettagli[[#This Row],[ProjType_]]="R", tabSuperdettagli[[#This Row],[ProjType_]]="E"), "C A R E", IF( tabSuperdettagli[[#This Row],[ProjType_]]="U", "U (" & tabSuperdettagli[[#This Row],[U ProjType_]] & ")", tabSuperdettagli[[#This Row],[ProjType_]]) ) | I72: =IF( TRIM(tabSuperdettagli[[#This Row],[Raggr. X Struttura]])> "", TRIM(tabSuperdettagli[[#This Row],[Raggr. X Struttura]]), TRIM(tabSuperdettagli[[#This Row],[Resp DT]] ) ) -> Gruppo struttura 5 | J72: =tabSuperdettagli[[#This Row],[Total]] -> 3055 | K72: =tabSuperdettagli[[#This Row],[01.2025]] -> 301 | L72: =tabSuperdettagli[[#This Row],[02.2025]] -> 302 | M72: =tabSuperdettagli[[#This Row],[03.2025]] -> 303 | N72: =tabSuperdettagli[[#This Row],[04.2025]] -> 304 | O72: =tabSuperdettagli[[#This Row],[05.2025]] -> 305 | P72: =tabSuperdettagli[[#This Row],[06.2025]] -> 306 | Q72: =tabSuperdettagli[[#This Row],[07.2025]] -> 307 | R72: =tabSuperdettagli[[#This Row],[08.2025]] -> 308 | S72: =tabSuperdettagli[[#This Row],[09.2025]] -> 309 | T72: =tabSuperdettagli[[#This Row],[10.2025]] -> 310 | U72: =tabSuperdettagli[[#This Row],[11.2025]] -> 0 | V72: =tabSuperdettagli[[#This Row],[12.2025]] -> 0 | W72: =tabSuperdettagli[[#This Row],[INT/EST]] -> Est. | X72: =tabSuperdettagli[[#This Row],[Resp 2°liv]]&"" | Y72: =INDEX( tab_resp1liv[EngUnit area cluster 1_], MATCH( SUBSTITUTE(tabSuperdettagli[[#This Row],[Resp 2°liv]], " ", ""), tab_resp1liv[SearchKey],0)) -> #N/A | Z72: =tabSuperdettagli[[#This Row],[WBS Element]]&"" | AA72: =tabSuperdettagli[[#This Row],[09.2025]] -> 309 | AC72: =IF( tabSuperdettagli[[#This Row],[ProjType_]]="M", IF( AND(tabSuperdettagli[[#This Row],[Resp 1°liv_]]="Guidotti C.", tabSuperdettagli[[#This Row],[WBE description_]]="Machine Mgmt"), "Documentation", tabSuperdettagli[[#This Row],[WBE description_]]), "" ) | AD72: =LEFT(tabSuperdettagli[[#This Row],[Network]], 18 ) | AE72: Send cost G | AP72: Est. | AQ72: Gruppo struttura 5 | AV72: Responsabile A | BJ72: 301 | BK72: 302 | BL72: 303 | BM72: 304 | BN72: 305 | BO72: 306 | BP72: 307 | BQ72: 308 | BR72: 309 | BS72: 310 | BV72: 3055 | BX72: 42213 | CB72: 42212 | CC72: 42252
A73: =IF(UPPER(LEFT(tabSuperdettagli[[#This Row],[WBE Status]],1))="S","sì","no") -> no | B73: 2022 | C73: =VLOOKUP(tabSuperdettagli[[#This Row],[WBS_]],Pivot_AnnoPrimaMarcatura!A:B,2,FALSE) -> #N/A | D73: =LEFT(tabSuperdettagli[[#This Row],[Network]], 10) | E73: =LEFT(tabSuperdettagli[[#This Row],[Network]], 1) | F73: =LOWER(TRIM( tabSuperdettagli[[#This Row],[Proj. Type ]] )) | G73: =IF( OR( tabSuperdettagli[[#This Row],[ProjType_]]="C", tabSuperdettagli[[#This Row],[ProjType_]]="A", tabSuperdettagli[[#This Row],[ProjType_]]="R", tabSuperdettagli[[#This Row],[ProjType_]]="E"), "C A R E", IF( tabSuperdettagli[[#This Row],[ProjType_]]="U", "U (" & tabSuperdettagli[[#This Row],[U ProjType_]] & ")", tabSuperdettagli[[#This Row],[ProjType_]]) ) | I73: =IF( TRIM(tabSuperdettagli[[#This Row],[Raggr. X Struttura]])> "", TRIM(tabSuperdettagli[[#This Row],[Raggr. X Struttura]]), TRIM(tabSuperdettagli[[#This Row],[Resp DT]] ) ) -> Gruppo struttura 1 | J73: =tabSuperdettagli[[#This Row],[Total]] -> 4055 | K73: =tabSuperdettagli[[#This Row],[01.2025]] -> 401 | L73: =tabSuperdettagli[[#This Row],[02.2025]] -> 402 | M73: =tabSuperdettagli[[#This Row],[03.2025]] -> 403 | N73: =tabSuperdettagli[[#This Row],[04.2025]] -> 404 | O73: =tabSuperdettagli[[#This Row],[05.2025]] -> 405 | P73: =tabSuperdettagli[[#This Row],[06.2025]] -> 406 | Q73: =tabSuperdettagli[[#This Row],[07.2025]] -> 407 | R73: =tabSuperdettagli[[#This Row],[08.2025]] -> 408 | S73: =tabSuperdettagli[[#This Row],[09.2025]] -> 409 | T73: =tabSuperdettagli[[#This Row],[10.2025]] -> 410 | U73: =tabSuperdettagli[[#This Row],[11.2025]] -> 0 | V73: =tabSuperdettagli[[#This Row],[12.2025]] -> 0 | W73: =tabSuperdettagli[[#This Row],[INT/EST]] -> Int. | X73: =tabSuperdettagli[[#This Row],[Resp 2°liv]]&"" | Y73: =INDEX( tab_resp1liv[EngUnit area cluster 1_], MATCH( SUBSTITUTE(tabSuperdettagli[[#This Row],[Resp 2°liv]], " ", ""), tab_resp1liv[SearchKey],0)) -> #N/A | Z73: =tabSuperdettagli[[#This Row],[WBS Element]]&"" | AA73: =tabSuperdettagli[[#This Row],[09.2025]] -> 409 | AC73: =IF( tabSuperdettagli[[#This Row],[ProjType_]]="M", IF( AND(tabSuperdettagli[[#This Row],[Resp 1°liv_]]="Guidotti C.", tabSuperdettagli[[#This Row],[WBE description_]]="Machine Mgmt"), "Documentation", tabSuperdettagli[[#This Row],[WBE description_]]), "" ) | AD73: =LEFT(tabSuperdettagli[[#This Row],[Network]], 18 ) | AE73: Send cost H | AP73: Int. | AQ73: Gruppo struttura 1 | AV73: Responsabile B | BJ73: 401 | BK73: 402 | BL73: 403 | BM73: 404 | BN73: 405 | BO73: 406 | BP73: 407 | BQ73: 408 | BR73: 409 | BS73: 410 | BV73: 4055 | BX73: 42216 | CB73: 42215 | CC73: 42255
... A83: =IF(UPPER(LEFT(tabSuperdettagli[[#This Row],[WBE Status]],1))="S","sì","no") -> no | B83: 2023 | C83: =VLOOKUP(tabSuperdettagli[[#This Row],[WBS_]],Pivot_AnnoPrimaMarcatura!A:B,2,FALSE) -> #N/A | D83: =LEFT(tabSuperdettagli[[#This Row],[Network]], 10) | E83: =LEFT(tabSuperdettagli[[#This Row],[Network]], 1) | F83: =LOWER(TRIM( tabSuperdettagli[[#This Row],[Proj. Type ]] )) | G83: =IF( OR( tabSuperdettagli[[#This Row],[ProjType_]]="C", tabSuperdettagli[[#This Row],[ProjType_]]="A", tabSuperdettagli[[#This Row],[ProjType_]]="R", tabSuperdettagli[[#This Row],[ProjType_]]="E"), "C A R E", IF( tabSuperdettagli[[#This Row],[ProjType_]]="U", "U (" & tabSuperdettagli[[#This Row],[U ProjType_]] & ")", tabSuperdettagli[[#This Row],[ProjType_]]) ) | I83: =IF( TRIM(tabSuperdettagli[[#This Row],[Raggr. X Struttura]])> "", TRIM(tabSuperdettagli[[#This Row],[Raggr. X Struttura]]), TRIM(tabSuperdettagli[[#This Row],[Resp DT]] ) ) -> Gruppo struttura 1 | J83: =tabSuperdettagli[[#This Row],[Total]] -> 55 | K83: =tabSuperdettagli[[#This Row],[01.2025]] -> 1 | L83: =tabSuperdettagli[[#This Row],[02.2025]] -> 2 | M83: =tabSuperdettagli[[#This Row],[03.2025]] -> 3 | N83: =tabSuperdettagli[[#This Row],[04.2025]] -> 4 | O83: =tabSuperdettagli[[#This Row],[05.2025]] -> 5 | P83: =tabSuperdettagli[[#This Row],[06.2025]] -> 6 | Q83: =tabSuperdettagli[[#This Row],[07.2025]] -> 7 | R83: =tabSuperdettagli[[#This Row],[08.2025]] -> 8 | S83: =tabSuperdettagli[[#This Row],[09.2025]] -> 9 | T83: =tabSuperdettagli[[#This Row],[10.2025]] -> 10 | U83: =tabSuperdettagli[[#This Row],[11.2025]] -> 0 | V83: =tabSuperdettagli[[#This Row],[12.2025]] -> 0 | W83: =tabSuperdettagli[[#This Row],[INT/EST]] -> Est. | X83: =tabSuperdettagli[[#This Row],[Resp 2°liv]]&"" | Y83: =INDEX( tab_resp1liv[EngUnit area cluster 1_], MATCH( SUBSTITUTE(tabSuperdettagli[[#This Row],[Resp 2°liv]], " ", ""), tab_resp1liv[SearchKey],0)) -> #N/A | Z83: =tabSuperdettagli[[#This Row],[WBS Element]]&"" | AA83: =tabSuperdettagli[[#This Row],[09.2025]] -> 9 | AC83: =IF( tabSuperdettagli[[#This Row],[ProjType_]]="M", IF( AND(tabSuperdettagli[[#This Row],[Resp 1°liv_]]="Guidotti C.", tabSuperdettagli[[#This Row],[WBE description_]]="Machine Mgmt"), "Documentation", tabSuperdettagli[[#This Row],[WBE description_]]), "" ) | AD83: =LEFT(tabSuperdettagli[[#This Row],[Network]], 18 ) | AE83: Send cost I | AP83: Est. | AQ83: Gruppo struttura 1 | AV83: Responsabile A | BJ83: 1 | BK83: 2 | BL83: 3 | BM83: 4 | BN83: 5 | BO83: 6 | BP83: 7 | BQ83: 8 | BR83: 9 | BS83: 10 | BV83: 55 | BX83: 42246 | CB83: 42245 | CC83: 42285
A84: =IF(UPPER(LEFT(tabSuperdettagli[[#This Row],[WBE Status]],1))="S","sì","no") -> no | B84: 2023 | C84: =VLOOKUP(tabSuperdettagli[[#This Row],[WBS_]],Pivot_AnnoPrimaMarcatura!A:B,2,FALSE) -> #N/A | D84: =LEFT(tabSuperdettagli[[#This Row],[Network]], 10) | E84: =LEFT(tabSuperdettagli[[#This Row],[Network]], 1) | F84: =LOWER(TRIM( tabSuperdettagli[[#This Row],[Proj. Type ]] )) | G84: =IF( OR( tabSuperdettagli[[#This Row],[ProjType_]]="C", tabSuperdettagli[[#This Row],[ProjType_]]="A", tabSuperdettagli[[#This Row],[ProjType_]]="R", tabSuperdettagli[[#This Row],[ProjType_]]="E"), "C A R E", IF( tabSuperdettagli[[#This Row],[ProjType_]]="U", "U (" & tabSuperdettagli[[#This Row],[U ProjType_]] & ")", tabSuperdettagli[[#This Row],[ProjType_]]) ) | I84: =IF( TRIM(tabSuperdettagli[[#This Row],[Raggr. X Struttura]])> "", TRIM(tabSuperdettagli[[#This Row],[Raggr. X Struttura]]), TRIM(tabSuperdettagli[[#This Row],[Resp DT]] ) ) -> Responsabile C | J84: =tabSuperdettagli[[#This Row],[Total]] -> 1055 | K84: =tabSuperdettagli[[#This Row],[01.2025]] -> 101 | L84: =tabSuperdettagli[[#This Row],[02.2025]] -> 102 | M84: =tabSuperdettagli[[#This Row],[03.2025]] -> 103 | N84: =tabSuperdettagli[[#This Row],[04.2025]] -> 104 | O84: =tabSuperdettagli[[#This Row],[05.2025]] -> 105 | P84: =tabSuperdettagli[[#This Row],[06.2025]] -> 106 | Q84: =tabSuperdettagli[[#This Row],[07.2025]] -> 107 | R84: =tabSuperdettagli[[#This Row],[08.2025]] -> 108 | S84: =tabSuperdettagli[[#This Row],[09.2025]] -> 109 | T84: =tabSuperdettagli[[#This Row],[10.2025]] -> 110 | U84: =tabSuperdettagli[[#This Row],[11.2025]] -> 0 | V84: =tabSuperdettagli[[#This Row],[12.2025]] -> 0 | W84: =tabSuperdettagli[[#This Row],[INT/EST]] -> Est. | X84: =tabSuperdettagli[[#This Row],[Resp 2°liv]]&"" | Y84: =INDEX( tab_resp1liv[EngUnit area cluster 1_], MATCH( SUBSTITUTE(tabSuperdettagli[[#This Row],[Resp 2°liv]], " ", ""), tab_resp1liv[SearchKey],0)) -> #N/A | Z84: =tabSuperdettagli[[#This Row],[WBS Element]]&"" | AA84: =tabSuperdettagli[[#This Row],[09.2025]] -> 109 | AC84: =IF( tabSuperdettagli[[#This Row],[ProjType_]]="M", IF( AND(tabSuperdettagli[[#This Row],[Resp 1°liv_]]="Guidotti C.", tabSuperdettagli[[#This Row],[WBE description_]]="Machine Mgmt"), "Documentation", tabSuperdettagli[[#This Row],[WBE description_]]), "" ) | AD84: =LEFT(tabSuperdettagli[[#This Row],[Network]], 18 ) | AE84: Send cost I | AP84: Est. | AV84: Responsabile C | BJ84: 101 | BK84: 102 | BL84: 103 | BM84: 104 | BN84: 105 | BO84: 106 | BP84: 107 | BQ84: 108 | BR84: 109 | BS84: 110 | BV84: 1055 | BX84: 42249 | CB84: 42248 | CC84: 42288
A85: =IF(UPPER(LEFT(tabSuperdettagli[[#This Row],[WBE Status]],1))="S","sì","no") -> no | B85: 2023 | C85: =VLOOKUP(tabSuperdettagli[[#This Row],[WBS_]],Pivot_AnnoPrimaMarcatura!A:B,2,FALSE) -> #N/A | D85: =LEFT(tabSuperdettagli[[#This Row],[Network]], 10) | E85: =LEFT(tabSuperdettagli[[#This Row],[Network]], 1) | F85: =LOWER(TRIM( tabSuperdettagli[[#This Row],[Proj. Type ]] )) | G85: =IF( OR( tabSuperdettagli[[#This Row],[ProjType_]]="C", tabSuperdettagli[[#This Row],[ProjType_]]="A", tabSuperdettagli[[#This Row],[ProjType_]]="R", tabSuperdettagli[[#This Row],[ProjType_]]="E"), "C A R E", IF( tabSuperdettagli[[#This Row],[ProjType_]]="U", "U (" & tabSuperdettagli[[#This Row],[U ProjType_]] & ")", tabSuperdettagli[[#This Row],[ProjType_]]) ) | I85: =IF( TRIM(tabSuperdettagli[[#This Row],[Raggr. X Struttura]])> "", TRIM(tabSuperdettagli[[#This Row],[Raggr. X Struttura]]), TRIM(tabSuperdettagli[[#This Row],[Resp DT]] ) ) -> Gruppo struttura 2 | J85: =tabSuperdettagli[[#This Row],[Total]] -> 2055 | K85: =tabSuperdettagli[[#This Row],[01.2025]] -> 201 | L85: =tabSuperdettagli[[#This Row],[02.2025]] -> 202 | M85: =tabSuperdettagli[[#This Row],[03.2025]] -> 203 | N85: =tabSuperdettagli[[#This Row],[04.2025]] -> 204 | O85: =tabSuperdettagli[[#This Row],[05.2025]] -> 205 | P85: =tabSuperdettagli[[#This Row],[06.2025]] -> 206 | Q85: =tabSuperdettagli[[#This Row],[07.2025]] -> 207 | R85: =tabSuperdettagli[[#This Row],[08.2025]] -> 208 | S85: =tabSuperdettagli[[#This Row],[09.2025]] -> 209 | T85: =tabSuperdettagli[[#This Row],[10.2025]] -> 210 | U85: =tabSuperdettagli[[#This Row],[11.2025]] -> 0 | V85: =tabSuperdettagli[[#This Row],[12.2025]] -> 0 | W85: =tabSuperdettagli[[#This Row],[INT/EST]] -> Int. | X85: =tabSuperdettagli[[#This Row],[Resp 2°liv]]&"" | Y85: =INDEX( tab_resp1liv[EngUnit area cluster 1_], MATCH( SUBSTITUTE(tabSuperdettagli[[#This Row],[Resp 2°liv]], " ", ""), tab_resp1liv[SearchKey],0)) -> #N/A | Z85: =tabSuperdettagli[[#This Row],[WBS Element]]&"" | AA85: =tabSuperdettagli[[#This Row],[09.2025]] -> 209 | AC85: =IF( tabSuperdettagli[[#This Row],[ProjType_]]="M", IF( AND(tabSuperdettagli[[#This Row],[Resp 1°liv_]]="Guidotti C.", tabSuperdettagli[[#This Row],[WBE description_]]="Machine Mgmt"), "Documentation", tabSuperdettagli[[#This Row],[WBE description_]]), "" ) | AD85: =LEFT(tabSuperdettagli[[#This Row],[Network]], 18 ) | AE85: Send cost I | AP85: Int. | AQ85: Gruppo struttura 2 | AV85: Responsabile A | BJ85: 201 | BK85: 202 | BL85: 203 | BM85: 204 | BN85: 205 | BO85: 206 | BP85: 207 | BQ85: 208 | BR85: 209 | BS85: 210 | BV85: 2055 | BX85: 42252 | CB85: 42251 | CC85: 42291
A86: =IF(UPPER(LEFT(tabSuperdettagli[[#This Row],[WBE Status]],1))="S","sì","no") -> no | B86: 2023 | C86: =VLOOKUP(tabSuperdettagli[[#This Row],[WBS_]],Pivot_AnnoPrimaMarcatura!A:B,2,FALSE) -> #N/A | D86: =LEFT(tabSuperdettagli[[#This Row],[Network]], 10) | E86: =LEFT(tabSuperdettagli[[#This Row],[Network]], 1) | F86: =LOWER(TRIM( tabSuperdettagli[[#This Row],[Proj. Type ]] )) | G86: =IF( OR( tabSuperdettagli[[#This Row],[ProjType_]]="C", tabSuperdettagli[[#This Row],[ProjType_]]="A", tabSuperdettagli[[#This Row],[ProjType_]]="R", tabSuperdettagli[[#This Row],[ProjType_]]="E"), "C A R E", IF( tabSuperdettagli[[#This Row],[ProjType_]]="U", "U (" & tabSuperdettagli[[#This Row],[U ProjType_]] & ")", tabSuperdettagli[[#This Row],[ProjType_]]) ) | I86: =IF( TRIM(tabSuperdettagli[[#This Row],[Raggr. X Struttura]])> "", TRIM(tabSuperdettagli[[#This Row],[Raggr. X Struttura]]), TRIM(tabSuperdettagli[[#This Row],[Resp DT]] ) ) -> Gruppo struttura 3 | J86: =tabSuperdettagli[[#This Row],[Total]] -> 3055 | K86: =tabSuperdettagli[[#This Row],[01.2025]] -> 301 | L86: =tabSuperdettagli[[#This Row],[02.2025]] -> 302 | M86: =tabSuperdettagli[[#This Row],[03.2025]] -> 303 | N86: =tabSuperdettagli[[#This Row],[04.2025]] -> 304 | O86: =tabSuperdettagli[[#This Row],[05.2025]] -> 305 | P86: =tabSuperdettagli[[#This Row],[06.2025]] -> 306 | Q86: =tabSuperdettagli[[#This Row],[07.2025]] -> 307 | R86: =tabSuperdettagli[[#This Row],[08.2025]] -> 308 | S86: =tabSuperdettagli[[#This Row],[09.2025]] -> 309 | T86: =tabSuperdettagli[[#This Row],[10.2025]] -> 310 | U86: =tabSuperdettagli[[#This Row],[11.2025]] -> 0 | V86: =tabSuperdettagli[[#This Row],[12.2025]] -> 0 | W86: =tabSuperdettagli[[#This Row],[INT/EST]] -> Est. | X86: =tabSuperdettagli[[#This Row],[Resp 2°liv]]&"" | Y86: =INDEX( tab_resp1liv[EngUnit area cluster 1_], MATCH( SUBSTITUTE(tabSuperdettagli[[#This Row],[Resp 2°liv]], " ", ""), tab_resp1liv[SearchKey],0)) -> #N/A | Z86: =tabSuperdettagli[[#This Row],[WBS Element]]&"" | AA86: =tabSuperdettagli[[#This Row],[09.2025]] -> 309 | AC86: =IF( tabSuperdettagli[[#This Row],[ProjType_]]="M", IF( AND(tabSuperdettagli[[#This Row],[Resp 1°liv_]]="Guidotti C.", tabSuperdettagli[[#This Row],[WBE description_]]="Machine Mgmt"), "Documentation", tabSuperdettagli[[#This Row],[WBE description_]]), "" ) | AD86: =LEFT(tabSuperdettagli[[#This Row],[Network]], 18 ) | AE86: Send cost I | AP86: Est. | AQ86: Gruppo struttura 3 | AV86: Responsabile A | BJ86: 301 | BK86: 302 | BL86: 303 | BM86: 304 | BN86: 305 | BO86: 306 | BP86: 307 | BQ86: 308 | BR86: 309 | BS86: 310 | BV86: 3055 | BX86: 42255 | CB86: 42254 | CC86: 42294
A87: =IF(UPPER(LEFT(tabSuperdettagli[[#This Row],[WBE Status]],1))="S","sì","no") -> no | B87: 2023 | C87: =VLOOKUP(tabSuperdettagli[[#This Row],[WBS_]],Pivot_AnnoPrimaMarcatura!A:B,2,FALSE) -> #N/A | D87: =LEFT(tabSuperdettagli[[#This Row],[Network]], 10) | E87: =LEFT(tabSuperdettagli[[#This Row],[Network]], 1) | F87: =LOWER(TRIM( tabSuperdettagli[[#This Row],[Proj. Type ]] )) | G87: =IF( OR( tabSuperdettagli[[#This Row],[ProjType_]]="C", tabSuperdettagli[[#This Row],[ProjType_]]="A", tabSuperdettagli[[#This Row],[ProjType_]]="R", tabSuperdettagli[[#This Row],[ProjType_]]="E"), "C A R E", IF( tabSuperdettagli[[#This Row],[ProjType_]]="U", "U (" & tabSuperdettagli[[#This Row],[U ProjType_]] & ")", tabSuperdettagli[[#This Row],[ProjType_]]) ) | I87: =IF( TRIM(tabSuperdettagli[[#This Row],[Raggr. X Struttura]])> "", TRIM(tabSuperdettagli[[#This Row],[Raggr. X Struttura]]), TRIM(tabSuperdettagli[[#This Row],[Resp DT]] ) ) -> Gruppo struttura 1 | J87: =tabSuperdettagli[[#This Row],[Total]] -> 4055 | K87: =tabSuperdettagli[[#This Row],[01.2025]] -> 401 | L87: =tabSuperdettagli[[#This Row],[02.2025]] -> 402 | M87: =tabSuperdettagli[[#This Row],[03.2025]] -> 403 | N87: =tabSuperdettagli[[#This Row],[04.2025]] -> 404 | O87: =tabSuperdettagli[[#This Row],[05.2025]] -> 405 | P87: =tabSuperdettagli[[#This Row],[06.2025]] -> 406 | Q87: =tabSuperdettagli[[#This Row],[07.2025]] -> 407 | R87: =tabSuperdettagli[[#This Row],[08.2025]] -> 408 | S87: =tabSuperdettagli[[#This Row],[09.2025]] -> 409 | T87: =tabSuperdettagli[[#This Row],[10.2025]] -> 410 | U87: =tabSuperdettagli[[#This Row],[11.2025]] -> 0 | V87: =tabSuperdettagli[[#This Row],[12.2025]] -> 0 | W87: =tabSuperdettagli[[#This Row],[INT/EST]] -> Est. | X87: =tabSuperdettagli[[#This Row],[Resp 2°liv]]&"" | Y87: =INDEX( tab_resp1liv[EngUnit area cluster 1_], MATCH( SUBSTITUTE(tabSuperdettagli[[#This Row],[Resp 2°liv]], " ", ""), tab_resp1liv[SearchKey],0)) -> #N/A | Z87: =tabSuperdettagli[[#This Row],[WBS Element]]&"" | AA87: =tabSuperdettagli[[#This Row],[09.2025]] -> 409 | AC87: =IF( tabSuperdettagli[[#This Row],[ProjType_]]="M", IF( AND(tabSuperdettagli[[#This Row],[Resp 1°liv_]]="Guidotti C.", tabSuperdettagli[[#This Row],[WBE description_]]="Machine Mgmt"), "Documentation", tabSuperdettagli[[#This Row],[WBE description_]]), "" ) | AD87: =LEFT(tabSuperdettagli[[#This Row],[Network]], 18 ) | AE87: Send cost I | AP87: Est. | AQ87: Gruppo struttura 1 | AV87: Responsabile A | BJ87: 401 | BK87: 402 | BL87: 403 | BM87: 404 | BN87: 405 | BO87: 406 | BP87: 407 | BQ87: 408 | BR87: 409 | BS87: 410 | BV87: 4055 | BX87: 42258 | CB87: 42257 | CC87: 42297
A88: =IF(UPPER(LEFT(tabSuperdettagli[[#This Row],[WBE Status]],1))="S","sì","no") -> no | B88: 2023 | C88: =VLOOKUP(tabSuperdettagli[[#This Row],[WBS_]],Pivot_AnnoPrimaMarcatura!A:B,2,FALSE) -> #N/A | D88: =LEFT(tabSuperdettagli[[#This Row],[Network]], 10) | E88: =LEFT(tabSuperdettagli[[#This Row],[Network]], 1) | F88: =LOWER(TRIM( tabSuperdettagli[[#This Row],[Proj. Type ]] )) | G88: =IF( OR( tabSuperdettagli[[#This Row],[ProjType_]]="C", tabSuperdettagli[[#This Row],[ProjType_]]="A", tabSuperdettagli[[#This Row],[ProjType_]]="R", tabSuperdettagli[[#This Row],[ProjType_]]="E"), "C A R E", IF( tabSuperdettagli[[#This Row],[ProjType_]]="U", "U (" & tabSuperdettagli[[#This Row],[U ProjType_]] & ")", tabSuperdettagli[[#This Row],[ProjType_]]) ) | I88: =IF( TRIM(tabSuperdettagli[[#This Row],[Raggr. X Struttura]])> "", TRIM(tabSuperdettagli[[#This Row],[Raggr. X Struttura]]), TRIM(tabSuperdettagli[[#This Row],[Resp DT]] ) ) -> Gruppo struttura 1 | J88: =tabSuperdettagli[[#This Row],[Total]] -> 5055 | K88: =tabSuperdettagli[[#This Row],[01.2025]] -> 501 | L88: =tabSuperdettagli[[#This Row],[02.2025]] -> 502 | M88: =tabSuperdettagli[[#This Row],[03.2025]] -> 503 | N88: =tabSuperdettagli[[#This Row],[04.2025]] -> 504 | O88: =tabSuperdettagli[[#This Row],[05.2025]] -> 505 | P88: =tabSuperdettagli[[#This Row],[06.2025]] -> 506 | Q88: =tabSuperdettagli[[#This Row],[07.2025]] -> 507 | R88: =tabSuperdettagli[[#This Row],[08.2025]] -> 508 | S88: =tabSuperdettagli[[#This Row],[09.2025]] -> 509 | T88: =tabSuperdettagli[[#This Row],[10.2025]] -> 510 | U88: =tabSuperdettagli[[#This Row],[11.2025]] -> 0 | V88: =tabSuperdettagli[[#This Row],[12.2025]] -> 0 | W88: =tabSuperdettagli[[#This Row],[INT/EST]] -> Int. | X88: =tabSuperdettagli[[#This Row],[Resp 2°liv]]&"" | Y88: =INDEX( tab_resp1liv[EngUnit area cluster 1_], MATCH( SUBSTITUTE(tabSuperdettagli[[#This Row],[Resp 2°liv]], " ", ""), tab_resp1liv[SearchKey],0)) -> #N/A | Z88: =tabSuperdettagli[[#This Row],[WBS Element]]&"" | AA88: =tabSuperdettagli[[#This Row],[09.2025]] -> 509 | AC88: =IF( tabSuperdettagli[[#This Row],[ProjType_]]="M", IF( AND(tabSuperdettagli[[#This Row],[Resp 1°liv_]]="Guidotti C.", tabSuperdettagli[[#This Row],[WBE description_]]="Machine Mgmt"), "Documentation", tabSuperdettagli[[#This Row],[WBE description_]]), "" ) | AD88: =LEFT(tabSuperdettagli[[#This Row],[Network]], 18 ) | AE88: Send cost I | AP88: Int. | AQ88: Gruppo struttura 1 | AV88: Responsabile A | BJ88: 501 | BK88: 502 | BL88: 503 | BM88: 504 | BN88: 505 | BO88: 506 | BP88: 507 | BQ88: 508 | BR88: 509 | BS88: 510 | BV88: 5055 | BX88: 42261 | CB88: 42260 | CC88: 42300
A89: =IF(UPPER(LEFT(tabSuperdettagli[[#This Row],[WBE Status]],1))="S","sì","no") -> no | B89: 2023 | C89: =VLOOKUP(tabSuperdettagli[[#This Row],[WBS_]],Pivot_AnnoPrimaMarcatura!A:B,2,FALSE) -> #N/A | D89: =LEFT(tabSuperdettagli[[#This Row],[Network]], 10) | E89: =LEFT(tabSuperdettagli[[#This Row],[Network]], 1) | F89: =LOWER(TRIM( tabSuperdettagli[[#This Row],[Proj. Type ]] )) | G89: =IF( OR( tabSuperdettagli[[#This Row],[ProjType_]]="C", tabSuperdettagli[[#This Row],[ProjType_]]="A", tabSuperdettagli[[#This Row],[ProjType_]]="R", tabSuperdettagli[[#This Row],[ProjType_]]="E"), "C A R E", IF( tabSuperdettagli[[#This Row],[ProjType_]]="U", "U (" & tabSuperdettagli[[#This Row],[U ProjType_]] & ")", tabSuperdettagli[[#This Row],[ProjType_]]) ) | I89: =IF( TRIM(tabSuperdettagli[[#This Row],[Raggr. X Struttura]])> "", TRIM(tabSuperdettagli[[#This Row],[Raggr. X Struttura]]), TRIM(tabSuperdettagli[[#This Row],[Resp DT]] ) ) -> Gruppo struttura 1 | J89: =tabSuperdettagli[[#This Row],[Total]] -> 6055 | K89: =tabSuperdettagli[[#This Row],[01.2025]] -> 601 | L89: =tabSuperdettagli[[#This Row],[02.2025]] -> 602 | M89: =tabSuperdettagli[[#This Row],[03.2025]] -> 603 | N89: =tabSuperdettagli[[#This Row],[04.2025]] -> 604 | O89: =tabSuperdettagli[[#This Row],[05.2025]] -> 605 | P89: =tabSuperdettagli[[#This Row],[06.2025]] -> 606 | Q89: =tabSuperdettagli[[#This Row],[07.2025]] -> 607 | R89: =tabSuperdettagli[[#This Row],[08.2025]] -> 608 | S89: =tabSuperdettagli[[#This Row],[09.2025]] -> 609 | T89: =tabSuperdettagli[[#This Row],[10.2025]] -> 610 | U89: =tabSuperdettagli[[#This Row],[11.2025]] -> 0 | V89: =tabSuperdettagli[[#This Row],[12.2025]] -> 0 | W89: =tabSuperdettagli[[#This Row],[INT/EST]] -> Int. | X89: =tabSuperdettagli[[#This Row],[Resp 2°liv]]&"" | Y89: =INDEX( tab_resp1liv[EngUnit area cluster 1_], MATCH( SUBSTITUTE(tabSuperdettagli[[#This Row],[Resp 2°liv]], " ", ""), tab_resp1liv[SearchKey],0)) -> #N/A | Z89: =tabSuperdettagli[[#This Row],[WBS Element]]&"" | AA89: =tabSuperdettagli[[#This Row],[09.2025]] -> 609 | AC89: =IF( tabSuperdettagli[[#This Row],[ProjType_]]="M", IF( AND(tabSuperdettagli[[#This Row],[Resp 1°liv_]]="Guidotti C.", tabSuperdettagli[[#This Row],[WBE description_]]="Machine Mgmt"), "Documentation", tabSuperdettagli[[#This Row],[WBE description_]]), "" ) | AD89: =LEFT(tabSuperdettagli[[#This Row],[Network]], 18 ) | AE89: Send cost I | AP89: Int. | AQ89: Gruppo struttura 1 | AV89: Responsabile A | BJ89: 601 | BK89: 602 | BL89: 603 | BM89: 604 | BN89: 605 | BO89: 606 | BP89: 607 | BQ89: 608 | BR89: 609 | BS89: 610 | BV89: 6055 | BX89: 42264 | CB89: 42263 | CC89: 42303
A90: =IF(UPPER(LEFT(tabSuperdettagli[[#This Row],[WBE Status]],1))="S","sì","no") -> no | B90: 2023 | C90: =VLOOKUP(tabSuperdettagli[[#This Row],[WBS_]],Pivot_AnnoPrimaMarcatura!A:B,2,FALSE) -> #N/A | D90: =LEFT(tabSuperdettagli[[#This Row],[Network]], 10) | E90: =LEFT(tabSuperdettagli[[#This Row],[Network]], 1) | F90: =LOWER(TRIM( tabSuperdettagli[[#This Row],[Proj. Type ]] )) | G90: =IF( OR( tabSuperdettagli[[#This Row],[ProjType_]]="C", tabSuperdettagli[[#This Row],[ProjType_]]="A", tabSuperdettagli[[#This Row],[ProjType_]]="R", tabSuperdettagli[[#This Row],[ProjType_]]="E"), "C A R E", IF( tabSuperdettagli[[#This Row],[ProjType_]]="U", "U (" & tabSuperdettagli[[#This Row],[U ProjType_]] & ")", tabSuperdettagli[[#This Row],[ProjType_]]) ) | I90: =IF( TRIM(tabSuperdettagli[[#This Row],[Raggr. X Struttura]])> "", TRIM(tabSuperdettagli[[#This Row],[Raggr. X Struttura]]), TRIM(tabSuperdettagli[[#This Row],[Resp DT]] ) ) -> Gruppo struttura 1 | J90: =tabSuperdettagli[[#This Row],[Total]] -> 55 | K90: =tabSuperdettagli[[#This Row],[01.2025]] -> 1 | L90: =tabSuperdettagli[[#This Row],[02.2025]] -> 2 | M90: =tabSuperdettagli[[#This Row],[03.2025]] -> 3 | N90: =tabSuperdettagli[[#This Row],[04.2025]] -> 4 | O90: =tabSuperdettagli[[#This Row],[05.2025]] -> 5 | P90: =tabSuperdettagli[[#This Row],[06.2025]] -> 6 | Q90: =tabSuperdettagli[[#This Row],[07.2025]] -> 7 | R90: =tabSuperdettagli[[#This Row],[08.2025]] -> 8 | S90: =tabSuperdettagli[[#This Row],[09.2025]] -> 9 | T90: =tabSuperdettagli[[#This Row],[10.2025]] -> 10 | U90: =tabSuperdettagli[[#This Row],[11.2025]] -> 0 | V90: =tabSuperdettagli[[#This Row],[12.2025]] -> 0 | W90: =tabSuperdettagli[[#This Row],[INT/EST]] -> Int. | X90: =tabSuperdettagli[[#This Row],[Resp 2°liv]]&"" | Y90: =INDEX( tab_resp1liv[EngUnit area cluster 1_], MATCH( SUBSTITUTE(tabSuperdettagli[[#This Row],[Resp 2°liv]], " ", ""), tab_resp1liv[SearchKey],0)) -> #N/A | Z90: =tabSuperdettagli[[#This Row],[WBS Element]]&"" | AA90: =tabSuperdettagli[[#This Row],[09.2025]] -> 9 | AC90: =IF( tabSuperdettagli[[#This Row],[ProjType_]]="M", IF( AND(tabSuperdettagli[[#This Row],[Resp 1°liv_]]="Guidotti C.", tabSuperdettagli[[#This Row],[WBE description_]]="Machine Mgmt"), "Documentation", tabSuperdettagli[[#This Row],[WBE description_]]), "" ) | AD90: =LEFT(tabSuperdettagli[[#This Row],[Network]], 18 ) | AE90: Send cost I | AP90: Int. | AQ90: Gruppo struttura 1 | AV90: Responsabile A | BJ90: 1 | BK90: 2 | BL90: 3 | BM90: 4 | BN90: 5 | BO90: 6 | BP90: 7 | BQ90: 8 | BR90: 9 | BS90: 10 | BV90: 55 | BX90: 42267 | CB90: 42266 | CC90: 42306
A91: =IF(UPPER(LEFT(tabSuperdettagli[[#This Row],[WBE Status]],1))="S","sì","no") -> no | B91: 2023 | C91: =VLOOKUP(tabSuperdettagli[[#This Row],[WBS_]],Pivot_AnnoPrimaMarcatura!A:B,2,FALSE) -> #N/A | D91: =LEFT(tabSuperdettagli[[#This Row],[Network]], 10) | E91: =LEFT(tabSuperdettagli[[#This Row],[Network]], 1) | F91: =LOWER(TRIM( tabSuperdettagli[[#This Row],[Proj. Type ]] )) | G91: =IF( OR( tabSuperdettagli[[#This Row],[ProjType_]]="C", tabSuperdettagli[[#This Row],[ProjType_]]="A", tabSuperdettagli[[#This Row],[ProjType_]]="R", tabSuperdettagli[[#This Row],[ProjType_]]="E"), "C A R E", IF( tabSuperdettagli[[#This Row],[ProjType_]]="U", "U (" & tabSuperdettagli[[#This Row],[U ProjType_]] & ")", tabSuperdettagli[[#This Row],[ProjType_]]) ) | I91: =IF( TRIM(tabSuperdettagli[[#This Row],[Raggr. X Struttura]])> "", TRIM(tabSuperdettagli[[#This Row],[Raggr. X Struttura]]), TRIM(tabSuperdettagli[[#This Row],[Resp DT]] ) ) -> Gruppo struttura 4 | J91: =tabSuperdettagli[[#This Row],[Total]] -> 1055 | K91: =tabSuperdettagli[[#This Row],[01.2025]] -> 101 | L91: =tabSuperdettagli[[#This Row],[02.2025]] -> 102 | M91: =tabSuperdettagli[[#This Row],[03.2025]] -> 103 | N91: =tabSuperdettagli[[#This Row],[04.2025]] -> 104 | O91: =tabSuperdettagli[[#This Row],[05.2025]] -> 105 | P91: =tabSuperdettagli[[#This Row],[06.2025]] -> 106 | Q91: =tabSuperdettagli[[#This Row],[07.2025]] -> 107 | R91: =tabSuperdettagli[[#This Row],[08.2025]] -> 108 | S91: =tabSuperdettagli[[#This Row],[09.2025]] -> 109 | T91: =tabSuperdettagli[[#This Row],[10.2025]] -> 110 | U91: =tabSuperdettagli[[#This Row],[11.2025]] -> 0 | V91: =tabSuperdettagli[[#This Row],[12.2025]] -> 0 | W91: =tabSuperdettagli[[#This Row],[INT/EST]] -> Int. | X91: =tabSuperdettagli[[#This Row],[Resp 2°liv]]&"" | Y91: =INDEX( tab_resp1liv[EngUnit area cluster 1_], MATCH( SUBSTITUTE(tabSuperdettagli[[#This Row],[Resp 2°liv]], " ", ""), tab_resp1liv[SearchKey],0)) -> #N/A | Z91: =tabSuperdettagli[[#This Row],[WBS Element]]&"" | AA91: =tabSuperdettagli[[#This Row],[09.2025]] -> 109 | AC91: =IF( tabSuperdettagli[[#This Row],[ProjType_]]="M", IF( AND(tabSuperdettagli[[#This Row],[Resp 1°liv_]]="Guidotti C.", tabSuperdettagli[[#This Row],[WBE description_]]="Machine Mgmt"), "Documentation", tabSuperdettagli[[#This Row],[WBE description_]]), "" ) | AD91: =LEFT(tabSuperdettagli[[#This Row],[Network]], 18 ) | AE91: Send cost I | AP91: Int. | AQ91: Gruppo struttura 4 | AV91: Responsabile A | BJ91: 101 | BK91: 102 | BL91: 103 | BM91: 104 | BN91: 105 | BO91: 106 | BP91: 107 | BQ91: 108 | BR91: 109 | BS91: 110 | BV91: 1055 | BX91: 42270 | CB91: 42269 | CC91: 42309
A92: =IF(UPPER(LEFT(tabSuperdettagli[[#This Row],[WBE Status]],1))="S","sì","no") -> no | B92: 2023 | C92: =VLOOKUP(tabSuperdettagli[[#This Row],[WBS_]],Pivot_AnnoPrimaMarcatura!A:B,2,FALSE) -> #N/A | D92: =LEFT(tabSuperdettagli[[#This Row],[Network]], 10) | E92: =LEFT(tabSuperdettagli[[#This Row],[Network]], 1) | F92: =LOWER(TRIM( tabSuperdettagli[[#This Row],[Proj. Type ]] )) | G92: =IF( OR( tabSuperdettagli[[#This Row],[ProjType_]]="C", tabSuperdettagli[[#This Row],[ProjType_]]="A", tabSuperdettagli[[#This Row],[ProjType_]]="R", tabSuperdettagli[[#This Row],[ProjType_]]="E"), "C A R E", IF( tabSuperdettagli[[#This Row],[ProjType_]]="U", "U (" & tabSuperdettagli[[#This Row],[U ProjType_]] & ")", tabSuperdettagli[[#This Row],[ProjType_]]) ) | I92: =IF( TRIM(tabSuperdettagli[[#This Row],[Raggr. X Struttura]])> "", TRIM(tabSuperdettagli[[#This Row],[Raggr. X Struttura]]), TRIM(tabSuperdettagli[[#This Row],[Resp DT]] ) ) -> Responsabile A | J92: =tabSuperdettagli[[#This Row],[Total]] -> 2055 | K92: =tabSuperdettagli[[#This Row],[01.2025]] -> 201 | L92: =tabSuperdettagli[[#This Row],[02.2025]] -> 202 | M92: =tabSuperdettagli[[#This Row],[03.2025]] -> 203 | N92: =tabSuperdettagli[[#This Row],[04.2025]] -> 204 | O92: =tabSuperdettagli[[#This Row],[05.2025]] -> 205 | P92: =tabSuperdettagli[[#This Row],[06.2025]] -> 206 | Q92: =tabSuperdettagli[[#This Row],[07.2025]] -> 207 | R92: =tabSuperdettagli[[#This Row],[08.2025]] -> 208 | S92: =tabSuperdettagli[[#This Row],[09.2025]] -> 209 | T92: =tabSuperdettagli[[#This Row],[10.2025]] -> 210 | U92: =tabSuperdettagli[[#This Row],[11.2025]] -> 0 | V92: =tabSuperdettagli[[#This Row],[12.2025]] -> 0 | W92: =tabSuperdettagli[[#This Row],[INT/EST]] -> Int. | X92: =tabSuperdettagli[[#This Row],[Resp 2°liv]]&"" | Y92: =INDEX( tab_resp1liv[EngUnit area cluster 1_], MATCH( SUBSTITUTE(tabSuperdettagli[[#This Row],[Resp 2°liv]], " ", ""), tab_resp1liv[SearchKey],0)) -> #N/A | Z92: =tabSuperdettagli[[#This Row],[WBS Element]]&"" | AA92: =tabSuperdettagli[[#This Row],[09.2025]] -> 209 | AC92: =IF( tabSuperdettagli[[#This Row],[ProjType_]]="M", IF( AND(tabSuperdettagli[[#This Row],[Resp 1°liv_]]="Guidotti C.", tabSuperdettagli[[#This Row],[WBE description_]]="Machine Mgmt"), "Documentation", tabSuperdettagli[[#This Row],[WBE description_]]), "" ) | AD92: =LEFT(tabSuperdettagli[[#This Row],[Network]], 18 ) | AE92: Send cost I | AP92: Int. | AV92: Responsabile A | BJ92: 201 | BK92: 202 | BL92: 203 | BM92: 204 | BN92: 205 | BO92: 206 | BP92: 207 | BQ92: 208 | BR92: 209 | BS92: 210 | BV92: 2055 | BX92: 42273 | CB92: 42272 | CC92: 42312
A93: =IF(UPPER(LEFT(tabSuperdettagli[[#This Row],[WBE Status]],1))="S","sì","no") -> no | B93: 2024 | C93: =VLOOKUP(tabSuperdettagli[[#This Row],[WBS_]],Pivot_AnnoPrimaMarcatura!A:B,2,FALSE) -> #N/A | D93: =LEFT(tabSuperdettagli[[#This Row],[Network]], 10) | E93: =LEFT(tabSuperdettagli[[#This Row],[Network]], 1) | F93: =LOWER(TRIM( tabSuperdettagli[[#This Row],[Proj. Type ]] )) | G93: =IF( OR( tabSuperdettagli[[#This Row],[ProjType_]]="C", tabSuperdettagli[[#This Row],[ProjType_]]="A", tabSuperdettagli[[#This Row],[ProjType_]]="R", tabSuperdettagli[[#This Row],[ProjType_]]="E"), "C A R E", IF( tabSuperdettagli[[#This Row],[ProjType_]]="U", "U (" & tabSuperdettagli[[#This Row],[U ProjType_]] & ")", tabSuperdettagli[[#This Row],[ProjType_]]) ) | I93: =IF( TRIM(tabSuperdettagli[[#This Row],[Raggr. X Struttura]])> "", TRIM(tabSuperdettagli[[#This Row],[Raggr. X Struttura]]), TRIM(tabSuperdettagli[[#This Row],[Resp DT]] ) ) -> Responsabile D | J93: =tabSuperdettagli[[#This Row],[Total]] -> 3055 | K93: =tabSuperdettagli[[#This Row],[01.2025]] -> 301 | L93: =tabSuperdettagli[[#This Row],[02.2025]] -> 302 | M93: =tabSuperdettagli[[#This Row],[03.2025]] -> 303 | N93: =tabSuperdettagli[[#This Row],[04.2025]] -> 304 | O93: =tabSuperdettagli[[#This Row],[05.2025]] -> 305 | P93: =tabSuperdettagli[[#This Row],[06.2025]] -> 306 | Q93: =tabSuperdettagli[[#This Row],[07.2025]] -> 307 | R93: =tabSuperdettagli[[#This Row],[08.2025]] -> 308 | S93: =tabSuperdettagli[[#This Row],[09.2025]] -> 309 | T93: =tabSuperdettagli[[#This Row],[10.2025]] -> 310 | U93: =tabSuperdettagli[[#This Row],[11.2025]] -> 0 | V93: =tabSuperdettagli[[#This Row],[12.2025]] -> 0 | W93: =tabSuperdettagli[[#This Row],[INT/EST]] -> Int. | X93: =tabSuperdettagli[[#This Row],[Resp 2°liv]]&"" | Y93: =INDEX( tab_resp1liv[EngUnit area cluster 1_], MATCH( SUBSTITUTE(tabSuperdettagli[[#This Row],[Resp 2°liv]], " ", ""), tab_resp1liv[SearchKey],0)) -> #N/A | Z93: =tabSuperdettagli[[#This Row],[WBS Element]]&"" | AA93: =tabSuperdettagli[[#This Row],[09.2025]] -> 309 | AC93: =IF( tabSuperdettagli[[#This Row],[ProjType_]]="M", IF( AND(tabSuperdettagli[[#This Row],[Resp 1°liv_]]="Guidotti C.", tabSuperdettagli[[#This Row],[WBE description_]]="Machine Mgmt"), "Documentation", tabSuperdettagli[[#This Row],[WBE description_]]), "" ) | AD93: =LEFT(tabSuperdettagli[[#This Row],[Network]], 18 ) | AE93: Send cost L | AP93: Int. | AV93: Responsabile D | BJ93: 301 | BK93: 302 | BL93: 303 | BM93: 304 | BN93: 305 | BO93: 306 | BP93: 307 | BQ93: 308 | BR93: 309 | BS93: 310 | BV93: 3055 | BX93: 42276 | CB93: 42275 | CC93: 42315
A94: =IF(UPPER(LEFT(tabSuperdettagli[[#This Row],[WBE Status]],1))="S","sì","no") -> no | B94: 2024 | C94: =VLOOKUP(tabSuperdettagli[[#This Row],[WBS_]],Pivot_AnnoPrimaMarcatura!A:B,2,FALSE) -> #N/A | D94: =LEFT(tabSuperdettagli[[#This Row],[Network]], 10) | E94: =LEFT(tabSuperdettagli[[#This Row],[Network]], 1) | F94: =LOWER(TRIM( tabSuperdettagli[[#This Row],[Proj. Type ]] )) | G94: =IF( OR( tabSuperdettagli[[#This Row],[ProjType_]]="C", tabSuperdettagli[[#This Row],[ProjType_]]="A", tabSuperdettagli[[#This Row],[ProjType_]]="R", tabSuperdettagli[[#This Row],[ProjType_]]="E"), "C A R E", IF( tabSuperdettagli[[#This Row],[ProjType_]]="U", "U (" & tabSuperdettagli[[#This Row],[U ProjType_]] & ")", tabSuperdettagli[[#This Row],[ProjType_]]) ) | I94: =IF( TRIM(tabSuperdettagli[[#This Row],[Raggr. X Struttura]])> "", TRIM(tabSuperdettagli[[#This Row],[Raggr. X Struttura]]), TRIM(tabSuperdettagli[[#This Row],[Resp DT]] ) ) -> Gruppo struttura 2 | J94: =tabSuperdettagli[[#This Row],[Total]] -> 4055 | K94: =tabSuperdettagli[[#This Row],[01.2025]] -> 401 | L94: =tabSuperdettagli[[#This Row],[02.2025]] -> 402 | M94: =tabSuperdettagli[[#This Row],[03.2025]] -> 403 | N94: =tabSuperdettagli[[#This Row],[04.2025]] -> 404 | O94: =tabSuperdettagli[[#This Row],[05.2025]] -> 405 | P94: =tabSuperdettagli[[#This Row],[06.2025]] -> 406 | Q94: =tabSuperdettagli[[#This Row],[07.2025]] -> 407 | R94: =tabSuperdettagli[[#This Row],[08.2025]] -> 408 | S94: =tabSuperdettagli[[#This Row],[09.2025]] -> 409 | T94: =tabSuperdettagli[[#This Row],[10.2025]] -> 410 | U94: =tabSuperdettagli[[#This Row],[11.2025]] -> 0 | V94: =tabSuperdettagli[[#This Row],[12.2025]] -> 0 | W94: =tabSuperdettagli[[#This Row],[INT/EST]] -> Int. | X94: =tabSuperdettagli[[#This Row],[Resp 2°liv]]&"" | Y94: =INDEX( tab_resp1liv[EngUnit area cluster 1_], MATCH( SUBSTITUTE(tabSuperdettagli[[#This Row],[Resp 2°liv]], " ", ""), tab_resp1liv[SearchKey],0)) -> #N/A | Z94: =tabSuperdettagli[[#This Row],[WBS Element]]&"" | AA94: =tabSuperdettagli[[#This Row],[09.2025]] -> 409 | AC94: =IF( tabSuperdettagli[[#This Row],[ProjType_]]="M", IF( AND(tabSuperdettagli[[#This Row],[Resp 1°liv_]]="Guidotti C.", tabSuperdettagli[[#This Row],[WBE description_]]="Machine Mgmt"), "Documentation", tabSuperdettagli[[#This Row],[WBE description_]]), "" ) | AD94: =LEFT(tabSuperdettagli[[#This Row],[Network]], 18 ) | AE94: Send cost L | AP94: Int. | AQ94: Gruppo struttura 2 | AV94: Responsabile A | BJ94: 401 | BK94: 402 | BL94: 403 | BM94: 404 | BN94: 405 | BO94: 406 | BP94: 407 | BQ94: 408 | BR94: 409 | BS94: 410 | BV94: 4055 | BX94: 42279 | CB94: 42278 | CC94: 42318
